Workbook

Sheet Contents
A1: PA-07 Forecast Workbook v2 — Rebuilt on Complete Voter File Data
A2: Companion file: PA07_Data.xlsx holds the raw source tables (House Vote Data, Carbon Estimates, Combined District Data, Model Inputs, Carbon 2026 Registration) on their own for easy review. This workbook keeps its own copies of those same sheets so every formula here still works standalone -- edit data in one place only if you want the two to stay in sync.
A4: Sheet | B4: What it does | C4: What it tells us
A5: House Vote Data (Actual) | B5: Real House + Governor vote counts for the 63 Lehigh+Northampton municipalities, 2018-2024 (4 cycles, no invalid 2016). | C5: The verified core of the dataset.
A6: Carbon County Estimates | B6: Estimated House vote counts for Carbon's 23 municipalities, derived from registration lean calibrated against Lehigh+Northampton's actual registration-to-vote relationship. | C6: Fills in the single biggest geography gap from the prior workbook, with a documented, validated method.
A7: Carbon 2026 Registration | B7: Raw Aug-2026 registration snapshot and historical ballot counts for Carbon, used to build the 2026 forecast. | C7: Supporting data for the forecast sheet.
A8: Combined District Data | B8: Merges actual (63 towns) + estimated (23 Carbon towns) into one 86-municipality table, flagged by source. | C8: The single source every downstream analysis sheet reads from.
A9: Geography Validation | B9: Compares the combined actual+estimated district total to the true PA-07 totals (from the prior external reference) for every year. | C9: CRITICAL: shows the Carbon estimate closes the gap from 20,000-42,000 missing votes/year down to just a few thousand (Monroe's residual).
A10: Predictability Ranking | B10: Classifies all 86 municipalities Easy/Medium/Hard to predict. | C10: Where more data/effort would change the forecast, now across the full reportable district.
A11: Kiley - 2026 Vote Forecast | B11: Trend-based forecast for Lehigh+Northampton + calibration-based forecast for Carbon, summed to a district total. | C11: MAJOR UPDATE: district flips to 49.4% Dem / Republican win, vs. the old 54.7% Dem estimate -- Carbon's inclusion changes the outcome.
A12: Magic Municipality | B12: Bellwether search across all 86 municipalities. | C12: Coplay is now the closest-tracking bellwether (updated from Catasauqua in the prior version).
A13: Beta Coefficients | B13: Each municipality's beta and R-squared against the self-computed combined-district index. | C13: No longer needs an external 'true' reference -- the district index is now built from data this workbook owns.
A14: Governor-House Correlation | B14: Correlates Governor vs. House Dem Share, Lehigh+Northampton, 2018 and 2022. | C14: r = 0.99 -- consistent with the prior finding; still no ticket-splitting to speak of.
A15: 2024 Backtest | B15: Reruns the trend method on 2018-2022 only, checks against real 2024, compares to a naive 'assume 2022 repeats' baseline. | C15: UPDATED FINDING: with 2016 no longer contaminating the trend, the trend model now performs about even with the naive baseline (2.17 vs 2.25 pts MAE), not clearly worse as before.
... A22: Model Comparison | B22: All three 2026 forecasts (trend, beta-adjusted, regression) side by side with their backtested accuracy. | C22: The real takeaway: methods span a 2.4-point range and split 2-1 on the winner -- this is a genuine toss-up, not a confident call.

Sheet House Vote Data (Actual)
A1: Year | B1: Municipality | C1: County | D1: Dem Votes | E1: Rep Votes | F1: Other Votes | G1: Total Votes | H1: Dem Share % | I1: Governor Dem Votes | J1: Governor Rep Votes | K1: Governor Total Votes | L1: Governor Dem Share | M1: Presidential Year (dummy)
A2: 2018 | B2: Alburtis | C2: Lehigh | D2: 454 | E2: 406 | F2: 36 | G2: =D2+E2+F2 -> 896 | H2: =D2/G2 -> 0.50669643 | I2: 519 | J2: 356 | K2: =I2+J2 -> 875 | L2: =IF(K2=0,"",I2/K2) -> 0.59314286 | M2: =IF(OR(A2=2020,A2=2024),1,0) -> 0
A3: 2020 | B3: Alburtis | C3: Lehigh | D3: 644 | E3: 735 | F3: 0 | G3: =D3+E3+F3 -> 1379 | H3: =D3/G3 -> 0.46700508 | I3: 0 | J3: 0 | K3: =I3+J3 -> 0 | L3: =IF(K3=0,"",I3/K3) | M3: =IF(OR(A3=2020,A3=2024),1,0) -> 1
A4: 2022 | B4: Alburtis | C4: Lehigh | D4: 494 | E4: 519 | F4: 0 | G4: =D4+E4+F4 -> 1013 | H4: =D4/G4 -> 0.48766041 | I4: 539 | J4: 447 | K4: =I4+J4 -> 986 | L4: =IF(K4=0,"",I4/K4) -> 0.54665314 | M4: =IF(OR(A4=2020,A4=2024),1,0) -> 0
A5: 2024 | B5: Alburtis | C5: Lehigh | D5: 601 | E5: 766 | F5: 0 | G5: =D5+E5+F5 -> 1367 | H5: =D5/G5 -> 0.43964887 | I5: 0 | J5: 0 | K5: =I5+J5 -> 0 | L5: =IF(K5=0,"",I5/K5) | M5: =IF(OR(A5=2020,A5=2024),1,0) -> 1
A6: 2018 | B6: Allentown | C6: Lehigh | D6: 19919 | E6: 7341 | F6: 773 | G6: =D6+E6+F6 -> 28033 | H6: =D6/G6 -> 0.71055542 | I6: 21066 | J6: 6512 | K6: =I6+J6 -> 27578 | L6: =IF(K6=0,"",I6/K6) -> 0.76386975 | M6: =IF(OR(A6=2020,A6=2024),1,0) -> 0
A7: 2020 | B7: Allentown | C7: Lehigh | D7: 27952 | E7: 12938 | F7: 0 | G7: =D7+E7+F7 -> 40890 | H7: =D7/G7 -> 0.68359012 | I7: 0 | J7: 0 | K7: =I7+J7 -> 0 | L7: =IF(K7=0,"",I7/K7) | M7: =IF(OR(A7=2020,A7=2024),1,0) -> 1
A8: 2022 | B8: Allentown | C8: Lehigh | D8: 16965 | E8: 7936 | F8: 0 | G8: =D8+E8+F8 -> 24901 | H8: =D8/G8 -> 0.68129794 | I8: 17605 | J8: 6760 | K8: =I8+J8 -> 24365 | L8: =IF(K8=0,"",I8/K8) -> 0.72255284 | M8: =IF(OR(A8=2020,A8=2024),1,0) -> 0
A9: 2024 | B9: Allentown | C9: Lehigh | D9: 26568 | E9: 14583 | F9: 0 | G9: =D9+E9+F9 -> 41151 | H9: =D9/G9 -> 0.64562222 | I9: 0 | J9: 0 | K9: =I9+J9 -> 0 | L9: =IF(K9=0,"",I9/K9) | M9: =IF(OR(A9=2020,A9=2024),1,0) -> 1
A10: 2018 | B10: Bethlehem | C10: Lehigh | D10: 4700 | E10: 2300 | F10: 378 | G10: =D10+E10+F10 -> 7378 | H10: =D10/G10 -> 0.63702901 | I10: 5072 | J10: 2132 | K10: =I10+J10 -> 7204 | L10: =IF(K10=0,"",I10/K10) -> 0.7040533 | M10: =IF(OR(A10=2020,A10=2024),1,0) -> 0
A11: 2020 | B11: Bethlehem | C11: Lehigh | D11: 6475 | E11: 3784 | F11: 0 | G11: =D11+E11+F11 -> 10259 | H11: =D11/G11 -> 0.63115313 | I11: 0 | J11: 0 | K11: =I11+J11 -> 0 | L11: =IF(K11=0,"",I11/K11) | M11: =IF(OR(A11=2020,A11=2024),1,0) -> 1
A12: 2022 | B12: Bethlehem | C12: Lehigh | D12: 5186 | E12: 2705 | F12: 0 | G12: =D12+E12+F12 -> 7891 | H12: =D12/G12 -> 0.65720441 | I12: 5445 | J12: 2279 | K12: =I12+J12 -> 7724 | L12: =IF(K12=0,"",I12/K12) -> 0.70494562 | M12: =IF(OR(A12=2020,A12=2024),1,0) -> 0
A13: 2024 | B13: Bethlehem | C13: Lehigh | D13: 6612 | E13: 3834 | F13: 0 | G13: =D13+E13+F13 -> 10446 | H13: =D13/G13 -> 0.63296956 | I13: 0 | J13: 0 | K13: =I13+J13 -> 0 | L13: =IF(K13=0,"",I13/K13) | M13: =IF(OR(A13=2020,A13=2024),1,0) -> 1
... A253: 2024 | B253: Wind Gap | C253: Northampton | D253: 634 | E253: 856 | F253: 0 | G253: =D253+E253+F253 -> 1490 | H253: =D253/G253 -> 0.42550336 | I253: 0 | J253: 0 | K253: =I253+J253 -> 0 | L253: =IF(K253=0,"",I253/K253) | M253: =IF(OR(A253=2020,A253=2024),1,0) -> 1

Sheet Carbon County Estimates
A1: Carbon County has no directly reported House vote counts in the source file. These figures are ESTIMATED from each municipality's voter-registration lean (Reg D minus Reg R), calibrated against the actual registration-to-vote relationship observed in Lehigh+Northampton municipalities each year (see Geography Validation sheet for the calibration and its accuracy).
A3: Year | B3: Municipality | C3: County | D3: Reg D-R (registration lean) | E3: Estimated Dem Votes | F3: Estimated Rep Votes | G3: Estimated Total Votes | H3: Estimated Dem Share %
A4: 2018 | B4: Banks Township | C4: Carbon | D4: 0.0544 | E4: 157 | F4: 133 | G4: =E4+F4 -> 290 | H4: =E4/G4 -> 0.54137931
A5: 2020 | B5: Banks Township | C5: Carbon | D5: 0.0544 | E5: 206 | F5: 192 | G5: =E5+F5 -> 398 | H5: =E5/G5 -> 0.51758794
A6: 2022 | B6: Banks Township | C6: Carbon | D6: 0.0544 | E6: 181 | F6: 155 | G6: =E6+F6 -> 336 | H6: =E6/G6 -> 0.53869048
A7: 2024 | B7: Banks Township | C7: Carbon | D7: 0.0544 | E7: 235 | F7: 220 | G7: =E7+F7 -> 455 | H7: =E7/G7 -> 0.51648352
A8: 2018 | B8: Beaver Meadows Borough | C8: Carbon | D8: -0.2367 | E8: 84 | F8: 131 | G8: =E8+F8 -> 215 | H8: =E8/G8 -> 0.39069767
A9: 2020 | B9: Beaver Meadows Borough | C9: Carbon | D9: -0.2367 | E9: 116 | F9: 203 | G9: =E9+F9 -> 319 | H9: =E9/G9 -> 0.36363636
A10: 2022 | B10: Beaver Meadows Borough | C10: Carbon | D10: -0.2367 | E10: 109 | F10: 168 | G10: =E10+F10 -> 277 | H10: =E10/G10 -> 0.39350181
A11: 2024 | B11: Beaver Meadows Borough | C11: Carbon | D11: -0.2367 | E11: 152 | F11: 255 | G11: =E11+F11 -> 407 | H11: =E11/G11 -> 0.37346437
A12: 2018 | B12: Bowmanstown Borough | C12: Carbon | D12: -0.2708 | E12: 90 | F12: 152 | G12: =E12+F12 -> 242 | H12: =E12/G12 -> 0.37190083
A13: 2020 | B13: Bowmanstown Borough | C13: Carbon | D13: -0.2708 | E13: 122 | F13: 231 | G13: =E13+F13 -> 353 | H13: =E13/G13 -> 0.34560907
A14: 2022 | B14: Bowmanstown Borough | C14: Carbon | D14: -0.2708 | E14: 120 | F14: 200 | G14: =E14+F14 -> 320 | H14: =E14/G14 -> 0.375
A15: 2024 | B15: Bowmanstown Borough | C15: Carbon | D15: -0.2708 | E15: 158 | F15: 285 | G15: =E15+F15 -> 443 | H15: =E15/G15 -> 0.35665914
... A95: 2024 | B95: Weissport Borough | C95: Carbon | D95: -0.177 | E95: 64 | F95: 95 | G95: =E95+F95 -> 159 | H95: =E95/G95 -> 0.40251572

Sheet Geography Validation
A1: Closing the Geography Gap: Carbon County Estimate vs. True Totals
A2: Method: for each year, fit a simple linear model (actual Dem vote share ~ registration D-minus-R) using the 63 Lehigh+Northampton municipalities where we have BOTH real votes and registration data. Apply that same model to Carbon County's registration lean to estimate its vote share, since Carbon's actual House vote counts aren't in the source file. Monroe County's 3 townships remain fully unaccounted for (no votes or registration data available anywhere in the source) -- the small residual gap below is entirely Monroe.
A4: Year | B4: Calibration (slope, intercept, R²) | C4: Estimated District Total (Actual LN + Estimated Carbon) | D4: True District Total | E4: Remaining Gap (Monroe only) | F4: Estimated vs True Dem Share
A5: 2018 | B5: slope=0.5165, intercept=0.5124, R²=0.937 | C5: =SUMIF('House Vote Data (Actual)'!A2:A253,A5,'House Vote Data (Actual)'!D2:D253)+SUMIF('House Vote Data (Actual)'!A2:A253,A5,'House Vote Data (Actual)'!E2:E253)+SUMIF('House Vote Data (Actual)'!A2:A253,A5,'House Vote Data (Actual)'!F2:F253)+SUMIF('Carbon County Estimates'!A4:A95,A5,'Carbon County Estimates'!E4:E95)+SUMIF('Carbon County Estimates'!A4:A95,A5,'Carbon County Estimates'!F4:F95) -> 260862 | D5: 263261 | E5: =D5-C5 -> 2399 | F5: =(SUMIF('House Vote Data (Actual)'!A2:A253,A5,'House Vote Data (Actual)'!D2:D253)+SUMIF('Carbon County Estimates'!A4:A95,A5,'Carbon County Estimates'!E4:E95))/C5 -> 0.5228205
A6: 2020 | B6: slope=0.5286, intercept=0.4879, R²=0.936 | C6: =SUMIF('House Vote Data (Actual)'!A2:A253,A6,'House Vote Data (Actual)'!D2:D253)+SUMIF('House Vote Data (Actual)'!A2:A253,A6,'House Vote Data (Actual)'!E2:E253)+SUMIF('House Vote Data (Actual)'!A2:A253,A6,'House Vote Data (Actual)'!F2:F253)+SUMIF('Carbon County Estimates'!A4:A95,A6,'Carbon County Estimates'!E4:E95)+SUMIF('Carbon County Estimates'!A4:A95,A6,'Carbon County Estimates'!F4:F95) -> 376092 | D6: 376882 | E6: =D6-C6 -> 790 | F6: =(SUMIF('House Vote Data (Actual)'!A2:A253,A6,'House Vote Data (Actual)'!D2:D253)+SUMIF('Carbon County Estimates'!A4:A95,A6,'Carbon County Estimates'!E4:E95))/C6 -> 0.50536039
A7: 2022 | B7: slope=0.4989, intercept=0.5112, R²=0.934 | C7: =SUMIF('House Vote Data (Actual)'!A2:A253,A7,'House Vote Data (Actual)'!D2:D253)+SUMIF('House Vote Data (Actual)'!A2:A253,A7,'House Vote Data (Actual)'!E2:E253)+SUMIF('House Vote Data (Actual)'!A2:A253,A7,'House Vote Data (Actual)'!F2:F253)+SUMIF('Carbon County Estimates'!A4:A95,A7,'Carbon County Estimates'!E4:E95)+SUMIF('Carbon County Estimates'!A4:A95,A7,'Carbon County Estimates'!F4:F95) -> 289186 | D7: 296891 | E7: =D7-C7 -> 7705 | F7: =(SUMIF('House Vote Data (Actual)'!A2:A253,A7,'House Vote Data (Actual)'!D2:D253)+SUMIF('Carbon County Estimates'!A4:A95,A7,'Carbon County Estimates'!E4:E95))/C7 -> 0.51824086
A8: 2024 | B8: slope=0.4899, intercept=0.489, R²=0.939 | C8: =SUMIF('House Vote Data (Actual)'!A2:A253,A8,'House Vote Data (Actual)'!D2:D253)+SUMIF('House Vote Data (Actual)'!A2:A253,A8,'House Vote Data (Actual)'!E2:E253)+SUMIF('House Vote Data (Actual)'!A2:A253,A8,'House Vote Data (Actual)'!F2:F253)+SUMIF('Carbon County Estimates'!A4:A95,A8,'Carbon County Estimates'!E4:E95)+SUMIF('Carbon County Estimates'!A4:A95,A8,'Carbon County Estimates'!F4:F95) -> 394740 | D8: 403314 | E8: =D8-C8 -> 8574 | F8: =(SUMIF('House Vote Data (Actual)'!A2:A253,A8,'House Vote Data (Actual)'!D2:D253)+SUMIF('Carbon County Estimates'!A4:A95,A8,'Carbon County Estimates'!E4:E95))/C8 -> 0.50230785
A10: Compare: before this estimate, our old Lehigh+Northampton-only totals were missing 20,000-42,000 votes per year (see prior 'Geography Gap Check' analysis). The registration-based Carbon estimate closes that down to just Monroe's residual (a few thousand votes from only 3 small townships) -- a real, validated improvement in district coverage.

Sheet Combined District Data
A1: Merges actual Lehigh+Northampton votes with estimated Carbon County votes into one 86-municipality table (all Combined District analyses -- Predictability, Magic Municipality, Beta, Forecast -- read from here). Monroe County's 3 townships are not included (no data available). 'Source' flags whether each row is Actual or Estimated.
A3: Year | B3: Municipality | C3: County | D3: Source | E3: Dem Votes | F3: Rep Votes | G3: Total Votes | H3: Dem Share %
A4: 2018 | B4: Alburtis | C4: Lehigh | D4: Actual | E4: ='House Vote Data (Actual)'!D2 -> 454 | F4: ='House Vote Data (Actual)'!E2 -> 406 | G4: ='House Vote Data (Actual)'!G2 -> 896 | H4: =E4/G4 -> 0.50669643
A5: 2020 | B5: Alburtis | C5: Lehigh | D5: Actual | E5: ='House Vote Data (Actual)'!D3 -> 644 | F5: ='House Vote Data (Actual)'!E3 -> 735 | G5: ='House Vote Data (Actual)'!G3 -> 1379 | H5: =E5/G5 -> 0.46700508
A6: 2022 | B6: Alburtis | C6: Lehigh | D6: Actual | E6: ='House Vote Data (Actual)'!D4 -> 494 | F6: ='House Vote Data (Actual)'!E4 -> 519 | G6: ='House Vote Data (Actual)'!G4 -> 1013 | H6: =E6/G6 -> 0.48766041
A7: 2024 | B7: Alburtis | C7: Lehigh | D7: Actual | E7: ='House Vote Data (Actual)'!D5 -> 601 | F7: ='House Vote Data (Actual)'!E5 -> 766 | G7: ='House Vote Data (Actual)'!G5 -> 1367 | H7: =E7/G7 -> 0.43964887
A8: 2018 | B8: Allentown | C8: Lehigh | D8: Actual | E8: ='House Vote Data (Actual)'!D6 -> 19919 | F8: ='House Vote Data (Actual)'!E6 -> 7341 | G8: ='House Vote Data (Actual)'!G6 -> 28033 | H8: =E8/G8 -> 0.71055542
A9: 2020 | B9: Allentown | C9: Lehigh | D9: Actual | E9: ='House Vote Data (Actual)'!D7 -> 27952 | F9: ='House Vote Data (Actual)'!E7 -> 12938 | G9: ='House Vote Data (Actual)'!G7 -> 40890 | H9: =E9/G9 -> 0.68359012
A10: 2022 | B10: Allentown | C10: Lehigh | D10: Actual | E10: ='House Vote Data (Actual)'!D8 -> 16965 | F10: ='House Vote Data (Actual)'!E8 -> 7936 | G10: ='House Vote Data (Actual)'!G8 -> 24901 | H10: =E10/G10 -> 0.68129794
A11: 2024 | B11: Allentown | C11: Lehigh | D11: Actual | E11: ='House Vote Data (Actual)'!D9 -> 26568 | F11: ='House Vote Data (Actual)'!E9 -> 14583 | G11: ='House Vote Data (Actual)'!G9 -> 41151 | H11: =E11/G11 -> 0.64562222
A12: 2018 | B12: Bethlehem | C12: Lehigh | D12: Actual | E12: ='House Vote Data (Actual)'!D10 -> 4700 | F12: ='House Vote Data (Actual)'!E10 -> 2300 | G12: ='House Vote Data (Actual)'!G10 -> 7378 | H12: =E12/G12 -> 0.63702901
A13: 2020 | B13: Bethlehem | C13: Lehigh | D13: Actual | E13: ='House Vote Data (Actual)'!D11 -> 6475 | F13: ='House Vote Data (Actual)'!E11 -> 3784 | G13: ='House Vote Data (Actual)'!G11 -> 10259 | H13: =E13/G13 -> 0.63115313
A14: 2022 | B14: Bethlehem | C14: Lehigh | D14: Actual | E14: ='House Vote Data (Actual)'!D12 -> 5186 | F14: ='House Vote Data (Actual)'!E12 -> 2705 | G14: ='House Vote Data (Actual)'!G12 -> 7891 | H14: =E14/G14 -> 0.65720441
A15: 2024 | B15: Bethlehem | C15: Lehigh | D15: Actual | E15: ='House Vote Data (Actual)'!D13 -> 6612 | F15: ='House Vote Data (Actual)'!E13 -> 3834 | G15: ='House Vote Data (Actual)'!G13 -> 10446 | H15: =E15/G15 -> 0.63296956
... A255: 2024 | B255: Wind Gap | C255: Northampton | D255: Actual | E255: ='House Vote Data (Actual)'!D253 -> 634 | F255: ='House Vote Data (Actual)'!E253 -> 856 | G255: ='House Vote Data (Actual)'!G253 -> 1490 | H255: =E255/G255 -> 0.42550336
A256: 2018 | B256: Banks Township | C256: Carbon | D256: Estimated | E256: ='Carbon County Estimates'!E4 -> 157 | F256: ='Carbon County Estimates'!F4 -> 133 | G256: ='Carbon County Estimates'!G4 -> 290 | H256: =E256/G256 -> 0.54137931
A257: 2020 | B257: Banks Township | C257: Carbon | D257: Estimated | E257: ='Carbon County Estimates'!E5 -> 206 | F257: ='Carbon County Estimates'!F5 -> 192 | G257: ='Carbon County Estimates'!G5 -> 398 | H257: =E257/G257 -> 0.51758794
A258: 2022 | B258: Banks Township | C258: Carbon | D258: Estimated | E258: ='Carbon County Estimates'!E6 -> 181 | F258: ='Carbon County Estimates'!F6 -> 155 | G258: ='Carbon County Estimates'!G6 -> 336 | H258: =E258/G258 -> 0.53869048
A259: 2024 | B259: Banks Township | C259: Carbon | D259: Estimated | E259: ='Carbon County Estimates'!E7 -> 235 | F259: ='Carbon County Estimates'!F7 -> 220 | G259: ='Carbon County Estimates'!G7 -> 455 | H259: =E259/G259 -> 0.51648352
A260: 2018 | B260: Beaver Meadows Borough | C260: Carbon | D260: Estimated | E260: ='Carbon County Estimates'!E8 -> 84 | F260: ='Carbon County Estimates'!F8 -> 131 | G260: ='Carbon County Estimates'!G8 -> 215 | H260: =E260/G260 -> 0.39069767
A261: 2020 | B261: Beaver Meadows Borough | C261: Carbon | D261: Estimated | E261: ='Carbon County Estimates'!E9 -> 116 | F261: ='Carbon County Estimates'!F9 -> 203 | G261: ='Carbon County Estimates'!G9 -> 319 | H261: =E261/G261 -> 0.36363636
A262: 2022 | B262: Beaver Meadows Borough | C262: Carbon | D262: Estimated | E262: ='Carbon County Estimates'!E10 -> 109 | F262: ='Carbon County Estimates'!F10 -> 168 | G262: ='Carbon County Estimates'!G10 -> 277 | H262: =E262/G262 -> 0.39350181
A263: 2024 | B263: Beaver Meadows Borough | C263: Carbon | D263: Estimated | E263: ='Carbon County Estimates'!E11 -> 152 | F263: ='Carbon County Estimates'!F11 -> 255 | G263: ='Carbon County Estimates'!G11 -> 407 | H263: =E263/G263 -> 0.37346437
A264: 2018 | B264: Bowmanstown Borough | C264: Carbon | D264: Estimated | E264: ='Carbon County Estimates'!E12 -> 90 | F264: ='Carbon County Estimates'!F12 -> 152 | G264: ='Carbon County Estimates'!G12 -> 242 | H264: =E264/G264 -> 0.37190083
A265: 2020 | B265: Bowmanstown Borough | C265: Carbon | D265: Estimated | E265: ='Carbon County Estimates'!E13 -> 122 | F265: ='Carbon County Estimates'!F13 -> 231 | G265: ='Carbon County Estimates'!G13 -> 353 | H265: =E265/G265 -> 0.34560907
A266: 2022 | B266: Bowmanstown Borough | C266: Carbon | D266: Estimated | E266: ='Carbon County Estimates'!E14 -> 120 | F266: ='Carbon County Estimates'!F14 -> 200 | G266: ='Carbon County Estimates'!G14 -> 320 | H266: =E266/G266 -> 0.375
A267: 2024 | B267: Bowmanstown Borough | C267: Carbon | D267: Estimated | E267: ='Carbon County Estimates'!E15 -> 158 | F267: ='Carbon County Estimates'!F15 -> 285 | G267: ='Carbon County Estimates'!G15 -> 443 | H267: =E267/G267 -> 0.35665914
... A347: 2024 | B347: Weissport Borough | C347: Carbon | D347: Estimated | E347: ='Carbon County Estimates'!E95 -> 64 | F347: ='Carbon County Estimates'!F95 -> 95 | G347: ='Carbon County Estimates'!G95 -> 159 | H347: =E347/G347 -> 0.40251572

Sheet Predictability Ranking
A1: Same methodology as before (margin from 50%, cycle-to-cycle volatility, party flips), now run on all 86 municipalities -- 63 with actual votes, 23 Carbon estimates. Estimated rows are flagged so you can weight confidence accordingly.
A3: Municipality | B3: County | C3: Source | D3: Avg Dem Share | E3: Avg Margin from 50pt | F3: Stdev Dem Share | G3: Party Flips | H3: Predictability
A4: Alburtis | B4: Lehigh | C4: Actual | D4: =AVERAGE('Combined District Data'!H4:H7) -> 0.4752527 | E4: =AVERAGE(ABS('Combined District Data'!H4-0.5),ABS('Combined District Data'!H5-0.5),ABS('Combined District Data'!H6-0.5),ABS('Combined District Data'!H7-0.5)) -> 0.028095518 | F4: =STDEV('Combined District Data'!H4:H7) -> 0.028742047 | G4: =IF(('Combined District Data'!H4>0.5)<>('Combined District Data'!H5>0.5),1,0)+IF(('Combined District Data'!H5>0.5)<>('Combined District Data'!H6>0.5),1,0)+IF(('Combined District Data'!H6>0.5)<>('Combined District Data'!H7>0.5),1,0) -> 1 | H4: =IF(OR(G4>=1,E4<0.05),"Hard",IF(AND(E4>=0.15,F4<0.05),"Easy","Medium")) -> Hard
A5: Allentown | B5: Lehigh | C5: Actual | D5: =AVERAGE('Combined District Data'!H8:H11) -> 0.68026642 | E5: =AVERAGE(ABS('Combined District Data'!H8-0.5),ABS('Combined District Data'!H9-0.5),ABS('Combined District Data'!H10-0.5),ABS('Combined District Data'!H11-0.5)) -> 0.18026642 | F5: =STDEV('Combined District Data'!H8:H11) -> 0.026644292 | G5: =IF(('Combined District Data'!H8>0.5)<>('Combined District Data'!H9>0.5),1,0)+IF(('Combined District Data'!H9>0.5)<>('Combined District Data'!H10>0.5),1,0)+IF(('Combined District Data'!H10>0.5)<>('Combined District Data'!H11>0.5),1,0) -> 0 | H5: =IF(OR(G5>=1,E5<0.05),"Hard",IF(AND(E5>=0.15,F5<0.05),"Easy","Medium")) -> Easy
A6: Bethlehem | B6: Lehigh | C6: Actual | D6: =AVERAGE('Combined District Data'!H12:H15) -> 0.63958903 | E6: =AVERAGE(ABS('Combined District Data'!H12-0.5),ABS('Combined District Data'!H13-0.5),ABS('Combined District Data'!H14-0.5),ABS('Combined District Data'!H15-0.5)) -> 0.13958903 | F6: =STDEV('Combined District Data'!H12:H15) -> 0.011997737 | G6: =IF(('Combined District Data'!H12>0.5)<>('Combined District Data'!H13>0.5),1,0)+IF(('Combined District Data'!H13>0.5)<>('Combined District Data'!H14>0.5),1,0)+IF(('Combined District Data'!H14>0.5)<>('Combined District Data'!H15>0.5),1,0) -> 0 | H6: =IF(OR(G6>=1,E6<0.05),"Hard",IF(AND(E6>=0.15,F6<0.05),"Easy","Medium")) -> Medium
A7: Catasauqua | B7: Lehigh | C7: Actual | D7: =AVERAGE('Combined District Data'!H16:H19) -> 0.52878358 | E7: =AVERAGE(ABS('Combined District Data'!H16-0.5),ABS('Combined District Data'!H17-0.5),ABS('Combined District Data'!H18-0.5),ABS('Combined District Data'!H19-0.5)) -> 0.028783579 | F7: =STDEV('Combined District Data'!H16:H19) -> 0.019532203 | G7: =IF(('Combined District Data'!H16>0.5)<>('Combined District Data'!H17>0.5),1,0)+IF(('Combined District Data'!H17>0.5)<>('Combined District Data'!H18>0.5),1,0)+IF(('Combined District Data'!H18>0.5)<>('Combined District Data'!H19>0.5),1,0) -> 0 | H7: =IF(OR(G7>=1,E7<0.05),"Hard",IF(AND(E7>=0.15,F7<0.05),"Easy","Medium")) -> Hard
A8: Coopersburg | B8: Lehigh | C8: Actual | D8: =AVERAGE('Combined District Data'!H20:H23) -> 0.49209189 | E8: =AVERAGE(ABS('Combined District Data'!H20-0.5),ABS('Combined District Data'!H21-0.5),ABS('Combined District Data'!H22-0.5),ABS('Combined District Data'!H23-0.5)) -> 0.017848967 | F8: =STDEV('Combined District Data'!H20:H23) -> 0.020793961 | G8: =IF(('Combined District Data'!H20>0.5)<>('Combined District Data'!H21>0.5),1,0)+IF(('Combined District Data'!H21>0.5)<>('Combined District Data'!H22>0.5),1,0)+IF(('Combined District Data'!H22>0.5)<>('Combined District Data'!H23>0.5),1,0) -> 3 | H8: =IF(OR(G8>=1,E8<0.05),"Hard",IF(AND(E8>=0.15,F8<0.05),"Easy","Medium")) -> Hard
A9: Coplay | B9: Lehigh | C9: Actual | D9: =AVERAGE('Combined District Data'!H24:H27) -> 0.51808912 | E9: =AVERAGE(ABS('Combined District Data'!H24-0.5),ABS('Combined District Data'!H25-0.5),ABS('Combined District Data'!H26-0.5),ABS('Combined District Data'!H27-0.5)) -> 0.018089117 | F9: =STDEV('Combined District Data'!H24:H27) -> 0.019500534 | G9: =IF(('Combined District Data'!H24>0.5)<>('Combined District Data'!H25>0.5),1,0)+IF(('Combined District Data'!H25>0.5)<>('Combined District Data'!H26>0.5),1,0)+IF(('Combined District Data'!H26>0.5)<>('Combined District Data'!H27>0.5),1,0) -> 0 | H9: =IF(OR(G9>=1,E9<0.05),"Hard",IF(AND(E9>=0.15,F9<0.05),"Easy","Medium")) -> Hard
A10: Emmaus | B10: Lehigh | C10: Actual | D10: =AVERAGE('Combined District Data'!H28:H31) -> 0.53633123 | E10: =AVERAGE(ABS('Combined District Data'!H28-0.5),ABS('Combined District Data'!H29-0.5),ABS('Combined District Data'!H30-0.5),ABS('Combined District Data'!H31-0.5)) -> 0.036331226 | F10: =STDEV('Combined District Data'!H28:H31) -> 0.014515116 | G10: =IF(('Combined District Data'!H28>0.5)<>('Combined District Data'!H29>0.5),1,0)+IF(('Combined District Data'!H29>0.5)<>('Combined District Data'!H30>0.5),1,0)+IF(('Combined District Data'!H30>0.5)<>('Combined District Data'!H31>0.5),1,0) -> 0 | H10: =IF(OR(G10>=1,E10<0.05),"Hard",IF(AND(E10>=0.15,F10<0.05),"Easy","Medium")) -> Hard
A11: Fountain Hill | B11: Lehigh | C11: Actual | D11: =AVERAGE('Combined District Data'!H32:H35) -> 0.66696978 | E11: =AVERAGE(ABS('Combined District Data'!H32-0.5),ABS('Combined District Data'!H33-0.5),ABS('Combined District Data'!H34-0.5),ABS('Combined District Data'!H35-0.5)) -> 0.16696978 | F11: =STDEV('Combined District Data'!H32:H35) -> 0.019214597 | G11: =IF(('Combined District Data'!H32>0.5)<>('Combined District Data'!H33>0.5),1,0)+IF(('Combined District Data'!H33>0.5)<>('Combined District Data'!H34>0.5),1,0)+IF(('Combined District Data'!H34>0.5)<>('Combined District Data'!H35>0.5),1,0) -> 0 | H11: =IF(OR(G11>=1,E11<0.05),"Hard",IF(AND(E11>=0.15,F11<0.05),"Easy","Medium")) -> Easy
A12: Hanover | B12: Lehigh | C12: Actual | D12: =AVERAGE('Combined District Data'!H36:H39) -> 0.56282592 | E12: =AVERAGE(ABS('Combined District Data'!H36-0.5),ABS('Combined District Data'!H37-0.5),ABS('Combined District Data'!H38-0.5),ABS('Combined District Data'!H39-0.5)) -> 0.062825918 | F12: =STDEV('Combined District Data'!H36:H39) -> 0.021154049 | G12: =IF(('Combined District Data'!H36>0.5)<>('Combined District Data'!H37>0.5),1,0)+IF(('Combined District Data'!H37>0.5)<>('Combined District Data'!H38>0.5),1,0)+IF(('Combined District Data'!H38>0.5)<>('Combined District Data'!H39>0.5),1,0) -> 0 | H12: =IF(OR(G12>=1,E12<0.05),"Hard",IF(AND(E12>=0.15,F12<0.05),"Easy","Medium")) -> Medium
A13: Heidelberg | B13: Lehigh | C13: Actual | D13: =AVERAGE('Combined District Data'!H40:H43) -> 0.32608704 | E13: =AVERAGE(ABS('Combined District Data'!H40-0.5),ABS('Combined District Data'!H41-0.5),ABS('Combined District Data'!H42-0.5),ABS('Combined District Data'!H43-0.5)) -> 0.17391296 | F13: =STDEV('Combined District Data'!H40:H43) -> 0.018403682 | G13: =IF(('Combined District Data'!H40>0.5)<>('Combined District Data'!H41>0.5),1,0)+IF(('Combined District Data'!H41>0.5)<>('Combined District Data'!H42>0.5),1,0)+IF(('Combined District Data'!H42>0.5)<>('Combined District Data'!H43>0.5),1,0) -> 0 | H13: =IF(OR(G13>=1,E13<0.05),"Hard",IF(AND(E13>=0.15,F13<0.05),"Easy","Medium")) -> Easy
A14: Lower Macungie | B14: Lehigh | C14: Actual | D14: =AVERAGE('Combined District Data'!H44:H47) -> 0.50330098 | E14: =AVERAGE(ABS('Combined District Data'!H44-0.5),ABS('Combined District Data'!H45-0.5),ABS('Combined District Data'!H46-0.5),ABS('Combined District Data'!H47-0.5)) -> 0.0086560224 | F14: =STDEV('Combined District Data'!H44:H47) -> 0.013930849 | G14: =IF(('Combined District Data'!H44>0.5)<>('Combined District Data'!H45>0.5),1,0)+IF(('Combined District Data'!H45>0.5)<>('Combined District Data'!H46>0.5),1,0)+IF(('Combined District Data'!H46>0.5)<>('Combined District Data'!H47>0.5),1,0) -> 2 | H14: =IF(OR(G14>=1,E14<0.05),"Hard",IF(AND(E14>=0.15,F14<0.05),"Easy","Medium")) -> Hard
A15: Lower Milford | B15: Lehigh | C15: Actual | D15: =AVERAGE('Combined District Data'!H48:H51) -> 0.38263416 | E15: =AVERAGE(ABS('Combined District Data'!H48-0.5),ABS('Combined District Data'!H49-0.5),ABS('Combined District Data'!H50-0.5),ABS('Combined District Data'!H51-0.5)) -> 0.11736584 | F15: =STDEV('Combined District Data'!H48:H51) -> 0.01206084 | G15: =IF(('Combined District Data'!H48>0.5)<>('Combined District Data'!H49>0.5),1,0)+IF(('Combined District Data'!H49>0.5)<>('Combined District Data'!H50>0.5),1,0)+IF(('Combined District Data'!H50>0.5)<>('Combined District Data'!H51>0.5),1,0) -> 0 | H15: =IF(OR(G15>=1,E15<0.05),"Hard",IF(AND(E15>=0.15,F15<0.05),"Easy","Medium")) -> Medium
A16: Lowhill | B16: Lehigh | C16: Actual | D16: =AVERAGE('Combined District Data'!H52:H55) -> 0.36298972 | E16: =AVERAGE(ABS('Combined District Data'!H52-0.5),ABS('Combined District Data'!H53-0.5),ABS('Combined District Data'!H54-0.5),ABS('Combined District Data'!H55-0.5)) -> 0.13701028 | F16: =STDEV('Combined District Data'!H52:H55) -> 0.0092741158 | G16: =IF(('Combined District Data'!H52>0.5)<>('Combined District Data'!H53>0.5),1,0)+IF(('Combined District Data'!H53>0.5)<>('Combined District Data'!H54>0.5),1,0)+IF(('Combined District Data'!H54>0.5)<>('Combined District Data'!H55>0.5),1,0) -> 0 | H16: =IF(OR(G16>=1,E16<0.05),"Hard",IF(AND(E16>=0.15,F16<0.05),"Easy","Medium")) -> Medium
A17: Lynn | B17: Lehigh | C17: Actual | D17: =AVERAGE('Combined District Data'!H56:H59) -> 0.32354375 | E17: =AVERAGE(ABS('Combined District Data'!H56-0.5),ABS('Combined District Data'!H57-0.5),ABS('Combined District Data'!H58-0.5),ABS('Combined District Data'!H59-0.5)) -> 0.17645625 | F17: =STDEV('Combined District Data'!H56:H59) -> 0.008182438 | G17: =IF(('Combined District Data'!H56>0.5)<>('Combined District Data'!H57>0.5),1,0)+IF(('Combined District Data'!H57>0.5)<>('Combined District Data'!H58>0.5),1,0)+IF(('Combined District Data'!H58>0.5)<>('Combined District Data'!H59>0.5),1,0) -> 0 | H17: =IF(OR(G17>=1,E17<0.05),"Hard",IF(AND(E17>=0.15,F17<0.05),"Easy","Medium")) -> Easy
A18: Macungie | B18: Lehigh | C18: Actual | D18: =AVERAGE('Combined District Data'!H60:H63) -> 0.5370044 | E18: =AVERAGE(ABS('Combined District Data'!H60-0.5),ABS('Combined District Data'!H61-0.5),ABS('Combined District Data'!H62-0.5),ABS('Combined District Data'!H63-0.5)) -> 0.037004395 | F18: =STDEV('Combined District Data'!H60:H63) -> 0.013838035 | G18: =IF(('Combined District Data'!H60>0.5)<>('Combined District Data'!H61>0.5),1,0)+IF(('Combined District Data'!H61>0.5)<>('Combined District Data'!H62>0.5),1,0)+IF(('Combined District Data'!H62>0.5)<>('Combined District Data'!H63>0.5),1,0) -> 0 | H18: =IF(OR(G18>=1,E18<0.05),"Hard",IF(AND(E18>=0.15,F18<0.05),"Easy","Medium")) -> Hard
A19: North Whitehall | B19: Lehigh | C19: Actual | D19: =AVERAGE('Combined District Data'!H64:H67) -> 0.40760578 | E19: =AVERAGE(ABS('Combined District Data'!H64-0.5),ABS('Combined District Data'!H65-0.5),ABS('Combined District Data'!H66-0.5),ABS('Combined District Data'!H67-0.5)) -> 0.092394223 | F19: =STDEV('Combined District Data'!H64:H67) -> 0.0097365715 | G19: =IF(('Combined District Data'!H64>0.5)<>('Combined District Data'!H65>0.5),1,0)+IF(('Combined District Data'!H65>0.5)<>('Combined District Data'!H66>0.5),1,0)+IF(('Combined District Data'!H66>0.5)<>('Combined District Data'!H67>0.5),1,0) -> 0 | H19: =IF(OR(G19>=1,E19<0.05),"Hard",IF(AND(E19>=0.15,F19<0.05),"Easy","Medium")) -> Medium
A20: Salisbury | B20: Lehigh | C20: Actual | D20: =AVERAGE('Combined District Data'!H68:H71) -> 0.49733365 | E20: =AVERAGE(ABS('Combined District Data'!H68-0.5),ABS('Combined District Data'!H69-0.5),ABS('Combined District Data'!H70-0.5),ABS('Combined District Data'!H71-0.5)) -> 0.0069848204 | F20: =STDEV('Combined District Data'!H68:H71) -> 0.0075513108 | G20: =IF(('Combined District Data'!H68>0.5)<>('Combined District Data'!H69>0.5),1,0)+IF(('Combined District Data'!H69>0.5)<>('Combined District Data'!H70>0.5),1,0)+IF(('Combined District Data'!H70>0.5)<>('Combined District Data'!H71>0.5),1,0) -> 2 | H20: =IF(OR(G20>=1,E20<0.05),"Hard",IF(AND(E20>=0.15,F20<0.05),"Easy","Medium")) -> Hard
A21: Slatington | B21: Lehigh | C21: Actual | D21: =AVERAGE('Combined District Data'!H72:H75) -> 0.424841 | E21: =AVERAGE(ABS('Combined District Data'!H72-0.5),ABS('Combined District Data'!H73-0.5),ABS('Combined District Data'!H74-0.5),ABS('Combined District Data'!H75-0.5)) -> 0.075159001 | F21: =STDEV('Combined District Data'!H72:H75) -> 0.027655711 | G21: =IF(('Combined District Data'!H72>0.5)<>('Combined District Data'!H73>0.5),1,0)+IF(('Combined District Data'!H73>0.5)<>('Combined District Data'!H74>0.5),1,0)+IF(('Combined District Data'!H74>0.5)<>('Combined District Data'!H75>0.5),1,0) -> 0 | H21: =IF(OR(G21>=1,E21<0.05),"Hard",IF(AND(E21>=0.15,F21<0.05),"Easy","Medium")) -> Medium
A22: South Whitehall | B22: Lehigh | C22: Actual | D22: =AVERAGE('Combined District Data'!H76:H79) -> 0.54503236 | E22: =AVERAGE(ABS('Combined District Data'!H76-0.5),ABS('Combined District Data'!H77-0.5),ABS('Combined District Data'!H78-0.5),ABS('Combined District Data'!H79-0.5)) -> 0.045032358 | F22: =STDEV('Combined District Data'!H76:H79) -> 0.014390127 | G22: =IF(('Combined District Data'!H76>0.5)<>('Combined District Data'!H77>0.5),1,0)+IF(('Combined District Data'!H77>0.5)<>('Combined District Data'!H78>0.5),1,0)+IF(('Combined District Data'!H78>0.5)<>('Combined District Data'!H79>0.5),1,0) -> 0 | H22: =IF(OR(G22>=1,E22<0.05),"Hard",IF(AND(E22>=0.15,F22<0.05),"Easy","Medium")) -> Hard
A23: Upper Macungie | B23: Lehigh | C23: Actual | D23: =AVERAGE('Combined District Data'!H80:H83) -> 0.52003115 | E23: =AVERAGE(ABS('Combined District Data'!H80-0.5),ABS('Combined District Data'!H81-0.5),ABS('Combined District Data'!H82-0.5),ABS('Combined District Data'!H83-0.5)) -> 0.020031155 | F23: =STDEV('Combined District Data'!H80:H83) -> 0.0090523443 | G23: =IF(('Combined District Data'!H80>0.5)<>('Combined District Data'!H81>0.5),1,0)+IF(('Combined District Data'!H81>0.5)<>('Combined District Data'!H82>0.5),1,0)+IF(('Combined District Data'!H82>0.5)<>('Combined District Data'!H83>0.5),1,0) -> 0 | H23: =IF(OR(G23>=1,E23<0.05),"Hard",IF(AND(E23>=0.15,F23<0.05),"Easy","Medium")) -> Hard
A24: Upper Milford | B24: Lehigh | C24: Actual | D24: =AVERAGE('Combined District Data'!H84:H87) -> 0.43966475 | E24: =AVERAGE(ABS('Combined District Data'!H84-0.5),ABS('Combined District Data'!H85-0.5),ABS('Combined District Data'!H86-0.5),ABS('Combined District Data'!H87-0.5)) -> 0.06033525 | F24: =STDEV('Combined District Data'!H84:H87) -> 0.011353998 | G24: =IF(('Combined District Data'!H84>0.5)<>('Combined District Data'!H85>0.5),1,0)+IF(('Combined District Data'!H85>0.5)<>('Combined District Data'!H86>0.5),1,0)+IF(('Combined District Data'!H86>0.5)<>('Combined District Data'!H87>0.5),1,0) -> 0 | H24: =IF(OR(G24>=1,E24<0.05),"Hard",IF(AND(E24>=0.15,F24<0.05),"Easy","Medium")) -> Medium
A25: Upper Saucon | B25: Lehigh | C25: Actual | D25: =AVERAGE('Combined District Data'!H88:H91) -> 0.48386045 | E25: =AVERAGE(ABS('Combined District Data'!H88-0.5),ABS('Combined District Data'!H89-0.5),ABS('Combined District Data'!H90-0.5),ABS('Combined District Data'!H91-0.5)) -> 0.017193676 | F25: =STDEV('Combined District Data'!H88:H91) -> 0.014841905 | G25: =IF(('Combined District Data'!H88>0.5)<>('Combined District Data'!H89>0.5),1,0)+IF(('Combined District Data'!H89>0.5)<>('Combined District Data'!H90>0.5),1,0)+IF(('Combined District Data'!H90>0.5)<>('Combined District Data'!H91>0.5),1,0) -> 2 | H25: =IF(OR(G25>=1,E25<0.05),"Hard",IF(AND(E25>=0.15,F25<0.05),"Easy","Medium")) -> Hard
A26: Washington | B26: Lehigh | C26: Actual | D26: =AVERAGE('Combined District Data'!H92:H95) -> 0.33473717 | E26: =AVERAGE(ABS('Combined District Data'!H92-0.5),ABS('Combined District Data'!H93-0.5),ABS('Combined District Data'!H94-0.5),ABS('Combined District Data'!H95-0.5)) -> 0.16526283 | F26: =STDEV('Combined District Data'!H92:H95) -> 0.014497891 | G26: =IF(('Combined District Data'!H92>0.5)<>('Combined District Data'!H93>0.5),1,0)+IF(('Combined District Data'!H93>0.5)<>('Combined District Data'!H94>0.5),1,0)+IF(('Combined District Data'!H94>0.5)<>('Combined District Data'!H95>0.5),1,0) -> 0 | H26: =IF(OR(G26>=1,E26<0.05),"Hard",IF(AND(E26>=0.15,F26<0.05),"Easy","Medium")) -> Easy
A27: Weisenberg | B27: Lehigh | C27: Actual | D27: =AVERAGE('Combined District Data'!H96:H99) -> 0.3464918 | E27: =AVERAGE(ABS('Combined District Data'!H96-0.5),ABS('Combined District Data'!H97-0.5),ABS('Combined District Data'!H98-0.5),ABS('Combined District Data'!H99-0.5)) -> 0.1535082 | F27: =STDEV('Combined District Data'!H96:H99) -> 0.013486092 | G27: =IF(('Combined District Data'!H96>0.5)<>('Combined District Data'!H97>0.5),1,0)+IF(('Combined District Data'!H97>0.5)<>('Combined District Data'!H98>0.5),1,0)+IF(('Combined District Data'!H98>0.5)<>('Combined District Data'!H99>0.5),1,0) -> 0 | H27: =IF(OR(G27>=1,E27<0.05),"Hard",IF(AND(E27>=0.15,F27<0.05),"Easy","Medium")) -> Easy
A28: Whitehall | B28: Lehigh | C28: Actual | D28: =AVERAGE('Combined District Data'!H100:H103) -> 0.52770789 | E28: =AVERAGE(ABS('Combined District Data'!H100-0.5),ABS('Combined District Data'!H101-0.5),ABS('Combined District Data'!H102-0.5),ABS('Combined District Data'!H103-0.5)) -> 0.027707894 | F28: =STDEV('Combined District Data'!H100:H103) -> 0.011717288 | G28: =IF(('Combined District Data'!H100>0.5)<>('Combined District Data'!H101>0.5),1,0)+IF(('Combined District Data'!H101>0.5)<>('Combined District Data'!H102>0.5),1,0)+IF(('Combined District Data'!H102>0.5)<>('Combined District Data'!H103>0.5),1,0) -> 0 | H28: =IF(OR(G28>=1,E28<0.05),"Hard",IF(AND(E28>=0.15,F28<0.05),"Easy","Medium")) -> Hard
A29: Allen | B29: Northampton | C29: Actual | D29: =AVERAGE('Combined District Data'!H104:H107) -> 0.4327543 | E29: =AVERAGE(ABS('Combined District Data'!H104-0.5),ABS('Combined District Data'!H105-0.5),ABS('Combined District Data'!H106-0.5),ABS('Combined District Data'!H107-0.5)) -> 0.067245698 | F29: =STDEV('Combined District Data'!H104:H107) -> 0.013636598 | G29: =IF(('Combined District Data'!H104>0.5)<>('Combined District Data'!H105>0.5),1,0)+IF(('Combined District Data'!H105>0.5)<>('Combined District Data'!H106>0.5),1,0)+IF(('Combined District Data'!H106>0.5)<>('Combined District Data'!H107>0.5),1,0) -> 0 | H29: =IF(OR(G29>=1,E29<0.05),"Hard",IF(AND(E29>=0.15,F29<0.05),"Easy","Medium")) -> Medium
A30: Bangor | B30: Northampton | C30: Actual | D30: =AVERAGE('Combined District Data'!H108:H111) -> 0.43283697 | E30: =AVERAGE(ABS('Combined District Data'!H108-0.5),ABS('Combined District Data'!H109-0.5),ABS('Combined District Data'!H110-0.5),ABS('Combined District Data'!H111-0.5)) -> 0.067163029 | F30: =STDEV('Combined District Data'!H108:H111) -> 0.021721023 | G30: =IF(('Combined District Data'!H108>0.5)<>('Combined District Data'!H109>0.5),1,0)+IF(('Combined District Data'!H109>0.5)<>('Combined District Data'!H110>0.5),1,0)+IF(('Combined District Data'!H110>0.5)<>('Combined District Data'!H111>0.5),1,0) -> 0 | H30: =IF(OR(G30>=1,E30<0.05),"Hard",IF(AND(E30>=0.15,F30<0.05),"Easy","Medium")) -> Medium
A31: Bath | B31: Northampton | C31: Actual | D31: =AVERAGE('Combined District Data'!H112:H115) -> 0.4583611 | E31: =AVERAGE(ABS('Combined District Data'!H112-0.5),ABS('Combined District Data'!H113-0.5),ABS('Combined District Data'!H114-0.5),ABS('Combined District Data'!H115-0.5)) -> 0.041638902 | F31: =STDEV('Combined District Data'!H112:H115) -> 0.0042595571 | G31: =IF(('Combined District Data'!H112>0.5)<>('Combined District Data'!H113>0.5),1,0)+IF(('Combined District Data'!H113>0.5)<>('Combined District Data'!H114>0.5),1,0)+IF(('Combined District Data'!H114>0.5)<>('Combined District Data'!H115>0.5),1,0) -> 0 | H31: =IF(OR(G31>=1,E31<0.05),"Hard",IF(AND(E31>=0.15,F31<0.05),"Easy","Medium")) -> Hard
A32: Bethlehem | B32: Northampton | C32: Actual | D32: =AVERAGE('Combined District Data'!H116:H119) -> 0.6784395 | E32: =AVERAGE(ABS('Combined District Data'!H116-0.5),ABS('Combined District Data'!H117-0.5),ABS('Combined District Data'!H118-0.5),ABS('Combined District Data'!H119-0.5)) -> 0.1784395 | F32: =STDEV('Combined District Data'!H116:H119) -> 0.0094557579 | G32: =IF(('Combined District Data'!H116>0.5)<>('Combined District Data'!H117>0.5),1,0)+IF(('Combined District Data'!H117>0.5)<>('Combined District Data'!H118>0.5),1,0)+IF(('Combined District Data'!H118>0.5)<>('Combined District Data'!H119>0.5),1,0) -> 0 | H32: =IF(OR(G32>=1,E32<0.05),"Hard",IF(AND(E32>=0.15,F32<0.05),"Easy","Medium")) -> Easy
A33: Bethlehem Township | B33: Northampton | C33: Actual | D33: =AVERAGE('Combined District Data'!H120:H123) -> 0.53552415 | E33: =AVERAGE(ABS('Combined District Data'!H120-0.5),ABS('Combined District Data'!H121-0.5),ABS('Combined District Data'!H122-0.5),ABS('Combined District Data'!H123-0.5)) -> 0.035524149 | F33: =STDEV('Combined District Data'!H120:H123) -> 0.0073642727 | G33: =IF(('Combined District Data'!H120>0.5)<>('Combined District Data'!H121>0.5),1,0)+IF(('Combined District Data'!H121>0.5)<>('Combined District Data'!H122>0.5),1,0)+IF(('Combined District Data'!H122>0.5)<>('Combined District Data'!H123>0.5),1,0) -> 0 | H33: =IF(OR(G33>=1,E33<0.05),"Hard",IF(AND(E33>=0.15,F33<0.05),"Easy","Medium")) -> Hard
A34: Bushkill | B34: Northampton | C34: Actual | D34: =AVERAGE('Combined District Data'!H124:H127) -> 0.38151885 | E34: =AVERAGE(ABS('Combined District Data'!H124-0.5),ABS('Combined District Data'!H125-0.5),ABS('Combined District Data'!H126-0.5),ABS('Combined District Data'!H127-0.5)) -> 0.11848115 | F34: =STDEV('Combined District Data'!H124:H127) -> 0.011176034 | G34: =IF(('Combined District Data'!H124>0.5)<>('Combined District Data'!H125>0.5),1,0)+IF(('Combined District Data'!H125>0.5)<>('Combined District Data'!H126>0.5),1,0)+IF(('Combined District Data'!H126>0.5)<>('Combined District Data'!H127>0.5),1,0) -> 0 | H34: =IF(OR(G34>=1,E34<0.05),"Hard",IF(AND(E34>=0.15,F34<0.05),"Easy","Medium")) -> Medium
A35: Chapman | B35: Northampton | C35: Actual | D35: =AVERAGE('Combined District Data'!H128:H131) -> 0.36273986 | E35: =AVERAGE(ABS('Combined District Data'!H128-0.5),ABS('Combined District Data'!H129-0.5),ABS('Combined District Data'!H130-0.5),ABS('Combined District Data'!H131-0.5)) -> 0.13726014 | F35: =STDEV('Combined District Data'!H128:H131) -> 0.050475047 | G35: =IF(('Combined District Data'!H128>0.5)<>('Combined District Data'!H129>0.5),1,0)+IF(('Combined District Data'!H129>0.5)<>('Combined District Data'!H130>0.5),1,0)+IF(('Combined District Data'!H130>0.5)<>('Combined District Data'!H131>0.5),1,0) -> 0 | H35: =IF(OR(G35>=1,E35<0.05),"Hard",IF(AND(E35>=0.15,F35<0.05),"Easy","Medium")) -> Medium
A36: East Allen | B36: Northampton | C36: Actual | D36: =AVERAGE('Combined District Data'!H132:H135) -> 0.42015114 | E36: =AVERAGE(ABS('Combined District Data'!H132-0.5),ABS('Combined District Data'!H133-0.5),ABS('Combined District Data'!H134-0.5),ABS('Combined District Data'!H135-0.5)) -> 0.079848862 | F36: =STDEV('Combined District Data'!H132:H135) -> 0.018509198 | G36: =IF(('Combined District Data'!H132>0.5)<>('Combined District Data'!H133>0.5),1,0)+IF(('Combined District Data'!H133>0.5)<>('Combined District Data'!H134>0.5),1,0)+IF(('Combined District Data'!H134>0.5)<>('Combined District Data'!H135>0.5),1,0) -> 0 | H36: =IF(OR(G36>=1,E36<0.05),"Hard",IF(AND(E36>=0.15,F36<0.05),"Easy","Medium")) -> Medium
A37: East Bangor | B37: Northampton | C37: Actual | D37: =AVERAGE('Combined District Data'!H136:H139) -> 0.37743937 | E37: =AVERAGE(ABS('Combined District Data'!H136-0.5),ABS('Combined District Data'!H137-0.5),ABS('Combined District Data'!H138-0.5),ABS('Combined District Data'!H139-0.5)) -> 0.12256063 | F37: =STDEV('Combined District Data'!H136:H139) -> 0.033459878 | G37: =IF(('Combined District Data'!H136>0.5)<>('Combined District Data'!H137>0.5),1,0)+IF(('Combined District Data'!H137>0.5)<>('Combined District Data'!H138>0.5),1,0)+IF(('Combined District Data'!H138>0.5)<>('Combined District Data'!H139>0.5),1,0) -> 0 | H37: =IF(OR(G37>=1,E37<0.05),"Hard",IF(AND(E37>=0.15,F37<0.05),"Easy","Medium")) -> Medium
A38: Easton | B38: Northampton | C38: Actual | D38: =AVERAGE('Combined District Data'!H140:H143) -> 0.71897369 | E38: =AVERAGE(ABS('Combined District Data'!H140-0.5),ABS('Combined District Data'!H141-0.5),ABS('Combined District Data'!H142-0.5),ABS('Combined District Data'!H143-0.5)) -> 0.21897369 | F38: =STDEV('Combined District Data'!H140:H143) -> 0.021399452 | G38: =IF(('Combined District Data'!H140>0.5)<>('Combined District Data'!H141>0.5),1,0)+IF(('Combined District Data'!H141>0.5)<>('Combined District Data'!H142>0.5),1,0)+IF(('Combined District Data'!H142>0.5)<>('Combined District Data'!H143>0.5),1,0) -> 0 | H38: =IF(OR(G38>=1,E38<0.05),"Hard",IF(AND(E38>=0.15,F38<0.05),"Easy","Medium")) -> Easy
A39: Forks | B39: Northampton | C39: Actual | D39: =AVERAGE('Combined District Data'!H144:H147) -> 0.5200637 | E39: =AVERAGE(ABS('Combined District Data'!H144-0.5),ABS('Combined District Data'!H145-0.5),ABS('Combined District Data'!H146-0.5),ABS('Combined District Data'!H147-0.5)) -> 0.020063701 | F39: =STDEV('Combined District Data'!H144:H147) -> 0.008007736 | G39: =IF(('Combined District Data'!H144>0.5)<>('Combined District Data'!H145>0.5),1,0)+IF(('Combined District Data'!H145>0.5)<>('Combined District Data'!H146>0.5),1,0)+IF(('Combined District Data'!H146>0.5)<>('Combined District Data'!H147>0.5),1,0) -> 0 | H39: =IF(OR(G39>=1,E39<0.05),"Hard",IF(AND(E39>=0.15,F39<0.05),"Easy","Medium")) -> Hard
A40: Freemansburg | B40: Northampton | C40: Actual | D40: =AVERAGE('Combined District Data'!H148:H151) -> 0.61340818 | E40: =AVERAGE(ABS('Combined District Data'!H148-0.5),ABS('Combined District Data'!H149-0.5),ABS('Combined District Data'!H150-0.5),ABS('Combined District Data'!H151-0.5)) -> 0.11340818 | F40: =STDEV('Combined District Data'!H148:H151) -> 0.022866505 | G40: =IF(('Combined District Data'!H148>0.5)<>('Combined District Data'!H149>0.5),1,0)+IF(('Combined District Data'!H149>0.5)<>('Combined District Data'!H150>0.5),1,0)+IF(('Combined District Data'!H150>0.5)<>('Combined District Data'!H151>0.5),1,0) -> 0 | H40: =IF(OR(G40>=1,E40<0.05),"Hard",IF(AND(E40>=0.15,F40<0.05),"Easy","Medium")) -> Medium
A41: Glendon | B41: Northampton | C41: Actual | D41: =AVERAGE('Combined District Data'!H152:H155) -> 0.54208476 | E41: =AVERAGE(ABS('Combined District Data'!H152-0.5),ABS('Combined District Data'!H153-0.5),ABS('Combined District Data'!H154-0.5),ABS('Combined District Data'!H155-0.5)) -> 0.042084758 | F41: =STDEV('Combined District Data'!H152:H155) -> 0.057099653 | G41: =IF(('Combined District Data'!H152>0.5)<>('Combined District Data'!H153>0.5),1,0)+IF(('Combined District Data'!H153>0.5)<>('Combined District Data'!H154>0.5),1,0)+IF(('Combined District Data'!H154>0.5)<>('Combined District Data'!H155>0.5),1,0) -> 0 | H41: =IF(OR(G41>=1,E41<0.05),"Hard",IF(AND(E41>=0.15,F41<0.05),"Easy","Medium")) -> Hard
A42: Hanover | B42: Northampton | C42: Actual | D42: =AVERAGE('Combined District Data'!H156:H159) -> 0.53837725 | E42: =AVERAGE(ABS('Combined District Data'!H156-0.5),ABS('Combined District Data'!H157-0.5),ABS('Combined District Data'!H158-0.5),ABS('Combined District Data'!H159-0.5)) -> 0.038377252 | F42: =STDEV('Combined District Data'!H156:H159) -> 0.01393453 | G42: =IF(('Combined District Data'!H156>0.5)<>('Combined District Data'!H157>0.5),1,0)+IF(('Combined District Data'!H157>0.5)<>('Combined District Data'!H158>0.5),1,0)+IF(('Combined District Data'!H158>0.5)<>('Combined District Data'!H159>0.5),1,0) -> 0 | H42: =IF(OR(G42>=1,E42<0.05),"Hard",IF(AND(E42>=0.15,F42<0.05),"Easy","Medium")) -> Hard
A43: Hellertown | B43: Northampton | C43: Actual | D43: =AVERAGE('Combined District Data'!H160:H163) -> 0.52217716 | E43: =AVERAGE(ABS('Combined District Data'!H160-0.5),ABS('Combined District Data'!H161-0.5),ABS('Combined District Data'!H162-0.5),ABS('Combined District Data'!H163-0.5)) -> 0.022177161 | F43: =STDEV('Combined District Data'!H160:H163) -> 0.019241433 | G43: =IF(('Combined District Data'!H160>0.5)<>('Combined District Data'!H161>0.5),1,0)+IF(('Combined District Data'!H161>0.5)<>('Combined District Data'!H162>0.5),1,0)+IF(('Combined District Data'!H162>0.5)<>('Combined District Data'!H163>0.5),1,0) -> 0 | H43: =IF(OR(G43>=1,E43<0.05),"Hard",IF(AND(E43>=0.15,F43<0.05),"Easy","Medium")) -> Hard
A44: Lehigh | B44: Northampton | C44: Actual | D44: =AVERAGE('Combined District Data'!H164:H167) -> 0.34387567 | E44: =AVERAGE(ABS('Combined District Data'!H164-0.5),ABS('Combined District Data'!H165-0.5),ABS('Combined District Data'!H166-0.5),ABS('Combined District Data'!H167-0.5)) -> 0.15612433 | F44: =STDEV('Combined District Data'!H164:H167) -> 0.010305311 | G44: =IF(('Combined District Data'!H164>0.5)<>('Combined District Data'!H165>0.5),1,0)+IF(('Combined District Data'!H165>0.5)<>('Combined District Data'!H166>0.5),1,0)+IF(('Combined District Data'!H166>0.5)<>('Combined District Data'!H167>0.5),1,0) -> 0 | H44: =IF(OR(G44>=1,E44<0.05),"Hard",IF(AND(E44>=0.15,F44<0.05),"Easy","Medium")) -> Easy
A45: Lower Mount Bethel | B45: Northampton | C45: Actual | D45: =AVERAGE('Combined District Data'!H168:H171) -> 0.3586056 | E45: =AVERAGE(ABS('Combined District Data'!H168-0.5),ABS('Combined District Data'!H169-0.5),ABS('Combined District Data'!H170-0.5),ABS('Combined District Data'!H171-0.5)) -> 0.1413944 | F45: =STDEV('Combined District Data'!H168:H171) -> 0.032628078 | G45: =IF(('Combined District Data'!H168>0.5)<>('Combined District Data'!H169>0.5),1,0)+IF(('Combined District Data'!H169>0.5)<>('Combined District Data'!H170>0.5),1,0)+IF(('Combined District Data'!H170>0.5)<>('Combined District Data'!H171>0.5),1,0) -> 0 | H45: =IF(OR(G45>=1,E45<0.05),"Hard",IF(AND(E45>=0.15,F45<0.05),"Easy","Medium")) -> Medium
A46: Nazareth | B46: Northampton | C46: Actual | D46: =AVERAGE('Combined District Data'!H172:H175) -> 0.44595897 | E46: =AVERAGE(ABS('Combined District Data'!H172-0.5),ABS('Combined District Data'!H173-0.5),ABS('Combined District Data'!H174-0.5),ABS('Combined District Data'!H175-0.5)) -> 0.054041031 | F46: =STDEV('Combined District Data'!H172:H175) -> 0.030038841 | G46: =IF(('Combined District Data'!H172>0.5)<>('Combined District Data'!H173>0.5),1,0)+IF(('Combined District Data'!H173>0.5)<>('Combined District Data'!H174>0.5),1,0)+IF(('Combined District Data'!H174>0.5)<>('Combined District Data'!H175>0.5),1,0) -> 0 | H46: =IF(OR(G46>=1,E46<0.05),"Hard",IF(AND(E46>=0.15,F46<0.05),"Easy","Medium")) -> Medium
A47: Lower Saucon | B47: Northampton | C47: Actual | D47: =AVERAGE('Combined District Data'!H176:H179) -> 0.47871624 | E47: =AVERAGE(ABS('Combined District Data'!H176-0.5),ABS('Combined District Data'!H177-0.5),ABS('Combined District Data'!H178-0.5),ABS('Combined District Data'!H179-0.5)) -> 0.021283762 | F47: =STDEV('Combined District Data'!H176:H179) -> 0.010199919 | G47: =IF(('Combined District Data'!H176>0.5)<>('Combined District Data'!H177>0.5),1,0)+IF(('Combined District Data'!H177>0.5)<>('Combined District Data'!H178>0.5),1,0)+IF(('Combined District Data'!H178>0.5)<>('Combined District Data'!H179>0.5),1,0) -> 0 | H47: =IF(OR(G47>=1,E47<0.05),"Hard",IF(AND(E47>=0.15,F47<0.05),"Easy","Medium")) -> Hard
A48: Moore | B48: Northampton | C48: Actual | D48: =AVERAGE('Combined District Data'!H180:H183) -> 0.33984609 | E48: =AVERAGE(ABS('Combined District Data'!H180-0.5),ABS('Combined District Data'!H181-0.5),ABS('Combined District Data'!H182-0.5),ABS('Combined District Data'!H183-0.5)) -> 0.16015391 | F48: =STDEV('Combined District Data'!H180:H183) -> 0.0098400603 | G48: =IF(('Combined District Data'!H180>0.5)<>('Combined District Data'!H181>0.5),1,0)+IF(('Combined District Data'!H181>0.5)<>('Combined District Data'!H182>0.5),1,0)+IF(('Combined District Data'!H182>0.5)<>('Combined District Data'!H183>0.5),1,0) -> 0 | H48: =IF(OR(G48>=1,E48<0.05),"Hard",IF(AND(E48>=0.15,F48<0.05),"Easy","Medium")) -> Easy
A49: Lower Nazareth | B49: Northampton | C49: Actual | D49: =AVERAGE('Combined District Data'!H184:H187) -> 0.48941111 | E49: =AVERAGE(ABS('Combined District Data'!H184-0.5),ABS('Combined District Data'!H185-0.5),ABS('Combined District Data'!H186-0.5),ABS('Combined District Data'!H187-0.5)) -> 0.025256261 | F49: =STDEV('Combined District Data'!H184:H187) -> 0.031346359 | G49: =IF(('Combined District Data'!H184>0.5)<>('Combined District Data'!H185>0.5),1,0)+IF(('Combined District Data'!H185>0.5)<>('Combined District Data'!H186>0.5),1,0)+IF(('Combined District Data'!H186>0.5)<>('Combined District Data'!H187>0.5),1,0) -> 3 | H49: =IF(OR(G49>=1,E49<0.05),"Hard",IF(AND(E49>=0.15,F49<0.05),"Easy","Medium")) -> Hard
A50: North Catasauqua | B50: Northampton | C50: Actual | D50: =AVERAGE('Combined District Data'!H188:H191) -> 0.48565646 | E50: =AVERAGE(ABS('Combined District Data'!H188-0.5),ABS('Combined District Data'!H189-0.5),ABS('Combined District Data'!H190-0.5),ABS('Combined District Data'!H191-0.5)) -> 0.016299724 | F50: =STDEV('Combined District Data'!H188:H191) -> 0.016225187 | G50: =IF(('Combined District Data'!H188>0.5)<>('Combined District Data'!H189>0.5),1,0)+IF(('Combined District Data'!H189>0.5)<>('Combined District Data'!H190>0.5),1,0)+IF(('Combined District Data'!H190>0.5)<>('Combined District Data'!H191>0.5),1,0) -> 2 | H50: =IF(OR(G50>=1,E50<0.05),"Hard",IF(AND(E50>=0.15,F50<0.05),"Easy","Medium")) -> Hard
A51: Northampton | B51: Northampton | C51: Actual | D51: =AVERAGE('Combined District Data'!H192:H195) -> 0.47171173 | E51: =AVERAGE(ABS('Combined District Data'!H192-0.5),ABS('Combined District Data'!H193-0.5),ABS('Combined District Data'!H194-0.5),ABS('Combined District Data'!H195-0.5)) -> 0.028288274 | F51: =STDEV('Combined District Data'!H192:H195) -> 0.023724553 | G51: =IF(('Combined District Data'!H192>0.5)<>('Combined District Data'!H193>0.5),1,0)+IF(('Combined District Data'!H193>0.5)<>('Combined District Data'!H194>0.5),1,0)+IF(('Combined District Data'!H194>0.5)<>('Combined District Data'!H195>0.5),1,0) -> 0 | H51: =IF(OR(G51>=1,E51<0.05),"Hard",IF(AND(E51>=0.15,F51<0.05),"Easy","Medium")) -> Hard
A52: Palmer | B52: Northampton | C52: Actual | D52: =AVERAGE('Combined District Data'!H196:H199) -> 0.51581923 | E52: =AVERAGE(ABS('Combined District Data'!H196-0.5),ABS('Combined District Data'!H197-0.5),ABS('Combined District Data'!H198-0.5),ABS('Combined District Data'!H199-0.5)) -> 0.015819232 | F52: =STDEV('Combined District Data'!H196:H199) -> 0.012168975 | G52: =IF(('Combined District Data'!H196>0.5)<>('Combined District Data'!H197>0.5),1,0)+IF(('Combined District Data'!H197>0.5)<>('Combined District Data'!H198>0.5),1,0)+IF(('Combined District Data'!H198>0.5)<>('Combined District Data'!H199>0.5),1,0) -> 0 | H52: =IF(OR(G52>=1,E52<0.05),"Hard",IF(AND(E52>=0.15,F52<0.05),"Easy","Medium")) -> Hard
A53: Pen Argyl | B53: Northampton | C53: Actual | D53: =AVERAGE('Combined District Data'!H200:H203) -> 0.38771142 | E53: =AVERAGE(ABS('Combined District Data'!H200-0.5),ABS('Combined District Data'!H201-0.5),ABS('Combined District Data'!H202-0.5),ABS('Combined District Data'!H203-0.5)) -> 0.11228858 | F53: =STDEV('Combined District Data'!H200:H203) -> 0.011430747 | G53: =IF(('Combined District Data'!H200>0.5)<>('Combined District Data'!H201>0.5),1,0)+IF(('Combined District Data'!H201>0.5)<>('Combined District Data'!H202>0.5),1,0)+IF(('Combined District Data'!H202>0.5)<>('Combined District Data'!H203>0.5),1,0) -> 0 | H53: =IF(OR(G53>=1,E53<0.05),"Hard",IF(AND(E53>=0.15,F53<0.05),"Easy","Medium")) -> Medium
A54: Plainfield | B54: Northampton | C54: Actual | D54: =AVERAGE('Combined District Data'!H204:H207) -> 0.35851037 | E54: =AVERAGE(ABS('Combined District Data'!H204-0.5),ABS('Combined District Data'!H205-0.5),ABS('Combined District Data'!H206-0.5),ABS('Combined District Data'!H207-0.5)) -> 0.14148963 | F54: =STDEV('Combined District Data'!H204:H207) -> 0.017864882 | G54: =IF(('Combined District Data'!H204>0.5)<>('Combined District Data'!H205>0.5),1,0)+IF(('Combined District Data'!H205>0.5)<>('Combined District Data'!H206>0.5),1,0)+IF(('Combined District Data'!H206>0.5)<>('Combined District Data'!H207>0.5),1,0) -> 0 | H54: =IF(OR(G54>=1,E54<0.05),"Hard",IF(AND(E54>=0.15,F54<0.05),"Easy","Medium")) -> Medium
A55: Portland | B55: Northampton | C55: Actual | D55: =AVERAGE('Combined District Data'!H208:H211) -> 0.34530962 | E55: =AVERAGE(ABS('Combined District Data'!H208-0.5),ABS('Combined District Data'!H209-0.5),ABS('Combined District Data'!H210-0.5),ABS('Combined District Data'!H211-0.5)) -> 0.15469038 | F55: =STDEV('Combined District Data'!H208:H211) -> 0.019298315 | G55: =IF(('Combined District Data'!H208>0.5)<>('Combined District Data'!H209>0.5),1,0)+IF(('Combined District Data'!H209>0.5)<>('Combined District Data'!H210>0.5),1,0)+IF(('Combined District Data'!H210>0.5)<>('Combined District Data'!H211>0.5),1,0) -> 0 | H55: =IF(OR(G55>=1,E55<0.05),"Hard",IF(AND(E55>=0.15,F55<0.05),"Easy","Medium")) -> Easy
A56: Roseto | B56: Northampton | C56: Actual | D56: =AVERAGE('Combined District Data'!H212:H215) -> 0.38137679 | E56: =AVERAGE(ABS('Combined District Data'!H212-0.5),ABS('Combined District Data'!H213-0.5),ABS('Combined District Data'!H214-0.5),ABS('Combined District Data'!H215-0.5)) -> 0.11862321 | F56: =STDEV('Combined District Data'!H212:H215) -> 0.02113813 | G56: =IF(('Combined District Data'!H212>0.5)<>('Combined District Data'!H213>0.5),1,0)+IF(('Combined District Data'!H213>0.5)<>('Combined District Data'!H214>0.5),1,0)+IF(('Combined District Data'!H214>0.5)<>('Combined District Data'!H215>0.5),1,0) -> 0 | H56: =IF(OR(G56>=1,E56<0.05),"Hard",IF(AND(E56>=0.15,F56<0.05),"Easy","Medium")) -> Medium
A57: Stockertown | B57: Northampton | C57: Actual | D57: =AVERAGE('Combined District Data'!H216:H219) -> 0.41500101 | E57: =AVERAGE(ABS('Combined District Data'!H216-0.5),ABS('Combined District Data'!H217-0.5),ABS('Combined District Data'!H218-0.5),ABS('Combined District Data'!H219-0.5)) -> 0.084998989 | F57: =STDEV('Combined District Data'!H216:H219) -> 0.013342836 | G57: =IF(('Combined District Data'!H216>0.5)<>('Combined District Data'!H217>0.5),1,0)+IF(('Combined District Data'!H217>0.5)<>('Combined District Data'!H218>0.5),1,0)+IF(('Combined District Data'!H218>0.5)<>('Combined District Data'!H219>0.5),1,0) -> 0 | H57: =IF(OR(G57>=1,E57<0.05),"Hard",IF(AND(E57>=0.15,F57<0.05),"Easy","Medium")) -> Medium
A58: Tatamy | B58: Northampton | C58: Actual | D58: =AVERAGE('Combined District Data'!H220:H223) -> 0.419622 | E58: =AVERAGE(ABS('Combined District Data'!H220-0.5),ABS('Combined District Data'!H221-0.5),ABS('Combined District Data'!H222-0.5),ABS('Combined District Data'!H223-0.5)) -> 0.080378001 | F58: =STDEV('Combined District Data'!H220:H223) -> 0.011633631 | G58: =IF(('Combined District Data'!H220>0.5)<>('Combined District Data'!H221>0.5),1,0)+IF(('Combined District Data'!H221>0.5)<>('Combined District Data'!H222>0.5),1,0)+IF(('Combined District Data'!H222>0.5)<>('Combined District Data'!H223>0.5),1,0) -> 0 | H58: =IF(OR(G58>=1,E58<0.05),"Hard",IF(AND(E58>=0.15,F58<0.05),"Easy","Medium")) -> Medium
A59: Upper Mount Bethel | B59: Northampton | C59: Actual | D59: =AVERAGE('Combined District Data'!H224:H227) -> 0.32900422 | E59: =AVERAGE(ABS('Combined District Data'!H224-0.5),ABS('Combined District Data'!H225-0.5),ABS('Combined District Data'!H226-0.5),ABS('Combined District Data'!H227-0.5)) -> 0.17099578 | F59: =STDEV('Combined District Data'!H224:H227) -> 0.019204892 | G59: =IF(('Combined District Data'!H224>0.5)<>('Combined District Data'!H225>0.5),1,0)+IF(('Combined District Data'!H225>0.5)<>('Combined District Data'!H226>0.5),1,0)+IF(('Combined District Data'!H226>0.5)<>('Combined District Data'!H227>0.5),1,0) -> 0 | H59: =IF(OR(G59>=1,E59<0.05),"Hard",IF(AND(E59>=0.15,F59<0.05),"Easy","Medium")) -> Easy
A60: Upper Nazereth | B60: Northampton | C60: Actual | D60: =AVERAGE('Combined District Data'!H228:H231) -> 0.4814544 | E60: =AVERAGE(ABS('Combined District Data'!H228-0.5),ABS('Combined District Data'!H229-0.5),ABS('Combined District Data'!H230-0.5),ABS('Combined District Data'!H231-0.5)) -> 0.018545595 | F60: =STDEV('Combined District Data'!H228:H231) -> 0.013631259 | G60: =IF(('Combined District Data'!H228>0.5)<>('Combined District Data'!H229>0.5),1,0)+IF(('Combined District Data'!H229>0.5)<>('Combined District Data'!H230>0.5),1,0)+IF(('Combined District Data'!H230>0.5)<>('Combined District Data'!H231>0.5),1,0) -> 0 | H60: =IF(OR(G60>=1,E60<0.05),"Hard",IF(AND(E60>=0.15,F60<0.05),"Easy","Medium")) -> Hard
A61: Walnutport | B61: Northampton | C61: Actual | D61: =AVERAGE('Combined District Data'!H232:H235) -> 0.39957528 | E61: =AVERAGE(ABS('Combined District Data'!H232-0.5),ABS('Combined District Data'!H233-0.5),ABS('Combined District Data'!H234-0.5),ABS('Combined District Data'!H235-0.5)) -> 0.10042472 | F61: =STDEV('Combined District Data'!H232:H235) -> 0.016859696 | G61: =IF(('Combined District Data'!H232>0.5)<>('Combined District Data'!H233>0.5),1,0)+IF(('Combined District Data'!H233>0.5)<>('Combined District Data'!H234>0.5),1,0)+IF(('Combined District Data'!H234>0.5)<>('Combined District Data'!H235>0.5),1,0) -> 0 | H61: =IF(OR(G61>=1,E61<0.05),"Hard",IF(AND(E61>=0.15,F61<0.05),"Easy","Medium")) -> Medium
A62: Washington | B62: Northampton | C62: Actual | D62: =AVERAGE('Combined District Data'!H236:H239) -> 0.35214955 | E62: =AVERAGE(ABS('Combined District Data'!H236-0.5),ABS('Combined District Data'!H237-0.5),ABS('Combined District Data'!H238-0.5),ABS('Combined District Data'!H239-0.5)) -> 0.14785045 | F62: =STDEV('Combined District Data'!H236:H239) -> 0.019459739 | G62: =IF(('Combined District Data'!H236>0.5)<>('Combined District Data'!H237>0.5),1,0)+IF(('Combined District Data'!H237>0.5)<>('Combined District Data'!H238>0.5),1,0)+IF(('Combined District Data'!H238>0.5)<>('Combined District Data'!H239>0.5),1,0) -> 0 | H62: =IF(OR(G62>=1,E62<0.05),"Hard",IF(AND(E62>=0.15,F62<0.05),"Easy","Medium")) -> Medium
A63: West Easton | B63: Northampton | C63: Actual | D63: =AVERAGE('Combined District Data'!H240:H243) -> 0.47567466 | E63: =AVERAGE(ABS('Combined District Data'!H240-0.5),ABS('Combined District Data'!H241-0.5),ABS('Combined District Data'!H242-0.5),ABS('Combined District Data'!H243-0.5)) -> 0.031082098 | F63: =STDEV('Combined District Data'!H240:H243) -> 0.033036631 | G63: =IF(('Combined District Data'!H240>0.5)<>('Combined District Data'!H241>0.5),1,0)+IF(('Combined District Data'!H241>0.5)<>('Combined District Data'!H242>0.5),1,0)+IF(('Combined District Data'!H242>0.5)<>('Combined District Data'!H243>0.5),1,0) -> 1 | H63: =IF(OR(G63>=1,E63<0.05),"Hard",IF(AND(E63>=0.15,F63<0.05),"Easy","Medium")) -> Hard
A64: Williams Township | B64: Northampton | C64: Actual | D64: =AVERAGE('Combined District Data'!H244:H247) -> 0.43609052 | E64: =AVERAGE(ABS('Combined District Data'!H244-0.5),ABS('Combined District Data'!H245-0.5),ABS('Combined District Data'!H246-0.5),ABS('Combined District Data'!H247-0.5)) -> 0.06390948 | F64: =STDEV('Combined District Data'!H244:H247) -> 0.0076561206 | G64: =IF(('Combined District Data'!H244>0.5)<>('Combined District Data'!H245>0.5),1,0)+IF(('Combined District Data'!H245>0.5)<>('Combined District Data'!H246>0.5),1,0)+IF(('Combined District Data'!H246>0.5)<>('Combined District Data'!H247>0.5),1,0) -> 0 | H64: =IF(OR(G64>=1,E64<0.05),"Hard",IF(AND(E64>=0.15,F64<0.05),"Easy","Medium")) -> Medium
A65: Wilson | B65: Northampton | C65: Actual | D65: =AVERAGE('Combined District Data'!H248:H251) -> 0.5693943 | E65: =AVERAGE(ABS('Combined District Data'!H248-0.5),ABS('Combined District Data'!H249-0.5),ABS('Combined District Data'!H250-0.5),ABS('Combined District Data'!H251-0.5)) -> 0.069394302 | F65: =STDEV('Combined District Data'!H248:H251) -> 0.019414269 | G65: =IF(('Combined District Data'!H248>0.5)<>('Combined District Data'!H249>0.5),1,0)+IF(('Combined District Data'!H249>0.5)<>('Combined District Data'!H250>0.5),1,0)+IF(('Combined District Data'!H250>0.5)<>('Combined District Data'!H251>0.5),1,0) -> 0 | H65: =IF(OR(G65>=1,E65<0.05),"Hard",IF(AND(E65>=0.15,F65<0.05),"Easy","Medium")) -> Medium
A66: Wind Gap | B66: Northampton | C66: Actual | D66: =AVERAGE('Combined District Data'!H252:H255) -> 0.42609641 | E66: =AVERAGE(ABS('Combined District Data'!H252-0.5),ABS('Combined District Data'!H253-0.5),ABS('Combined District Data'!H254-0.5),ABS('Combined District Data'!H255-0.5)) -> 0.073903588 | F66: =STDEV('Combined District Data'!H252:H255) -> 0.025601249 | G66: =IF(('Combined District Data'!H252>0.5)<>('Combined District Data'!H253>0.5),1,0)+IF(('Combined District Data'!H253>0.5)<>('Combined District Data'!H254>0.5),1,0)+IF(('Combined District Data'!H254>0.5)<>('Combined District Data'!H255>0.5),1,0) -> 0 | H66: =IF(OR(G66>=1,E66<0.05),"Hard",IF(AND(E66>=0.15,F66<0.05),"Easy","Medium")) -> Medium
A67: Banks Township | B67: Carbon | C67: Estimated | D67: =AVERAGE('Combined District Data'!H256:H259) -> 0.52853531 | E67: =AVERAGE(ABS('Combined District Data'!H256-0.5),ABS('Combined District Data'!H257-0.5),ABS('Combined District Data'!H258-0.5),ABS('Combined District Data'!H259-0.5)) -> 0.028535311 | F67: =STDEV('Combined District Data'!H256:H259) -> 0.013331496 | G67: =IF(('Combined District Data'!H256>0.5)<>('Combined District Data'!H257>0.5),1,0)+IF(('Combined District Data'!H257>0.5)<>('Combined District Data'!H258>0.5),1,0)+IF(('Combined District Data'!H258>0.5)<>('Combined District Data'!H259>0.5),1,0) -> 0 | H67: =IF(OR(G67>=1,E67<0.05),"Hard",IF(AND(E67>=0.15,F67<0.05),"Easy","Medium")) -> Hard
A68: Beaver Meadows Borough | B68: Carbon | C68: Estimated | D68: =AVERAGE('Combined District Data'!H260:H263) -> 0.38032505 | E68: =AVERAGE(ABS('Combined District Data'!H260-0.5),ABS('Combined District Data'!H261-0.5),ABS('Combined District Data'!H262-0.5),ABS('Combined District Data'!H263-0.5)) -> 0.11967495 | F68: =STDEV('Combined District Data'!H260:H263) -> 0.014222041 | G68: =IF(('Combined District Data'!H260>0.5)<>('Combined District Data'!H261>0.5),1,0)+IF(('Combined District Data'!H261>0.5)<>('Combined District Data'!H262>0.5),1,0)+IF(('Combined District Data'!H262>0.5)<>('Combined District Data'!H263>0.5),1,0) -> 0 | H68: =IF(OR(G68>=1,E68<0.05),"Hard",IF(AND(E68>=0.15,F68<0.05),"Easy","Medium")) -> Medium
A69: Bowmanstown Borough | B69: Carbon | C69: Estimated | D69: =AVERAGE('Combined District Data'!H264:H267) -> 0.36229226 | E69: =AVERAGE(ABS('Combined District Data'!H264-0.5),ABS('Combined District Data'!H265-0.5),ABS('Combined District Data'!H266-0.5),ABS('Combined District Data'!H267-0.5)) -> 0.13770774 | F69: =STDEV('Combined District Data'!H264:H267) -> 0.013709756 | G69: =IF(('Combined District Data'!H264>0.5)<>('Combined District Data'!H265>0.5),1,0)+IF(('Combined District Data'!H265>0.5)<>('Combined District Data'!H266>0.5),1,0)+IF(('Combined District Data'!H266>0.5)<>('Combined District Data'!H267>0.5),1,0) -> 0 | H69: =IF(OR(G69>=1,E69<0.05),"Hard",IF(AND(E69>=0.15,F69<0.05),"Easy","Medium")) -> Medium
A70: East Penn Township | B70: Carbon | C70: Estimated | D70: =AVERAGE('Combined District Data'!H268:H271) -> 0.31917228 | E70: =AVERAGE(ABS('Combined District Data'!H268-0.5),ABS('Combined District Data'!H269-0.5),ABS('Combined District Data'!H270-0.5),ABS('Combined District Data'!H271-0.5)) -> 0.18082772 | F70: =STDEV('Combined District Data'!H268:H271) -> 0.015187103 | G70: =IF(('Combined District Data'!H268>0.5)<>('Combined District Data'!H269>0.5),1,0)+IF(('Combined District Data'!H269>0.5)<>('Combined District Data'!H270>0.5),1,0)+IF(('Combined District Data'!H270>0.5)<>('Combined District Data'!H271>0.5),1,0) -> 0 | H70: =IF(OR(G70>=1,E70<0.05),"Hard",IF(AND(E70>=0.15,F70<0.05),"Easy","Medium")) -> Easy
A71: East Side Borough | B71: Carbon | C71: Estimated | D71: =AVERAGE('Combined District Data'!H272:H275) -> 0.41030297 | E71: =AVERAGE(ABS('Combined District Data'!H272-0.5),ABS('Combined District Data'!H273-0.5),ABS('Combined District Data'!H274-0.5),ABS('Combined District Data'!H275-0.5)) -> 0.089697026 | F71: =STDEV('Combined District Data'!H272:H275) -> 0.015969498 | G71: =IF(('Combined District Data'!H272>0.5)<>('Combined District Data'!H273>0.5),1,0)+IF(('Combined District Data'!H273>0.5)<>('Combined District Data'!H274>0.5),1,0)+IF(('Combined District Data'!H274>0.5)<>('Combined District Data'!H275>0.5),1,0) -> 0 | H71: =IF(OR(G71>=1,E71<0.05),"Hard",IF(AND(E71>=0.15,F71<0.05),"Easy","Medium")) -> Medium
A72: Franklin Township | B72: Carbon | C72: Estimated | D72: =AVERAGE('Combined District Data'!H276:H279) -> 0.32651974 | E72: =AVERAGE(ABS('Combined District Data'!H276-0.5),ABS('Combined District Data'!H277-0.5),ABS('Combined District Data'!H278-0.5),ABS('Combined District Data'!H279-0.5)) -> 0.17348026 | F72: =STDEV('Combined District Data'!H276:H279) -> 0.015115588 | G72: =IF(('Combined District Data'!H276>0.5)<>('Combined District Data'!H277>0.5),1,0)+IF(('Combined District Data'!H277>0.5)<>('Combined District Data'!H278>0.5),1,0)+IF(('Combined District Data'!H278>0.5)<>('Combined District Data'!H279>0.5),1,0) -> 0 | H72: =IF(OR(G72>=1,E72<0.05),"Hard",IF(AND(E72>=0.15,F72<0.05),"Easy","Medium")) -> Easy
A73: Jim Thorpe Borough | B73: Carbon | C73: Estimated | D73: =AVERAGE('Combined District Data'!H280:H283) -> 0.47474496 | E73: =AVERAGE(ABS('Combined District Data'!H280-0.5),ABS('Combined District Data'!H281-0.5),ABS('Combined District Data'!H282-0.5),ABS('Combined District Data'!H283-0.5)) -> 0.025255043 | F73: =STDEV('Combined District Data'!H280:H283) -> 0.013655443 | G73: =IF(('Combined District Data'!H280>0.5)<>('Combined District Data'!H281>0.5),1,0)+IF(('Combined District Data'!H281>0.5)<>('Combined District Data'!H282>0.5),1,0)+IF(('Combined District Data'!H282>0.5)<>('Combined District Data'!H283>0.5),1,0) -> 0 | H73: =IF(OR(G73>=1,E73<0.05),"Hard",IF(AND(E73>=0.15,F73<0.05),"Easy","Medium")) -> Hard
A74: Kidder Township | B74: Carbon | C74: Estimated | D74: =AVERAGE('Combined District Data'!H284:H287) -> 0.35952623 | E74: =AVERAGE(ABS('Combined District Data'!H284-0.5),ABS('Combined District Data'!H285-0.5),ABS('Combined District Data'!H286-0.5),ABS('Combined District Data'!H287-0.5)) -> 0.14047377 | F74: =STDEV('Combined District Data'!H284:H287) -> 0.014672452 | G74: =IF(('Combined District Data'!H284>0.5)<>('Combined District Data'!H285>0.5),1,0)+IF(('Combined District Data'!H285>0.5)<>('Combined District Data'!H286>0.5),1,0)+IF(('Combined District Data'!H286>0.5)<>('Combined District Data'!H287>0.5),1,0) -> 0 | H74: =IF(OR(G74>=1,E74<0.05),"Hard",IF(AND(E74>=0.15,F74<0.05),"Easy","Medium")) -> Medium
A75: Lansford Borough | B75: Carbon | C75: Estimated | D75: =AVERAGE('Combined District Data'!H288:H291) -> 0.48180103 | E75: =AVERAGE(ABS('Combined District Data'!H288-0.5),ABS('Combined District Data'!H289-0.5),ABS('Combined District Data'!H290-0.5),ABS('Combined District Data'!H291-0.5)) -> 0.018198968 | F75: =STDEV('Combined District Data'!H288:H291) -> 0.013807351 | G75: =IF(('Combined District Data'!H288>0.5)<>('Combined District Data'!H289>0.5),1,0)+IF(('Combined District Data'!H289>0.5)<>('Combined District Data'!H290>0.5),1,0)+IF(('Combined District Data'!H290>0.5)<>('Combined District Data'!H291>0.5),1,0) -> 0 | H75: =IF(OR(G75>=1,E75<0.05),"Hard",IF(AND(E75>=0.15,F75<0.05),"Easy","Medium")) -> Hard
A76: Lausanne Township | B76: Carbon | C76: Estimated | D76: =AVERAGE('Combined District Data'!H292:H295) -> 0.30179495 | E76: =AVERAGE(ABS('Combined District Data'!H292-0.5),ABS('Combined District Data'!H293-0.5),ABS('Combined District Data'!H294-0.5),ABS('Combined District Data'!H295-0.5)) -> 0.19820505 | F76: =STDEV('Combined District Data'!H292:H295) -> 0.015586616 | G76: =IF(('Combined District Data'!H292>0.5)<>('Combined District Data'!H293>0.5),1,0)+IF(('Combined District Data'!H293>0.5)<>('Combined District Data'!H294>0.5),1,0)+IF(('Combined District Data'!H294>0.5)<>('Combined District Data'!H295>0.5),1,0) -> 0 | H76: =IF(OR(G76>=1,E76<0.05),"Hard",IF(AND(E76>=0.15,F76<0.05),"Easy","Medium")) -> Easy
A77: Lehigh Township | B77: Carbon | C77: Estimated | D77: =AVERAGE('Combined District Data'!H296:H299) -> 0.22271712 | E77: =AVERAGE(ABS('Combined District Data'!H296-0.5),ABS('Combined District Data'!H297-0.5),ABS('Combined District Data'!H298-0.5),ABS('Combined District Data'!H299-0.5)) -> 0.27728288 | F77: =STDEV('Combined District Data'!H296:H299) -> 0.016888679 | G77: =IF(('Combined District Data'!H296>0.5)<>('Combined District Data'!H297>0.5),1,0)+IF(('Combined District Data'!H297>0.5)<>('Combined District Data'!H298>0.5),1,0)+IF(('Combined District Data'!H298>0.5)<>('Combined District Data'!H299>0.5),1,0) -> 0 | H77: =IF(OR(G77>=1,E77<0.05),"Hard",IF(AND(E77>=0.15,F77<0.05),"Easy","Medium")) -> Easy
A78: Lehighton Borough | B78: Carbon | C78: Estimated | D78: =AVERAGE('Combined District Data'!H300:H303) -> 0.422348 | E78: =AVERAGE(ABS('Combined District Data'!H300-0.5),ABS('Combined District Data'!H301-0.5),ABS('Combined District Data'!H302-0.5),ABS('Combined District Data'!H303-0.5)) -> 0.077651998 | F78: =STDEV('Combined District Data'!H300:H303) -> 0.013957009 | G78: =IF(('Combined District Data'!H300>0.5)<>('Combined District Data'!H301>0.5),1,0)+IF(('Combined District Data'!H301>0.5)<>('Combined District Data'!H302>0.5),1,0)+IF(('Combined District Data'!H302>0.5)<>('Combined District Data'!H303>0.5),1,0) -> 0 | H78: =IF(OR(G78>=1,E78<0.05),"Hard",IF(AND(E78>=0.15,F78<0.05),"Easy","Medium")) -> Medium
A79: Lower Towamensing Twp. | B79: Carbon | C79: Estimated | D79: =AVERAGE('Combined District Data'!H304:H307) -> 0.34159224 | E79: =AVERAGE(ABS('Combined District Data'!H304-0.5),ABS('Combined District Data'!H305-0.5),ABS('Combined District Data'!H306-0.5),ABS('Combined District Data'!H307-0.5)) -> 0.15840776 | F79: =STDEV('Combined District Data'!H304:H307) -> 0.015017798 | G79: =IF(('Combined District Data'!H304>0.5)<>('Combined District Data'!H305>0.5),1,0)+IF(('Combined District Data'!H305>0.5)<>('Combined District Data'!H306>0.5),1,0)+IF(('Combined District Data'!H306>0.5)<>('Combined District Data'!H307>0.5),1,0) -> 0 | H79: =IF(OR(G79>=1,E79<0.05),"Hard",IF(AND(E79>=0.15,F79<0.05),"Easy","Medium")) -> Easy
A80: Mahoning Township | B80: Carbon | C80: Estimated | D80: =AVERAGE('Combined District Data'!H308:H311) -> 0.32281781 | E80: =AVERAGE(ABS('Combined District Data'!H308-0.5),ABS('Combined District Data'!H309-0.5),ABS('Combined District Data'!H310-0.5),ABS('Combined District Data'!H311-0.5)) -> 0.17718219 | F80: =STDEV('Combined District Data'!H308:H311) -> 0.015271252 | G80: =IF(('Combined District Data'!H308>0.5)<>('Combined District Data'!H309>0.5),1,0)+IF(('Combined District Data'!H309>0.5)<>('Combined District Data'!H310>0.5),1,0)+IF(('Combined District Data'!H310>0.5)<>('Combined District Data'!H311>0.5),1,0) -> 0 | H80: =IF(OR(G80>=1,E80<0.05),"Hard",IF(AND(E80>=0.15,F80<0.05),"Easy","Medium")) -> Easy
A81: Nesquehoning Borough | B81: Carbon | C81: Estimated | D81: =AVERAGE('Combined District Data'!H312:H315) -> 0.45334584 | E81: =AVERAGE(ABS('Combined District Data'!H312-0.5),ABS('Combined District Data'!H313-0.5),ABS('Combined District Data'!H314-0.5),ABS('Combined District Data'!H315-0.5)) -> 0.046654162 | F81: =STDEV('Combined District Data'!H312:H315) -> 0.013913966 | G81: =IF(('Combined District Data'!H312>0.5)<>('Combined District Data'!H313>0.5),1,0)+IF(('Combined District Data'!H313>0.5)<>('Combined District Data'!H314>0.5),1,0)+IF(('Combined District Data'!H314>0.5)<>('Combined District Data'!H315>0.5),1,0) -> 0 | H81: =IF(OR(G81>=1,E81<0.05),"Hard",IF(AND(E81>=0.15,F81<0.05),"Easy","Medium")) -> Hard
A82: Packer Township | B82: Carbon | C82: Estimated | D82: =AVERAGE('Combined District Data'!H316:H319) -> 0.23303432 | E82: =AVERAGE(ABS('Combined District Data'!H316-0.5),ABS('Combined District Data'!H317-0.5),ABS('Combined District Data'!H318-0.5),ABS('Combined District Data'!H319-0.5)) -> 0.26696568 | F82: =STDEV('Combined District Data'!H316:H319) -> 0.01679543 | G82: =IF(('Combined District Data'!H316>0.5)<>('Combined District Data'!H317>0.5),1,0)+IF(('Combined District Data'!H317>0.5)<>('Combined District Data'!H318>0.5),1,0)+IF(('Combined District Data'!H318>0.5)<>('Combined District Data'!H319>0.5),1,0) -> 0 | H82: =IF(OR(G82>=1,E82<0.05),"Hard",IF(AND(E82>=0.15,F82<0.05),"Easy","Medium")) -> Easy
A83: Palmerton Borough | B83: Carbon | C83: Estimated | D83: =AVERAGE('Combined District Data'!H320:H323) -> 0.41814895 | E83: =AVERAGE(ABS('Combined District Data'!H320-0.5),ABS('Combined District Data'!H321-0.5),ABS('Combined District Data'!H322-0.5),ABS('Combined District Data'!H323-0.5)) -> 0.081851049 | F83: =STDEV('Combined District Data'!H320:H323) -> 0.014141343 | G83: =IF(('Combined District Data'!H320>0.5)<>('Combined District Data'!H321>0.5),1,0)+IF(('Combined District Data'!H321>0.5)<>('Combined District Data'!H322>0.5),1,0)+IF(('Combined District Data'!H322>0.5)<>('Combined District Data'!H323>0.5),1,0) -> 0 | H83: =IF(OR(G83>=1,E83<0.05),"Hard",IF(AND(E83>=0.15,F83<0.05),"Easy","Medium")) -> Medium
A84: Parryville Borough | B84: Carbon | C84: Estimated | D84: =AVERAGE('Combined District Data'!H324:H327) -> 0.38261196 | E84: =AVERAGE(ABS('Combined District Data'!H324-0.5),ABS('Combined District Data'!H325-0.5),ABS('Combined District Data'!H326-0.5),ABS('Combined District Data'!H327-0.5)) -> 0.11738804 | F84: =STDEV('Combined District Data'!H324:H327) -> 0.014423092 | G84: =IF(('Combined District Data'!H324>0.5)<>('Combined District Data'!H325>0.5),1,0)+IF(('Combined District Data'!H325>0.5)<>('Combined District Data'!H326>0.5),1,0)+IF(('Combined District Data'!H326>0.5)<>('Combined District Data'!H327>0.5),1,0) -> 0 | H84: =IF(OR(G84>=1,E84<0.05),"Hard",IF(AND(E84>=0.15,F84<0.05),"Easy","Medium")) -> Medium
A85: Penn Forest Township | B85: Carbon | C85: Estimated | D85: =AVERAGE('Combined District Data'!H328:H331) -> 0.39899825 | E85: =AVERAGE(ABS('Combined District Data'!H328-0.5),ABS('Combined District Data'!H329-0.5),ABS('Combined District Data'!H330-0.5),ABS('Combined District Data'!H331-0.5)) -> 0.10100175 | F85: =STDEV('Combined District Data'!H328:H331) -> 0.014109968 | G85: =IF(('Combined District Data'!H328>0.5)<>('Combined District Data'!H329>0.5),1,0)+IF(('Combined District Data'!H329>0.5)<>('Combined District Data'!H330>0.5),1,0)+IF(('Combined District Data'!H330>0.5)<>('Combined District Data'!H331>0.5),1,0) -> 0 | H85: =IF(OR(G85>=1,E85<0.05),"Hard",IF(AND(E85>=0.15,F85<0.05),"Easy","Medium")) -> Medium
A86: Summit Hill Borough | B86: Carbon | C86: Estimated | D86: =AVERAGE('Combined District Data'!H332:H335) -> 0.49181887 | E86: =AVERAGE(ABS('Combined District Data'!H332-0.5),ABS('Combined District Data'!H333-0.5),ABS('Combined District Data'!H334-0.5),ABS('Combined District Data'!H335-0.5)) -> 0.011694211 | F86: =STDEV('Combined District Data'!H332:H335) -> 0.013515385 | G86: =IF(('Combined District Data'!H332>0.5)<>('Combined District Data'!H333>0.5),1,0)+IF(('Combined District Data'!H333>0.5)<>('Combined District Data'!H334>0.5),1,0)+IF(('Combined District Data'!H334>0.5)<>('Combined District Data'!H335>0.5),1,0) -> 3 | H86: =IF(OR(G86>=1,E86<0.05),"Hard",IF(AND(E86>=0.15,F86<0.05),"Easy","Medium")) -> Hard
A87: Towamensing Township | B87: Carbon | C87: Estimated | D87: =AVERAGE('Combined District Data'!H336:H339) -> 0.32973935 | E87: =AVERAGE(ABS('Combined District Data'!H336-0.5),ABS('Combined District Data'!H337-0.5),ABS('Combined District Data'!H338-0.5),ABS('Combined District Data'!H339-0.5)) -> 0.17026065 | F87: =STDEV('Combined District Data'!H336:H339) -> 0.015186511 | G87: =IF(('Combined District Data'!H336>0.5)<>('Combined District Data'!H337>0.5),1,0)+IF(('Combined District Data'!H337>0.5)<>('Combined District Data'!H338>0.5),1,0)+IF(('Combined District Data'!H338>0.5)<>('Combined District Data'!H339>0.5),1,0) -> 0 | H87: =IF(OR(G87>=1,E87<0.05),"Hard",IF(AND(E87>=0.15,F87<0.05),"Easy","Medium")) -> Easy
A88: Weatherly Borough | B88: Carbon | C88: Estimated | D88: =AVERAGE('Combined District Data'!H340:H343) -> 0.34803903 | E88: =AVERAGE(ABS('Combined District Data'!H340-0.5),ABS('Combined District Data'!H341-0.5),ABS('Combined District Data'!H342-0.5),ABS('Combined District Data'!H343-0.5)) -> 0.15196097 | F88: =STDEV('Combined District Data'!H340:H343) -> 0.01501898 | G88: =IF(('Combined District Data'!H340>0.5)<>('Combined District Data'!H341>0.5),1,0)+IF(('Combined District Data'!H341>0.5)<>('Combined District Data'!H342>0.5),1,0)+IF(('Combined District Data'!H342>0.5)<>('Combined District Data'!H343>0.5),1,0) -> 0 | H88: =IF(OR(G88>=1,E88<0.05),"Hard",IF(AND(E88>=0.15,F88<0.05),"Easy","Medium")) -> Easy
A89: Weissport Borough | B89: Carbon | C89: Estimated | D89: =AVERAGE('Combined District Data'!H344:H347) -> 0.40983724 | E89: =AVERAGE(ABS('Combined District Data'!H344-0.5),ABS('Combined District Data'!H345-0.5),ABS('Combined District Data'!H346-0.5),ABS('Combined District Data'!H347-0.5)) -> 0.090162763 | F89: =STDEV('Combined District Data'!H344:H347) -> 0.011745829 | G89: =IF(('Combined District Data'!H344>0.5)<>('Combined District Data'!H345>0.5),1,0)+IF(('Combined District Data'!H345>0.5)<>('Combined District Data'!H346>0.5),1,0)+IF(('Combined District Data'!H346>0.5)<>('Combined District Data'!H347>0.5),1,0) -> 0 | H89: =IF(OR(G89>=1,E89<0.05),"Hard",IF(AND(E89>=0.15,F89<0.05),"Easy","Medium")) -> Medium

Sheet Magic Municipality
A1: Bellwether Search (86 Municipalities)
A2: District-wide result now computed directly from the Combined District Data (actual + Carbon estimate), not an external reference. Match = municipality's own winner equals the combined-district winner that year.
A4: District-wide result by year
A5: Year | B5: District Dem Votes | C5: District Rep Votes | D5: District Dem Share | E5: District Winner
A6: 2018 | B6: =SUMIF('Combined District Data'!$A:$A,A6,'Combined District Data'!$E:$E) -> 136384 | C6: =SUMIF('Combined District Data'!$A:$A,A6,'Combined District Data'!$F:$F) -> 116835 | D6: =B6/(B6+C6) -> 0.53860097 | E6: =IF(D6>0.5,"D","R") -> D
A7: 2020 | B7: =SUMIF('Combined District Data'!$A:$A,A7,'Combined District Data'!$E:$E) -> 190062 | C7: =SUMIF('Combined District Data'!$A:$A,A7,'Combined District Data'!$F:$F) -> 186030 | D7: =B7/(B7+C7) -> 0.50536039 | E7: =IF(D7>0.5,"D","R") -> D
A8: 2022 | B8: =SUMIF('Combined District Data'!$A:$A,A8,'Combined District Data'!$E:$E) -> 149868 | C8: =SUMIF('Combined District Data'!$A:$A,A8,'Combined District Data'!$F:$F) -> 139318 | D8: =B8/(B8+C8) -> 0.51824086 | E8: =IF(D8>0.5,"D","R") -> D
A9: 2024 | B9: =SUMIF('Combined District Data'!$A:$A,A9,'Combined District Data'!$E:$E) -> 198281 | C9: =SUMIF('Combined District Data'!$A:$A,A9,'Combined District Data'!$F:$F) -> 196459 | D9: =B9/(B9+C9) -> 0.50230785 | E9: =IF(D9>0.5,"D","R") -> D
A12: Per-municipality bellwether test
A13: Municipality | B13: County | C13: Source | D13: Match 2018 | E13: Match 2020 | F13: Match 2022 | G13: Match 2024 | H13: Total Matches (/4) | I13: Avg Point Gap vs District | J13: Magic Municipality? | K13: (helper)
A14: Alburtis | B14: Lehigh | C14: Actual | D14: =IF(IF('Combined District Data'!H4>0.5,"D","R")=$E$6,1,0) -> 1 | E14: =IF(IF('Combined District Data'!H5>0.5,"D","R")=$E$7,1,0) -> 0 | F14: =IF(IF('Combined District Data'!H6>0.5,"D","R")=$E$8,1,0) -> 0 | G14: =IF(IF('Combined District Data'!H7>0.5,"D","R")=$E$9,1,0) -> 0 | H14: =SUM(D14:G14) -> 1 | I14: =AVERAGE(ABS('Combined District Data'!H4-$D$6),ABS('Combined District Data'!H5-$D$7),ABS('Combined District Data'!H6-$D$8),ABS('Combined District Data'!H7-$D$9)) -> 0.040874821 | J14: =IF(AND(H14=4,I14=MIN(K14:K99)),"<< MAGIC MUNICIPALITY","") | K14: =IF(H14=4,I14,"")
A15: Allentown | B15: Lehigh | C15: Actual | D15: =IF(IF('Combined District Data'!H8>0.5,"D","R")=$E$6,1,0) -> 1 | E15: =IF(IF('Combined District Data'!H9>0.5,"D","R")=$E$7,1,0) -> 1 | F15: =IF(IF('Combined District Data'!H10>0.5,"D","R")=$E$8,1,0) -> 1 | G15: =IF(IF('Combined District Data'!H11>0.5,"D","R")=$E$9,1,0) -> 1 | H15: =SUM(D15:G15) -> 4 | I15: =AVERAGE(ABS('Combined District Data'!H8-$D$6),ABS('Combined District Data'!H9-$D$7),ABS('Combined District Data'!H10-$D$8),ABS('Combined District Data'!H11-$D$9)) -> 0.16413891 | J15: =IF(AND(H15=4,I15=MIN(K14:K99)),"<< MAGIC MUNICIPALITY","") | K15: =IF(H15=4,I15,"") -> 0.16413891
A16: Bethlehem | B16: Lehigh | C16: Actual | D16: =IF(IF('Combined District Data'!H12>0.5,"D","R")=$E$6,1,0) -> 1 | E16: =IF(IF('Combined District Data'!H13>0.5,"D","R")=$E$7,1,0) -> 1 | F16: =IF(IF('Combined District Data'!H14>0.5,"D","R")=$E$8,1,0) -> 1 | G16: =IF(IF('Combined District Data'!H15>0.5,"D","R")=$E$9,1,0) -> 1 | H16: =SUM(D16:G16) -> 4 | I16: =AVERAGE(ABS('Combined District Data'!H12-$D$6),ABS('Combined District Data'!H13-$D$7),ABS('Combined District Data'!H14-$D$8),ABS('Combined District Data'!H15-$D$9)) -> 0.12346151 | J16: =IF(AND(H16=4,I16=MIN(K14:K99)),"<< MAGIC MUNICIPALITY","") | K16: =IF(H16=4,I16,"") -> 0.12346151
A17: Catasauqua | B17: Lehigh | C17: Actual | D17: =IF(IF('Combined District Data'!H16>0.5,"D","R")=$E$6,1,0) -> 1 | E17: =IF(IF('Combined District Data'!H17>0.5,"D","R")=$E$7,1,0) -> 1 | F17: =IF(IF('Combined District Data'!H18>0.5,"D","R")=$E$8,1,0) -> 1 | G17: =IF(IF('Combined District Data'!H19>0.5,"D","R")=$E$9,1,0) -> 1 | H17: =SUM(D17:G17) -> 4 | I17: =AVERAGE(ABS('Combined District Data'!H16-$D$6),ABS('Combined District Data'!H17-$D$7),ABS('Combined District Data'!H18-$D$8),ABS('Combined District Data'!H19-$D$9)) -> 0.012656062 | J17: =IF(AND(H17=4,I17=MIN(K14:K99)),"<< MAGIC MUNICIPALITY","") | K17: =IF(H17=4,I17,"") -> 0.012656062
A18: Coopersburg | B18: Lehigh | C18: Actual | D18: =IF(IF('Combined District Data'!H20>0.5,"D","R")=$E$6,1,0) -> 1 | E18: =IF(IF('Combined District Data'!H21>0.5,"D","R")=$E$7,1,0) -> 0 | F18: =IF(IF('Combined District Data'!H22>0.5,"D","R")=$E$8,1,0) -> 1 | G18: =IF(IF('Combined District Data'!H23>0.5,"D","R")=$E$9,1,0) -> 0 | H18: =SUM(D18:G18) -> 2 | I18: =AVERAGE(ABS('Combined District Data'!H20-$D$6),ABS('Combined District Data'!H21-$D$7),ABS('Combined District Data'!H22-$D$8),ABS('Combined District Data'!H23-$D$9)) -> 0.024035622 | J18: =IF(AND(H18=4,I18=MIN(K14:K99)),"<< MAGIC MUNICIPALITY","") | K18: =IF(H18=4,I18,"")
A19: Coplay | B19: Lehigh | C19: Actual | D19: =IF(IF('Combined District Data'!H24>0.5,"D","R")=$E$6,1,0) -> 1 | E19: =IF(IF('Combined District Data'!H25>0.5,"D","R")=$E$7,1,0) -> 1 | F19: =IF(IF('Combined District Data'!H26>0.5,"D","R")=$E$8,1,0) -> 1 | G19: =IF(IF('Combined District Data'!H27>0.5,"D","R")=$E$9,1,0) -> 1 | H19: =SUM(D19:G19) -> 4 | I19: =AVERAGE(ABS('Combined District Data'!H24-$D$6),ABS('Combined District Data'!H25-$D$7),ABS('Combined District Data'!H26-$D$8),ABS('Combined District Data'!H27-$D$9)) -> 0.0053019358 | J19: =IF(AND(H19=4,I19=MIN(K14:K99)),"<< MAGIC MUNICIPALITY","") -> << MAGIC MUNICIPALITY | K19: =IF(H19=4,I19,"") -> 0.0053019358
A20: Emmaus | B20: Lehigh | C20: Actual | D20: =IF(IF('Combined District Data'!H28>0.5,"D","R")=$E$6,1,0) -> 1 | E20: =IF(IF('Combined District Data'!H29>0.5,"D","R")=$E$7,1,0) -> 1 | F20: =IF(IF('Combined District Data'!H30>0.5,"D","R")=$E$8,1,0) -> 1 | G20: =IF(IF('Combined District Data'!H31>0.5,"D","R")=$E$9,1,0) -> 1 | H20: =SUM(D20:G20) -> 4 | I20: =AVERAGE(ABS('Combined District Data'!H28-$D$6),ABS('Combined District Data'!H29-$D$7),ABS('Combined District Data'!H30-$D$8),ABS('Combined District Data'!H31-$D$9)) -> 0.023202226 | J20: =IF(AND(H20=4,I20=MIN(K14:K99)),"<< MAGIC MUNICIPALITY","") | K20: =IF(H20=4,I20,"") -> 0.023202226
A21: Fountain Hill | B21: Lehigh | C21: Actual | D21: =IF(IF('Combined District Data'!H32>0.5,"D","R")=$E$6,1,0) -> 1 | E21: =IF(IF('Combined District Data'!H33>0.5,"D","R")=$E$7,1,0) -> 1 | F21: =IF(IF('Combined District Data'!H34>0.5,"D","R")=$E$8,1,0) -> 1 | G21: =IF(IF('Combined District Data'!H35>0.5,"D","R")=$E$9,1,0) -> 1 | H21: =SUM(D21:G21) -> 4 | I21: =AVERAGE(ABS('Combined District Data'!H32-$D$6),ABS('Combined District Data'!H33-$D$7),ABS('Combined District Data'!H34-$D$8),ABS('Combined District Data'!H35-$D$9)) -> 0.15084226 | J21: =IF(AND(H21=4,I21=MIN(K14:K99)),"<< MAGIC MUNICIPALITY","") | K21: =IF(H21=4,I21,"") -> 0.15084226
A22: Hanover | B22: Lehigh | C22: Actual | D22: =IF(IF('Combined District Data'!H36>0.5,"D","R")=$E$6,1,0) -> 1 | E22: =IF(IF('Combined District Data'!H37>0.5,"D","R")=$E$7,1,0) -> 1 | F22: =IF(IF('Combined District Data'!H38>0.5,"D","R")=$E$8,1,0) -> 1 | G22: =IF(IF('Combined District Data'!H39>0.5,"D","R")=$E$9,1,0) -> 1 | H22: =SUM(D22:G22) -> 4 | I22: =AVERAGE(ABS('Combined District Data'!H36-$D$6),ABS('Combined District Data'!H37-$D$7),ABS('Combined District Data'!H38-$D$8),ABS('Combined District Data'!H39-$D$9)) -> 0.046698401 | J22: =IF(AND(H22=4,I22=MIN(K14:K99)),"<< MAGIC MUNICIPALITY","") | K22: =IF(H22=4,I22,"") -> 0.046698401
A23: Heidelberg | B23: Lehigh | C23: Actual | D23: =IF(IF('Combined District Data'!H40>0.5,"D","R")=$E$6,1,0) -> 0 | E23: =IF(IF('Combined District Data'!H41>0.5,"D","R")=$E$7,1,0) -> 0 | F23: =IF(IF('Combined District Data'!H42>0.5,"D","R")=$E$8,1,0) -> 0 | G23: =IF(IF('Combined District Data'!H43>0.5,"D","R")=$E$9,1,0) -> 0 | H23: =SUM(D23:G23) -> 0 | I23: =AVERAGE(ABS('Combined District Data'!H40-$D$6),ABS('Combined District Data'!H41-$D$7),ABS('Combined District Data'!H42-$D$8),ABS('Combined District Data'!H43-$D$9)) -> 0.19004048 | J23: =IF(AND(H23=4,I23=MIN(K14:K99)),"<< MAGIC MUNICIPALITY","") | K23: =IF(H23=4,I23,"")
A24: Lower Macungie | B24: Lehigh | C24: Actual | D24: =IF(IF('Combined District Data'!H44>0.5,"D","R")=$E$6,1,0) -> 0 | E24: =IF(IF('Combined District Data'!H45>0.5,"D","R")=$E$7,1,0) -> 0 | F24: =IF(IF('Combined District Data'!H46>0.5,"D","R")=$E$8,1,0) -> 1 | G24: =IF(IF('Combined District Data'!H47>0.5,"D","R")=$E$9,1,0) -> 0 | H24: =SUM(D24:G24) -> 1 | I24: =AVERAGE(ABS('Combined District Data'!H44-$D$6),ABS('Combined District Data'!H45-$D$7),ABS('Combined District Data'!H46-$D$8),ABS('Combined District Data'!H47-$D$9)) -> 0.015663112 | J24: =IF(AND(H24=4,I24=MIN(K14:K99)),"<< MAGIC MUNICIPALITY","") | K24: =IF(H24=4,I24,"")
A25: Lower Milford | B25: Lehigh | C25: Actual | D25: =IF(IF('Combined District Data'!H48>0.5,"D","R")=$E$6,1,0) -> 0 | E25: =IF(IF('Combined District Data'!H49>0.5,"D","R")=$E$7,1,0) -> 0 | F25: =IF(IF('Combined District Data'!H50>0.5,"D","R")=$E$8,1,0) -> 0 | G25: =IF(IF('Combined District Data'!H51>0.5,"D","R")=$E$9,1,0) -> 0 | H25: =SUM(D25:G25) -> 0 | I25: =AVERAGE(ABS('Combined District Data'!H48-$D$6),ABS('Combined District Data'!H49-$D$7),ABS('Combined District Data'!H50-$D$8),ABS('Combined District Data'!H51-$D$9)) -> 0.13349335 | J25: =IF(AND(H25=4,I25=MIN(K14:K99)),"<< MAGIC MUNICIPALITY","") | K25: =IF(H25=4,I25,"")
A26: Lowhill | B26: Lehigh | C26: Actual | D26: =IF(IF('Combined District Data'!H52>0.5,"D","R")=$E$6,1,0) -> 0 | E26: =IF(IF('Combined District Data'!H53>0.5,"D","R")=$E$7,1,0) -> 0 | F26: =IF(IF('Combined District Data'!H54>0.5,"D","R")=$E$8,1,0) -> 0 | G26: =IF(IF('Combined District Data'!H55>0.5,"D","R")=$E$9,1,0) -> 0 | H26: =SUM(D26:G26) -> 0 | I26: =AVERAGE(ABS('Combined District Data'!H52-$D$6),ABS('Combined District Data'!H53-$D$7),ABS('Combined District Data'!H54-$D$8),ABS('Combined District Data'!H55-$D$9)) -> 0.15313779 | J26: =IF(AND(H26=4,I26=MIN(K14:K99)),"<< MAGIC MUNICIPALITY","") | K26: =IF(H26=4,I26,"")
A27: Lynn | B27: Lehigh | C27: Actual | D27: =IF(IF('Combined District Data'!H56>0.5,"D","R")=$E$6,1,0) -> 0 | E27: =IF(IF('Combined District Data'!H57>0.5,"D","R")=$E$7,1,0) -> 0 | F27: =IF(IF('Combined District Data'!H58>0.5,"D","R")=$E$8,1,0) -> 0 | G27: =IF(IF('Combined District Data'!H59>0.5,"D","R")=$E$9,1,0) -> 0 | H27: =SUM(D27:G27) -> 0 | I27: =AVERAGE(ABS('Combined District Data'!H56-$D$6),ABS('Combined District Data'!H57-$D$7),ABS('Combined District Data'!H58-$D$8),ABS('Combined District Data'!H59-$D$9)) -> 0.19258376 | J27: =IF(AND(H27=4,I27=MIN(K14:K99)),"<< MAGIC MUNICIPALITY","") | K27: =IF(H27=4,I27,"")
A28: Macungie | B28: Lehigh | C28: Actual | D28: =IF(IF('Combined District Data'!H60>0.5,"D","R")=$E$6,1,0) -> 1 | E28: =IF(IF('Combined District Data'!H61>0.5,"D","R")=$E$7,1,0) -> 1 | F28: =IF(IF('Combined District Data'!H62>0.5,"D","R")=$E$8,1,0) -> 1 | G28: =IF(IF('Combined District Data'!H63>0.5,"D","R")=$E$9,1,0) -> 1 | H28: =SUM(D28:G28) -> 4 | I28: =AVERAGE(ABS('Combined District Data'!H60-$D$6),ABS('Combined District Data'!H61-$D$7),ABS('Combined District Data'!H62-$D$8),ABS('Combined District Data'!H63-$D$9)) -> 0.027439722 | J28: =IF(AND(H28=4,I28=MIN(K14:K99)),"<< MAGIC MUNICIPALITY","") | K28: =IF(H28=4,I28,"") -> 0.027439722
A29: North Whitehall | B29: Lehigh | C29: Actual | D29: =IF(IF('Combined District Data'!H64>0.5,"D","R")=$E$6,1,0) -> 0 | E29: =IF(IF('Combined District Data'!H65>0.5,"D","R")=$E$7,1,0) -> 0 | F29: =IF(IF('Combined District Data'!H66>0.5,"D","R")=$E$8,1,0) -> 0 | G29: =IF(IF('Combined District Data'!H67>0.5,"D","R")=$E$9,1,0) -> 0 | H29: =SUM(D29:G29) -> 0 | I29: =AVERAGE(ABS('Combined District Data'!H64-$D$6),ABS('Combined District Data'!H65-$D$7),ABS('Combined District Data'!H66-$D$8),ABS('Combined District Data'!H67-$D$9)) -> 0.10852174 | J29: =IF(AND(H29=4,I29=MIN(K14:K99)),"<< MAGIC MUNICIPALITY","") | K29: =IF(H29=4,I29,"")
A30: Salisbury | B30: Lehigh | C30: Actual | D30: =IF(IF('Combined District Data'!H68>0.5,"D","R")=$E$6,1,0) -> 0 | E30: =IF(IF('Combined District Data'!H69>0.5,"D","R")=$E$7,1,0) -> 0 | F30: =IF(IF('Combined District Data'!H70>0.5,"D","R")=$E$8,1,0) -> 1 | G30: =IF(IF('Combined District Data'!H71>0.5,"D","R")=$E$9,1,0) -> 0 | H30: =SUM(D30:G30) -> 1 | I30: =AVERAGE(ABS('Combined District Data'!H68-$D$6),ABS('Combined District Data'!H69-$D$7),ABS('Combined District Data'!H70-$D$8),ABS('Combined District Data'!H71-$D$9)) -> 0.01879387 | J30: =IF(AND(H30=4,I30=MIN(K14:K99)),"<< MAGIC MUNICIPALITY","") | K30: =IF(H30=4,I30,"")
A31: Slatington | B31: Lehigh | C31: Actual | D31: =IF(IF('Combined District Data'!H72>0.5,"D","R")=$E$6,1,0) -> 0 | E31: =IF(IF('Combined District Data'!H73>0.5,"D","R")=$E$7,1,0) -> 0 | F31: =IF(IF('Combined District Data'!H74>0.5,"D","R")=$E$8,1,0) -> 0 | G31: =IF(IF('Combined District Data'!H75>0.5,"D","R")=$E$9,1,0) -> 0 | H31: =SUM(D31:G31) -> 0 | I31: =AVERAGE(ABS('Combined District Data'!H72-$D$6),ABS('Combined District Data'!H73-$D$7),ABS('Combined District Data'!H74-$D$8),ABS('Combined District Data'!H75-$D$9)) -> 0.091286518 | J31: =IF(AND(H31=4,I31=MIN(K14:K99)),"<< MAGIC MUNICIPALITY","") | K31: =IF(H31=4,I31,"")
A32: South Whitehall | B32: Lehigh | C32: Actual | D32: =IF(IF('Combined District Data'!H76>0.5,"D","R")=$E$6,1,0) -> 1 | E32: =IF(IF('Combined District Data'!H77>0.5,"D","R")=$E$7,1,0) -> 1 | F32: =IF(IF('Combined District Data'!H78>0.5,"D","R")=$E$8,1,0) -> 1 | G32: =IF(IF('Combined District Data'!H79>0.5,"D","R")=$E$9,1,0) -> 1 | H32: =SUM(D32:G32) -> 4 | I32: =AVERAGE(ABS('Combined District Data'!H76-$D$6),ABS('Combined District Data'!H77-$D$7),ABS('Combined District Data'!H78-$D$8),ABS('Combined District Data'!H79-$D$9)) -> 0.028904841 | J32: =IF(AND(H32=4,I32=MIN(K14:K99)),"<< MAGIC MUNICIPALITY","") | K32: =IF(H32=4,I32,"") -> 0.028904841
A33: Upper Macungie | B33: Lehigh | C33: Actual | D33: =IF(IF('Combined District Data'!H80>0.5,"D","R")=$E$6,1,0) -> 1 | E33: =IF(IF('Combined District Data'!H81>0.5,"D","R")=$E$7,1,0) -> 1 | F33: =IF(IF('Combined District Data'!H82>0.5,"D","R")=$E$8,1,0) -> 1 | G33: =IF(IF('Combined District Data'!H83>0.5,"D","R")=$E$9,1,0) -> 1 | H33: =SUM(D33:G33) -> 4 | I33: =AVERAGE(ABS('Combined District Data'!H80-$D$6),ABS('Combined District Data'!H81-$D$7),ABS('Combined District Data'!H82-$D$8),ABS('Combined District Data'!H83-$D$9)) -> 0.014777724 | J33: =IF(AND(H33=4,I33=MIN(K14:K99)),"<< MAGIC MUNICIPALITY","") | K33: =IF(H33=4,I33,"") -> 0.014777724
A34: Upper Milford | B34: Lehigh | C34: Actual | D34: =IF(IF('Combined District Data'!H84>0.5,"D","R")=$E$6,1,0) -> 0 | E34: =IF(IF('Combined District Data'!H85>0.5,"D","R")=$E$7,1,0) -> 0 | F34: =IF(IF('Combined District Data'!H86>0.5,"D","R")=$E$8,1,0) -> 0 | G34: =IF(IF('Combined District Data'!H87>0.5,"D","R")=$E$9,1,0) -> 0 | H34: =SUM(D34:G34) -> 0 | I34: =AVERAGE(ABS('Combined District Data'!H84-$D$6),ABS('Combined District Data'!H85-$D$7),ABS('Combined District Data'!H86-$D$8),ABS('Combined District Data'!H87-$D$9)) -> 0.076462767 | J34: =IF(AND(H34=4,I34=MIN(K14:K99)),"<< MAGIC MUNICIPALITY","") | K34: =IF(H34=4,I34,"")
A35: Upper Saucon | B35: Lehigh | C35: Actual | D35: =IF(IF('Combined District Data'!H88>0.5,"D","R")=$E$6,1,0) -> 0 | E35: =IF(IF('Combined District Data'!H89>0.5,"D","R")=$E$7,1,0) -> 0 | F35: =IF(IF('Combined District Data'!H90>0.5,"D","R")=$E$8,1,0) -> 1 | G35: =IF(IF('Combined District Data'!H91>0.5,"D","R")=$E$9,1,0) -> 0 | H35: =SUM(D35:G35) -> 1 | I35: =AVERAGE(ABS('Combined District Data'!H88-$D$6),ABS('Combined District Data'!H89-$D$7),ABS('Combined District Data'!H90-$D$8),ABS('Combined District Data'!H91-$D$9)) -> 0.032267062 | J35: =IF(AND(H35=4,I35=MIN(K14:K99)),"<< MAGIC MUNICIPALITY","") | K35: =IF(H35=4,I35,"")
A36: Washington | B36: Lehigh | C36: Actual | D36: =IF(IF('Combined District Data'!H92>0.5,"D","R")=$E$6,1,0) -> 0 | E36: =IF(IF('Combined District Data'!H93>0.5,"D","R")=$E$7,1,0) -> 0 | F36: =IF(IF('Combined District Data'!H94>0.5,"D","R")=$E$8,1,0) -> 0 | G36: =IF(IF('Combined District Data'!H95>0.5,"D","R")=$E$9,1,0) -> 0 | H36: =SUM(D36:G36) -> 0 | I36: =AVERAGE(ABS('Combined District Data'!H92-$D$6),ABS('Combined District Data'!H93-$D$7),ABS('Combined District Data'!H94-$D$8),ABS('Combined District Data'!H95-$D$9)) -> 0.18139035 | J36: =IF(AND(H36=4,I36=MIN(K14:K99)),"<< MAGIC MUNICIPALITY","") | K36: =IF(H36=4,I36,"")
A37: Weisenberg | B37: Lehigh | C37: Actual | D37: =IF(IF('Combined District Data'!H96>0.5,"D","R")=$E$6,1,0) -> 0 | E37: =IF(IF('Combined District Data'!H97>0.5,"D","R")=$E$7,1,0) -> 0 | F37: =IF(IF('Combined District Data'!H98>0.5,"D","R")=$E$8,1,0) -> 0 | G37: =IF(IF('Combined District Data'!H99>0.5,"D","R")=$E$9,1,0) -> 0 | H37: =SUM(D37:G37) -> 0 | I37: =AVERAGE(ABS('Combined District Data'!H96-$D$6),ABS('Combined District Data'!H97-$D$7),ABS('Combined District Data'!H98-$D$8),ABS('Combined District Data'!H99-$D$9)) -> 0.16963572 | J37: =IF(AND(H37=4,I37=MIN(K14:K99)),"<< MAGIC MUNICIPALITY","") | K37: =IF(H37=4,I37,"")
A38: Whitehall | B38: Lehigh | C38: Actual | D38: =IF(IF('Combined District Data'!H100>0.5,"D","R")=$E$6,1,0) -> 1 | E38: =IF(IF('Combined District Data'!H101>0.5,"D","R")=$E$7,1,0) -> 1 | F38: =IF(IF('Combined District Data'!H102>0.5,"D","R")=$E$8,1,0) -> 1 | G38: =IF(IF('Combined District Data'!H103>0.5,"D","R")=$E$9,1,0) -> 1 | H38: =SUM(D38:G38) -> 4 | I38: =AVERAGE(ABS('Combined District Data'!H100-$D$6),ABS('Combined District Data'!H101-$D$7),ABS('Combined District Data'!H102-$D$8),ABS('Combined District Data'!H103-$D$9)) -> 0.011877136 | J38: =IF(AND(H38=4,I38=MIN(K14:K99)),"<< MAGIC MUNICIPALITY","") | K38: =IF(H38=4,I38,"") -> 0.011877136
A39: Allen | B39: Northampton | C39: Actual | D39: =IF(IF('Combined District Data'!H104>0.5,"D","R")=$E$6,1,0) -> 0 | E39: =IF(IF('Combined District Data'!H105>0.5,"D","R")=$E$7,1,0) -> 0 | F39: =IF(IF('Combined District Data'!H106>0.5,"D","R")=$E$8,1,0) -> 0 | G39: =IF(IF('Combined District Data'!H107>0.5,"D","R")=$E$9,1,0) -> 0 | H39: =SUM(D39:G39) -> 0 | I39: =AVERAGE(ABS('Combined District Data'!H104-$D$6),ABS('Combined District Data'!H105-$D$7),ABS('Combined District Data'!H106-$D$8),ABS('Combined District Data'!H107-$D$9)) -> 0.083373215 | J39: =IF(AND(H39=4,I39=MIN(K14:K99)),"<< MAGIC MUNICIPALITY","") | K39: =IF(H39=4,I39,"")
A40: Bangor | B40: Northampton | C40: Actual | D40: =IF(IF('Combined District Data'!H108>0.5,"D","R")=$E$6,1,0) -> 0 | E40: =IF(IF('Combined District Data'!H109>0.5,"D","R")=$E$7,1,0) -> 0 | F40: =IF(IF('Combined District Data'!H110>0.5,"D","R")=$E$8,1,0) -> 0 | G40: =IF(IF('Combined District Data'!H111>0.5,"D","R")=$E$9,1,0) -> 0 | H40: =SUM(D40:G40) -> 0 | I40: =AVERAGE(ABS('Combined District Data'!H108-$D$6),ABS('Combined District Data'!H109-$D$7),ABS('Combined District Data'!H110-$D$8),ABS('Combined District Data'!H111-$D$9)) -> 0.083290546 | J40: =IF(AND(H40=4,I40=MIN(K14:K99)),"<< MAGIC MUNICIPALITY","") | K40: =IF(H40=4,I40,"")
A41: Bath | B41: Northampton | C41: Actual | D41: =IF(IF('Combined District Data'!H112>0.5,"D","R")=$E$6,1,0) -> 0 | E41: =IF(IF('Combined District Data'!H113>0.5,"D","R")=$E$7,1,0) -> 0 | F41: =IF(IF('Combined District Data'!H114>0.5,"D","R")=$E$8,1,0) -> 0 | G41: =IF(IF('Combined District Data'!H115>0.5,"D","R")=$E$9,1,0) -> 0 | H41: =SUM(D41:G41) -> 0 | I41: =AVERAGE(ABS('Combined District Data'!H112-$D$6),ABS('Combined District Data'!H113-$D$7),ABS('Combined District Data'!H114-$D$8),ABS('Combined District Data'!H115-$D$9)) -> 0.057766419 | J41: =IF(AND(H41=4,I41=MIN(K14:K99)),"<< MAGIC MUNICIPALITY","") | K41: =IF(H41=4,I41,"")
A42: Bethlehem | B42: Northampton | C42: Actual | D42: =IF(IF('Combined District Data'!H116>0.5,"D","R")=$E$6,1,0) -> 1 | E42: =IF(IF('Combined District Data'!H117>0.5,"D","R")=$E$7,1,0) -> 1 | F42: =IF(IF('Combined District Data'!H118>0.5,"D","R")=$E$8,1,0) -> 1 | G42: =IF(IF('Combined District Data'!H119>0.5,"D","R")=$E$9,1,0) -> 1 | H42: =SUM(D42:G42) -> 4 | I42: =AVERAGE(ABS('Combined District Data'!H116-$D$6),ABS('Combined District Data'!H117-$D$7),ABS('Combined District Data'!H118-$D$8),ABS('Combined District Data'!H119-$D$9)) -> 0.16231199 | J42: =IF(AND(H42=4,I42=MIN(K14:K99)),"<< MAGIC MUNICIPALITY","") | K42: =IF(H42=4,I42,"") -> 0.16231199
A43: Bethlehem Township | B43: Northampton | C43: Actual | D43: =IF(IF('Combined District Data'!H120>0.5,"D","R")=$E$6,1,0) -> 1 | E43: =IF(IF('Combined District Data'!H121>0.5,"D","R")=$E$7,1,0) -> 1 | F43: =IF(IF('Combined District Data'!H122>0.5,"D","R")=$E$8,1,0) -> 1 | G43: =IF(IF('Combined District Data'!H123>0.5,"D","R")=$E$9,1,0) -> 1 | H43: =SUM(D43:G43) -> 4 | I43: =AVERAGE(ABS('Combined District Data'!H120-$D$6),ABS('Combined District Data'!H121-$D$7),ABS('Combined District Data'!H122-$D$8),ABS('Combined District Data'!H123-$D$9)) -> 0.02410568 | J43: =IF(AND(H43=4,I43=MIN(K14:K99)),"<< MAGIC MUNICIPALITY","") | K43: =IF(H43=4,I43,"") -> 0.02410568
A44: Bushkill | B44: Northampton | C44: Actual | D44: =IF(IF('Combined District Data'!H124>0.5,"D","R")=$E$6,1,0) -> 0 | E44: =IF(IF('Combined District Data'!H125>0.5,"D","R")=$E$7,1,0) -> 0 | F44: =IF(IF('Combined District Data'!H126>0.5,"D","R")=$E$8,1,0) -> 0 | G44: =IF(IF('Combined District Data'!H127>0.5,"D","R")=$E$9,1,0) -> 0 | H44: =SUM(D44:G44) -> 0 | I44: =AVERAGE(ABS('Combined District Data'!H124-$D$6),ABS('Combined District Data'!H125-$D$7),ABS('Combined District Data'!H126-$D$8),ABS('Combined District Data'!H127-$D$9)) -> 0.13460867 | J44: =IF(AND(H44=4,I44=MIN(K14:K99)),"<< MAGIC MUNICIPALITY","") | K44: =IF(H44=4,I44,"")
A45: Chapman | B45: Northampton | C45: Actual | D45: =IF(IF('Combined District Data'!H128>0.5,"D","R")=$E$6,1,0) -> 0 | E45: =IF(IF('Combined District Data'!H129>0.5,"D","R")=$E$7,1,0) -> 0 | F45: =IF(IF('Combined District Data'!H130>0.5,"D","R")=$E$8,1,0) -> 0 | G45: =IF(IF('Combined District Data'!H131>0.5,"D","R")=$E$9,1,0) -> 0 | H45: =SUM(D45:G45) -> 0 | I45: =AVERAGE(ABS('Combined District Data'!H128-$D$6),ABS('Combined District Data'!H129-$D$7),ABS('Combined District Data'!H130-$D$8),ABS('Combined District Data'!H131-$D$9)) -> 0.15338765 | J45: =IF(AND(H45=4,I45=MIN(K14:K99)),"<< MAGIC MUNICIPALITY","") | K45: =IF(H45=4,I45,"")
A46: East Allen | B46: Northampton | C46: Actual | D46: =IF(IF('Combined District Data'!H132>0.5,"D","R")=$E$6,1,0) -> 0 | E46: =IF(IF('Combined District Data'!H133>0.5,"D","R")=$E$7,1,0) -> 0 | F46: =IF(IF('Combined District Data'!H134>0.5,"D","R")=$E$8,1,0) -> 0 | G46: =IF(IF('Combined District Data'!H135>0.5,"D","R")=$E$9,1,0) -> 0 | H46: =SUM(D46:G46) -> 0 | I46: =AVERAGE(ABS('Combined District Data'!H132-$D$6),ABS('Combined District Data'!H133-$D$7),ABS('Combined District Data'!H134-$D$8),ABS('Combined District Data'!H135-$D$9)) -> 0.095976379 | J46: =IF(AND(H46=4,I46=MIN(K14:K99)),"<< MAGIC MUNICIPALITY","") | K46: =IF(H46=4,I46,"")
A47: East Bangor | B47: Northampton | C47: Actual | D47: =IF(IF('Combined District Data'!H136>0.5,"D","R")=$E$6,1,0) -> 0 | E47: =IF(IF('Combined District Data'!H137>0.5,"D","R")=$E$7,1,0) -> 0 | F47: =IF(IF('Combined District Data'!H138>0.5,"D","R")=$E$8,1,0) -> 0 | G47: =IF(IF('Combined District Data'!H139>0.5,"D","R")=$E$9,1,0) -> 0 | H47: =SUM(D47:G47) -> 0 | I47: =AVERAGE(ABS('Combined District Data'!H136-$D$6),ABS('Combined District Data'!H137-$D$7),ABS('Combined District Data'!H138-$D$8),ABS('Combined District Data'!H139-$D$9)) -> 0.13868815 | J47: =IF(AND(H47=4,I47=MIN(K14:K99)),"<< MAGIC MUNICIPALITY","") | K47: =IF(H47=4,I47,"")
A48: Easton | B48: Northampton | C48: Actual | D48: =IF(IF('Combined District Data'!H140>0.5,"D","R")=$E$6,1,0) -> 1 | E48: =IF(IF('Combined District Data'!H141>0.5,"D","R")=$E$7,1,0) -> 1 | F48: =IF(IF('Combined District Data'!H142>0.5,"D","R")=$E$8,1,0) -> 1 | G48: =IF(IF('Combined District Data'!H143>0.5,"D","R")=$E$9,1,0) -> 1 | H48: =SUM(D48:G48) -> 4 | I48: =AVERAGE(ABS('Combined District Data'!H140-$D$6),ABS('Combined District Data'!H141-$D$7),ABS('Combined District Data'!H142-$D$8),ABS('Combined District Data'!H143-$D$9)) -> 0.20284617 | J48: =IF(AND(H48=4,I48=MIN(K14:K99)),"<< MAGIC MUNICIPALITY","") | K48: =IF(H48=4,I48,"") -> 0.20284617
A49: Forks | B49: Northampton | C49: Actual | D49: =IF(IF('Combined District Data'!H144>0.5,"D","R")=$E$6,1,0) -> 1 | E49: =IF(IF('Combined District Data'!H145>0.5,"D","R")=$E$7,1,0) -> 1 | F49: =IF(IF('Combined District Data'!H146>0.5,"D","R")=$E$8,1,0) -> 1 | G49: =IF(IF('Combined District Data'!H147>0.5,"D","R")=$E$9,1,0) -> 1 | H49: =SUM(D49:G49) -> 4 | I49: =AVERAGE(ABS('Combined District Data'!H144-$D$6),ABS('Combined District Data'!H145-$D$7),ABS('Combined District Data'!H146-$D$8),ABS('Combined District Data'!H147-$D$9)) -> 0.0085744585 | J49: =IF(AND(H49=4,I49=MIN(K14:K99)),"<< MAGIC MUNICIPALITY","") | K49: =IF(H49=4,I49,"") -> 0.0085744585
A50: Freemansburg | B50: Northampton | C50: Actual | D50: =IF(IF('Combined District Data'!H148>0.5,"D","R")=$E$6,1,0) -> 1 | E50: =IF(IF('Combined District Data'!H149>0.5,"D","R")=$E$7,1,0) -> 1 | F50: =IF(IF('Combined District Data'!H150>0.5,"D","R")=$E$8,1,0) -> 1 | G50: =IF(IF('Combined District Data'!H151>0.5,"D","R")=$E$9,1,0) -> 1 | H50: =SUM(D50:G50) -> 4 | I50: =AVERAGE(ABS('Combined District Data'!H148-$D$6),ABS('Combined District Data'!H149-$D$7),ABS('Combined District Data'!H150-$D$8),ABS('Combined District Data'!H151-$D$9)) -> 0.097280663 | J50: =IF(AND(H50=4,I50=MIN(K14:K99)),"<< MAGIC MUNICIPALITY","") | K50: =IF(H50=4,I50,"") -> 0.097280663
A51: Glendon | B51: Northampton | C51: Actual | D51: =IF(IF('Combined District Data'!H152>0.5,"D","R")=$E$6,1,0) -> 1 | E51: =IF(IF('Combined District Data'!H153>0.5,"D","R")=$E$7,1,0) -> 1 | F51: =IF(IF('Combined District Data'!H154>0.5,"D","R")=$E$8,1,0) -> 1 | G51: =IF(IF('Combined District Data'!H155>0.5,"D","R")=$E$9,1,0) -> 1 | H51: =SUM(D51:G51) -> 4 | I51: =AVERAGE(ABS('Combined District Data'!H152-$D$6),ABS('Combined District Data'!H153-$D$7),ABS('Combined District Data'!H154-$D$8),ABS('Combined District Data'!H155-$D$9)) -> 0.031194933 | J51: =IF(AND(H51=4,I51=MIN(K14:K99)),"<< MAGIC MUNICIPALITY","") | K51: =IF(H51=4,I51,"") -> 0.031194933
A52: Hanover | B52: Northampton | C52: Actual | D52: =IF(IF('Combined District Data'!H156>0.5,"D","R")=$E$6,1,0) -> 1 | E52: =IF(IF('Combined District Data'!H157>0.5,"D","R")=$E$7,1,0) -> 1 | F52: =IF(IF('Combined District Data'!H158>0.5,"D","R")=$E$8,1,0) -> 1 | G52: =IF(IF('Combined District Data'!H159>0.5,"D","R")=$E$9,1,0) -> 1 | H52: =SUM(D52:G52) -> 4 | I52: =AVERAGE(ABS('Combined District Data'!H156-$D$6),ABS('Combined District Data'!H157-$D$7),ABS('Combined District Data'!H158-$D$8),ABS('Combined District Data'!H159-$D$9)) -> 0.030912826 | J52: =IF(AND(H52=4,I52=MIN(K14:K99)),"<< MAGIC MUNICIPALITY","") | K52: =IF(H52=4,I52,"") -> 0.030912826
A53: Hellertown | B53: Northampton | C53: Actual | D53: =IF(IF('Combined District Data'!H160>0.5,"D","R")=$E$6,1,0) -> 1 | E53: =IF(IF('Combined District Data'!H161>0.5,"D","R")=$E$7,1,0) -> 1 | F53: =IF(IF('Combined District Data'!H162>0.5,"D","R")=$E$8,1,0) -> 1 | G53: =IF(IF('Combined District Data'!H163>0.5,"D","R")=$E$9,1,0) -> 1 | H53: =SUM(D53:G53) -> 4 | I53: =AVERAGE(ABS('Combined District Data'!H160-$D$6),ABS('Combined District Data'!H161-$D$7),ABS('Combined District Data'!H162-$D$8),ABS('Combined District Data'!H163-$D$9)) -> 0.0060496444 | J53: =IF(AND(H53=4,I53=MIN(K14:K99)),"<< MAGIC MUNICIPALITY","") | K53: =IF(H53=4,I53,"") -> 0.0060496444
A54: Lehigh | B54: Northampton | C54: Actual | D54: =IF(IF('Combined District Data'!H164>0.5,"D","R")=$E$6,1,0) -> 0 | E54: =IF(IF('Combined District Data'!H165>0.5,"D","R")=$E$7,1,0) -> 0 | F54: =IF(IF('Combined District Data'!H166>0.5,"D","R")=$E$8,1,0) -> 0 | G54: =IF(IF('Combined District Data'!H167>0.5,"D","R")=$E$9,1,0) -> 0 | H54: =SUM(D54:G54) -> 0 | I54: =AVERAGE(ABS('Combined District Data'!H164-$D$6),ABS('Combined District Data'!H165-$D$7),ABS('Combined District Data'!H166-$D$8),ABS('Combined District Data'!H167-$D$9)) -> 0.17225185 | J54: =IF(AND(H54=4,I54=MIN(K14:K99)),"<< MAGIC MUNICIPALITY","") | K54: =IF(H54=4,I54,"")
A55: Lower Mount Bethel | B55: Northampton | C55: Actual | D55: =IF(IF('Combined District Data'!H168>0.5,"D","R")=$E$6,1,0) -> 0 | E55: =IF(IF('Combined District Data'!H169>0.5,"D","R")=$E$7,1,0) -> 0 | F55: =IF(IF('Combined District Data'!H170>0.5,"D","R")=$E$8,1,0) -> 0 | G55: =IF(IF('Combined District Data'!H171>0.5,"D","R")=$E$9,1,0) -> 0 | H55: =SUM(D55:G55) -> 0 | I55: =AVERAGE(ABS('Combined District Data'!H168-$D$6),ABS('Combined District Data'!H169-$D$7),ABS('Combined District Data'!H170-$D$8),ABS('Combined District Data'!H171-$D$9)) -> 0.15752192 | J55: =IF(AND(H55=4,I55=MIN(K14:K99)),"<< MAGIC MUNICIPALITY","") | K55: =IF(H55=4,I55,"")
A56: Nazareth | B56: Northampton | C56: Actual | D56: =IF(IF('Combined District Data'!H172>0.5,"D","R")=$E$6,1,0) -> 0 | E56: =IF(IF('Combined District Data'!H173>0.5,"D","R")=$E$7,1,0) -> 0 | F56: =IF(IF('Combined District Data'!H174>0.5,"D","R")=$E$8,1,0) -> 0 | G56: =IF(IF('Combined District Data'!H175>0.5,"D","R")=$E$9,1,0) -> 0 | H56: =SUM(D56:G56) -> 0 | I56: =AVERAGE(ABS('Combined District Data'!H172-$D$6),ABS('Combined District Data'!H173-$D$7),ABS('Combined District Data'!H174-$D$8),ABS('Combined District Data'!H175-$D$9)) -> 0.070168548 | J56: =IF(AND(H56=4,I56=MIN(K14:K99)),"<< MAGIC MUNICIPALITY","") | K56: =IF(H56=4,I56,"")
A57: Lower Saucon | B57: Northampton | C57: Actual | D57: =IF(IF('Combined District Data'!H176>0.5,"D","R")=$E$6,1,0) -> 0 | E57: =IF(IF('Combined District Data'!H177>0.5,"D","R")=$E$7,1,0) -> 0 | F57: =IF(IF('Combined District Data'!H178>0.5,"D","R")=$E$8,1,0) -> 0 | G57: =IF(IF('Combined District Data'!H179>0.5,"D","R")=$E$9,1,0) -> 0 | H57: =SUM(D57:G57) -> 0 | I57: =AVERAGE(ABS('Combined District Data'!H176-$D$6),ABS('Combined District Data'!H177-$D$7),ABS('Combined District Data'!H178-$D$8),ABS('Combined District Data'!H179-$D$9)) -> 0.037411279 | J57: =IF(AND(H57=4,I57=MIN(K14:K99)),"<< MAGIC MUNICIPALITY","") | K57: =IF(H57=4,I57,"")
A58: Moore | B58: Northampton | C58: Actual | D58: =IF(IF('Combined District Data'!H180>0.5,"D","R")=$E$6,1,0) -> 0 | E58: =IF(IF('Combined District Data'!H181>0.5,"D","R")=$E$7,1,0) -> 0 | F58: =IF(IF('Combined District Data'!H182>0.5,"D","R")=$E$8,1,0) -> 0 | G58: =IF(IF('Combined District Data'!H183>0.5,"D","R")=$E$9,1,0) -> 0 | H58: =SUM(D58:G58) -> 0 | I58: =AVERAGE(ABS('Combined District Data'!H180-$D$6),ABS('Combined District Data'!H181-$D$7),ABS('Combined District Data'!H182-$D$8),ABS('Combined District Data'!H183-$D$9)) -> 0.17628143 | J58: =IF(AND(H58=4,I58=MIN(K14:K99)),"<< MAGIC MUNICIPALITY","") | K58: =IF(H58=4,I58,"")
A59: Lower Nazareth | B59: Northampton | C59: Actual | D59: =IF(IF('Combined District Data'!H184>0.5,"D","R")=$E$6,1,0) -> 1 | E59: =IF(IF('Combined District Data'!H185>0.5,"D","R")=$E$7,1,0) -> 0 | F59: =IF(IF('Combined District Data'!H186>0.5,"D","R")=$E$8,1,0) -> 1 | G59: =IF(IF('Combined District Data'!H187>0.5,"D","R")=$E$9,1,0) -> 0 | H59: =SUM(D59:G59) -> 2 | I59: =AVERAGE(ABS('Combined District Data'!H184-$D$6),ABS('Combined District Data'!H185-$D$7),ABS('Combined District Data'!H186-$D$8),ABS('Combined District Data'!H187-$D$9)) -> 0.026716403 | J59: =IF(AND(H59=4,I59=MIN(K14:K99)),"<< MAGIC MUNICIPALITY","") | K59: =IF(H59=4,I59,"")
A60: North Catasauqua | B60: Northampton | C60: Actual | D60: =IF(IF('Combined District Data'!H188>0.5,"D","R")=$E$6,1,0) -> 0 | E60: =IF(IF('Combined District Data'!H189>0.5,"D","R")=$E$7,1,0) -> 0 | F60: =IF(IF('Combined District Data'!H190>0.5,"D","R")=$E$8,1,0) -> 1 | G60: =IF(IF('Combined District Data'!H191>0.5,"D","R")=$E$9,1,0) -> 0 | H60: =SUM(D60:G60) -> 1 | I60: =AVERAGE(ABS('Combined District Data'!H188-$D$6),ABS('Combined District Data'!H189-$D$7),ABS('Combined District Data'!H190-$D$8),ABS('Combined District Data'!H191-$D$9)) -> 0.03047106 | J60: =IF(AND(H60=4,I60=MIN(K14:K99)),"<< MAGIC MUNICIPALITY","") | K60: =IF(H60=4,I60,"")
A61: Northampton | B61: Northampton | C61: Actual | D61: =IF(IF('Combined District Data'!H192>0.5,"D","R")=$E$6,1,0) -> 0 | E61: =IF(IF('Combined District Data'!H193>0.5,"D","R")=$E$7,1,0) -> 0 | F61: =IF(IF('Combined District Data'!H194>0.5,"D","R")=$E$8,1,0) -> 0 | G61: =IF(IF('Combined District Data'!H195>0.5,"D","R")=$E$9,1,0) -> 0 | H61: =SUM(D61:G61) -> 0 | I61: =AVERAGE(ABS('Combined District Data'!H192-$D$6),ABS('Combined District Data'!H193-$D$7),ABS('Combined District Data'!H194-$D$8),ABS('Combined District Data'!H195-$D$9)) -> 0.044415791 | J61: =IF(AND(H61=4,I61=MIN(K14:K99)),"<< MAGIC MUNICIPALITY","") | K61: =IF(H61=4,I61,"")
A62: Palmer | B62: Northampton | C62: Actual | D62: =IF(IF('Combined District Data'!H196>0.5,"D","R")=$E$6,1,0) -> 1 | E62: =IF(IF('Combined District Data'!H197>0.5,"D","R")=$E$7,1,0) -> 1 | F62: =IF(IF('Combined District Data'!H198>0.5,"D","R")=$E$8,1,0) -> 1 | G62: =IF(IF('Combined District Data'!H199>0.5,"D","R")=$E$9,1,0) -> 1 | H62: =SUM(D62:G62) -> 4 | I62: =AVERAGE(ABS('Combined District Data'!H196-$D$6),ABS('Combined District Data'!H197-$D$7),ABS('Combined District Data'!H198-$D$8),ABS('Combined District Data'!H199-$D$9)) -> 0.0063247671 | J62: =IF(AND(H62=4,I62=MIN(K14:K99)),"<< MAGIC MUNICIPALITY","") | K62: =IF(H62=4,I62,"") -> 0.0063247671
A63: Pen Argyl | B63: Northampton | C63: Actual | D63: =IF(IF('Combined District Data'!H200>0.5,"D","R")=$E$6,1,0) -> 0 | E63: =IF(IF('Combined District Data'!H201>0.5,"D","R")=$E$7,1,0) -> 0 | F63: =IF(IF('Combined District Data'!H202>0.5,"D","R")=$E$8,1,0) -> 0 | G63: =IF(IF('Combined District Data'!H203>0.5,"D","R")=$E$9,1,0) -> 0 | H63: =SUM(D63:G63) -> 0 | I63: =AVERAGE(ABS('Combined District Data'!H200-$D$6),ABS('Combined District Data'!H201-$D$7),ABS('Combined District Data'!H202-$D$8),ABS('Combined District Data'!H203-$D$9)) -> 0.1284161 | J63: =IF(AND(H63=4,I63=MIN(K14:K99)),"<< MAGIC MUNICIPALITY","") | K63: =IF(H63=4,I63,"")
A64: Plainfield | B64: Northampton | C64: Actual | D64: =IF(IF('Combined District Data'!H204>0.5,"D","R")=$E$6,1,0) -> 0 | E64: =IF(IF('Combined District Data'!H205>0.5,"D","R")=$E$7,1,0) -> 0 | F64: =IF(IF('Combined District Data'!H206>0.5,"D","R")=$E$8,1,0) -> 0 | G64: =IF(IF('Combined District Data'!H207>0.5,"D","R")=$E$9,1,0) -> 0 | H64: =SUM(D64:G64) -> 0 | I64: =AVERAGE(ABS('Combined District Data'!H204-$D$6),ABS('Combined District Data'!H205-$D$7),ABS('Combined District Data'!H206-$D$8),ABS('Combined District Data'!H207-$D$9)) -> 0.15761715 | J64: =IF(AND(H64=4,I64=MIN(K14:K99)),"<< MAGIC MUNICIPALITY","") | K64: =IF(H64=4,I64,"")
A65: Portland | B65: Northampton | C65: Actual | D65: =IF(IF('Combined District Data'!H208>0.5,"D","R")=$E$6,1,0) -> 0 | E65: =IF(IF('Combined District Data'!H209>0.5,"D","R")=$E$7,1,0) -> 0 | F65: =IF(IF('Combined District Data'!H210>0.5,"D","R")=$E$8,1,0) -> 0 | G65: =IF(IF('Combined District Data'!H211>0.5,"D","R")=$E$9,1,0) -> 0 | H65: =SUM(D65:G65) -> 0 | I65: =AVERAGE(ABS('Combined District Data'!H208-$D$6),ABS('Combined District Data'!H209-$D$7),ABS('Combined District Data'!H210-$D$8),ABS('Combined District Data'!H211-$D$9)) -> 0.1708179 | J65: =IF(AND(H65=4,I65=MIN(K14:K99)),"<< MAGIC MUNICIPALITY","") | K65: =IF(H65=4,I65,"")
A66: Roseto | B66: Northampton | C66: Actual | D66: =IF(IF('Combined District Data'!H212>0.5,"D","R")=$E$6,1,0) -> 0 | E66: =IF(IF('Combined District Data'!H213>0.5,"D","R")=$E$7,1,0) -> 0 | F66: =IF(IF('Combined District Data'!H214>0.5,"D","R")=$E$8,1,0) -> 0 | G66: =IF(IF('Combined District Data'!H215>0.5,"D","R")=$E$9,1,0) -> 0 | H66: =SUM(D66:G66) -> 0 | I66: =AVERAGE(ABS('Combined District Data'!H212-$D$6),ABS('Combined District Data'!H213-$D$7),ABS('Combined District Data'!H214-$D$8),ABS('Combined District Data'!H215-$D$9)) -> 0.13475073 | J66: =IF(AND(H66=4,I66=MIN(K14:K99)),"<< MAGIC MUNICIPALITY","") | K66: =IF(H66=4,I66,"")
A67: Stockertown | B67: Northampton | C67: Actual | D67: =IF(IF('Combined District Data'!H216>0.5,"D","R")=$E$6,1,0) -> 0 | E67: =IF(IF('Combined District Data'!H217>0.5,"D","R")=$E$7,1,0) -> 0 | F67: =IF(IF('Combined District Data'!H218>0.5,"D","R")=$E$8,1,0) -> 0 | G67: =IF(IF('Combined District Data'!H219>0.5,"D","R")=$E$9,1,0) -> 0 | H67: =SUM(D67:G67) -> 0 | I67: =AVERAGE(ABS('Combined District Data'!H216-$D$6),ABS('Combined District Data'!H217-$D$7),ABS('Combined District Data'!H218-$D$8),ABS('Combined District Data'!H219-$D$9)) -> 0.10112651 | J67: =IF(AND(H67=4,I67=MIN(K14:K99)),"<< MAGIC MUNICIPALITY","") | K67: =IF(H67=4,I67,"")
A68: Tatamy | B68: Northampton | C68: Actual | D68: =IF(IF('Combined District Data'!H220>0.5,"D","R")=$E$6,1,0) -> 0 | E68: =IF(IF('Combined District Data'!H221>0.5,"D","R")=$E$7,1,0) -> 0 | F68: =IF(IF('Combined District Data'!H222>0.5,"D","R")=$E$8,1,0) -> 0 | G68: =IF(IF('Combined District Data'!H223>0.5,"D","R")=$E$9,1,0) -> 0 | H68: =SUM(D68:G68) -> 0 | I68: =AVERAGE(ABS('Combined District Data'!H220-$D$6),ABS('Combined District Data'!H221-$D$7),ABS('Combined District Data'!H222-$D$8),ABS('Combined District Data'!H223-$D$9)) -> 0.096505518 | J68: =IF(AND(H68=4,I68=MIN(K14:K99)),"<< MAGIC MUNICIPALITY","") | K68: =IF(H68=4,I68,"")
A69: Upper Mount Bethel | B69: Northampton | C69: Actual | D69: =IF(IF('Combined District Data'!H224>0.5,"D","R")=$E$6,1,0) -> 0 | E69: =IF(IF('Combined District Data'!H225>0.5,"D","R")=$E$7,1,0) -> 0 | F69: =IF(IF('Combined District Data'!H226>0.5,"D","R")=$E$8,1,0) -> 0 | G69: =IF(IF('Combined District Data'!H227>0.5,"D","R")=$E$9,1,0) -> 0 | H69: =SUM(D69:G69) -> 0 | I69: =AVERAGE(ABS('Combined District Data'!H224-$D$6),ABS('Combined District Data'!H225-$D$7),ABS('Combined District Data'!H226-$D$8),ABS('Combined District Data'!H227-$D$9)) -> 0.1871233 | J69: =IF(AND(H69=4,I69=MIN(K14:K99)),"<< MAGIC MUNICIPALITY","") | K69: =IF(H69=4,I69,"")
A70: Upper Nazereth | B70: Northampton | C70: Actual | D70: =IF(IF('Combined District Data'!H228>0.5,"D","R")=$E$6,1,0) -> 0 | E70: =IF(IF('Combined District Data'!H229>0.5,"D","R")=$E$7,1,0) -> 0 | F70: =IF(IF('Combined District Data'!H230>0.5,"D","R")=$E$8,1,0) -> 0 | G70: =IF(IF('Combined District Data'!H231>0.5,"D","R")=$E$9,1,0) -> 0 | H70: =SUM(D70:G70) -> 0 | I70: =AVERAGE(ABS('Combined District Data'!H228-$D$6),ABS('Combined District Data'!H229-$D$7),ABS('Combined District Data'!H230-$D$8),ABS('Combined District Data'!H231-$D$9)) -> 0.034673112 | J70: =IF(AND(H70=4,I70=MIN(K14:K99)),"<< MAGIC MUNICIPALITY","") | K70: =IF(H70=4,I70,"")
A71: Walnutport | B71: Northampton | C71: Actual | D71: =IF(IF('Combined District Data'!H232>0.5,"D","R")=$E$6,1,0) -> 0 | E71: =IF(IF('Combined District Data'!H233>0.5,"D","R")=$E$7,1,0) -> 0 | F71: =IF(IF('Combined District Data'!H234>0.5,"D","R")=$E$8,1,0) -> 0 | G71: =IF(IF('Combined District Data'!H235>0.5,"D","R")=$E$9,1,0) -> 0 | H71: =SUM(D71:G71) -> 0 | I71: =AVERAGE(ABS('Combined District Data'!H232-$D$6),ABS('Combined District Data'!H233-$D$7),ABS('Combined District Data'!H234-$D$8),ABS('Combined District Data'!H235-$D$9)) -> 0.11655224 | J71: =IF(AND(H71=4,I71=MIN(K14:K99)),"<< MAGIC MUNICIPALITY","") | K71: =IF(H71=4,I71,"")
A72: Washington | B72: Northampton | C72: Actual | D72: =IF(IF('Combined District Data'!H236>0.5,"D","R")=$E$6,1,0) -> 0 | E72: =IF(IF('Combined District Data'!H237>0.5,"D","R")=$E$7,1,0) -> 0 | F72: =IF(IF('Combined District Data'!H238>0.5,"D","R")=$E$8,1,0) -> 0 | G72: =IF(IF('Combined District Data'!H239>0.5,"D","R")=$E$9,1,0) -> 0 | H72: =SUM(D72:G72) -> 0 | I72: =AVERAGE(ABS('Combined District Data'!H236-$D$6),ABS('Combined District Data'!H237-$D$7),ABS('Combined District Data'!H238-$D$8),ABS('Combined District Data'!H239-$D$9)) -> 0.16397796 | J72: =IF(AND(H72=4,I72=MIN(K14:K99)),"<< MAGIC MUNICIPALITY","") | K72: =IF(H72=4,I72,"")
A73: West Easton | B73: Northampton | C73: Actual | D73: =IF(IF('Combined District Data'!H240>0.5,"D","R")=$E$6,1,0) -> 1 | E73: =IF(IF('Combined District Data'!H241>0.5,"D","R")=$E$7,1,0) -> 0 | F73: =IF(IF('Combined District Data'!H242>0.5,"D","R")=$E$8,1,0) -> 0 | G73: =IF(IF('Combined District Data'!H243>0.5,"D","R")=$E$9,1,0) -> 0 | H73: =SUM(D73:G73) -> 1 | I73: =AVERAGE(ABS('Combined District Data'!H240-$D$6),ABS('Combined District Data'!H241-$D$7),ABS('Combined District Data'!H242-$D$8),ABS('Combined District Data'!H243-$D$9)) -> 0.040452859 | J73: =IF(AND(H73=4,I73=MIN(K14:K99)),"<< MAGIC MUNICIPALITY","") | K73: =IF(H73=4,I73,"")
A74: Williams Township | B74: Northampton | C74: Actual | D74: =IF(IF('Combined District Data'!H244>0.5,"D","R")=$E$6,1,0) -> 0 | E74: =IF(IF('Combined District Data'!H245>0.5,"D","R")=$E$7,1,0) -> 0 | F74: =IF(IF('Combined District Data'!H246>0.5,"D","R")=$E$8,1,0) -> 0 | G74: =IF(IF('Combined District Data'!H247>0.5,"D","R")=$E$9,1,0) -> 0 | H74: =SUM(D74:G74) -> 0 | I74: =AVERAGE(ABS('Combined District Data'!H244-$D$6),ABS('Combined District Data'!H245-$D$7),ABS('Combined District Data'!H246-$D$8),ABS('Combined District Data'!H247-$D$9)) -> 0.080036997 | J74: =IF(AND(H74=4,I74=MIN(K14:K99)),"<< MAGIC MUNICIPALITY","") | K74: =IF(H74=4,I74,"")
A75: Wilson | B75: Northampton | C75: Actual | D75: =IF(IF('Combined District Data'!H248>0.5,"D","R")=$E$6,1,0) -> 1 | E75: =IF(IF('Combined District Data'!H249>0.5,"D","R")=$E$7,1,0) -> 1 | F75: =IF(IF('Combined District Data'!H250>0.5,"D","R")=$E$8,1,0) -> 1 | G75: =IF(IF('Combined District Data'!H251>0.5,"D","R")=$E$9,1,0) -> 1 | H75: =SUM(D75:G75) -> 4 | I75: =AVERAGE(ABS('Combined District Data'!H248-$D$6),ABS('Combined District Data'!H249-$D$7),ABS('Combined District Data'!H250-$D$8),ABS('Combined District Data'!H251-$D$9)) -> 0.053266785 | J75: =IF(AND(H75=4,I75=MIN(K14:K99)),"<< MAGIC MUNICIPALITY","") | K75: =IF(H75=4,I75,"") -> 0.053266785
A76: Wind Gap | B76: Northampton | C76: Actual | D76: =IF(IF('Combined District Data'!H252>0.5,"D","R")=$E$6,1,0) -> 0 | E76: =IF(IF('Combined District Data'!H253>0.5,"D","R")=$E$7,1,0) -> 0 | F76: =IF(IF('Combined District Data'!H254>0.5,"D","R")=$E$8,1,0) -> 0 | G76: =IF(IF('Combined District Data'!H255>0.5,"D","R")=$E$9,1,0) -> 0 | H76: =SUM(D76:G76) -> 0 | I76: =AVERAGE(ABS('Combined District Data'!H252-$D$6),ABS('Combined District Data'!H253-$D$7),ABS('Combined District Data'!H254-$D$8),ABS('Combined District Data'!H255-$D$9)) -> 0.090031105 | J76: =IF(AND(H76=4,I76=MIN(K14:K99)),"<< MAGIC MUNICIPALITY","") | K76: =IF(H76=4,I76,"")
A77: Banks Township | B77: Carbon | C77: Estimated | D77: =IF(IF('Combined District Data'!H256>0.5,"D","R")=$E$6,1,0) -> 1 | E77: =IF(IF('Combined District Data'!H257>0.5,"D","R")=$E$7,1,0) -> 1 | F77: =IF(IF('Combined District Data'!H258>0.5,"D","R")=$E$8,1,0) -> 1 | G77: =IF(IF('Combined District Data'!H259>0.5,"D","R")=$E$9,1,0) -> 1 | H77: =SUM(D77:G77) -> 4 | I77: =AVERAGE(ABS('Combined District Data'!H256-$D$6),ABS('Combined District Data'!H257-$D$7),ABS('Combined District Data'!H258-$D$8),ABS('Combined District Data'!H259-$D$9)) -> 0.012407794 | J77: =IF(AND(H77=4,I77=MIN(K14:K99)),"<< MAGIC MUNICIPALITY","") | K77: =IF(H77=4,I77,"") -> 0.012407794
A78: Beaver Meadows Borough | B78: Carbon | C78: Estimated | D78: =IF(IF('Combined District Data'!H260>0.5,"D","R")=$E$6,1,0) -> 0 | E78: =IF(IF('Combined District Data'!H261>0.5,"D","R")=$E$7,1,0) -> 0 | F78: =IF(IF('Combined District Data'!H262>0.5,"D","R")=$E$8,1,0) -> 0 | G78: =IF(IF('Combined District Data'!H263>0.5,"D","R")=$E$9,1,0) -> 0 | H78: =SUM(D78:G78) -> 0 | I78: =AVERAGE(ABS('Combined District Data'!H260-$D$6),ABS('Combined District Data'!H261-$D$7),ABS('Combined District Data'!H262-$D$8),ABS('Combined District Data'!H263-$D$9)) -> 0.13580246 | J78: =IF(AND(H78=4,I78=MIN(K14:K99)),"<< MAGIC MUNICIPALITY","") | K78: =IF(H78=4,I78,"")
A79: Bowmanstown Borough | B79: Carbon | C79: Estimated | D79: =IF(IF('Combined District Data'!H264>0.5,"D","R")=$E$6,1,0) -> 0 | E79: =IF(IF('Combined District Data'!H265>0.5,"D","R")=$E$7,1,0) -> 0 | F79: =IF(IF('Combined District Data'!H266>0.5,"D","R")=$E$8,1,0) -> 0 | G79: =IF(IF('Combined District Data'!H267>0.5,"D","R")=$E$9,1,0) -> 0 | H79: =SUM(D79:G79) -> 0 | I79: =AVERAGE(ABS('Combined District Data'!H264-$D$6),ABS('Combined District Data'!H265-$D$7),ABS('Combined District Data'!H266-$D$8),ABS('Combined District Data'!H267-$D$9)) -> 0.15383526 | J79: =IF(AND(H79=4,I79=MIN(K14:K99)),"<< MAGIC MUNICIPALITY","") | K79: =IF(H79=4,I79,"")
A80: East Penn Township | B80: Carbon | C80: Estimated | D80: =IF(IF('Combined District Data'!H268>0.5,"D","R")=$E$6,1,0) -> 0 | E80: =IF(IF('Combined District Data'!H269>0.5,"D","R")=$E$7,1,0) -> 0 | F80: =IF(IF('Combined District Data'!H270>0.5,"D","R")=$E$8,1,0) -> 0 | G80: =IF(IF('Combined District Data'!H271>0.5,"D","R")=$E$9,1,0) -> 0 | H80: =SUM(D80:G80) -> 0 | I80: =AVERAGE(ABS('Combined District Data'!H268-$D$6),ABS('Combined District Data'!H269-$D$7),ABS('Combined District Data'!H270-$D$8),ABS('Combined District Data'!H271-$D$9)) -> 0.19695524 | J80: =IF(AND(H80=4,I80=MIN(K14:K99)),"<< MAGIC MUNICIPALITY","") | K80: =IF(H80=4,I80,"")
A81: East Side Borough | B81: Carbon | C81: Estimated | D81: =IF(IF('Combined District Data'!H272>0.5,"D","R")=$E$6,1,0) -> 0 | E81: =IF(IF('Combined District Data'!H273>0.5,"D","R")=$E$7,1,0) -> 0 | F81: =IF(IF('Combined District Data'!H274>0.5,"D","R")=$E$8,1,0) -> 0 | G81: =IF(IF('Combined District Data'!H275>0.5,"D","R")=$E$9,1,0) -> 0 | H81: =SUM(D81:G81) -> 0 | I81: =AVERAGE(ABS('Combined District Data'!H272-$D$6),ABS('Combined District Data'!H273-$D$7),ABS('Combined District Data'!H274-$D$8),ABS('Combined District Data'!H275-$D$9)) -> 0.10582454 | J81: =IF(AND(H81=4,I81=MIN(K14:K99)),"<< MAGIC MUNICIPALITY","") | K81: =IF(H81=4,I81,"")
A82: Franklin Township | B82: Carbon | C82: Estimated | D82: =IF(IF('Combined District Data'!H276>0.5,"D","R")=$E$6,1,0) -> 0 | E82: =IF(IF('Combined District Data'!H277>0.5,"D","R")=$E$7,1,0) -> 0 | F82: =IF(IF('Combined District Data'!H278>0.5,"D","R")=$E$8,1,0) -> 0 | G82: =IF(IF('Combined District Data'!H279>0.5,"D","R")=$E$9,1,0) -> 0 | H82: =SUM(D82:G82) -> 0 | I82: =AVERAGE(ABS('Combined District Data'!H276-$D$6),ABS('Combined District Data'!H277-$D$7),ABS('Combined District Data'!H278-$D$8),ABS('Combined District Data'!H279-$D$9)) -> 0.18960778 | J82: =IF(AND(H82=4,I82=MIN(K14:K99)),"<< MAGIC MUNICIPALITY","") | K82: =IF(H82=4,I82,"")
A83: Jim Thorpe Borough | B83: Carbon | C83: Estimated | D83: =IF(IF('Combined District Data'!H280>0.5,"D","R")=$E$6,1,0) -> 0 | E83: =IF(IF('Combined District Data'!H281>0.5,"D","R")=$E$7,1,0) -> 0 | F83: =IF(IF('Combined District Data'!H282>0.5,"D","R")=$E$8,1,0) -> 0 | G83: =IF(IF('Combined District Data'!H283>0.5,"D","R")=$E$9,1,0) -> 0 | H83: =SUM(D83:G83) -> 0 | I83: =AVERAGE(ABS('Combined District Data'!H280-$D$6),ABS('Combined District Data'!H281-$D$7),ABS('Combined District Data'!H282-$D$8),ABS('Combined District Data'!H283-$D$9)) -> 0.04138256 | J83: =IF(AND(H83=4,I83=MIN(K14:K99)),"<< MAGIC MUNICIPALITY","") | K83: =IF(H83=4,I83,"")
A84: Kidder Township | B84: Carbon | C84: Estimated | D84: =IF(IF('Combined District Data'!H284>0.5,"D","R")=$E$6,1,0) -> 0 | E84: =IF(IF('Combined District Data'!H285>0.5,"D","R")=$E$7,1,0) -> 0 | F84: =IF(IF('Combined District Data'!H286>0.5,"D","R")=$E$8,1,0) -> 0 | G84: =IF(IF('Combined District Data'!H287>0.5,"D","R")=$E$9,1,0) -> 0 | H84: =SUM(D84:G84) -> 0 | I84: =AVERAGE(ABS('Combined District Data'!H284-$D$6),ABS('Combined District Data'!H285-$D$7),ABS('Combined District Data'!H286-$D$8),ABS('Combined District Data'!H287-$D$9)) -> 0.15660129 | J84: =IF(AND(H84=4,I84=MIN(K14:K99)),"<< MAGIC MUNICIPALITY","") | K84: =IF(H84=4,I84,"")
A85: Lansford Borough | B85: Carbon | C85: Estimated | D85: =IF(IF('Combined District Data'!H288>0.5,"D","R")=$E$6,1,0) -> 0 | E85: =IF(IF('Combined District Data'!H289>0.5,"D","R")=$E$7,1,0) -> 0 | F85: =IF(IF('Combined District Data'!H290>0.5,"D","R")=$E$8,1,0) -> 0 | G85: =IF(IF('Combined District Data'!H291>0.5,"D","R")=$E$9,1,0) -> 0 | H85: =SUM(D85:G85) -> 0 | I85: =AVERAGE(ABS('Combined District Data'!H288-$D$6),ABS('Combined District Data'!H289-$D$7),ABS('Combined District Data'!H290-$D$8),ABS('Combined District Data'!H291-$D$9)) -> 0.034326485 | J85: =IF(AND(H85=4,I85=MIN(K14:K99)),"<< MAGIC MUNICIPALITY","") | K85: =IF(H85=4,I85,"")
A86: Lausanne Township | B86: Carbon | C86: Estimated | D86: =IF(IF('Combined District Data'!H292>0.5,"D","R")=$E$6,1,0) -> 0 | E86: =IF(IF('Combined District Data'!H293>0.5,"D","R")=$E$7,1,0) -> 0 | F86: =IF(IF('Combined District Data'!H294>0.5,"D","R")=$E$8,1,0) -> 0 | G86: =IF(IF('Combined District Data'!H295>0.5,"D","R")=$E$9,1,0) -> 0 | H86: =SUM(D86:G86) -> 0 | I86: =AVERAGE(ABS('Combined District Data'!H292-$D$6),ABS('Combined District Data'!H293-$D$7),ABS('Combined District Data'!H294-$D$8),ABS('Combined District Data'!H295-$D$9)) -> 0.21433256 | J86: =IF(AND(H86=4,I86=MIN(K14:K99)),"<< MAGIC MUNICIPALITY","") | K86: =IF(H86=4,I86,"")
A87: Lehigh Township | B87: Carbon | C87: Estimated | D87: =IF(IF('Combined District Data'!H296>0.5,"D","R")=$E$6,1,0) -> 0 | E87: =IF(IF('Combined District Data'!H297>0.5,"D","R")=$E$7,1,0) -> 0 | F87: =IF(IF('Combined District Data'!H298>0.5,"D","R")=$E$8,1,0) -> 0 | G87: =IF(IF('Combined District Data'!H299>0.5,"D","R")=$E$9,1,0) -> 0 | H87: =SUM(D87:G87) -> 0 | I87: =AVERAGE(ABS('Combined District Data'!H296-$D$6),ABS('Combined District Data'!H297-$D$7),ABS('Combined District Data'!H298-$D$8),ABS('Combined District Data'!H299-$D$9)) -> 0.2934104 | J87: =IF(AND(H87=4,I87=MIN(K14:K99)),"<< MAGIC MUNICIPALITY","") | K87: =IF(H87=4,I87,"")
A88: Lehighton Borough | B88: Carbon | C88: Estimated | D88: =IF(IF('Combined District Data'!H300>0.5,"D","R")=$E$6,1,0) -> 0 | E88: =IF(IF('Combined District Data'!H301>0.5,"D","R")=$E$7,1,0) -> 0 | F88: =IF(IF('Combined District Data'!H302>0.5,"D","R")=$E$8,1,0) -> 0 | G88: =IF(IF('Combined District Data'!H303>0.5,"D","R")=$E$9,1,0) -> 0 | H88: =SUM(D88:G88) -> 0 | I88: =AVERAGE(ABS('Combined District Data'!H300-$D$6),ABS('Combined District Data'!H301-$D$7),ABS('Combined District Data'!H302-$D$8),ABS('Combined District Data'!H303-$D$9)) -> 0.093779515 | J88: =IF(AND(H88=4,I88=MIN(K14:K99)),"<< MAGIC MUNICIPALITY","") | K88: =IF(H88=4,I88,"")
A89: Lower Towamensing Twp. | B89: Carbon | C89: Estimated | D89: =IF(IF('Combined District Data'!H304>0.5,"D","R")=$E$6,1,0) -> 0 | E89: =IF(IF('Combined District Data'!H305>0.5,"D","R")=$E$7,1,0) -> 0 | F89: =IF(IF('Combined District Data'!H306>0.5,"D","R")=$E$8,1,0) -> 0 | G89: =IF(IF('Combined District Data'!H307>0.5,"D","R")=$E$9,1,0) -> 0 | H89: =SUM(D89:G89) -> 0 | I89: =AVERAGE(ABS('Combined District Data'!H304-$D$6),ABS('Combined District Data'!H305-$D$7),ABS('Combined District Data'!H306-$D$8),ABS('Combined District Data'!H307-$D$9)) -> 0.17453528 | J89: =IF(AND(H89=4,I89=MIN(K14:K99)),"<< MAGIC MUNICIPALITY","") | K89: =IF(H89=4,I89,"")
A90: Mahoning Township | B90: Carbon | C90: Estimated | D90: =IF(IF('Combined District Data'!H308>0.5,"D","R")=$E$6,1,0) -> 0 | E90: =IF(IF('Combined District Data'!H309>0.5,"D","R")=$E$7,1,0) -> 0 | F90: =IF(IF('Combined District Data'!H310>0.5,"D","R")=$E$8,1,0) -> 0 | G90: =IF(IF('Combined District Data'!H311>0.5,"D","R")=$E$9,1,0) -> 0 | H90: =SUM(D90:G90) -> 0 | I90: =AVERAGE(ABS('Combined District Data'!H308-$D$6),ABS('Combined District Data'!H309-$D$7),ABS('Combined District Data'!H310-$D$8),ABS('Combined District Data'!H311-$D$9)) -> 0.19330971 | J90: =IF(AND(H90=4,I90=MIN(K14:K99)),"<< MAGIC MUNICIPALITY","") | K90: =IF(H90=4,I90,"")
A91: Nesquehoning Borough | B91: Carbon | C91: Estimated | D91: =IF(IF('Combined District Data'!H312>0.5,"D","R")=$E$6,1,0) -> 0 | E91: =IF(IF('Combined District Data'!H313>0.5,"D","R")=$E$7,1,0) -> 0 | F91: =IF(IF('Combined District Data'!H314>0.5,"D","R")=$E$8,1,0) -> 0 | G91: =IF(IF('Combined District Data'!H315>0.5,"D","R")=$E$9,1,0) -> 0 | H91: =SUM(D91:G91) -> 0 | I91: =AVERAGE(ABS('Combined District Data'!H312-$D$6),ABS('Combined District Data'!H313-$D$7),ABS('Combined District Data'!H314-$D$8),ABS('Combined District Data'!H315-$D$9)) -> 0.062781679 | J91: =IF(AND(H91=4,I91=MIN(K14:K99)),"<< MAGIC MUNICIPALITY","") | K91: =IF(H91=4,I91,"")
A92: Packer Township | B92: Carbon | C92: Estimated | D92: =IF(IF('Combined District Data'!H316>0.5,"D","R")=$E$6,1,0) -> 0 | E92: =IF(IF('Combined District Data'!H317>0.5,"D","R")=$E$7,1,0) -> 0 | F92: =IF(IF('Combined District Data'!H318>0.5,"D","R")=$E$8,1,0) -> 0 | G92: =IF(IF('Combined District Data'!H319>0.5,"D","R")=$E$9,1,0) -> 0 | H92: =SUM(D92:G92) -> 0 | I92: =AVERAGE(ABS('Combined District Data'!H316-$D$6),ABS('Combined District Data'!H317-$D$7),ABS('Combined District Data'!H318-$D$8),ABS('Combined District Data'!H319-$D$9)) -> 0.2830932 | J92: =IF(AND(H92=4,I92=MIN(K14:K99)),"<< MAGIC MUNICIPALITY","") | K92: =IF(H92=4,I92,"")
A93: Palmerton Borough | B93: Carbon | C93: Estimated | D93: =IF(IF('Combined District Data'!H320>0.5,"D","R")=$E$6,1,0) -> 0 | E93: =IF(IF('Combined District Data'!H321>0.5,"D","R")=$E$7,1,0) -> 0 | F93: =IF(IF('Combined District Data'!H322>0.5,"D","R")=$E$8,1,0) -> 0 | G93: =IF(IF('Combined District Data'!H323>0.5,"D","R")=$E$9,1,0) -> 0 | H93: =SUM(D93:G93) -> 0 | I93: =AVERAGE(ABS('Combined District Data'!H320-$D$6),ABS('Combined District Data'!H321-$D$7),ABS('Combined District Data'!H322-$D$8),ABS('Combined District Data'!H323-$D$9)) -> 0.097978566 | J93: =IF(AND(H93=4,I93=MIN(K14:K99)),"<< MAGIC MUNICIPALITY","") | K93: =IF(H93=4,I93,"")
A94: Parryville Borough | B94: Carbon | C94: Estimated | D94: =IF(IF('Combined District Data'!H324>0.5,"D","R")=$E$6,1,0) -> 0 | E94: =IF(IF('Combined District Data'!H325>0.5,"D","R")=$E$7,1,0) -> 0 | F94: =IF(IF('Combined District Data'!H326>0.5,"D","R")=$E$8,1,0) -> 0 | G94: =IF(IF('Combined District Data'!H327>0.5,"D","R")=$E$9,1,0) -> 0 | H94: =SUM(D94:G94) -> 0 | I94: =AVERAGE(ABS('Combined District Data'!H324-$D$6),ABS('Combined District Data'!H325-$D$7),ABS('Combined District Data'!H326-$D$8),ABS('Combined District Data'!H327-$D$9)) -> 0.13351556 | J94: =IF(AND(H94=4,I94=MIN(K14:K99)),"<< MAGIC MUNICIPALITY","") | K94: =IF(H94=4,I94,"")
A95: Penn Forest Township | B95: Carbon | C95: Estimated | D95: =IF(IF('Combined District Data'!H328>0.5,"D","R")=$E$6,1,0) -> 0 | E95: =IF(IF('Combined District Data'!H329>0.5,"D","R")=$E$7,1,0) -> 0 | F95: =IF(IF('Combined District Data'!H330>0.5,"D","R")=$E$8,1,0) -> 0 | G95: =IF(IF('Combined District Data'!H331>0.5,"D","R")=$E$9,1,0) -> 0 | H95: =SUM(D95:G95) -> 0 | I95: =AVERAGE(ABS('Combined District Data'!H328-$D$6),ABS('Combined District Data'!H329-$D$7),ABS('Combined District Data'!H330-$D$8),ABS('Combined District Data'!H331-$D$9)) -> 0.11712927 | J95: =IF(AND(H95=4,I95=MIN(K14:K99)),"<< MAGIC MUNICIPALITY","") | K95: =IF(H95=4,I95,"")
A96: Summit Hill Borough | B96: Carbon | C96: Estimated | D96: =IF(IF('Combined District Data'!H332>0.5,"D","R")=$E$6,1,0) -> 1 | E96: =IF(IF('Combined District Data'!H333>0.5,"D","R")=$E$7,1,0) -> 0 | F96: =IF(IF('Combined District Data'!H334>0.5,"D","R")=$E$8,1,0) -> 1 | G96: =IF(IF('Combined District Data'!H335>0.5,"D","R")=$E$9,1,0) -> 0 | H96: =SUM(D96:G96) -> 2 | I96: =AVERAGE(ABS('Combined District Data'!H332-$D$6),ABS('Combined District Data'!H333-$D$7),ABS('Combined District Data'!H334-$D$8),ABS('Combined District Data'!H335-$D$9)) -> 0.024308652 | J96: =IF(AND(H96=4,I96=MIN(K14:K99)),"<< MAGIC MUNICIPALITY","") | K96: =IF(H96=4,I96,"")
A97: Towamensing Township | B97: Carbon | C97: Estimated | D97: =IF(IF('Combined District Data'!H336>0.5,"D","R")=$E$6,1,0) -> 0 | E97: =IF(IF('Combined District Data'!H337>0.5,"D","R")=$E$7,1,0) -> 0 | F97: =IF(IF('Combined District Data'!H338>0.5,"D","R")=$E$8,1,0) -> 0 | G97: =IF(IF('Combined District Data'!H339>0.5,"D","R")=$E$9,1,0) -> 0 | H97: =SUM(D97:G97) -> 0 | I97: =AVERAGE(ABS('Combined District Data'!H336-$D$6),ABS('Combined District Data'!H337-$D$7),ABS('Combined District Data'!H338-$D$8),ABS('Combined District Data'!H339-$D$9)) -> 0.18638817 | J97: =IF(AND(H97=4,I97=MIN(K14:K99)),"<< MAGIC MUNICIPALITY","") | K97: =IF(H97=4,I97,"")
A98: Weatherly Borough | B98: Carbon | C98: Estimated | D98: =IF(IF('Combined District Data'!H340>0.5,"D","R")=$E$6,1,0) -> 0 | E98: =IF(IF('Combined District Data'!H341>0.5,"D","R")=$E$7,1,0) -> 0 | F98: =IF(IF('Combined District Data'!H342>0.5,"D","R")=$E$8,1,0) -> 0 | G98: =IF(IF('Combined District Data'!H343>0.5,"D","R")=$E$9,1,0) -> 0 | H98: =SUM(D98:G98) -> 0 | I98: =AVERAGE(ABS('Combined District Data'!H340-$D$6),ABS('Combined District Data'!H341-$D$7),ABS('Combined District Data'!H342-$D$8),ABS('Combined District Data'!H343-$D$9)) -> 0.16808849 | J98: =IF(AND(H98=4,I98=MIN(K14:K99)),"<< MAGIC MUNICIPALITY","") | K98: =IF(H98=4,I98,"")
A99: Weissport Borough | B99: Carbon | C99: Estimated | D99: =IF(IF('Combined District Data'!H344>0.5,"D","R")=$E$6,1,0) -> 0 | E99: =IF(IF('Combined District Data'!H345>0.5,"D","R")=$E$7,1,0) -> 0 | F99: =IF(IF('Combined District Data'!H346>0.5,"D","R")=$E$8,1,0) -> 0 | G99: =IF(IF('Combined District Data'!H347>0.5,"D","R")=$E$9,1,0) -> 0 | H99: =SUM(D99:G99) -> 0 | I99: =AVERAGE(ABS('Combined District Data'!H344-$D$6),ABS('Combined District Data'!H345-$D$7),ABS('Combined District Data'!H346-$D$8),ABS('Combined District Data'!H347-$D$9)) -> 0.10629028 | J99: =IF(AND(H99=4,I99=MIN(K14:K99)),"<< MAGIC MUNICIPALITY","") | K99: =IF(H99=4,I99,"")

Sheet Beta Coefficients
A1: Municipality "Beta" vs. the Combined District (86 Municipalities)
A2: Beta = slope of a municipality's Dem Share regressed on the Combined District's Dem Share (computed directly from the Combined District Data sheet -- actual + Carbon estimate) across 2018-2024. Beta=1.0 means moving in lockstep with the district; R-squared shows how reliable that relationship is.
A4: District Dem Share (the 'index') -- pulled from Magic Municipality sheet
A5: 2018 | B5: 2020 | C5: 2022 | D5: 2024
A6: ='Magic Municipality'!D6 -> 0.53860097 | B6: ='Magic Municipality'!D7 -> 0.50536039 | C6: ='Magic Municipality'!D8 -> 0.51824086 | D6: ='Magic Municipality'!D9 -> 0.50230785
A8: Municipality | B8: County | C8: Source | D8: Beta | E8: R-squared | F8: Deviation from 1.0 | G8: Avg Dem Share | H8: Selected (Top 30 fit) | N8: (helper) score | O8: (helper) rank
A9: Alburtis | B9: Lehigh | C9: Actual | D9: =SLOPE(J9:M9,$A$6:$D$6) -> 1.6090743 | E9: =RSQ(J9:M9,$A$6:$D$6) -> 0.85293928 | F9: =ABS(D9-1) -> 0.60907434 | G9: =AVERAGE(J9:M9) -> 0.4752527 | H9: =IF(O9<=30,"YES","") | J9: ='Combined District Data'!H4 -> 0.50669643 | K9: ='Combined District Data'!H5 -> 0.46700508 | L9: ='Combined District Data'!H6 -> 0.48766041 | M9: ='Combined District Data'!H7 -> 0.43964887 | N9: =F9+(1-E9) -> 0.75613506 | O9: =RANK(N9,$N$9:$N$94,1) -> 31
A10: Allentown | B10: Lehigh | C10: Actual | D10: =SLOPE(J10:M10,$A$6:$D$6) -> 1.3789961 | E10: =RSQ(J10:M10,$A$6:$D$6) -> 0.72898569 | F10: =ABS(D10-1) -> 0.37899613 | G10: =AVERAGE(J10:M10) -> 0.68026642 | H10: =IF(O10<=30,"YES","") -> YES | J10: ='Combined District Data'!H8 -> 0.71055542 | K10: ='Combined District Data'!H9 -> 0.68359012 | L10: ='Combined District Data'!H10 -> 0.68129794 | M10: ='Combined District Data'!H11 -> 0.64562222 | N10: =F10+(1-E10) -> 0.65001045 | O10: =RANK(N10,$N$9:$N$94,1) -> 22
A11: Bethlehem | B11: Lehigh | C11: Actual | D11: =SLOPE(J11:M11,$A$6:$D$6) -> 0.19842802 | E11: =RSQ(J11:M11,$A$6:$D$6) -> 0.074440383 | F11: =ABS(D11-1) -> 0.80157198 | G11: =AVERAGE(J11:M11) -> 0.63958903 | H11: =IF(O11<=30,"YES","") | J11: ='Combined District Data'!H12 -> 0.63702901 | K11: ='Combined District Data'!H13 -> 0.63115313 | L11: ='Combined District Data'!H14 -> 0.65720441 | M11: ='Combined District Data'!H15 -> 0.63296956 | N11: =F11+(1-E11) -> 1.7271316 | O11: =RANK(N11,$N$9:$N$94,1) -> 68
A12: Catasauqua | B12: Lehigh | C12: Actual | D12: =SLOPE(J12:M12,$A$6:$D$6) -> 1.1522628 | E12: =RSQ(J12:M12,$A$6:$D$6) -> 0.94711322 | F12: =ABS(D12-1) -> 0.15226278 | G12: =AVERAGE(J12:M12) -> 0.52878358 | H12: =IF(O12<=30,"YES","") -> YES | J12: ='Combined District Data'!H16 -> 0.55194175 | K12: ='Combined District Data'!H17 -> 0.51397011 | L12: ='Combined District Data'!H18 -> 0.53791469 | M12: ='Combined District Data'!H19 -> 0.51130777 | N12: =F12+(1-E12) -> 0.20514956 | O12: =RANK(N12,$N$9:$N$94,1) -> 5
A13: Coopersburg | B13: Lehigh | C13: Actual | D13: =SLOPE(J13:M13,$A$6:$D$6) -> 1.0751881 | E13: =RSQ(J13:M13,$A$6:$D$6) -> 0.72760512 | F13: =ABS(D13-1) -> 0.07518814 | G13: =AVERAGE(J13:M13) -> 0.49209189 | H13: =IF(O13<=30,"YES","") -> YES | J13: ='Combined District Data'!H20 -> 0.51044776 | K13: ='Combined District Data'!H21 -> 0.47090301 | L13: ='Combined District Data'!H22 -> 0.50943396 | M13: ='Combined District Data'!H23 -> 0.47758285 | N13: =F13+(1-E13) -> 0.34758302 | O13: =RANK(N13,$N$9:$N$94,1) -> 12
A14: Coplay | B14: Lehigh | C14: Actual | D14: =SLOPE(J14:M14,$A$6:$D$6) -> 1.069008 | E14: =RSQ(J14:M14,$A$6:$D$6) -> 0.81784347 | F14: =ABS(D14-1) -> 0.06900802 | G14: =AVERAGE(J14:M14) -> 0.51808912 | H14: =IF(O14<=30,"YES","") -> YES | J14: ='Combined District Data'!H24 -> 0.53702197 | K14: ='Combined District Data'!H25 -> 0.50228833 | L14: ='Combined District Data'!H26 -> 0.53276793 | M14: ='Combined District Data'!H27 -> 0.50027824 | N14: =F14+(1-E14) -> 0.25116455 | O14: =RANK(N14,$N$9:$N$94,1) -> 8
A15: Emmaus | B15: Lehigh | C15: Actual | D15: =SLOPE(J15:M15,$A$6:$D$6) -> 0.20132295 | E15: =RSQ(J15:M15,$A$6:$D$6) -> 0.052353636 | F15: =ABS(D15-1) -> 0.79867705 | G15: =AVERAGE(J15:M15) -> 0.53633123 | H15: =IF(O15<=30,"YES","") | J15: ='Combined District Data'!H28 -> 0.53260394 | K15: ='Combined District Data'!H29 -> 0.52433936 | L15: ='Combined District Data'!H30 -> 0.55743509 | M15: ='Combined District Data'!H31 -> 0.53094651 | N15: =F15+(1-E15) -> 1.7463234 | O15: =RANK(N15,$N$9:$N$94,1) -> 70
A16: Fountain Hill | B16: Lehigh | C16: Actual | D16: =SLOPE(J16:M16,$A$6:$D$6) -> 0.40796976 | E16: =RSQ(J16:M16,$A$6:$D$6) -> 0.1226859 | F16: =ABS(D16-1) -> 0.59203024 | G16: =AVERAGE(J16:M16) -> 0.66696978 | H16: =IF(O16<=30,"YES","") | J16: ='Combined District Data'!H32 -> 0.66563659 | K16: ='Combined District Data'!H33 -> 0.66771867 | L16: ='Combined District Data'!H34 -> 0.69076824 | M16: ='Combined District Data'!H35 -> 0.64375562 | N16: =F16+(1-E16) -> 1.4693443 | O16: =RANK(N16,$N$9:$N$94,1) -> 62
A17: Hanover | B17: Lehigh | C17: Actual | D17: =SLOPE(J17:M17,$A$6:$D$6) -> 0.95949104 | E17: =RSQ(J17:M17,$A$6:$D$6) -> 0.55988148 | F17: =ABS(D17-1) -> 0.040508957 | G17: =AVERAGE(J17:M17) -> 0.56282592 | H17: =IF(O17<=30,"YES","") -> YES | J17: ='Combined District Data'!H36 -> 0.58449304 | K17: ='Combined District Data'!H37 -> 0.57122708 | L17: ='Combined District Data'!H38 -> 0.56102784 | M17: ='Combined District Data'!H39 -> 0.53455571 | N17: =F17+(1-E17) -> 0.48062748 | O17: =RANK(N17,$N$9:$N$94,1) -> 15
A18: Heidelberg | B18: Lehigh | C18: Actual | D18: =SLOPE(J18:M18,$A$6:$D$6) -> 1.0942764 | E18: =RSQ(J18:M18,$A$6:$D$6) -> 0.96215692 | F18: =ABS(D18-1) -> 0.094276401 | G18: =AVERAGE(J18:M18) -> 0.32608704 | H18: =IF(O18<=30,"YES","") -> YES | J18: ='Combined District Data'!H40 -> 0.34922861 | K18: ='Combined District Data'!H41 -> 0.31014941 | L18: ='Combined District Data'!H42 -> 0.3325 | M18: ='Combined District Data'!H43 -> 0.31247014 | N18: =F18+(1-E18) -> 0.13211949 | O18: =RANK(N18,$N$9:$N$94,1) -> 1
A19: Lower Macungie | B19: Lehigh | C19: Actual | D19: =SLOPE(J19:M19,$A$6:$D$6) -> 0.2013321 | E19: =RSQ(J19:M19,$A$6:$D$6) -> 0.056842366 | F19: =ABS(D19-1) -> 0.7986679 | G19: =AVERAGE(J19:M19) -> 0.50330098 | H19: =IF(O19<=30,"YES","") | J19: ='Combined District Data'!H44 -> 0.49955126 | K19: ='Combined District Data'!H45 -> 0.49414023 | L19: ='Combined District Data'!H46 -> 0.523914 | M19: ='Combined District Data'!H47 -> 0.49559842 | N19: =F19+(1-E19) -> 1.7418255 | O19: =RANK(N19,$N$9:$N$94,1) -> 69
A20: Lower Milford | B20: Lehigh | C20: Actual | D20: =SLOPE(J20:M20,$A$6:$D$6) -> 0.40263784 | E20: =RSQ(J20:M20,$A$6:$D$6) -> 0.30330205 | F20: =ABS(D20-1) -> 0.59736216 | G20: =AVERAGE(J20:M20) -> 0.38263416 | H20: =IF(O20<=30,"YES","") | J20: ='Combined District Data'!H48 -> 0.38842105 | K20: ='Combined District Data'!H49 -> 0.36565978 | L20: ='Combined District Data'!H50 -> 0.39333642 | M20: ='Combined District Data'!H51 -> 0.38311941 | N20: =F20+(1-E20) -> 1.2940601 | O20: =RANK(N20,$N$9:$N$94,1) -> 60
A21: Lowhill | B21: Lehigh | C21: Actual | D21: =SLOPE(J21:M21,$A$6:$D$6) -> 0.27313665 | E21: =RSQ(J21:M21,$A$6:$D$6) -> 0.23605662 | F21: =ABS(D21-1) -> 0.72686335 | G21: =AVERAGE(J21:M21) -> 0.36298972 | H21: =IF(O21<=30,"YES","") | J21: ='Combined District Data'!H52 -> 0.36403897 | K21: ='Combined District Data'!H53 -> 0.35819892 | L21: ='Combined District Data'!H54 -> 0.37551356 | M21: ='Combined District Data'!H55 -> 0.35420744 | N21: =F21+(1-E21) -> 1.4908067 | O21: =RANK(N21,$N$9:$N$94,1) -> 63
A22: Lynn | B22: Lehigh | C22: Actual | D22: =SLOPE(J22:M22,$A$6:$D$6) -> 0.23066855 | E22: =RSQ(J22:M22,$A$6:$D$6) -> 0.21627812 | F22: =ABS(D22-1) -> 0.76933145 | G22: =AVERAGE(J22:M22) -> 0.32354375 | H22: =IF(O22<=30,"YES","") | J22: ='Combined District Data'!H56 -> 0.32431026 | K22: ='Combined District Data'!H57 -> 0.32179536 | L22: ='Combined District Data'!H58 -> 0.33395262 | M22: ='Combined District Data'!H59 -> 0.31411678 | N22: =F22+(1-E22) -> 1.5530533 | O22: =RANK(N22,$N$9:$N$94,1) -> 64
A23: Macungie | B23: Lehigh | C23: Actual | D23: =SLOPE(J23:M23,$A$6:$D$6) -> -0.13253422 | E23: =RSQ(J23:M23,$A$6:$D$6) -> 0.024963672 | F23: =ABS(D23-1) -> 1.1325342 | G23: =AVERAGE(J23:M23) -> 0.5370044 | H23: =IF(O23<=30,"YES","") | J23: ='Combined District Data'!H60 -> 0.52547529 | K23: ='Combined District Data'!H61 -> 0.53688745 | L23: ='Combined District Data'!H62 -> 0.55649718 | M23: ='Combined District Data'!H63 -> 0.52915767 | N23: =F23+(1-E23) -> 2.1075705 | O23: =RANK(N23,$N$9:$N$94,1) -> 81
A24: North Whitehall | B24: Lehigh | C24: Actual | D24: =SLOPE(J24:M24,$A$6:$D$6) -> 0.09776023 | E24: =RSQ(J24:M24,$A$6:$D$6) -> 0.027435545 | F24: =ABS(D24-1) -> 0.90223977 | G24: =AVERAGE(J24:M24) -> 0.40760578 | H24: =IF(O24<=30,"YES","") | J24: ='Combined District Data'!H64 -> 0.40424604 | K24: ='Combined District Data'!H65 -> 0.39963111 | L24: ='Combined District Data'!H66 -> 0.42179603 | M24: ='Combined District Data'!H67 -> 0.40474992 | N24: =F24+(1-E24) -> 1.8748042 | O24: =RANK(N24,$N$9:$N$94,1) -> 72
A25: Salisbury | B25: Lehigh | C25: Actual | D25: =SLOPE(J25:M25,$A$6:$D$6) -> 0.032510768 | E25: =RSQ(J25:M25,$A$6:$D$6) -> 0.0050444177 | F25: =ABS(D25-1) -> 0.96748923 | G25: =AVERAGE(J25:M25) -> 0.49733365 | H25: =IF(O25<=30,"YES","") | J25: ='Combined District Data'!H68 -> 0.49346515 | K25: ='Combined District Data'!H69 -> 0.49302496 | L25: ='Combined District Data'!H70 -> 0.50863693 | M25: ='Combined District Data'!H71 -> 0.49420754 | N25: =F25+(1-E25) -> 1.9624448 | O25: =RANK(N25,$N$9:$N$94,1) -> 75
A26: Slatington | B26: Lehigh | C26: Actual | D26: =SLOPE(J26:M26,$A$6:$D$6) -> 1.2637393 | E26: =RSQ(J26:M26,$A$6:$D$6) -> 0.56825936 | F26: =ABS(D26-1) -> 0.26373929 | G26: =AVERAGE(J26:M26) -> 0.424841 | H26: =IF(O26<=30,"YES","") -> YES | J26: ='Combined District Data'!H72 -> 0.44380165 | K26: ='Combined District Data'!H73 -> 0.3943068 | L26: ='Combined District Data'!H74 -> 0.45225759 | M26: ='Combined District Data'!H75 -> 0.40899796 | N26: =F26+(1-E26) -> 0.69547993 | O26: =RANK(N26,$N$9:$N$94,1) -> 27
A27: South Whitehall | B27: Lehigh | C27: Actual | D27: =SLOPE(J27:M27,$A$6:$D$6) -> 0.52353352 | E27: =RSQ(J27:M27,$A$6:$D$6) -> 0.36021435 | F27: =ABS(D27-1) -> 0.47646648 | G27: =AVERAGE(J27:M27) -> 0.54503236 | H27: =IF(O27<=30,"YES","") | J27: ='Combined District Data'!H76 -> 0.54989571 | K27: ='Combined District Data'!H77 -> 0.53241776 | L27: ='Combined District Data'!H78 -> 0.56319794 | M27: ='Combined District Data'!H79 -> 0.53461802 | N27: =F27+(1-E27) -> 1.1162521 | O27: =RANK(N27,$N$9:$N$94,1) -> 55
A28: Upper Macungie | B28: Lehigh | C28: Actual | D28: =SLOPE(J28:M28,$A$6:$D$6) -> 0.10659761 | E28: =RSQ(J28:M28,$A$6:$D$6) -> 0.037737586 | F28: =ABS(D28-1) -> 0.89340239 | G28: =AVERAGE(J28:M28) -> 0.52003115 | H28: =IF(O28<=30,"YES","") | J28: ='Combined District Data'!H80 -> 0.5168528 | K28: ='Combined District Data'!H81 -> 0.51668275 | L28: ='Combined District Data'!H82 -> 0.53337476 | M28: ='Combined District Data'!H83 -> 0.51321431 | N28: =F28+(1-E28) -> 1.8556648 | O28: =RANK(N28,$N$9:$N$94,1) -> 71
A29: Upper Milford | B29: Lehigh | C29: Actual | D29: =SLOPE(J29:M29,$A$6:$D$6) -> 0.44477277 | E29: =RSQ(J29:M29,$A$6:$D$6) -> 0.41761879 | F29: =ABS(D29-1) -> 0.55522723 | G29: =AVERAGE(J29:M29) -> 0.43966475 | H29: =IF(O29<=30,"YES","") | J29: ='Combined District Data'!H84 -> 0.44453355 | K29: ='Combined District Data'!H85 -> 0.4292061 | L29: ='Combined District Data'!H86 -> 0.45336903 | M29: ='Combined District Data'!H87 -> 0.43155032 | N29: =F29+(1-E29) -> 1.1376084 | O29: =RANK(N29,$N$9:$N$94,1) -> 56
A30: Upper Saucon | B30: Lehigh | C30: Actual | D30: =SLOPE(J30:M30,$A$6:$D$6) -> 0.071486552 | E30: =RSQ(J30:M30,$A$6:$D$6) -> 0.0063135071 | F30: =ABS(D30-1) -> 0.92851345 | G30: =AVERAGE(J30:M30) -> 0.48386045 | H30: =IF(O30<=30,"YES","") | J30: ='Combined District Data'!H88 -> 0.47888801 | K30: ='Combined District Data'!H89 -> 0.46685404 | L30: ='Combined District Data'!H90 -> 0.50210826 | M30: ='Combined District Data'!H91 -> 0.4875915 | N30: =F30+(1-E30) -> 1.9221999 | O30: =RANK(N30,$N$9:$N$94,1) -> 74
A31: Washington | B31: Lehigh | C31: Actual | D31: =SLOPE(J31:M31,$A$6:$D$6) -> 0.65237286 | E31: =RSQ(J31:M31,$A$6:$D$6) -> 0.55104035 | F31: =ABS(D31-1) -> 0.34762714 | G31: =AVERAGE(J31:M31) -> 0.33473717 | H31: =IF(O31<=30,"YES","") | J31: ='Combined District Data'!H92 -> 0.34340659 | K31: ='Combined District Data'!H93 -> 0.32318194 | L31: ='Combined District Data'!H94 -> 0.35063207 | M31: ='Combined District Data'!H95 -> 0.32172808 | N31: =F31+(1-E31) -> 0.79658679 | O31: =RANK(N31,$N$9:$N$94,1) -> 35
A32: Weisenberg | B32: Lehigh | C32: Actual | D32: =SLOPE(J32:M32,$A$6:$D$6) -> 0.087580689 | E32: =RSQ(J32:M32,$A$6:$D$6) -> 0.011477459 | F32: =ABS(D32-1) -> 0.91241931 | G32: =AVERAGE(J32:M32) -> 0.3464918 | H32: =IF(O32<=30,"YES","") | J32: ='Combined District Data'!H96 -> 0.34178794 | K32: ='Combined District Data'!H97 -> 0.33230102 | L32: ='Combined District Data'!H98 -> 0.36441308 | M32: ='Combined District Data'!H99 -> 0.34746516 | N32: =F32+(1-E32) -> 1.9009419 | O32: =RANK(N32,$N$9:$N$94,1) -> 73
A33: Whitehall | B33: Lehigh | C33: Actual | D33: =SLOPE(J33:M33,$A$6:$D$6) -> 0.59571785 | E33: =RSQ(J33:M33,$A$6:$D$6) -> 0.70344201 | F33: =ABS(D33-1) -> 0.40428215 | G33: =AVERAGE(J33:M33) -> 0.52770789 | H33: =IF(O33<=30,"YES","") -> YES | J33: ='Combined District Data'!H100 -> 0.53800746 | K33: ='Combined District Data'!H101 -> 0.52561844 | L33: ='Combined District Data'!H102 -> 0.53517295 | M33: ='Combined District Data'!H103 -> 0.51203273 | N33: =F33+(1-E33) -> 0.70084015 | O33: =RANK(N33,$N$9:$N$94,1) -> 28
A34: Allen | B34: Northampton | C34: Actual | D34: =SLOPE(J34:M34,$A$6:$D$6) -> -0.23811233 | E34: =RSQ(J34:M34,$A$6:$D$6) -> 0.08297609 | F34: =ABS(D34-1) -> 1.2381123 | G34: =AVERAGE(J34:M34) -> 0.4327543 | H34: =IF(O34<=30,"YES","") | J34: ='Combined District Data'!H104 -> 0.41920591 | K34: ='Combined District Data'!H105 -> 0.43210622 | L34: ='Combined District Data'!H106 -> 0.45153846 | M34: ='Combined District Data'!H107 -> 0.42816662 | N34: =F34+(1-E34) -> 2.1551362 | O34: =RANK(N34,$N$9:$N$94,1) -> 83
A35: Bangor | B35: Northampton | C35: Actual | D35: =SLOPE(J35:M35,$A$6:$D$6) -> 1.3042046 | E35: =RSQ(J35:M35,$A$6:$D$6) -> 0.98114269 | F35: =ABS(D35-1) -> 0.30420456 | G35: =AVERAGE(J35:M35) -> 0.43283697 | H35: =IF(O35<=30,"YES","") -> YES | J35: ='Combined District Data'!H108 -> 0.46027577 | K35: ='Combined District Data'!H109 -> 0.41829215 | L35: ='Combined District Data'!H110 -> 0.43995172 | M35: ='Combined District Data'!H111 -> 0.41282824 | N35: =F35+(1-E35) -> 0.32306187 | O35: =RANK(N35,$N$9:$N$94,1) -> 11
A36: Bath | B36: Northampton | C36: Actual | D36: =SLOPE(J36:M36,$A$6:$D$6) -> -0.09299494 | E36: =RSQ(J36:M36,$A$6:$D$6) -> 0.12971525 | F36: =ABS(D36-1) -> 1.0929949 | G36: =AVERAGE(J36:M36) -> 0.4583611 | H36: =IF(O36<=30,"YES","") | J36: ='Combined District Data'!H112 -> 0.45488257 | K36: ='Combined District Data'!H113 -> 0.4544741 | L36: ='Combined District Data'!H114 -> 0.46226415 | M36: ='Combined District Data'!H115 -> 0.46182357 | N36: =F36+(1-E36) -> 1.9632797 | O36: =RANK(N36,$N$9:$N$94,1) -> 76
A37: Bethlehem | B37: Northampton | C37: Actual | D37: =SLOPE(J37:M37,$A$6:$D$6) -> 0.51740563 | E37: =RSQ(J37:M37,$A$6:$D$6) -> 0.81483726 | F37: =ABS(D37-1) -> 0.48259437 | G37: =AVERAGE(J37:M37) -> 0.6784395 | H37: =IF(O37<=30,"YES","") -> YES | J37: ='Combined District Data'!H116 -> 0.68752127 | K37: ='Combined District Data'!H117 -> 0.67240965 | L37: ='Combined District Data'!H118 -> 0.68542058 | M37: ='Combined District Data'!H119 -> 0.66840651 | N37: =F37+(1-E37) -> 0.66775711 | O37: =RANK(N37,$N$9:$N$94,1) -> 23
A38: Bethlehem Township | B38: Northampton | C38: Actual | D38: =SLOPE(J38:M38,$A$6:$D$6) -> -0.099482827 | E38: =RSQ(J38:M38,$A$6:$D$6) -> 0.049663553 | F38: =ABS(D38-1) -> 1.0994828 | G38: =AVERAGE(J38:M38) -> 0.53552415 | H38: =IF(O38<=30,"YES","") | J38: ='Combined District Data'!H120 -> 0.52918288 | K38: ='Combined District Data'!H121 -> 0.53119917 | L38: ='Combined District Data'!H122 -> 0.54569958 | M38: ='Combined District Data'!H123 -> 0.53601497 | N38: =F38+(1-E38) -> 2.0498193 | O38: =RANK(N38,$N$9:$N$94,1) -> 78
A39: Bushkill | B39: Northampton | C39: Actual | D39: =SLOPE(J39:M39,$A$6:$D$6) -> 0.011841448 | E39: =RSQ(J39:M39,$A$6:$D$6) -> 0.00030551703 | F39: =ABS(D39-1) -> 0.98815855 | G39: =AVERAGE(J39:M39) -> 0.38151885 | H39: =IF(O39<=30,"YES","") | J39: ='Combined District Data'!H124 -> 0.37699505 | K39: ='Combined District Data'!H125 -> 0.36882342 | L39: ='Combined District Data'!H126 -> 0.39486247 | M39: ='Combined District Data'!H127 -> 0.38539446 | N39: =F39+(1-E39) -> 1.987853 | O39: =RANK(N39,$N$9:$N$94,1) -> 77
A40: Chapman | B40: Northampton | C40: Actual | D40: =SLOPE(J40:M40,$A$6:$D$6) -> 3.0376208 | E40: =RSQ(J40:M40,$A$6:$D$6) -> 0.98563231 | F40: =ABS(D40-1) -> 2.0376208 | G40: =AVERAGE(J40:M40) -> 0.36273986 | H40: =IF(O40<=30,"YES","") | J40: ='Combined District Data'!H128 -> 0.43478261 | K40: ='Combined District Data'!H129 -> 0.33050847 | L40: ='Combined District Data'!H130 -> 0.36046512 | M40: ='Combined District Data'!H131 -> 0.32520325 | N40: =F40+(1-E40) -> 2.0519885 | O40: =RANK(N40,$N$9:$N$94,1) -> 79
A41: East Allen | B41: Northampton | C41: Actual | D41: =SLOPE(J41:M41,$A$6:$D$6) -> -0.38180816 | E41: =RSQ(J41:M41,$A$6:$D$6) -> 0.11580212 | F41: =ABS(D41-1) -> 1.3818082 | G41: =AVERAGE(J41:M41) -> 0.42015114 | H41: =IF(O41<=30,"YES","") | J41: ='Combined District Data'!H132 -> 0.40384615 | K41: ='Combined District Data'!H133 -> 0.40513505 | L41: ='Combined District Data'!H134 -> 0.44060389 | M41: ='Combined District Data'!H135 -> 0.43101946 | N41: =F41+(1-E41) -> 2.266006 | O41: =RANK(N41,$N$9:$N$94,1) -> 85
A42: East Bangor | B42: Northampton | C42: Actual | D42: =SLOPE(J42:M42,$A$6:$D$6) -> -0.085972632 | E42: =RSQ(J42:M42,$A$6:$D$6) -> 0.0017966895 | F42: =ABS(D42-1) -> 1.0859726 | G42: =AVERAGE(J42:M42) -> 0.37743937 | H42: =IF(O42<=30,"YES","") | J42: ='Combined District Data'!H136 -> 0.37356322 | K42: ='Combined District Data'!H137 -> 0.33333333 | L42: ='Combined District Data'!H138 -> 0.39031339 | M42: ='Combined District Data'!H139 -> 0.41254753 | N42: =F42+(1-E42) -> 2.0841759 | O42: =RANK(N42,$N$9:$N$94,1) -> 80
A43: Easton | B43: Northampton | C43: Actual | D43: =SLOPE(J43:M43,$A$6:$D$6) -> 1.180715 | E43: =RSQ(J43:M43,$A$6:$D$6) -> 0.82848791 | F43: =ABS(D43-1) -> 0.18071504 | G43: =AVERAGE(J43:M43) -> 0.71897369 | H43: =IF(O43<=30,"YES","") -> YES | J43: ='Combined District Data'!H140 -> 0.73994442 | K43: ='Combined District Data'!H141 -> 0.70425638 | L43: ='Combined District Data'!H142 -> 0.734527 | M43: ='Combined District Data'!H143 -> 0.69716696 | N43: =F43+(1-E43) -> 0.35222714 | O43: =RANK(N43,$N$9:$N$94,1) -> 13
A44: Forks | B44: Northampton | C44: Actual | D44: =SLOPE(J44:M44,$A$6:$D$6) -> 0.44948853 | E44: =RSQ(J44:M44,$A$6:$D$6) -> 0.85747015 | F44: =ABS(D44-1) -> 0.55051147 | G44: =AVERAGE(J44:M44) -> 0.5200637 | H44: =IF(O44<=30,"YES","") -> YES | J44: ='Combined District Data'!H144 -> 0.52932442 | K44: ='Combined District Data'!H145 -> 0.51131635 | L44: ='Combined District Data'!H146 -> 0.52367758 | M44: ='Combined District Data'!H147 -> 0.51593645 | N44: =F44+(1-E44) -> 0.69304131 | O44: =RANK(N44,$N$9:$N$94,1) -> 26
A45: Freemansburg | B45: Northampton | C45: Actual | D45: =SLOPE(J45:M45,$A$6:$D$6) -> 0.80470923 | E45: =RSQ(J45:M45,$A$6:$D$6) -> 0.33703862 | F45: =ABS(D45-1) -> 0.19529077 | G45: =AVERAGE(J45:M45) -> 0.61340818 | H45: =IF(O45<=30,"YES","") | J45: ='Combined District Data'!H148 -> 0.63963964 | K45: ='Combined District Data'!H149 -> 0.62540717 | L45: ='Combined District Data'!H150 -> 0.59259259 | M45: ='Combined District Data'!H151 -> 0.59599332 | N45: =F45+(1-E45) -> 0.85825215 | O45: =RANK(N45,$N$9:$N$94,1) -> 40
A46: Glendon | B46: Northampton | C46: Actual | D46: =SLOPE(J46:M46,$A$6:$D$6) -> 2.9724209 | E46: =RSQ(J46:M46,$A$6:$D$6) -> 0.737488 | F46: =ABS(D46-1) -> 1.9724209 | G46: =AVERAGE(J46:M46) -> 0.54208476 | H46: =IF(O46<=30,"YES","") | J46: ='Combined District Data'!H152 -> 0.62608696 | K46: ='Combined District Data'!H153 -> 0.50248756 | L46: ='Combined District Data'!H154 -> 0.5106383 | M46: ='Combined District Data'!H155 -> 0.52912621 | N46: =F46+(1-E46) -> 2.2349329 | O46: =RANK(N46,$N$9:$N$94,1) -> 84
A47: Hanover | B47: Northampton | C47: Actual | D47: =SLOPE(J47:M47,$A$6:$D$6) -> -0.48779373 | E47: =RSQ(J47:M47,$A$6:$D$6) -> 0.33349479 | F47: =ABS(D47-1) -> 1.4877937 | G47: =AVERAGE(J47:M47) -> 0.53837725 | H47: =IF(O47<=30,"YES","") | J47: ='Combined District Data'!H156 -> 0.52127479 | K47: ='Combined District Data'!H157 -> 0.5337199 | L47: ='Combined District Data'!H158 -> 0.55323106 | M47: ='Combined District Data'!H159 -> 0.54528326 | N47: =F47+(1-E47) -> 2.1542989 | O47: =RANK(N47,$N$9:$N$94,1) -> 82
A48: Hellertown | B48: Northampton | C48: Actual | D48: =SLOPE(J48:M48,$A$6:$D$6) -> 1.1082527 | E48: =RSQ(J48:M48,$A$6:$D$6) -> 0.90282606 | F48: =ABS(D48-1) -> 0.10825275 | G48: =AVERAGE(J48:M48) -> 0.52217716 | H48: =IF(O48<=30,"YES","") -> YES | J48: ='Combined District Data'!H160 -> 0.54363002 | K48: ='Combined District Data'!H161 -> 0.50583897 | L48: ='Combined District Data'!H162 -> 0.53322969 | M48: ='Combined District Data'!H163 -> 0.50600997 | N48: =F48+(1-E48) -> 0.20542669 | O48: =RANK(N48,$N$9:$N$94,1) -> 6
A49: Lehigh | B49: Northampton | C49: Actual | D49: =SLOPE(J49:M49,$A$6:$D$6) -> 0.52488055 | E49: =RSQ(J49:M49,$A$6:$D$6) -> 0.70599235 | F49: =ABS(D49-1) -> 0.47511945 | G49: =AVERAGE(J49:M49) -> 0.34387567 | H49: =IF(O49<=30,"YES","") | J49: ='Combined District Data'!H164 -> 0.35244404 | K49: ='Combined District Data'!H165 -> 0.33416732 | L49: ='Combined District Data'!H166 -> 0.35311398 | M49: ='Combined District Data'!H167 -> 0.33577735 | N49: =F49+(1-E49) -> 0.7691271 | O49: =RANK(N49,$N$9:$N$94,1) -> 33
A50: Lower Mount Bethel | B50: Northampton | C50: Actual | D50: =SLOPE(J50:M50,$A$6:$D$6) -> 1.9253212 | E50: =RSQ(J50:M50,$A$6:$D$6) -> 0.94759918 | F50: =ABS(D50-1) -> 0.92532119 | G50: =AVERAGE(J50:M50) -> 0.3586056 | H50: =IF(O50<=30,"YES","") | J50: ='Combined District Data'!H168 -> 0.40169492 | K50: ='Combined District Data'!H169 -> 0.32786885 | L50: ='Combined District Data'!H170 -> 0.365 | M50: ='Combined District Data'!H171 -> 0.33985862 | N50: =F50+(1-E50) -> 0.97772201 | O50: =RANK(N50,$N$9:$N$94,1) -> 51
A51: Nazareth | B51: Northampton | C51: Actual | D51: =SLOPE(J51:M51,$A$6:$D$6) -> -0.87780337 | E51: =RSQ(J51:M51,$A$6:$D$6) -> 0.2323964 | F51: =ABS(D51-1) -> 1.8778034 | G51: =AVERAGE(J51:M51) -> 0.44595897 | H51: =IF(O51<=30,"YES","") | J51: ='Combined District Data'!H172 -> 0.43024772 | K51: ='Combined District Data'!H173 -> 0.42281728 | L51: ='Combined District Data'!H174 -> 0.44120032 | M51: ='Combined District Data'!H175 -> 0.48957055 | N51: =F51+(1-E51) -> 2.645407 | O51: =RANK(N51,$N$9:$N$94,1) -> 86
A52: Lower Saucon | B52: Northampton | C52: Actual | D52: =SLOPE(J52:M52,$A$6:$D$6) -> 0.21213334 | E52: =RSQ(J52:M52,$A$6:$D$6) -> 0.11771334 | F52: =ABS(D52-1) -> 0.78786666 | G52: =AVERAGE(J52:M52) -> 0.47871624 | H52: =IF(O52<=30,"YES","") | J52: ='Combined District Data'!H176 -> 0.47834275 | K52: ='Combined District Data'!H177 -> 0.46799056 | L52: ='Combined District Data'!H178 -> 0.49249199 | M52: ='Combined District Data'!H179 -> 0.47603966 | N52: =F52+(1-E52) -> 1.6701533 | O52: =RANK(N52,$N$9:$N$94,1) -> 67
A53: Moore | B53: Northampton | C53: Actual | D53: =SLOPE(J53:M53,$A$6:$D$6) -> 0.48163005 | E53: =RSQ(J53:M53,$A$6:$D$6) -> 0.65197795 | F53: =ABS(D53-1) -> 0.51836995 | G53: =AVERAGE(J53:M53) -> 0.33984609 | H53: =IF(O53<=30,"YES","") | J53: ='Combined District Data'!H180 -> 0.34709518 | K53: ='Combined District Data'!H181 -> 0.33189283 | L53: ='Combined District Data'!H182 -> 0.34953704 | M53: ='Combined District Data'!H183 -> 0.33085931 | N53: =F53+(1-E53) -> 0.86639201 | O53: =RANK(N53,$N$9:$N$94,1) -> 42
A54: Lower Nazareth | B54: Northampton | C54: Actual | D54: =SLOPE(J54:M54,$A$6:$D$6) -> 1.5130311 | E54: =RSQ(J54:M54,$A$6:$D$6) -> 0.63404892 | F54: =ABS(D54-1) -> 0.51303108 | G54: =AVERAGE(J54:M54) -> 0.48941111 | H54: =IF(O54<=30,"YES","") | J54: ='Combined District Data'!H184 -> 0.51226158 | K54: ='Combined District Data'!H185 -> 0.47802374 | L54: ='Combined District Data'!H186 -> 0.51707317 | M54: ='Combined District Data'!H187 -> 0.45028597 | N54: =F54+(1-E54) -> 0.87898217 | O54: =RANK(N54,$N$9:$N$94,1) -> 45
A55: North Catasauqua | B55: Northampton | C55: Actual | D55: =SLOPE(J55:M55,$A$6:$D$6) -> 0.30941271 | E55: =RSQ(J55:M55,$A$6:$D$6) -> 0.09896876 | F55: =ABS(D55-1) -> 0.69058729 | G55: =AVERAGE(J55:M55) -> 0.48565646 | H55: =IF(O55<=30,"YES","") | J55: ='Combined District Data'!H188 -> 0.48638838 | K55: ='Combined District Data'!H189 -> 0.46442186 | L55: ='Combined District Data'!H190 -> 0.50391236 | M55: ='Combined District Data'!H191 -> 0.48790323 | N55: =F55+(1-E55) -> 1.5916185 | O55: =RANK(N55,$N$9:$N$94,1) -> 66
A56: Northampton | B56: Northampton | C56: Actual | D56: =SLOPE(J56:M56,$A$6:$D$6) -> 0.94247599 | E56: =RSQ(J56:M56,$A$6:$D$6) -> 0.4294828 | F56: =ABS(D56-1) -> 0.057524007 | G56: =AVERAGE(J56:M56) -> 0.47171173 | H56: =IF(O56<=30,"YES","") -> YES | J56: ='Combined District Data'!H192 -> 0.48344565 | K56: ='Combined District Data'!H193 -> 0.44526375 | L56: ='Combined District Data'!H194 -> 0.49834479 | M56: ='Combined District Data'!H195 -> 0.45979271 | N56: =F56+(1-E56) -> 0.62804121 | O56: =RANK(N56,$N$9:$N$94,1) -> 21
A57: Palmer | B57: Northampton | C57: Actual | D57: =SLOPE(J57:M57,$A$6:$D$6) -> 0.65601168 | E57: =RSQ(J57:M57,$A$6:$D$6) -> 0.79089063 | F57: =ABS(D57-1) -> 0.34398832 | G57: =AVERAGE(J57:M57) -> 0.51581923 | H57: =IF(O57<=30,"YES","") -> YES | J57: ='Combined District Data'!H196 -> 0.52814424 | K57: ='Combined District Data'!H197 -> 0.50255102 | L57: ='Combined District Data'!H198 -> 0.52390187 | M57: ='Combined District Data'!H199 -> 0.5086798 | N57: =F57+(1-E57) -> 0.55309769 | O57: =RANK(N57,$N$9:$N$94,1) -> 19
A58: Pen Argyl | B58: Northampton | C58: Actual | D58: =SLOPE(J58:M58,$A$6:$D$6) -> 0.5846536 | E58: =RSQ(J58:M58,$A$6:$D$6) -> 0.71194964 | F58: =ABS(D58-1) -> 0.4153464 | G58: =AVERAGE(J58:M58) -> 0.38771142 | H58: =IF(O58<=30,"YES","") -> YES | J58: ='Combined District Data'!H200 -> 0.39737274 | K58: ='Combined District Data'!H201 -> 0.38370119 | L58: ='Combined District Data'!H202 -> 0.39643134 | M58: ='Combined District Data'!H203 -> 0.37334041 | N58: =F58+(1-E58) -> 0.70339676 | O58: =RANK(N58,$N$9:$N$94,1) -> 29
A59: Plainfield | B59: Northampton | C59: Actual | D59: =SLOPE(J59:M59,$A$6:$D$6) -> 0.99343785 | E59: =RSQ(J59:M59,$A$6:$D$6) -> 0.84155473 | F59: =ABS(D59-1) -> 0.0065621499 | G59: =AVERAGE(J59:M59) -> 0.35851037 | H59: =IF(O59<=30,"YES","") -> YES | J59: ='Combined District Data'!H204 -> 0.38514026 | K59: ='Combined District Data'!H205 -> 0.35185185 | L59: ='Combined District Data'!H206 -> 0.35003253 | M59: ='Combined District Data'!H207 -> 0.34701683 | N59: =F59+(1-E59) -> 0.16500742 | O59: =RANK(N59,$N$9:$N$94,1) -> 2
A60: Portland | B60: Northampton | C60: Actual | D60: =SLOPE(J60:M60,$A$6:$D$6) -> 0.67870509 | E60: =RSQ(J60:M60,$A$6:$D$6) -> 0.33660822 | F60: =ABS(D60-1) -> 0.32129491 | G60: =AVERAGE(J60:M60) -> 0.34530962 | H60: =IF(O60<=30,"YES","") | J60: ='Combined District Data'!H208 -> 0.36686391 | K60: ='Combined District Data'!H209 -> 0.32411067 | L60: ='Combined District Data'!H210 -> 0.33505155 | M60: ='Combined District Data'!H211 -> 0.35521236 | N60: =F60+(1-E60) -> 0.9846867 | O60: =RANK(N60,$N$9:$N$94,1) -> 52
A61: Roseto | B61: Northampton | C61: Actual | D61: =SLOPE(J61:M61,$A$6:$D$6) -> 1.2758604 | E61: =RSQ(J61:M61,$A$6:$D$6) -> 0.99145833 | F61: =ABS(D61-1) -> 0.27586039 | G61: =AVERAGE(J61:M61) -> 0.38137679 | H61: =IF(O61<=30,"YES","") -> YES | J61: ='Combined District Data'!H212 -> 0.41116751 | K61: ='Combined District Data'!H213 -> 0.36696231 | L61: ='Combined District Data'!H214 -> 0.3816568 | M61: ='Combined District Data'!H215 -> 0.36572052 | N61: =F61+(1-E61) -> 0.28440206 | O61: =RANK(N61,$N$9:$N$94,1) -> 10
A62: Stockertown | B62: Northampton | C62: Actual | D62: =SLOPE(J62:M62,$A$6:$D$6) -> 0.79785648 | E62: =RSQ(J62:M62,$A$6:$D$6) -> 0.97309335 | F62: =ABS(D62-1) -> 0.20214352 | G62: =AVERAGE(J62:M62) -> 0.41500101 | H62: =IF(O62<=30,"YES","") -> YES | J62: ='Combined District Data'!H216 -> 0.43425076 | K62: ='Combined District Data'!H217 -> 0.40769231 | L62: ='Combined District Data'!H218 -> 0.41343669 | M62: ='Combined District Data'!H219 -> 0.40462428 | N62: =F62+(1-E62) -> 0.22905017 | O62: =RANK(N62,$N$9:$N$94,1) -> 7
A63: Tatamy | B63: Northampton | C63: Actual | D63: =SLOPE(J63:M63,$A$6:$D$6) -> 0.27213838 | E63: =RSQ(J63:M63,$A$6:$D$6) -> 0.14891905 | F63: =ABS(D63-1) -> 0.72786162 | G63: =AVERAGE(J63:M63) -> 0.419622 | H63: =IF(O63<=30,"YES","") | J63: ='Combined District Data'!H220 -> 0.42105263 | K63: ='Combined District Data'!H221 -> 0.4047619 | L63: ='Combined District Data'!H222 -> 0.43315508 | M63: ='Combined District Data'!H223 -> 0.41951838 | N63: =F63+(1-E63) -> 1.5789426 | O63: =RANK(N63,$N$9:$N$94,1) -> 65
A64: Upper Mount Bethel | B64: Northampton | C64: Actual | D64: =SLOPE(J64:M64,$A$6:$D$6) -> 1.161601 | E64: =RSQ(J64:M64,$A$6:$D$6) -> 0.99561521 | F64: =ABS(D64-1) -> 0.16160102 | G64: =AVERAGE(J64:M64) -> 0.32900422 | H64: =IF(O64<=30,"YES","") -> YES | J64: ='Combined District Data'!H224 -> 0.35590725 | K64: ='Combined District Data'!H225 -> 0.31671477 | L64: ='Combined District Data'!H226 -> 0.3296 | M64: ='Combined District Data'!H227 -> 0.31379485 | N64: =F64+(1-E64) -> 0.1659858 | O64: =RANK(N64,$N$9:$N$94,1) -> 3
A65: Upper Nazereth | B65: Northampton | C65: Actual | D65: =SLOPE(J65:M65,$A$6:$D$6) -> 0.41080476 | E65: =RSQ(J65:M65,$A$6:$D$6) -> 0.24717255 | F65: =ABS(D65-1) -> 0.58919524 | G65: =AVERAGE(J65:M65) -> 0.4814544 | H65: =IF(O65<=30,"YES","") | J65: ='Combined District Data'!H228 -> 0.48481353 | K65: ='Combined District Data'!H229 -> 0.46531646 | L65: ='Combined District Data'!H230 -> 0.49794499 | M65: ='Combined District Data'!H231 -> 0.47774264 | N65: =F65+(1-E65) -> 1.3420227 | O65: =RANK(N65,$N$9:$N$94,1) -> 61
A66: Walnutport | B66: Northampton | C66: Actual | D66: =SLOPE(J66:M66,$A$6:$D$6) -> 0.58979161 | E66: =RSQ(J66:M66,$A$6:$D$6) -> 0.33304197 | F66: =ABS(D66-1) -> 0.41020839 | G66: =AVERAGE(J66:M66) -> 0.39957528 | H66: =IF(O66<=30,"YES","") | J66: ='Combined District Data'!H232 -> 0.40453074 | K66: ='Combined District Data'!H233 -> 0.3851626 | L66: ='Combined District Data'!H234 -> 0.42127072 | M66: ='Combined District Data'!H235 -> 0.38733706 | N66: =F66+(1-E66) -> 1.0771664 | O66: =RANK(N66,$N$9:$N$94,1) -> 53
A67: Washington | B67: Northampton | C67: Actual | D67: =SLOPE(J67:M67,$A$6:$D$6) -> 1.1649421 | E67: =RSQ(J67:M67,$A$6:$D$6) -> 0.97529488 | F67: =ABS(D67-1) -> 0.16494213 | G67: =AVERAGE(J67:M67) -> 0.35214955 | H67: =IF(O67<=30,"YES","") -> YES | J67: ='Combined District Data'!H236 -> 0.37826541 | K67: ='Combined District Data'!H237 -> 0.34365634 | L67: ='Combined District Data'!H238 -> 0.3539823 | M67: ='Combined District Data'!H239 -> 0.33269415 | N67: =F67+(1-E67) -> 0.18964725 | O67: =RANK(N67,$N$9:$N$94,1) -> 4
A68: West Easton | B68: Northampton | C68: Actual | D68: =SLOPE(J68:M68,$A$6:$D$6) -> 1.6202707 | E68: =RSQ(J68:M68,$A$6:$D$6) -> 0.65461344 | F68: =ABS(D68-1) -> 0.62027069 | G68: =AVERAGE(J68:M68) -> 0.47567466 | H68: =IF(O68<=30,"YES","") | J68: ='Combined District Data'!H240 -> 0.51351351 | K68: ='Combined District Data'!H241 -> 0.43304348 | L68: ='Combined District Data'!H242 -> 0.48067633 | M68: ='Combined District Data'!H243 -> 0.47546531 | N68: =F68+(1-E68) -> 0.96565725 | O68: =RANK(N68,$N$9:$N$94,1) -> 50
A69: Williams Township | B69: Northampton | C69: Actual | D69: =SLOPE(J69:M69,$A$6:$D$6) -> 0.38598634 | E69: =RSQ(J69:M69,$A$6:$D$6) -> 0.69171566 | F69: =ABS(D69-1) -> 0.61401366 | G69: =AVERAGE(J69:M69) -> 0.43609052 | H69: =IF(O69<=30,"YES","") | J69: ='Combined District Data'!H244 -> 0.44429208 | K69: ='Combined District Data'!H245 -> 0.42619392 | L69: ='Combined District Data'!H246 -> 0.43908323 | M69: ='Combined District Data'!H247 -> 0.43479284 | N69: =F69+(1-E69) -> 0.922298 | O69: =RANK(N69,$N$9:$N$94,1) -> 48
A70: Wilson | B70: Northampton | C70: Actual | D70: =SLOPE(J70:M70,$A$6:$D$6) -> 1.0552881 | E70: =RSQ(J70:M70,$A$6:$D$6) -> 0.80408368 | F70: =ABS(D70-1) -> 0.055288098 | G70: =AVERAGE(J70:M70) -> 0.5693943 | H70: =IF(O70<=30,"YES","") -> YES | J70: ='Combined District Data'!H248 -> 0.58793022 | K70: ='Combined District Data'!H249 -> 0.55300353 | L70: ='Combined District Data'!H250 -> 0.58438727 | M70: ='Combined District Data'!H251 -> 0.55225619 | N70: =F70+(1-E70) -> 0.25120441 | O70: =RANK(N70,$N$9:$N$94,1) -> 9
A71: Wind Gap | B71: Northampton | C71: Actual | D71: =SLOPE(J71:M71,$A$6:$D$6) -> 0.82786386 | E71: =RSQ(J71:M71,$A$6:$D$6) -> 0.28457504 | F71: =ABS(D71-1) -> 0.17213614 | G71: =AVERAGE(J71:M71) -> 0.42609641 | H71: =IF(O71<=30,"YES","") | J71: ='Combined District Data'!H252 -> 0.43667069 | K71: ='Combined District Data'!H253 -> 0.39107005 | L71: ='Combined District Data'!H254 -> 0.45114155 | M71: ='Combined District Data'!H255 -> 0.42550336 | N71: =F71+(1-E71) -> 0.8875611 | O71: =RANK(N71,$N$9:$N$94,1) -> 47
A72: Banks Township | B72: Carbon | C72: Estimated | D72: =SLOPE(J72:M72,$A$6:$D$6) -> 0.72820574 | E72: =RSQ(J72:M72,$A$6:$D$6) -> 0.81199185 | F72: =ABS(D72-1) -> 0.27179426 | G72: =AVERAGE(J72:M72) -> 0.52853531 | H72: =IF(O72<=30,"YES","") -> YES | J72: ='Combined District Data'!H256 -> 0.54137931 | K72: ='Combined District Data'!H257 -> 0.51758794 | L72: ='Combined District Data'!H258 -> 0.53869048 | M72: ='Combined District Data'!H259 -> 0.51648352 | N72: =F72+(1-E72) -> 0.45980241 | O72: =RANK(N72,$N$9:$N$94,1) -> 14
A73: Beaver Meadows Borough | B73: Carbon | C73: Estimated | D73: =SLOPE(J73:M73,$A$6:$D$6) -> 0.65584647 | E73: =RSQ(J73:M73,$A$6:$D$6) -> 0.57873773 | F73: =ABS(D73-1) -> 0.34415353 | G73: =AVERAGE(J73:M73) -> 0.38032505 | H73: =IF(O73<=30,"YES","") | J73: ='Combined District Data'!H260 -> 0.39069767 | K73: ='Combined District Data'!H261 -> 0.36363636 | L73: ='Combined District Data'!H262 -> 0.39350181 | M73: ='Combined District Data'!H263 -> 0.37346437 | N73: =F73+(1-E73) -> 0.76541579 | O73: =RANK(N73,$N$9:$N$94,1) -> 32
A74: Bowmanstown Borough | B74: Carbon | C74: Estimated | D74: =SLOPE(J74:M74,$A$6:$D$6) -> 0.61274969 | E74: =RSQ(J74:M74,$A$6:$D$6) -> 0.54363579 | F74: =ABS(D74-1) -> 0.38725031 | G74: =AVERAGE(J74:M74) -> 0.36229226 | H74: =IF(O74<=30,"YES","") | J74: ='Combined District Data'!H264 -> 0.37190083 | K74: ='Combined District Data'!H265 -> 0.34560907 | L74: ='Combined District Data'!H266 -> 0.375 | M74: ='Combined District Data'!H267 -> 0.35665914 | N74: =F74+(1-E74) -> 0.84361452 | O74: =RANK(N74,$N$9:$N$94,1) -> 39
A75: East Penn Township | B75: Carbon | C75: Estimated | D75: =SLOPE(J75:M75,$A$6:$D$6) -> 0.61821838 | E75: =RSQ(J75:M75,$A$6:$D$6) -> 0.45095708 | F75: =ABS(D75-1) -> 0.38178162 | G75: =AVERAGE(J75:M75) -> 0.31917228 | H75: =IF(O75<=30,"YES","") | J75: ='Combined District Data'!H268 -> 0.32824427 | K75: ='Combined District Data'!H269 -> 0.29985549 | L75: ='Combined District Data'!H270 -> 0.33388704 | M75: ='Combined District Data'!H271 -> 0.31470231 | N75: =F75+(1-E75) -> 0.93082454 | O75: =RANK(N75,$N$9:$N$94,1) -> 49
A76: East Side Borough | B76: Carbon | C76: Estimated | D76: =SLOPE(J76:M76,$A$6:$D$6) -> 0.50827941 | E76: =RSQ(J76:M76,$A$6:$D$6) -> 0.27569176 | F76: =ABS(D76-1) -> 0.49172059 | G76: =AVERAGE(J76:M76) -> 0.41030297 | H76: =IF(O76<=30,"YES","") | J76: ='Combined District Data'!H272 -> 0.41538462 | K76: ='Combined District Data'!H273 -> 0.39047619 | L76: ='Combined District Data'!H274 -> 0.42857143 | M76: ='Combined District Data'!H275 -> 0.40677966 | N76: =F76+(1-E76) -> 1.2160288 | O76: =RANK(N76,$N$9:$N$94,1) -> 59
A77: Franklin Township | B77: Carbon | C77: Estimated | D77: =SLOPE(J77:M77,$A$6:$D$6) -> 0.63970221 | E77: =RSQ(J77:M77,$A$6:$D$6) -> 0.48742395 | F77: =ABS(D77-1) -> 0.36029779 | G77: =AVERAGE(J77:M77) -> 0.32651974 | H77: =IF(O77<=30,"YES","") | J77: ='Combined District Data'!H276 -> 0.33632287 | K77: ='Combined District Data'!H277 -> 0.30735509 | L77: ='Combined District Data'!H278 -> 0.34064081 | M77: ='Combined District Data'!H279 -> 0.32176019 | N77: =F77+(1-E77) -> 0.87287384 | O77: =RANK(N77,$N$9:$N$94,1) -> 44
A78: Jim Thorpe Borough | B78: Carbon | C78: Estimated | D78: =SLOPE(J78:M78,$A$6:$D$6) -> 0.71177539 | E78: =RSQ(J78:M78,$A$6:$D$6) -> 0.73939349 | F78: =ABS(D78-1) -> 0.28822461 | G78: =AVERAGE(J78:M78) -> 0.47474496 | H78: =IF(O78<=30,"YES","") -> YES | J78: ='Combined District Data'!H280 -> 0.48688635 | K78: ='Combined District Data'!H281 -> 0.46132208 | L78: ='Combined District Data'!H282 -> 0.48613291 | M78: ='Combined District Data'!H283 -> 0.46463848 | N78: =F78+(1-E78) -> 0.54883111 | O78: =RANK(N78,$N$9:$N$94,1) -> 18
A79: Kidder Township | B79: Carbon | C79: Estimated | D79: =SLOPE(J79:M79,$A$6:$D$6) -> 0.6440932 | E79: =RSQ(J79:M79,$A$6:$D$6) -> 0.52443701 | F79: =ABS(D79-1) -> 0.3559068 | G79: =AVERAGE(J79:M79) -> 0.35952623 | H79: =IF(O79<=30,"YES","") | J79: ='Combined District Data'!H284 -> 0.36942675 | K79: ='Combined District Data'!H285 -> 0.34162304 | L79: ='Combined District Data'!H286 -> 0.37340877 | M79: ='Combined District Data'!H287 -> 0.35364635 | N79: =F79+(1-E79) -> 0.83146979 | O79: =RANK(N79,$N$9:$N$94,1) -> 38
A80: Lansford Borough | B80: Carbon | C80: Estimated | D80: =SLOPE(J80:M80,$A$6:$D$6) -> 0.72157997 | E80: =RSQ(J80:M80,$A$6:$D$6) -> 0.74327496 | F80: =ABS(D80-1) -> 0.27842003 | G80: =AVERAGE(J80:M80) -> 0.48180103 | H80: =IF(O80<=30,"YES","") -> YES | J80: ='Combined District Data'!H288 -> 0.49408284 | K80: ='Combined District Data'!H289 -> 0.46850044 | L80: ='Combined District Data'!H290 -> 0.49334812 | M80: ='Combined District Data'!H291 -> 0.47127273 | N80: =F80+(1-E80) -> 0.53514507 | O80: =RANK(N80,$N$9:$N$94,1) -> 17
A81: Lausanne Township | B81: Carbon | C81: Estimated | D81: =SLOPE(J81:M81,$A$6:$D$6) -> 0.67130328 | E81: =RSQ(J81:M81,$A$6:$D$6) -> 0.50481835 | F81: =ABS(D81-1) -> 0.32869672 | G81: =AVERAGE(J81:M81) -> 0.30179495 | H81: =IF(O81<=30,"YES","") | J81: ='Combined District Data'!H292 -> 0.31343284 | K81: ='Combined District Data'!H293 -> 0.28070175 | L81: ='Combined District Data'!H294 -> 0.31372549 | M81: ='Combined District Data'!H295 -> 0.29931973 | N81: =F81+(1-E81) -> 0.82387837 | O81: =RANK(N81,$N$9:$N$94,1) -> 36
A82: Lehigh Township | B82: Carbon | C82: Estimated | D82: =SLOPE(J82:M82,$A$6:$D$6) -> 0.5338732 | E82: =RSQ(J82:M82,$A$6:$D$6) -> 0.27194817 | F82: =ABS(D82-1) -> 0.4661268 | G82: =AVERAGE(J82:M82) -> 0.22271712 | H82: =IF(O82<=30,"YES","") | J82: ='Combined District Data'!H296 -> 0.22905028 | K82: ='Combined District Data'!H297 -> 0.2 | L82: ='Combined District Data'!H298 -> 0.24 | M82: ='Combined District Data'!H299 -> 0.22181818 | N82: =F82+(1-E82) -> 1.1941786 | O82: =RANK(N82,$N$9:$N$94,1) -> 58
A83: Lehighton Borough | B83: Carbon | C83: Estimated | D83: =SLOPE(J83:M83,$A$6:$D$6) -> 0.6790877 | E83: =RSQ(J83:M83,$A$6:$D$6) -> 0.64427054 | F83: =ABS(D83-1) -> 0.3209123 | G83: =AVERAGE(J83:M83) -> 0.422348 | H83: =IF(O83<=30,"YES","") -> YES | J83: ='Combined District Data'!H300 -> 0.43336199 | K83: ='Combined District Data'!H301 -> 0.40707497 | L83: ='Combined District Data'!H302 -> 0.4349835 | M83: ='Combined District Data'!H303 -> 0.41397154 | N83: =F83+(1-E83) -> 0.67664176 | O83: =RANK(N83,$N$9:$N$94,1) -> 25
A84: Lower Towamensing Twp. | B84: Carbon | C84: Estimated | D84: =SLOPE(J84:M84,$A$6:$D$6) -> 0.64123473 | E84: =RSQ(J84:M84,$A$6:$D$6) -> 0.49616126 | F84: =ABS(D84-1) -> 0.35876527 | G84: =AVERAGE(J84:M84) -> 0.34159224 | H84: =IF(O84<=30,"YES","") | J84: ='Combined District Data'!H304 -> 0.35126235 | K84: ='Combined District Data'!H305 -> 0.32299013 | L84: ='Combined District Data'!H306 -> 0.35598706 | M84: ='Combined District Data'!H307 -> 0.33612942 | N84: =F84+(1-E84) -> 0.86260402 | O84: =RANK(N84,$N$9:$N$94,1) -> 41
A85: Mahoning Township | B85: Carbon | C85: Estimated | D85: =SLOPE(J85:M85,$A$6:$D$6) -> 0.63953208 | E85: =RSQ(J85:M85,$A$6:$D$6) -> 0.47728377 | F85: =ABS(D85-1) -> 0.36046792 | G85: =AVERAGE(J85:M85) -> 0.32281781 | H85: =IF(O85<=30,"YES","") | J85: ='Combined District Data'!H308 -> 0.33253968 | K85: ='Combined District Data'!H309 -> 0.30338266 | L85: ='Combined District Data'!H310 -> 0.33716707 | M85: ='Combined District Data'!H311 -> 0.31818182 | N85: =F85+(1-E85) -> 0.88318416 | O85: =RANK(N85,$N$9:$N$94,1) -> 46
A86: Nesquehoning Borough | B86: Carbon | C86: Estimated | D86: =SLOPE(J86:M86,$A$6:$D$6) -> 0.70626491 | E86: =RSQ(J86:M86,$A$6:$D$6) -> 0.70118826 | F86: =ABS(D86-1) -> 0.29373509 | G86: =AVERAGE(J86:M86) -> 0.45334584 | H86: =IF(O86<=30,"YES","") -> YES | J86: ='Combined District Data'!H312 -> 0.46517413 | K86: ='Combined District Data'!H313 -> 0.43892508 | L86: ='Combined District Data'!H314 -> 0.46535581 | M86: ='Combined District Data'!H315 -> 0.44392833 | N86: =F86+(1-E86) -> 0.59254682 | O86: =RANK(N86,$N$9:$N$94,1) -> 20
A87: Packer Township | B87: Carbon | C87: Estimated | D87: =SLOPE(J87:M87,$A$6:$D$6) -> 0.57539997 | E87: =RSQ(J87:M87,$A$6:$D$6) -> 0.3194175 | F87: =ABS(D87-1) -> 0.42460003 | G87: =AVERAGE(J87:M87) -> 0.23303432 | H87: =IF(O87<=30,"YES","") | J87: ='Combined District Data'!H316 -> 0.24065421 | K87: ='Combined District Data'!H317 -> 0.21034483 | L87: ='Combined District Data'!H318 -> 0.24950884 | M87: ='Combined District Data'!H319 -> 0.23162939 | N87: =F87+(1-E87) -> 1.1051825 | O87: =RANK(N87,$N$9:$N$94,1) -> 54
A88: Palmerton Borough | B88: Carbon | C88: Estimated | D88: =SLOPE(J88:M88,$A$6:$D$6) -> 0.68752687 | E88: =RSQ(J88:M88,$A$6:$D$6) -> 0.64327887 | F88: =ABS(D88-1) -> 0.31247313 | G88: =AVERAGE(J88:M88) -> 0.41814895 | H88: =IF(O88<=30,"YES","") -> YES | J88: ='Combined District Data'!H320 -> 0.42936508 | K88: ='Combined District Data'!H321 -> 0.40247973 | L88: ='Combined District Data'!H322 -> 0.43083236 | M88: ='Combined District Data'!H323 -> 0.40991864 | N88: =F88+(1-E88) -> 0.66919427 | O88: =RANK(N88,$N$9:$N$94,1) -> 24
A89: Parryville Borough | B89: Carbon | C89: Estimated | D89: =SLOPE(J89:M89,$A$6:$D$6) -> 0.6389981 | E89: =RSQ(J89:M89,$A$6:$D$6) -> 0.53417512 | F89: =ABS(D89-1) -> 0.3610019 | G89: =AVERAGE(J89:M89) -> 0.38261196 | H89: =IF(O89<=30,"YES","") | J89: ='Combined District Data'!H324 -> 0.39230769 | K89: ='Combined District Data'!H325 -> 0.36548223 | L89: ='Combined District Data'!H326 -> 0.39655172 | M89: ='Combined District Data'!H327 -> 0.37610619 | N89: =F89+(1-E89) -> 0.82682678 | O89: =RANK(N89,$N$9:$N$94,1) -> 37
A90: Penn Forest Township | B90: Carbon | C90: Estimated | D90: =SLOPE(J90:M90,$A$6:$D$6) -> 0.66276884 | E90: =RSQ(J90:M90,$A$6:$D$6) -> 0.60044523 | F90: =ABS(D90-1) -> 0.33723116 | G90: =AVERAGE(J90:M90) -> 0.39899825 | H90: =IF(O90<=30,"YES","") -> YES | J90: ='Combined District Data'!H328 -> 0.40954198 | K90: ='Combined District Data'!H329 -> 0.38284663 | L90: ='Combined District Data'!H330 -> 0.41203704 | M90: ='Combined District Data'!H331 -> 0.39156734 | N90: =F90+(1-E90) -> 0.73678593 | O90: =RANK(N90,$N$9:$N$94,1) -> 30
A91: Summit Hill Borough | B91: Carbon | C91: Estimated | D91: =SLOPE(J91:M91,$A$6:$D$6) -> 0.71282823 | E91: =RSQ(J91:M91,$A$6:$D$6) -> 0.75703194 | F91: =ABS(D91-1) -> 0.28717177 | G91: =AVERAGE(J91:M91) -> 0.49181887 | H91: =IF(O91<=30,"YES","") -> YES | J91: ='Combined District Data'!H332 -> 0.50393701 | K91: ='Combined District Data'!H333 -> 0.47956823 | L91: ='Combined District Data'!H334 -> 0.50308914 | M91: ='Combined District Data'!H335 -> 0.48068107 | N91: =F91+(1-E91) -> 0.53013982 | O91: =RANK(N91,$N$9:$N$94,1) -> 16
A92: Towamensing Township | B92: Carbon | C92: Estimated | D92: =SLOPE(J92:M92,$A$6:$D$6) -> 0.64311862 | E92: =RSQ(J92:M92,$A$6:$D$6) -> 0.48805348 | F92: =ABS(D92-1) -> 0.35688138 | G92: =AVERAGE(J92:M92) -> 0.32973935 | H92: =IF(O92<=30,"YES","") | J92: ='Combined District Data'!H336 -> 0.3395189 | K92: ='Combined District Data'!H337 -> 0.31061947 | L92: ='Combined District Data'!H338 -> 0.3440806 | M92: ='Combined District Data'!H339 -> 0.32473842 | N92: =F92+(1-E92) -> 0.8688279 | O92: =RANK(N92,$N$9:$N$94,1) -> 43
A93: Weatherly Borough | B93: Carbon | C93: Estimated | D93: =SLOPE(J93:M93,$A$6:$D$6) -> 0.66929087 | E93: =RSQ(J93:M93,$A$6:$D$6) -> 0.54044341 | F93: =ABS(D93-1) -> 0.33070913 | G93: =AVERAGE(J93:M93) -> 0.34803903 | H93: =IF(O93<=30,"YES","") | J93: ='Combined District Data'!H340 -> 0.35857805 | K93: ='Combined District Data'!H341 -> 0.3296146 | L93: ='Combined District Data'!H342 -> 0.36185819 | M93: ='Combined District Data'!H343 -> 0.34210526 | N93: =F93+(1-E93) -> 0.79026572 | O93: =RANK(N93,$N$9:$N$94,1) -> 34
A94: Weissport Borough | B94: Carbon | C94: Estimated | D94: =SLOPE(J94:M94,$A$6:$D$6) -> 0.43575298 | E94: =RSQ(J94:M94,$A$6:$D$6) -> 0.37455421 | F94: =ABS(D94-1) -> 0.56424702 | G94: =AVERAGE(J94:M94) -> 0.40983724 | H94: =IF(O94<=30,"YES","") | J94: ='Combined District Data'!H344 -> 0.41428571 | K94: ='Combined District Data'!H345 -> 0.39830508 | L94: ='Combined District Data'!H346 -> 0.42424242 | M94: ='Combined District Data'!H347 -> 0.40251572 | N94: =F94+(1-E94) -> 1.1896928 | O94: =RANK(N94,$N$9:$N$94,1) -> 57

Sheet Carbon 2026 Registration
A1: Municipality | B1: Reg D-R (Aug 2026 snapshot) | C1: 2018 Ballots (actual turnout) | D1: 2022 Ballots (actual turnout)
A2: Banks Township | B2: 0.0544 | C2: 290 | D2: 336
A3: Beaver Meadows Borough | B3: -0.2367 | C3: 215 | D3: 277
A4: Bowmanstown Borough | B4: -0.2708 | C4: 242 | D4: 320
A5: East Penn Township | B5: -0.3559 | C5: 917 | D5: 1204
A6: East Side Borough | B6: -0.1758 | C6: 65 | D6: 84
A7: Franklin Township | B7: -0.3415 | C7: 1338 | D7: 1779
A8: Jim Thorpe Borough | B8: -0.0499 | C8: 1487 | D8: 1911
A9: Kidder Township | B9: -0.2766 | C9: 471 | D9: 707
A10: Lansford Borough | B10: -0.0367 | C10: 676 | D10: 902
A11: Lausanne Township | B11: -0.388 | C11: 67 | D11: 102
A12: Lehigh Township | B12: -0.5436 | C12: 179 | D12: 225
A13: Lehighton Borough | B13: -0.1529 | C13: 1163 | D13: 1515
... A24: Weissport Borough | B24: -0.177 | C24: 70 | D24: 99

Sheet Kiley - 2026 Vote Forecast
A1: 2026 House Vote Forecast (86 Municipalities: Actual Trend + Carbon Estimate)
A2: Lehigh+Northampton (63 towns): same trend method as before -- turnout extrapolated from the two prior midterm cycles (2018, 2022); Dem share via linear trend across 2018-2024. Carbon (23 towns): Dem share estimated by applying the 2024 registration-to-vote calibration to each town's most current (Aug 2026) registration lean; turnout extrapolated the same midterm-only way from actual historical ballot counts.
A4: Municipality | B4: County | C4: Source | D4: Projected Total Votes 2026 | E4: Projected Dem Share 2026 | F4: Projected Dem Votes 2026 | G4: Projected Rep Votes 2026 | H4: Projected Winner
A5: Alburtis | B5: Lehigh | C5: Actual-based | D5: =MAX(0, 2*'House Vote Data (Actual)'!G4 - 'House Vote Data (Actual)'!G2) -> 1130 | E5: =MIN(1,MAX(0, SLOPE(J5:M5,{2018,2020,2022,2024})*2026 + INTERCEPT(J5:M5,{2018,2020,2022,2024}))) -> 0.43013086 | F5: =ROUND(D5*E5,0) -> 486 | G5: =ROUND(D5*(1-E5),0) -> 644 | H5: =IF(E5>0.5,"Democrat","Republican") -> Republican | J5: ='House Vote Data (Actual)'!H2 -> 0.50669643 | K5: ='House Vote Data (Actual)'!H3 -> 0.46700508 | L5: ='House Vote Data (Actual)'!H4 -> 0.48766041 | M5: ='House Vote Data (Actual)'!H5 -> 0.43964887
A6: Allentown | B6: Lehigh | C6: Actual-based | D6: =MAX(0, 2*'House Vote Data (Actual)'!G8 - 'House Vote Data (Actual)'!G6) -> 21769 | E6: =MIN(1,MAX(0, SLOPE(J6:M6,{2018,2020,2022,2024})*2026 + INTERCEPT(J6:M6,{2018,2020,2022,2024}))) -> 0.63099348 | F6: =ROUND(D6*E6,0) -> 13736 | G6: =ROUND(D6*(1-E6),0) -> 8033 | H6: =IF(E6>0.5,"Democrat","Republican") -> Democrat | J6: ='House Vote Data (Actual)'!H6 -> 0.71055542 | K6: ='House Vote Data (Actual)'!H7 -> 0.68359012 | L6: ='House Vote Data (Actual)'!H8 -> 0.68129794 | M6: ='House Vote Data (Actual)'!H9 -> 0.64562222
A7: Bethlehem | B7: Lehigh | C7: Actual-based | D7: =MAX(0, 2*'House Vote Data (Actual)'!G12 - 'House Vote Data (Actual)'!G10) -> 8404 | E7: =MIN(1,MAX(0, SLOPE(J7:M7,{2018,2020,2022,2024})*2026 + INTERCEPT(J7:M7,{2018,2020,2022,2024}))) -> 0.64305726 | F7: =ROUND(D7*E7,0) -> 5404 | G7: =ROUND(D7*(1-E7),0) -> 3000 | H7: =IF(E7>0.5,"Democrat","Republican") -> Democrat | J7: ='House Vote Data (Actual)'!H10 -> 0.63702901 | K7: ='House Vote Data (Actual)'!H11 -> 0.63115313 | L7: ='House Vote Data (Actual)'!H12 -> 0.65720441 | M7: ='House Vote Data (Actual)'!H13 -> 0.63296956
A8: Catasauqua | B8: Lehigh | C8: Actual-based | D8: =MAX(0, 2*'House Vote Data (Actual)'!G16 - 'House Vote Data (Actual)'!G14) -> 2160 | E8: =MIN(1,MAX(0, SLOPE(J8:M8,{2018,2020,2022,2024})*2026 + INTERCEPT(J8:M8,{2018,2020,2022,2024}))) -> 0.50429424 | F8: =ROUND(D8*E8,0) -> 1089 | G8: =ROUND(D8*(1-E8),0) -> 1071 | H8: =IF(E8>0.5,"Democrat","Republican") -> Democrat | J8: ='House Vote Data (Actual)'!H14 -> 0.55194175 | K8: ='House Vote Data (Actual)'!H15 -> 0.51397011 | L8: ='House Vote Data (Actual)'!H16 -> 0.53791469 | M8: ='House Vote Data (Actual)'!H17 -> 0.51130777
A9: Coopersburg | B9: Lehigh | C9: Actual-based | D9: =MAX(0, 2*'House Vote Data (Actual)'!G20 - 'House Vote Data (Actual)'!G18) -> 1433 | E9: =MIN(1,MAX(0, SLOPE(J9:M9,{2018,2020,2022,2024})*2026 + INTERCEPT(J9:M9,{2018,2020,2022,2024}))) -> 0.47707595 | F9: =ROUND(D9*E9,0) -> 684 | G9: =ROUND(D9*(1-E9),0) -> 749 | H9: =IF(E9>0.5,"Democrat","Republican") -> Republican | J9: ='House Vote Data (Actual)'!H18 -> 0.51044776 | K9: ='House Vote Data (Actual)'!H19 -> 0.47090301 | L9: ='House Vote Data (Actual)'!H20 -> 0.50943396 | M9: ='House Vote Data (Actual)'!H21 -> 0.47758285
A10: Coplay | B10: Lehigh | C10: Actual-based | D10: =MAX(0, 2*'House Vote Data (Actual)'!G24 - 'House Vote Data (Actual)'!G22) -> 1365 | E10: =MIN(1,MAX(0, SLOPE(J10:M10,{2018,2020,2022,2024})*2026 + INTERCEPT(J10:M10,{2018,2020,2022,2024}))) -> 0.49815122 | F10: =ROUND(D10*E10,0) -> 680 | G10: =ROUND(D10*(1-E10),0) -> 685 | H10: =IF(E10>0.5,"Democrat","Republican") -> Republican | J10: ='House Vote Data (Actual)'!H22 -> 0.53702197 | K10: ='House Vote Data (Actual)'!H23 -> 0.50228833 | L10: ='House Vote Data (Actual)'!H24 -> 0.53276793 | M10: ='House Vote Data (Actual)'!H25 -> 0.50027824
A11: Emmaus | B11: Lehigh | C11: Actual-based | D11: =MAX(0, 2*'House Vote Data (Actual)'!G28 - 'House Vote Data (Actual)'!G26) -> 5598 | E11: =MIN(1,MAX(0, SLOPE(J11:M11,{2018,2020,2022,2024})*2026 + INTERCEPT(J11:M11,{2018,2020,2022,2024}))) -> 0.54336209 | F11: =ROUND(D11*E11,0) -> 3042 | G11: =ROUND(D11*(1-E11),0) -> 2556 | H11: =IF(E11>0.5,"Democrat","Republican") -> Democrat | J11: ='House Vote Data (Actual)'!H26 -> 0.53260394 | K11: ='House Vote Data (Actual)'!H27 -> 0.52433936 | L11: ='House Vote Data (Actual)'!H28 -> 0.55743509 | M11: ='House Vote Data (Actual)'!H29 -> 0.53094651
A12: Fountain Hill | B12: Lehigh | C12: Actual-based | D12: =MAX(0, 2*'House Vote Data (Actual)'!G32 - 'House Vote Data (Actual)'!G30) -> 1480 | E12: =MIN(1,MAX(0, SLOPE(J12:M12,{2018,2020,2022,2024})*2026 + INTERCEPT(J12:M12,{2018,2020,2022,2024}))) -> 0.65632144 | F12: =ROUND(D12*E12,0) -> 971 | G12: =ROUND(D12*(1-E12),0) -> 509 | H12: =IF(E12>0.5,"Democrat","Republican") -> Democrat | J12: ='House Vote Data (Actual)'!H30 -> 0.66563659 | K12: ='House Vote Data (Actual)'!H31 -> 0.66771867 | L12: ='House Vote Data (Actual)'!H32 -> 0.69076824 | M12: ='House Vote Data (Actual)'!H33 -> 0.64375562
A13: Hanover | B13: Lehigh | C13: Actual-based | D13: =MAX(0, 2*'House Vote Data (Actual)'!G36 - 'House Vote Data (Actual)'!G34) -> 431 | E13: =MIN(1,MAX(0, SLOPE(J13:M13,{2018,2020,2022,2024})*2026 + INTERCEPT(J13:M13,{2018,2020,2022,2024}))) -> 0.52282311 | F13: =ROUND(D13*E13,0) -> 225 | G13: =ROUND(D13*(1-E13),0) -> 206 | H13: =IF(E13>0.5,"Democrat","Republican") -> Democrat | J13: ='House Vote Data (Actual)'!H34 -> 0.58449304 | K13: ='House Vote Data (Actual)'!H35 -> 0.57122708 | L13: ='House Vote Data (Actual)'!H36 -> 0.56102784 | M13: ='House Vote Data (Actual)'!H37 -> 0.53455571
A14: Heidelberg | B14: Lehigh | C14: Actual-based | D14: =MAX(0, 2*'House Vote Data (Actual)'!G40 - 'House Vote Data (Actual)'!G38) -> 1774 | E14: =MIN(1,MAX(0, SLOPE(J14:M14,{2018,2020,2022,2024})*2026 + INTERCEPT(J14:M14,{2018,2020,2022,2024}))) -> 0.30410583 | F14: =ROUND(D14*E14,0) -> 539 | G14: =ROUND(D14*(1-E14),0) -> 1235 | H14: =IF(E14>0.5,"Democrat","Republican") -> Republican | J14: ='House Vote Data (Actual)'!H38 -> 0.34922861 | K14: ='House Vote Data (Actual)'!H39 -> 0.31014941 | L14: ='House Vote Data (Actual)'!H40 -> 0.3325 | M14: ='House Vote Data (Actual)'!H41 -> 0.31247014
A15: Lower Macungie | B15: Lehigh | C15: Actual-based | D15: =MAX(0, 2*'House Vote Data (Actual)'!G44 - 'House Vote Data (Actual)'!G42) -> 17421 | E15: =MIN(1,MAX(0, SLOPE(J15:M15,{2018,2020,2022,2024})*2026 + INTERCEPT(J15:M15,{2018,2020,2022,2024}))) -> 0.50777979 | F15: =ROUND(D15*E15,0) -> 8846 | G15: =ROUND(D15*(1-E15),0) -> 8575 | H15: =IF(E15>0.5,"Democrat","Republican") -> Democrat | J15: ='House Vote Data (Actual)'!H42 -> 0.49955126 | K15: ='House Vote Data (Actual)'!H43 -> 0.49414023 | L15: ='House Vote Data (Actual)'!H44 -> 0.523914 | M15: ='House Vote Data (Actual)'!H45 -> 0.49559842
A16: Lower Milford | B16: Lehigh | C16: Actual-based | D16: =MAX(0, 2*'House Vote Data (Actual)'!G48 - 'House Vote Data (Actual)'!G46) -> 2422 | E16: =MIN(1,MAX(0, SLOPE(J16:M16,{2018,2020,2022,2024})*2026 + INTERCEPT(J16:M16,{2018,2020,2022,2024}))) -> 0.38557709 | F16: =ROUND(D16*E16,0) -> 934 | G16: =ROUND(D16*(1-E16),0) -> 1488 | H16: =IF(E16>0.5,"Democrat","Republican") -> Republican | J16: ='House Vote Data (Actual)'!H46 -> 0.38842105 | K16: ='House Vote Data (Actual)'!H47 -> 0.36565978 | L16: ='House Vote Data (Actual)'!H48 -> 0.39333642 | M16: ='House Vote Data (Actual)'!H49 -> 0.38311941
A17: Lowhill | B17: Lehigh | C17: Actual-based | D17: =MAX(0, 2*'House Vote Data (Actual)'!G52 - 'House Vote Data (Actual)'!G50) -> 1305 | E17: =MIN(1,MAX(0, SLOPE(J17:M17,{2018,2020,2022,2024})*2026 + INTERCEPT(J17:M17,{2018,2020,2022,2024}))) -> 0.35994473 | F17: =ROUND(D17*E17,0) -> 470 | G17: =ROUND(D17*(1-E17),0) -> 835 | H17: =IF(E17>0.5,"Democrat","Republican") -> Republican | J17: ='House Vote Data (Actual)'!H50 -> 0.36403897 | K17: ='House Vote Data (Actual)'!H51 -> 0.35819892 | L17: ='House Vote Data (Actual)'!H52 -> 0.37551356 | M17: ='House Vote Data (Actual)'!H53 -> 0.35420744
A18: Lynn | B18: Lehigh | C18: Actual-based | D18: =MAX(0, 2*'House Vote Data (Actual)'!G56 - 'House Vote Data (Actual)'!G54) -> 2385 | E18: =MIN(1,MAX(0, SLOPE(J18:M18,{2018,2020,2022,2024})*2026 + INTERCEPT(J18:M18,{2018,2020,2022,2024}))) -> 0.31893796 | F18: =ROUND(D18*E18,0) -> 761 | G18: =ROUND(D18*(1-E18),0) -> 1624 | H18: =IF(E18>0.5,"Democrat","Republican") -> Republican | J18: ='House Vote Data (Actual)'!H54 -> 0.32431026 | K18: ='House Vote Data (Actual)'!H55 -> 0.32179536 | L18: ='House Vote Data (Actual)'!H56 -> 0.33395262 | M18: ='House Vote Data (Actual)'!H57 -> 0.31411678
A19: Macungie | B19: Lehigh | C19: Actual-based | D19: =MAX(0, 2*'House Vote Data (Actual)'!G60 - 'House Vote Data (Actual)'!G58) -> 1517 | E19: =MIN(1,MAX(0, SLOPE(J19:M19,{2018,2020,2022,2024})*2026 + INTERCEPT(J19:M19,{2018,2020,2022,2024}))) -> 0.54466861 | F19: =ROUND(D19*E19,0) -> 826 | G19: =ROUND(D19*(1-E19),0) -> 691 | H19: =IF(E19>0.5,"Democrat","Republican") -> Democrat | J19: ='House Vote Data (Actual)'!H58 -> 0.52547529 | K19: ='House Vote Data (Actual)'!H59 -> 0.53688745 | L19: ='House Vote Data (Actual)'!H60 -> 0.55649718 | M19: ='House Vote Data (Actual)'!H61 -> 0.52915767
A20: North Whitehall | B20: Lehigh | C20: Actual-based | D20: =MAX(0, 2*'House Vote Data (Actual)'!G64 - 'House Vote Data (Actual)'!G62) -> 8557 | E20: =MIN(1,MAX(0, SLOPE(J20:M20,{2018,2020,2022,2024})*2026 + INTERCEPT(J20:M20,{2018,2020,2022,2024}))) -> 0.41352492 | F20: =ROUND(D20*E20,0) -> 3539 | G20: =ROUND(D20*(1-E20),0) -> 5018 | H20: =IF(E20>0.5,"Democrat","Republican") -> Republican | J20: ='House Vote Data (Actual)'!H62 -> 0.40424604 | K20: ='House Vote Data (Actual)'!H63 -> 0.39963111 | L20: ='House Vote Data (Actual)'!H64 -> 0.42179603 | M20: ='House Vote Data (Actual)'!H65 -> 0.40474992
A21: Salisbury | B21: Lehigh | C21: Actual-based | D21: =MAX(0, 2*'House Vote Data (Actual)'!G68 - 'House Vote Data (Actual)'!G66) -> 6768 | E21: =MIN(1,MAX(0, SLOPE(J21:M21,{2018,2020,2022,2024})*2026 + INTERCEPT(J21:M21,{2018,2020,2022,2024}))) -> 0.50179344 | F21: =ROUND(D21*E21,0) -> 3396 | G21: =ROUND(D21*(1-E21),0) -> 3372 | H21: =IF(E21>0.5,"Democrat","Republican") -> Democrat | J21: ='House Vote Data (Actual)'!H66 -> 0.49346515 | K21: ='House Vote Data (Actual)'!H67 -> 0.49302496 | L21: ='House Vote Data (Actual)'!H68 -> 0.50863693 | M21: ='House Vote Data (Actual)'!H69 -> 0.49420754
A22: Slatington | B22: Lehigh | C22: Actual-based | D22: =MAX(0, 2*'House Vote Data (Actual)'!G72 - 'House Vote Data (Actual)'!G70) -> 1492 | E22: =MIN(1,MAX(0, SLOPE(J22:M22,{2018,2020,2022,2024})*2026 + INTERCEPT(J22:M22,{2018,2020,2022,2024}))) -> 0.41322592 | F22: =ROUND(D22*E22,0) -> 617 | G22: =ROUND(D22*(1-E22),0) -> 875 | H22: =IF(E22>0.5,"Democrat","Republican") -> Republican | J22: ='House Vote Data (Actual)'!H70 -> 0.44380165 | K22: ='House Vote Data (Actual)'!H71 -> 0.3943068 | L22: ='House Vote Data (Actual)'!H72 -> 0.45225759 | M22: ='House Vote Data (Actual)'!H73 -> 0.40899796
A23: South Whitehall | B23: Lehigh | C23: Actual-based | D23: =MAX(0, 2*'House Vote Data (Actual)'!G76 - 'House Vote Data (Actual)'!G74) -> 11129 | E23: =MIN(1,MAX(0, SLOPE(J23:M23,{2018,2020,2022,2024})*2026 + INTERCEPT(J23:M23,{2018,2020,2022,2024}))) -> 0.54126914 | F23: =ROUND(D23*E23,0) -> 6024 | G23: =ROUND(D23*(1-E23),0) -> 5105 | H23: =IF(E23>0.5,"Democrat","Republican") -> Democrat | J23: ='House Vote Data (Actual)'!H74 -> 0.54989571 | K23: ='House Vote Data (Actual)'!H75 -> 0.53241776 | L23: ='House Vote Data (Actual)'!H76 -> 0.56319794 | M23: ='House Vote Data (Actual)'!H77 -> 0.53461802
A24: Upper Macungie | B24: Lehigh | C24: Actual-based | D24: =MAX(0, 2*'House Vote Data (Actual)'!G80 - 'House Vote Data (Actual)'!G78) -> 12593 | E24: =MIN(1,MAX(0, SLOPE(J24:M24,{2018,2020,2022,2024})*2026 + INTERCEPT(J24:M24,{2018,2020,2022,2024}))) -> 0.52147529 | F24: =ROUND(D24*E24,0) -> 6567 | G24: =ROUND(D24*(1-E24),0) -> 6026 | H24: =IF(E24>0.5,"Democrat","Republican") -> Democrat | J24: ='House Vote Data (Actual)'!H78 -> 0.5168528 | K24: ='House Vote Data (Actual)'!H79 -> 0.51668275 | L24: ='House Vote Data (Actual)'!H80 -> 0.53337476 | M24: ='House Vote Data (Actual)'!H81 -> 0.51321431
A25: Upper Milford | B25: Lehigh | C25: Actual-based | D25: =MAX(0, 2*'House Vote Data (Actual)'!G84 - 'House Vote Data (Actual)'!G82) -> 5223 | E25: =MIN(1,MAX(0, SLOPE(J25:M25,{2018,2020,2022,2024})*2026 + INTERCEPT(J25:M25,{2018,2020,2022,2024}))) -> 0.43596806 | F25: =ROUND(D25*E25,0) -> 2277 | G25: =ROUND(D25*(1-E25),0) -> 2946 | H25: =IF(E25>0.5,"Democrat","Republican") -> Republican | J25: ='House Vote Data (Actual)'!H82 -> 0.44453355 | K25: ='House Vote Data (Actual)'!H83 -> 0.4292061 | L25: ='House Vote Data (Actual)'!H84 -> 0.45336903 | M25: ='House Vote Data (Actual)'!H85 -> 0.43155032
A26: Upper Saucon | B26: Lehigh | C26: Actual-based | D26: =MAX(0, 2*'House Vote Data (Actual)'!G88 - 'House Vote Data (Actual)'!G86) -> 9924 | E26: =MIN(1,MAX(0, SLOPE(J26:M26,{2018,2020,2022,2024})*2026 + INTERCEPT(J26:M26,{2018,2020,2022,2024}))) -> 0.49920163 | F26: =ROUND(D26*E26,0) -> 4954 | G26: =ROUND(D26*(1-E26),0) -> 4970 | H26: =IF(E26>0.5,"Democrat","Republican") -> Republican | J26: ='House Vote Data (Actual)'!H86 -> 0.47888801 | K26: ='House Vote Data (Actual)'!H87 -> 0.46685404 | L26: ='House Vote Data (Actual)'!H88 -> 0.50210826 | M26: ='House Vote Data (Actual)'!H89 -> 0.4875915
A27: Washington | B27: Lehigh | C27: Actual-based | D27: =MAX(0, 2*'House Vote Data (Actual)'!G92 - 'House Vote Data (Actual)'!G90) -> 3464 | E27: =MIN(1,MAX(0, SLOPE(J27:M27,{2018,2020,2022,2024})*2026 + INTERCEPT(J27:M27,{2018,2020,2022,2024}))) -> 0.32534082 | F27: =ROUND(D27*E27,0) -> 1127 | G27: =ROUND(D27*(1-E27),0) -> 2337 | H27: =IF(E27>0.5,"Democrat","Republican") -> Republican | J27: ='House Vote Data (Actual)'!H90 -> 0.34340659 | K27: ='House Vote Data (Actual)'!H91 -> 0.32318194 | L27: ='House Vote Data (Actual)'!H92 -> 0.35063207 | M27: ='House Vote Data (Actual)'!H93 -> 0.32172808
