Workbook

Sheet Intro
A1: PA-07 2026 House Forecasts: Every Forecast, Compiled
A2: Kiley Meringer · PSTD 400: Senior Seminar Congressional Forecasting Project · Compiled Oct. 26, 2026
A4: Bottom line
A5: Of 19 forecasts, 14 predict that Rep. Ryan Mackenzie (R) wins, including every forecast that came within half a point of the real 2024 result. The margin is narrow: the best-tested forecasts put Bob Brooks (D) between 49.5% and 50.0% of the two-party vote. Best description: Lean Republican.
A7: What is in this workbook
A8: How to Read | B8: Definitions, how strict each backtest is, and what the ratings mean. Start here if any term is unfamiliar.
A9: Summary | B9: Headline numbers, a chart of every forecast, and how the project developed.
A10: Results | B10: One row per forecast: predicted winner, margin, 2024 backtest accuracy, rating and a one-sentence verdict.
A11: F01 Trend v2 | B11: F01–F19: one tab per forecast with its methodology, 2026 forecast, 2024 backtest and a plain-language summary on one page, followed by the town- or precinct-level detail.
A12: Bellwether Tests | B12: Every bellwether test: selection rule, stability, registration, demographics, comparison with Professor Crain’s precincts, and whether bellwethers improve the baseline.
A13: Backtest-Only Tests | B13: Twelve methods tested on 2024 but never used for a 2026 forecast.
A14: Final Assessment | B14: Ranking by backtest accuracy, how often each candidate is predicted, an accuracy-weighted forecast, and the conclusion.
A15: Data & Caveats | B15: How the data improved over the project and the main limitations.
A16: Sources | B16: Where every number comes from.
A18: Suggested reading order
A19: Summary → Results → Final Assessment, then open any forecast tab from Results for detail. Use How to Read for definitions.
A21: Conventions
A22: • All shares are Brooks’s (D) share of the two-party vote; above 50% means Brooks wins.
A23: • A “miss” is forecast minus actual, in percentage points: negative = too Republican, positive = too Democratic.
A24: • Blue numbers are typed in from source files; black numbers are formulas.

Sheet How to Read
A1: How to read this workbook
A3: The question
A4: Every forecast here answers the same question: what share of the two-party vote will Bob Brooks (D) win against Rep. Ryan Mackenzie (R) in Pennsylvania’s 7th District on Nov. 3, 2026? Above 50% means Brooks wins; below 50% means Mackenzie wins.
A6: Key terms
A7: Term | B7: Meaning
A8: Two-party share | B8: Votes for one major-party candidate divided by votes for both major-party candidates. Third-party and write-in votes are left out.
A9: Margin | B9: Brooks’s share minus Mackenzie’s share, in percentage points. A margin of −2.0 means Mackenzie leads by 2 points.
A10: Backtest | B10: A test of the method on an election that already happened. The method is run using only data from before that election, and its prediction is compared with the real result.
A11: Out of sample | B11: The election being predicted was not used to build or tune the method. This is what makes a backtest fair.
A12: In sample | B12: The method was fitted and scored on the same data. In-sample results look better than the method would do on a new election.
A13: Miss | B13: Forecast minus actual result, in percentage points. Negative = the forecast was too Republican; positive = too Democratic.
A14: Average miss per town or precinct | B14: The typical size of the error for individual towns or precincts. Good for judging the map, but towns of very different sizes count equally, so it is not comparable across levels.
A15: District result miss | B15: How far the forecast’s district-wide total was from the real district result. This is the fairest single comparison across all forecasts, and the one used to rank them.
A16: Municipal / precinct | B16: Municipal forecasts predict each of the 89 towns; precinct forecasts predict each of roughly 370 voting precincts. District totals add up those rows.
A17: Beta | B17: How strongly a town moves when the whole district moves. A beta of 1.5 means a town shifts 1.5 points for every 1 point the district shifts.
A18: Bellwether precinct | B18: A precinct whose vote has closely matched the district’s. Reading a set of bellwethers gives an estimate of the district result.
... A21: Random forest | B21: A machine-learning model that averages the predictions of hundreds of decision trees.
A23: How strict each backtest is
A24: Level | B24: Forecasts | C24: What it means
A25: Strongest | B25: F18, F19, group baseline v11 | C25: Tested on two elections (2022 and 2024). Only earlier elections were used, and turnout was projected rather than taken from the real result.
A26: Standard | B26: F04–F15 | C26: Tested on 2024 only. Trained on 2018–2022; nothing from 2024 was used.
A27: Limited | B27: F01, F16, F17, group baseline v0.1 | C27: F01 covers only Lehigh and Northampton. F16 and F17 rest on v0.1, whose 2024 backtest used actual 2024 turnout; F17’s precinct selection data are not available.
A28: Not available | B28: F02, F03 | C28: Only town-by-town accuracy was saved; the district-level check cannot be computed.
A30: What the ratings mean
A31: Rating | B31: Meaning
A32: Strongest | B32: Passed the strictest backtests. Most reliable evidence, though only two elections.
A33: Good | B33: District result miss under half a point in a standard backtest.
A34: Fair | B34: Miss between half a point and 1.5 points, or a caveat about the test.
A35: Weak | B35: Miss larger than 1.5 points. Kept for completeness; should carry little weight.
A36: Superseded | B36: Built on early data that was later corrected. Replaced by a newer version.
A38: Cell colors and formulas
A39: Blue numbers are values typed in from source files; black numbers are formulas. The Results, Final Assessment and Summary tabs recalculate automatically if a forecast tab changes.

Sheet Summary
A1: Summary
A3: Forecasts compiled | C3: =COUNTA(Results!A5:A23) -> 19
A4: Predict Mackenzie | C4: =COUNTIF(Results!H5:H23,"Mackenzie") -> 14
A5: Predict Brooks | C5: =COUNTIF(Results!H5:H23,"Brooks") -> 5
A6: Average Brooks share across forecasts | C6: =AVERAGE(Results!E5:E23) -> 0.48812613
A7: Range of Brooks share | C7: =TEXT(MIN(Results!E5:E23),"0.0%")&" to "&TEXT(MAX(Results!E5:E23),"0.0%") -> 46.0% to 51.2%
A8: Accuracy-weighted Brooks share | C8: ='Final Assessment'!F37 -> 0.48351408
A9: Accuracy-weighted winner | C9: ='Final Assessment'!F39 -> Mackenzie
A10: Best 2024 district-level backtest | C10: ='Final Assessment'!B7&": "&'Final Assessment'!C7&" ("&TEXT('Final Assessment'!E7,"+0.00;-0.00")&" pts)" -> F16: Bellwether reading, 10-precinct set, on the v0.1 baseline (-0.15 pts)
A11: Methods tested on 2024 only (no 2026 forecast) | C11: 8 new methods, plus a calibration check
A13: Story of the project
A14: • Sept. 14: three municipal methods (Trend, Beta-Adjusted, Regression) on early data with Carbon estimated and Monroe missing. Two of three favored Mackenzie.
A15: • Sept. 16–17: rebuilt on certified returns for all 89 towns, then repeated at the precinct level. Correcting the 2020 result reversed the method ranking: Beta-Adjusted became the best backtest and Regression the worst.
A16: • Sept. 24: the same methods entered in the class template; four new adjustments tested (Cycle-Type Beta adopted).
A17: • Sept. 27: five more methods backtested (Stacking and Uniform Swing best on average miss per town); no 2026 forecasts were run for these.
A18: • Oct. 21–26: bellwether precincts selected by a fixed rule, compared with Professor Crain’s set, and combined with the group baseline. Adding bellwethers did not improve the honest v11 backtests.
A20: Bottom line
A21: Most forecasts, and all of the best-backtested ones, predict a narrow Mackenzie win. The race is best described as Lean Republican with a small margin; the newest and most rigorously tested forecasts put Brooks between 49.5% and 50.0%.
A23: Brooks share by forecast (50% line = tie)
A46: Reading the chart: bars to the right of 50% predict Brooks. Most bars sit between 46% and 50%; the bars above 50% are mostly regression versions (F03, F06, F09, F15) and the v11 bellwether reading (F18).

Sheet Results
A1: Results: every forecast at a glance
A2: Each row is one 2026 forecast. “Brooks share” is Bob Brooks’s (D) share of the two-party House vote; above 50% means Brooks wins. A “miss” is the forecast minus the actual result, in percentage points: negative means the forecast was too Republican, positive too Democratic. Click a forecast name to open its full tab.
A4: ID | B4: Forecast (click to open) | C4: Date run | D4: Level of detail | E4: Brooks (D) share | F4: Mackenzie (R) share | G4: Margin, Brooks − Mackenzie (pts) | H4: Predicted winner | I4: 2024 backtest: average miss per town or precinct (pts) | J4: 2024 backtest: winners called correctly | K4: 2024 backtest: district result miss (pts) | L4: 2022 backtest: district result miss (pts) | M4: How strict the backtest was | N4: Built on superseded data? | O4: Rating | P4: Verdict in brief
A5: F01 | B5: =HYPERLINK("#'F01 Trend v2'!A1","Simple Trend (municipal, v2)") -> Simple Trend (municipal, v2) | C5: Sept. 14 | D5: Municipality (86) | E5: ='F01 Trend v2'!C14 -> 0.49372 | F5: ='F01 Trend v2'!C15 -> 0.50628 | G5: ='F01 Trend v2'!C16 -> -1.256 | H5: ='F01 Trend v2'!C17 -> Mackenzie | I5: =IF(ISNUMBER('F01 Trend v2'!C22),'F01 Trend v2'!C22,"") -> 2.18 | J5: ='F01 Trend v2'!C23 -> 57 of 63 towns | K5: =IF(ISNUMBER('F01 Trend v2'!C24),'F01 Trend v2'!C24,"") -> 1.7409974 | L5: =IF(ISNUMBER('F01 Trend v2'!C25),'F01 Trend v2'!C25,"") | M5: Out of sample (unit-level); district miss is for Lehigh + Northampton only | N5: Yes | O5: Superseded | P5: The first forecast of the project. It predicted a narrow Mackenzie win (49.4% Brooks).
A6: F02 | B6: =HYPERLINK("#'F02 Beta v2'!A1","Beta-Adjusted (municipal, v2)") -> Beta-Adjusted (municipal, v2) | C6: Sept. 14 | D6: Municipality (86) | E6: ='F02 Beta v2'!C14 -> 0.48763 | F6: ='F02 Beta v2'!C15 -> 0.51237 | G6: ='F02 Beta v2'!C16 -> -2.474 | H6: ='F02 Beta v2'!C17 -> Mackenzie | I6: =IF(ISNUMBER('F02 Beta v2'!C22),'F02 Beta v2'!C22,"") -> 1.57 | J6: ='F02 Beta v2'!C23 -> 59 of 63 towns | K6: =IF(ISNUMBER('F02 Beta v2'!C24),'F02 Beta v2'!C24,"") | L6: =IF(ISNUMBER('F02 Beta v2'!C25),'F02 Beta v2'!C25,"") | M6: Out of sample (unit-level); town-by-town backtest predictions not saved in the source file | N6: Yes | O6: Superseded | P6: Predicted Mackenzie (48.8% Brooks). Replaced by F05, which uses the same method on corrected data.
A7: F03 | B7: =HYPERLINK("#'F03 Regression v2'!A1","Multi-Variable Regression (municipal, v2)") -> Multi-Variable Regression (municipal, v2) | C7: Sept. 14 | D7: Municipality (86) | E7: ='F03 Regression v2'!C14 -> 0.51198 | F7: ='F03 Regression v2'!C15 -> 0.48802 | G7: ='F03 Regression v2'!C16 -> 2.396 | H7: ='F03 Regression v2'!C17 -> Brooks | I7: =IF(ISNUMBER('F03 Regression v2'!C22),'F03 Regression v2'!C22,"") -> 1.13 | J7: ='F03 Regression v2'!C23 -> 61 of 63 towns | K7: =IF(ISNUMBER('F03 Regression v2'!C24),'F03 Regression v2'!C24,"") | L7: =IF(ISNUMBER('F03 Regression v2'!C25),'F03 Regression v2'!C25,"") | M7: Out of sample (unit-level); town-by-town backtest predictions not saved in the source file | N7: Yes | O7: Superseded | P7: Predicted a Brooks win (51.2%). Its strong-looking backtest did not survive the switch to complete, corrected data.
A8: F04 | B8: =HYPERLINK("#'F04 Trend v3'!A1","Simple Trend (municipal, v3)") -> Simple Trend (municipal, v3) | C8: Sept. 16 | D8: Municipality (89) | E8: ='F04 Trend v3'!C14 -> 0.47727 | F8: ='F04 Trend v3'!C15 -> 0.52273 | G8: ='F04 Trend v3'!C16 -> -4.546 | H8: ='F04 Trend v3'!C17 -> Mackenzie | I8: =IF(ISNUMBER('F04 Trend v3'!C22),'F04 Trend v3'!C22,"") -> 1.99 | J8: ='F04 Trend v3'!C23 -> 86 of 89 towns | K8: =IF(ISNUMBER('F04 Trend v3'!C24),'F04 Trend v3'!C24,"") -> 0.26874283 | L8: =IF(ISNUMBER('F04 Trend v3'!C25),'F04 Trend v3'!C25,"") | M8: Out of sample | N8: No | O8: Good | P8: Predicts Mackenzie (47.7% Brooks). In 2024 it came within about a quarter point of the district result, one of the best simple-method backtests.
A9: F05 | B9: =HYPERLINK("#'F05 Beta v3'!A1","Beta-Adjusted (municipal, v3)") -> Beta-Adjusted (municipal, v3) | C9: Sept. 16 | D9: Municipality (89) | E9: ='F05 Beta v3'!C14 -> 0.46765 | F9: ='F05 Beta v3'!C15 -> 0.53235 | G9: ='F05 Beta v3'!C16 -> -6.47 | H9: ='F05 Beta v3'!C17 -> Mackenzie | I9: =IF(ISNUMBER('F05 Beta v3'!C22),'F05 Beta v3'!C22,"") -> 1.81 | J9: ='F05 Beta v3'!C23 -> 86 of 89 towns | K9: =IF(ISNUMBER('F05 Beta v3'!C24),'F05 Beta v3'!C24,"") -> 1.2854274 | L9: =IF(ISNUMBER('F05 Beta v3'!C25),'F05 Beta v3'!C25,"") | M9: Out of sample | N9: No | O9: Fair | P9: Predicts a clear Mackenzie win (46.8% Brooks). It placed individual towns well, but the town-level errors leaned in the same direction, so the district total missed by 1.3 points.
A10: F06 | B10: =HYPERLINK("#'F06 Regression v3'!A1","Multi-Variable Regression (municipal, v3)") -> Multi-Variable Regression (municipal, v3) | C10: Sept. 16 | D10: Municipality (89) | E10: ='F06 Regression v3'!C14 -> 0.50644 | F10: ='F06 Regression v3'!C15 -> 0.49356 | G10: ='F06 Regression v3'!C16 -> 1.288 | H10: ='F06 Regression v3'!C17 -> Brooks | I10: =IF(ISNUMBER('F06 Regression v3'!C22),'F06 Regression v3'!C22,"") -> 3.09 | J10: ='F06 Regression v3'!C23 -> 82 of 89 towns | K10: =IF(ISNUMBER('F06 Regression v3'!C24),'F06 Regression v3'!C24,"") -> -2.2876796 | L10: =IF(ISNUMBER('F06 Regression v3'!C25),'F06 Regression v3'!C25,"") | M10: Out of sample | N10: No | O10: Weak | P10: Predicts a Brooks win (50.6%), but it had the worst backtest of the municipal methods: it missed the 2024 district result by about 2.3 points, predicting it too Republican. Treat with caution.
A11: F07 | B11: =HYPERLINK("#'F07 Precinct Trend'!A1","Simple Trend (precinct)") -> Simple Trend (precinct) | C11: Sept. 17 | D11: Precinct (408) | E11: ='F07 Precinct Trend'!C14 -> 0.48313 | F11: ='F07 Precinct Trend'!C15 -> 0.51687 | G11: ='F07 Precinct Trend'!C16 -> -3.374 | H11: ='F07 Precinct Trend'!C17 -> Mackenzie | I11: =IF(ISNUMBER('F07 Precinct Trend'!C22),'F07 Precinct Trend'!C22,"") -> 2.24 | J11: ='F07 Precinct Trend'!C23 -> 387 of 408 precincts | K11: =IF(ISNUMBER('F07 Precinct Trend'!C24),'F07 Precinct Trend'!C24,"") -> 0.38745946 | L11: =IF(ISNUMBER('F07 Precinct Trend'!C25),'F07 Precinct Trend'!C25,"") | M11: Out of sample | N11: No | O11: Good | P11: Predicts Mackenzie (48.3% Brooks). Its 2024 backtest came within about 0.4 points of the district result.
A12: F08 | B12: =HYPERLINK("#'F08 Precinct Beta'!A1","Beta-Adjusted (precinct)") -> Beta-Adjusted (precinct) | C12: Sept. 17 | D12: Precinct (408) | E12: ='F08 Precinct Beta'!C14 -> 0.47277 | F12: ='F08 Precinct Beta'!C15 -> 0.52723 | G12: ='F08 Precinct Beta'!C16 -> -5.446 | H12: ='F08 Precinct Beta'!C17 -> Mackenzie | I12: =IF(ISNUMBER('F08 Precinct Beta'!C22),'F08 Precinct Beta'!C22,"") -> 2.09 | J12: ='F08 Precinct Beta'!C23 -> 390 of 408 precincts | K12: =IF(ISNUMBER('F08 Precinct Beta'!C24),'F08 Precinct Beta'!C24,"") -> 0.20996571 | L12: =IF(ISNUMBER('F08 Precinct Beta'!C25),'F08 Precinct Beta'!C25,"") | M12: Out of sample | N12: No | O12: Good | P12: Predicts Mackenzie (47.3% Brooks). Best district-level backtest of any town- or precinct-level method: it missed 2024 by only 0.21 points.
A13: F09 | B13: =HYPERLINK("#'F09 Precinct Regression'!A1","Multi-Variable Regression (precinct)") -> Multi-Variable Regression (precinct) | C13: Sept. 17 | D13: Precinct (408) | E13: ='F09 Precinct Regression'!C14 -> 0.50897 | F13: ='F09 Precinct Regression'!C15 -> 0.49103 | G13: ='F09 Precinct Regression'!C16 -> 1.794 | H13: ='F09 Precinct Regression'!C17 -> Brooks | I13: =IF(ISNUMBER('F09 Precinct Regression'!C22),'F09 Precinct Regression'!C22,"") -> 2.46 | J13: ='F09 Precinct Regression'!C23 -> 366 of 408 precincts | K13: =IF(ISNUMBER('F09 Precinct Regression'!C24),'F09 Precinct Regression'!C24,"") -> -1.8266567 | L13: =IF(ISNUMBER('F09 Precinct Regression'!C25),'F09 Precinct Regression'!C25,"") | M13: Out of sample | N13: No | O13: Weak | P13: Predicts a narrow Brooks win (50.9%), but like F06 it had the weakest backtest at its level, missing 2024 by about 1.8 points. Treat with caution.
A14: F10 | B14: =HYPERLINK("#'F10 Muni Template Trend'!A1","Simple Trend (municipal template)") -> Simple Trend (municipal template) | C14: Sept. 24 | D14: Municipality (89) | E14: ='F10 Muni Template Trend'!C14 -> 0.46939 | F14: ='F10 Muni Template Trend'!C15 -> 0.53061 | G14: ='F10 Muni Template Trend'!C16 -> -6.122 | H14: ='F10 Muni Template Trend'!C17 -> Mackenzie | I14: =IF(ISNUMBER('F10 Muni Template Trend'!C22),'F10 Muni Template Trend'!C22,"") -> 1.99 | J14: ='F10 Muni Template Trend'!C23 -> 86 of 89 towns | K14: =IF(ISNUMBER('F10 Muni Template Trend'!C24),'F10 Muni Template Trend'!C24,"") -> 0.26874283 | L14: =IF(ISNUMBER('F10 Muni Template Trend'!C25),'F10 Muni Template Trend'!C25,"") | M14: Out of sample (same backtest as F04) | N14: No | O14: Good | P14: Predicts Mackenzie (46.9% Brooks). The template version of F04; same strong backtest.
A15: F11 | B15: =HYPERLINK("#'F11 Muni Template Beta'!A1","Beta-Adjusted (municipal template)") -> Beta-Adjusted (municipal template) | C15: Sept. 24 | D15: Municipality (89) | E15: ='F11 Muni Template Beta'!C14 -> 0.4597 | F15: ='F11 Muni Template Beta'!C15 -> 0.5403 | G15: ='F11 Muni Template Beta'!C16 -> -8.06 | H15: ='F11 Muni Template Beta'!C17 -> Mackenzie | I15: =IF(ISNUMBER('F11 Muni Template Beta'!C22),'F11 Muni Template Beta'!C22,"") -> 1.81 | J15: ='F11 Muni Template Beta'!C23 -> 86 of 89 towns | K15: =IF(ISNUMBER('F11 Muni Template Beta'!C24),'F11 Muni Template Beta'!C24,"") -> 1.2854274 | L15: =IF(ISNUMBER('F11 Muni Template Beta'!C25),'F11 Muni Template Beta'!C25,"") | M15: Out of sample (same backtest as F05) | N15: No | O15: Fair | P15: Predicts Mackenzie (46.0% Brooks), the lowest Brooks share of any forecast. The template version of F05.
A16: F12 | B16: =HYPERLINK("#'F12 Muni Template Reg'!A1","Regression (municipal template)") -> Regression (municipal template) | C16: Sept. 24 | D16: Municipality (89) | E16: ='F12 Muni Template Reg'!C14 -> 0.49935 | F16: ='F12 Muni Template Reg'!C15 -> 0.50065 | G16: ='F12 Muni Template Reg'!C16 -> -0.13 | H16: ='F12 Muni Template Reg'!C17 -> Mackenzie | I16: =IF(ISNUMBER('F12 Muni Template Reg'!C22),'F12 Muni Template Reg'!C22,"") -> 3.09 | J16: ='F12 Muni Template Reg'!C23 -> 82 of 89 towns | K16: =IF(ISNUMBER('F12 Muni Template Reg'!C24),'F12 Muni Template Reg'!C24,"") -> -2.2876796 | L16: =IF(ISNUMBER('F12 Muni Template Reg'!C25),'F12 Muni Template Reg'!C25,"") | M16: Out of sample (same backtest as F06) | N16: No | O16: Weak | P16: Essentially a tie (49.9% Brooks), tipping to Mackenzie. The template version of F06, which had the worst municipal backtest.
A17: F13 | B17: =HYPERLINK("#'F13 Pct Template Trend'!A1","Simple Trend (precinct template)") -> Simple Trend (precinct template) | C17: Sept. 24 | D17: Precinct (370) | E17: ='F13 Pct Template Trend'!C14 -> 0.4763 | F17: ='F13 Pct Template Trend'!C15 -> 0.5237 | G17: ='F13 Pct Template Trend'!C16 -> -4.74 | H17: ='F13 Pct Template Trend'!C17 -> Mackenzie | I17: =IF(ISNUMBER('F13 Pct Template Trend'!C22),'F13 Pct Template Trend'!C22,"") -> 2.24 | J17: ='F13 Pct Template Trend'!C23 -> 387 of 408 precincts | K17: =IF(ISNUMBER('F13 Pct Template Trend'!C24),'F13 Pct Template Trend'!C24,"") -> 0.38745946 | L17: =IF(ISNUMBER('F13 Pct Template Trend'!C25),'F13 Pct Template Trend'!C25,"") | M17: Out of sample (same backtest as F07) | N17: No | O17: Good | P17: Predicts Mackenzie (47.6% Brooks). The template version of F07.
A18: F14 | B18: =HYPERLINK("#'F14 Pct Template Beta'!A1","Beta-Adjusted (precinct template)") -> Beta-Adjusted (precinct template) | C18: Sept. 24 | D18: Precinct (370) | E18: ='F14 Pct Template Beta'!C14 -> 0.46573 | F18: ='F14 Pct Template Beta'!C15 -> 0.53427 | G18: ='F14 Pct Template Beta'!C16 -> -6.854 | H18: ='F14 Pct Template Beta'!C17 -> Mackenzie | I18: =IF(ISNUMBER('F14 Pct Template Beta'!C22),'F14 Pct Template Beta'!C22,"") -> 2.09 | J18: ='F14 Pct Template Beta'!C23 -> 390 of 408 precincts | K18: =IF(ISNUMBER('F14 Pct Template Beta'!C24),'F14 Pct Template Beta'!C24,"") -> 0.20996571 | L18: =IF(ISNUMBER('F14 Pct Template Beta'!C25),'F14 Pct Template Beta'!C25,"") | M18: Out of sample (same backtest as F08) | N18: No | O18: Good | P18: Predicts Mackenzie (46.6% Brooks). The template version of F08, which had the best unit-level backtest.
A19: F15 | B19: =HYPERLINK("#'F15 Pct Template Reg'!A1","Regression (precinct template)") -> Regression (precinct template) | C19: Sept. 24 | D19: Precinct (370) | E19: ='F15 Pct Template Reg'!C14 -> 0.50487 | F19: ='F15 Pct Template Reg'!C15 -> 0.49513 | G19: ='F15 Pct Template Reg'!C16 -> 0.974 | H19: ='F15 Pct Template Reg'!C17 -> Brooks | I19: =IF(ISNUMBER('F15 Pct Template Reg'!C22),'F15 Pct Template Reg'!C22,"") -> 2.46 | J19: ='F15 Pct Template Reg'!C23 -> 366 of 408 precincts | K19: =IF(ISNUMBER('F15 Pct Template Reg'!C24),'F15 Pct Template Reg'!C24,"") -> -1.8266567 | L19: =IF(ISNUMBER('F15 Pct Template Reg'!C25),'F15 Pct Template Reg'!C25,"") | M19: Out of sample (same backtest as F09) | N19: No | O19: Weak | P19: Predicts a narrow Brooks win (50.5%). The template version of F09, which had a weak backtest.
A20: F16 | B20: =HYPERLINK("#'F16 Bellwether (v0.1)'!A1","Bellwether reading, 10-precinct set, on the v0.1 baseline") -> Bellwether reading, 10-precinct set, on the v0.1 baseline | C20: Oct. 21–22 | D20: 10 precincts | E20: ='F16 Bellwether (v0.1)'!C14 -> 0.49968331 | F20: ='F16 Bellwether (v0.1)'!C15 -> 0.50031669 | G20: ='F16 Bellwether (v0.1)'!C16 -> -0.063337901 | H20: ='F16 Bellwether (v0.1)'!C17 -> Mackenzie | I20: =IF(ISNUMBER('F16 Bellwether (v0.1)'!C22),'F16 Bellwether (v0.1)'!C22,"") | J20: ='F16 Bellwether (v0.1)'!C23 -> — | K20: =IF(ISNUMBER('F16 Bellwether (v0.1)'!C24),'F16 Bellwether (v0.1)'!C24,"") -> -0.14586132 | L20: =IF(ISNUMBER('F16 Bellwether (v0.1)'!C25),'F16 Bellwether (v0.1)'!C25,"") | M20: Out of sample selection; baseline backtest used actual turnout | N20: No | O20: Good (with caveat) | P20: Essentially a tie (49.97% Brooks), tipping to Mackenzie. Best 2024 backtest in the workbook (0.15 pts), though that test is less strict than F18’s.
A21: F17 | B21: =HYPERLINK("#'F17 Bellwether Crain 6'!A1","Bellwether reading, Professor Crain’s 6 precincts, on the v0.1 baseline") -> Bellwether reading, Professor Crain’s 6 precincts, on the v0.1 baseline | C21: Oct. 22 | D21: 6 precincts | E21: ='F17 Bellwether Crain 6'!C14 -> 0.49217551 | F21: ='F17 Bellwether Crain 6'!C15 -> 0.50782449 | G21: ='F17 Bellwether Crain 6'!C16 -> -1.5648982 | H21: ='F17 Bellwether Crain 6'!C17 -> Mackenzie | I21: =IF(ISNUMBER('F17 Bellwether Crain 6'!C22),'F17 Bellwether Crain 6'!C22,"") | J21: ='F17 Bellwether Crain 6'!C23 -> — | K21: =IF(ISNUMBER('F17 Bellwether Crain 6'!C24),'F17 Bellwether Crain 6'!C24,"") -> -0.62822898 | L21: =IF(ISNUMBER('F17 Bellwether Crain 6'!C25),'F17 Bellwether Crain 6'!C25,"") | M21: Selection data unknown; baseline backtest used actual turnout | N21: No | O21: Fair (with caveat) | P21: Predicts Mackenzie (49.2% Brooks). Its backtest missed by about 0.6 points.
A22: F18 | B22: =HYPERLINK("#'F18 Bellwether (v11)'!A1","Bellwether reading on the v11 baseline (honest rule)") -> Bellwether reading on the v11 baseline (honest rule) | C22: Oct. 26 | D22: 10 precincts | E22: ='F18 Bellwether (v11)'!C14 -> 0.50011074 | F22: ='F18 Bellwether (v11)'!C15 -> 0.49988926 | G22: ='F18 Bellwether (v11)'!C16 -> 0.022148892 | H22: ='F18 Bellwether (v11)'!C17 -> Brooks | I22: =IF(ISNUMBER('F18 Bellwether (v11)'!C22),'F18 Bellwether (v11)'!C22,"") | J22: ='F18 Bellwether (v11)'!C23 -> — | K22: =IF(ISNUMBER('F18 Bellwether (v11)'!C24),'F18 Bellwether (v11)'!C24,"") -> -0.51046282 | L22: =IF(ISNUMBER('F18 Bellwether (v11)'!C25),'F18 Bellwether (v11)'!C25,"") -> 0.2670494 | M22: Fully out of sample (2022 and 2024) | N22: No | O22: Strongest | P22: A dead heat (50.01% Brooks). The most rigorous bellwether test, but it missed both backtests by more than the v11 baseline alone (0.27 pts in 2022, 0.51 in 2024), because bellwethers chosen from earlier elections drifted away from the district.
A23: F19 | B23: =HYPERLINK("#'F19 Baseline+Bellwether'!A1","Baseline + bellwether blend (50/50, v11)") -> Baseline + bellwether blend (50/50, v11) | C23: Oct. 26 | D23: District | E23: ='F19 Baseline+Bellwether'!C14 -> 0.49752688 | F23: ='F19 Baseline+Bellwether'!C15 -> 0.50247312 | G23: ='F19 Baseline+Bellwether'!C16 -> -0.49462402 | H23: ='F19 Baseline+Bellwether'!C17 -> Mackenzie | I23: =IF(ISNUMBER('F19 Baseline+Bellwether'!C22),'F19 Baseline+Bellwether'!C22,"") | J23: ='F19 Baseline+Bellwether'!C23 -> — | K23: =IF(ISNUMBER('F19 Baseline+Bellwether'!C24),'F19 Baseline+Bellwether'!C24,"") -> -0.34444009 | L23: =IF(ISNUMBER('F19 Baseline+Bellwether'!C25),'F19 Baseline+Bellwether'!C25,"") -> 0.14387802 | M23: Fully out of sample (2022 and 2024) | N23: No | O23: Strongest | P23: Predicts a narrow Mackenzie win (49.75% Brooks). In both backtests the blend was further from the result than the v11 baseline alone (0.14 vs 0.02 pts in 2022; 0.34 vs 0.18 in 2024).
A25: Group baselines (for reference; these are the group’s models, not Kiley’s forecasts, and are not counted in any tally)
A26: G1 | B26: Group baseline v0.1 (precinct random forest, Oct. 4) | E26: 0.48727 | F26: =1-E26 -> 0.51273 | G26: =(E26-F26)*100 -> -2.546 | H26: =IF(E26>0.5,"Brooks","Mackenzie") -> Mackenzie | K26: -0.1 | M26: 2024 backtest used actual 2024 turnout
A27: G2 | B27: Group baseline v11, Forecast A (Oct. 6) | E27: 0.49496 | F27: =1-E27 -> 0.50504 | G27: =(E27-F27)*100 -> -1.008 | H27: =IF(E27>0.5,"Brooks","Mackenzie") -> Mackenzie | K27: -0.18 | L27: 0.02 | M27: Fully out of sample (2022 and 2024), projected turnout
A30: Note on F10–F15: these repeat the methods of F04–F09 in the class template and share their backtests. They differ only in projected turnout, which changes how much each town or precinct counts.

Sheet F01 Trend v2
A1: F01 · Simple Trend (municipal, v2)
A2: Run Sept. 14, 2026 · Level: Municipality (86) · Source: PA07_Analysis.xlsx (tracker: "Analysis Workbook," Sept. 14)
A3: ← Back to Results
A5: Methodology
A6: What it does: extends each town’s Democratic share along a straight line drawn through its 2018–2024 House results.
A7: Data: the first municipal file. Carbon County votes were not reported, so they were estimated from voter registration; Monroe was missing.
A8: Votes: turnout projected from the two most recent midterms (2018 and 2022).
A9: Backtest: the same straight line drawn through 2018–2022 only, used to predict 2024.
A10: Why it is superseded: this source also reported the 2020 race wrongly (as a Democratic win). F04 repeats this method on corrected data.
A13: 2026 forecast | E13: In plain terms
A14: Brooks (D) share of the two-party vote | C14: 0.49372 | E14: The first forecast of the project. It predicted a narrow Mackenzie win (49.4% Brooks). Its backtest was the weakest of the trend forecasts and it rests on incomplete data, so it is kept only to show where the project started. Read F04 instead.
A15: Mackenzie (R) share of the two-party vote | C15: =1-C14 -> 0.50628
A16: Margin: Brooks minus Mackenzie (points) | C16: =(C14-C15)*100 -> -1.256
A17: Predicted winner | C17: =IF(C14>0.5,"Brooks","Mackenzie") -> Mackenzie
A18: Brooks votes
A19: Mackenzie votes
A21: 2024 backtest | E21: Rating
A22: Average miss per town or precinct (points) | C22: 2.18 | E22: Superseded | F22: See “How to Read” for what the ratings mean.
A23: Towns or precincts where the winner was called correctly | C23: 57 of 63 towns
A24: District result miss, 2024 (points; negative = too Republican) | C24: 1.7409974
A25: District result miss, 2022 (points) | C25: not available
A26: How strict the backtest was | C26: Out of sample (unit-level); district miss is for Lehigh + Northampton only
A29: 2026 forecast detail | J29: 2024 backtest detail
A30: Municipality | B30: County | C30: Source | D30: Projected Total Votes 2026 | E30: Projected Dem Share 2026 | F30: Projected Dem Votes 2026 | G30: Projected Rep Votes 2026 | H30: Projected Winner | J30: Municipality | K30: Predicted Dem Share | L30: Actual Dem Share | M30: Error (pts) | N30: Winner Correct? (Trend)
A31: Alburtis | B31: Lehigh | C31: Actual-based | D31: 1130 | E31: 0.43013086 | F31: 486 | G31: 644 | H31: Republican | J31: Alburtis | K31: 0.46808463 | L31: 0.43964887 | M31: 2.843576 | N31: 1
A32: Allentown | B32: Lehigh | C32: Actual-based | D32: 21769 | E32: 0.63099348 | F32: 13736 | G32: 8033 | H32: Democrat | J32: Allentown | K32: 0.66255702 | L32: 0.64562222 | M32: 1.6934795 | N32: 1
A33: Bethlehem | B33: Lehigh | C33: Actual-based | D33: 8404 | E33: 0.64305726 | F33: 5404 | G33: 3000 | H33: Democrat | J33: Bethlehem | K33: 0.66197092 | L33: 0.63296956 | M33: 2.9001364 | N33: 1
A34: Catasauqua | B34: Lehigh | C34: Actual-based | D34: 2160 | E34: 0.50429424 | F34: 1089 | G34: 1071 | H34: Democrat | J34: Catasauqua | K34: 0.52058179 | L34: 0.51130777 | M34: 0.92740264 | N34: 1
A35: Coopersburg | B35: Lehigh | C35: Actual-based | D35: 1433 | E35: 0.47707595 | F35: 684 | G35: 749 | H35: Republican | J35: Coopersburg | K35: 0.49591445 | L35: 0.47758285 | M35: 1.83316 | N35: 1
A36: Coplay | B36: Lehigh | C36: Actual-based | D36: 1365 | E36: 0.49815122 | F36: 680 | G36: 685 | H36: Republican | J36: Coplay | K36: 0.51977203 | L36: 0.50027824 | M36: 1.949379 | N36: 1
A37: Emmaus | B37: Lehigh | C37: Actual-based | D37: 5598 | E37: 0.54336209 | F37: 3042 | G37: 2556 | H37: Democrat | J37: Emmaus | K37: 0.56295728 | L37: 0.53094651 | M37: 3.2010768 | N37: 1
A38: Fountain Hill | B38: Lehigh | C38: Actual-based | D38: 1480 | E38: 0.65632144 | F38: 971 | G38: 509 | H38: Democrat | J38: Fountain Hill | K38: 0.69983948 | L38: 0.64375562 | M38: 5.6083864 | N38: 1
A39: Hanover | B39: Lehigh | C39: Actual-based | D39: 431 | E39: 0.52282311 | F39: 225 | G39: 206 | H39: Democrat | J39: Hanover | K39: 0.54878412 | L39: 0.53455571 | M39: 1.4228403 | N39: 1
A40: Heidelberg | B40: Lehigh | C40: Actual-based | D40: 1774 | E40: 0.30410583 | F40: 539 | G40: 1235 | H40: Republican | J40: Heidelberg | K40: 0.31389739 | L40: 0.31247014 | M40: 0.14272563 | N40: 1
A41: Lower Macungie | B41: Lehigh | C41: Actual-based | D41: 17421 | E41: 0.50777979 | F41: 8846 | G41: 8575 | H41: Democrat | J41: Lower Macungie | K41: 0.53023123 | L41: 0.49559842 | M41: 3.4632816 | N41: 0
A42: Lower Milford | B42: Lehigh | C42: Actual-based | D42: 2422 | E42: 0.38557709 | F42: 934 | G42: 1488 | H42: Republican | J42: Lower Milford | K42: 0.38738778 | L42: 0.38311941 | M42: 0.4268373 | N42: 1
... A93: Wind Gap | B93: Northampton | C93: Actual-based | D93: 1361 | E93: 0.43273879 | F93: 589 | G93: 772 | H93: Republican | J93: Wind Gap | K93: 0.44076496 | L93: 0.42550336 | M93: 1.5261607 | N93: 1
A94: Banks Township | B94: Carbon | C94: Estimated | D94: 382 | E94: 0.5165016 | F94: 197 | G94: 185 | H94: Democrat | J94: Trend model MAE (pts) | K94: 2.1746586
A95: Beaver Meadows Borough | B95: Carbon | C95: Estimated | D95: 339 | E95: 0.3741537 | F95: 127 | G95: 212 | H95: Republican | J95: Naive model MAE (pts) | K95: 2.2487813
A96: Bowmanstown Borough | B96: Carbon | C96: Estimated | D96: 398 | E96: 0.3574788 | F96: 142 | G96: 256 | H96: Republican
A97: East Penn Township | B97: Carbon | C97: Estimated | D97: 1491 | E97: 0.3158649 | F97: 471 | G97: 1020 | H97: Republican
A98: East Side Borough | B98: Carbon | C98: Estimated | D98: 103 | E98: 0.4039338 | F98: 42 | G98: 61 | H98: Republican
A99: Franklin Township | B99: Carbon | C99: Estimated | D99: 2220 | E99: 0.3229065 | F99: 717 | G99: 1503 | H99: Republican
A100: Jim Thorpe Borough | B100: Carbon | C100: Estimated | D100: 2335 | E100: 0.4654989 | F100: 1087 | G100: 1248 | H100: Republican
A101: Kidder Township | B101: Carbon | C101: Estimated | D101: 943 | E101: 0.3546426 | F101: 334 | G101: 609 | H101: Republican
A102: Lansford Borough | B102: Carbon | C102: Estimated | D102: 1128 | E102: 0.4719537 | F102: 532 | G102: 596 | H102: Republican
A103: Lausanne Township | B103: Carbon | C103: Estimated | D103: 137 | E103: 0.300168 | F103: 41 | G103: 96 | H103: Republican
A104: Lehigh Township | B104: Carbon | C104: Estimated | D104: 271 | E104: 0.2240796 | F104: 61 | G104: 210 | H104: Republican
A105: Lehighton Borough | B105: Carbon | C105: Estimated | D105: 1867 | E105: 0.4151319 | F105: 775 | G105: 1092 | H105: Republican
A106: Lower Towamensing Twp. | B106: Carbon | C106: Estimated | D106: 1561 | E106: 0.3374787 | F106: 527 | G106: 1034 | H106: Republican
A107: Mahoning Township | B107: Carbon | C107: Estimated | D107: 2044 | E107: 0.3193857 | F107: 653 | G107: 1391 | H107: Republican
... A116: Weissport Borough | B116: Carbon | C116: Estimated | D116: 128 | E116: 0.403347 | F116: 52 | G116: 76 | H116: Republican

Sheet F02 Beta v2
A1: F02 · Beta-Adjusted (municipal, v2)
A2: Run Sept. 14, 2026 · Level: Municipality (86) · Source: PA07_Analysis.xlsx (tracker: "Analysis Workbook," Sept. 14)
A3: ← Back to Results
A5: Methodology
A6: What it does: measures each town’s “beta,” how strongly it moves when the district as a whole moves (an idea borrowed from finance).
A7: Forecast: each town’s 2024 result plus its beta times the district’s projected shift from 2024 to 2026.
A8: Data: the same early file as F01 (Carbon estimated, Monroe missing, 2020 misreported).
A9: Backtest: town-level accuracy only. The town-by-town backtest predictions were not saved, so a district-level check is not possible.
A13: 2026 forecast | E13: In plain terms
A14: Brooks (D) share of the two-party vote | C14: 0.48763 | E14: Predicted Mackenzie (48.8% Brooks). Replaced by F05, which uses the same method on corrected data.
A15: Mackenzie (R) share of the two-party vote | C15: =1-C14 -> 0.51237
A16: Margin: Brooks minus Mackenzie (points) | C16: =(C14-C15)*100 -> -2.474
A17: Predicted winner | C17: =IF(C14>0.5,"Brooks","Mackenzie") -> Mackenzie
A18: Brooks votes
A19: Mackenzie votes
A21: 2024 backtest | E21: Rating
A22: Average miss per town or precinct (points) | C22: 1.57 | E22: Superseded | F22: See “How to Read” for what the ratings mean.
A23: Towns or precincts where the winner was called correctly | C23: 59 of 63 towns
A24: District result miss, 2024 (points; negative = too Republican) | C24: not available
A25: District result miss, 2022 (points) | C25: not available
A26: How strict the backtest was | C26: Out of sample (unit-level); town-by-town backtest predictions not saved in the source file
A29: 2026 forecast detail | J29: 2024 backtest detail
A30: Municipality | B30: County | C30: Method | D30: Projected Total Votes | E30: Projected Dem Share | F30: Projected Dem Votes | G30: Projected Rep Votes | H30: Projected Winner | J30: Town-by-town backtest predictions for this method were not saved in the source file; the summary metrics above come from its Model Comparison sheet.
A31: Alburtis | B31: Lehigh | C31: Beta-Adjusted | D31: 1130 | E31: 0.42583526 | F31: 481 | G31: 649 | H31: Republican
A32: Allentown | B32: Lehigh | C32: Beta-Adjusted | D32: 21769 | E32: 0.63378379 | F32: 13797 | G32: 7972 | H32: Democrat
A33: Bethlehem | B33: Lehigh | C33: Beta-Adjusted | D33: 8404 | E33: 0.63126609 | F33: 5305 | G33: 3099 | H33: Democrat
A34: Catasauqua | B34: Lehigh | C34: Beta-Adjusted | D34: 2160 | E34: 0.5014158 | F34: 1083 | G34: 1077 | H34: Democrat
A35: Coopersburg | B35: Lehigh | C35: Beta-Adjusted | D35: 1433 | E35: 0.46835255 | F35: 671 | G35: 762 | H35: Republican
A36: Coplay | B36: Lehigh | C36: Beta-Adjusted | D36: 1365 | E36: 0.491101 | F36: 670 | G36: 695 | H36: Republican
A37: Emmaus | B37: Lehigh | C37: Beta-Adjusted | D37: 5598 | E37: 0.52921819 | F37: 2963 | G37: 2635 | H37: Democrat
A38: Fountain Hill | B38: Lehigh | C38: Beta-Adjusted | D38: 1480 | E38: 0.64025327 | F38: 948 | G38: 532 | H38: Democrat
A39: Hanover | B39: Lehigh | C39: Beta-Adjusted | D39: 431 | E39: 0.52631866 | F39: 227 | G39: 204 | H39: Democrat
A40: Heidelberg | B40: Lehigh | C40: Beta-Adjusted | D40: 1774 | E40: 0.30307598 | F40: 538 | G40: 1236 | H40: Republican
A41: Lower Macungie | B41: Lehigh | C41: Beta-Adjusted | D41: 17421 | E41: 0.49387002 | F41: 8604 | G41: 8817 | H41: Republican
A42: Lower Milford | B42: Lehigh | C42: Beta-Adjusted | D42: 2422 | E42: 0.37966284 | F42: 920 | G42: 1502 | H42: Republican
... A116: Weissport Borough | B116: Carbon | C116: Registration Calibration | D116: 128 | E116: 0.403347 | F116: 52 | G116: 76 | H116: Republican

Sheet F03 Regression v2
A1: F03 · Multi-Variable Regression (municipal, v2)
A2: Run Sept. 14, 2026 · Level: Municipality (86) · Source: PA07_Analysis.xlsx (tracker: "Analysis Workbook," Sept. 14)
A3: ← Back to Results
A5: Methodology
A6: What it does: a regression that predicts each town’s Democratic share from four things: party registration, share of adults with a bachelor’s degree, whether it is a presidential year, and the town’s previous result.
A7: Equation: Dem share = 16.63 + 18.07 × (registration D−R) + 7.62 × (% bachelor’s) − 3.67 × (presidential year) + 0.656 × (previous Dem share).
A8: Data: the same early file as F01. On this incomplete data the regression looked like the best method; on corrected data (F06) it became the worst.
A9: Backtest: town-level accuracy only; a district-level check is not possible.
A13: 2026 forecast | E13: In plain terms
A14: Brooks (D) share of the two-party vote | C14: 0.51198 | E14: Predicted a Brooks win (51.2%). Its strong-looking backtest did not survive the switch to complete, corrected data. Read F06 instead.
A15: Mackenzie (R) share of the two-party vote | C15: =1-C14 -> 0.48802
A16: Margin: Brooks minus Mackenzie (points) | C16: =(C14-C15)*100 -> 2.396
A17: Predicted winner | C17: =IF(C14>0.5,"Brooks","Mackenzie") -> Brooks
A18: Brooks votes
A19: Mackenzie votes
A21: 2024 backtest | E21: Rating
A22: Average miss per town or precinct (points) | C22: 1.13 | E22: Superseded | F22: See “How to Read” for what the ratings mean.
A23: Towns or precincts where the winner was called correctly | C23: 61 of 63 towns
A24: District result miss, 2024 (points; negative = too Republican) | C24: not available
A25: District result miss, 2022 (points) | C25: not available
A26: How strict the backtest was | C26: Out of sample (unit-level); town-by-town backtest predictions not saved in the source file
A29: 2026 forecast detail | J29: 2024 backtest detail
A30: Municipality | B30: County | C30: Method | D30: Projected Total Votes | E30: Projected Dem Share | F30: Projected Dem Votes | G30: Projected Rep Votes | H30: Projected Winner | J30: Town-by-town backtest predictions for this method were not saved in the source file; the summary metrics above come from its Model Comparison sheet.
A31: Alburtis | B31: Lehigh | C31: Regression | D31: 1130 | E31: 0.47577554 | F31: 538 | G31: 592 | H31: Republican
A32: Allentown | B32: Lehigh | C32: Regression | D32: 21769 | E32: 0.66458249 | F32: 14467 | G32: 7302 | H32: Democrat
A33: Bethlehem | B33: Lehigh | C33: Regression | D33: 8404 | E33: 0.65763423 | F33: 5527 | G33: 2877 | H33: Democrat
A34: Catasauqua | B34: Lehigh | C34: Regression | D34: 2160 | E34: 0.54232395 | F34: 1171 | G34: 989 | H34: Democrat
A35: Coopersburg | B35: Lehigh | C35: Regression | D35: 1433 | E35: 0.49255005 | F35: 706 | G35: 727 | H35: Republican
A36: Coplay | B36: Lehigh | C36: Regression | D36: 1365 | E36: 0.5274993 | F36: 720 | G36: 645 | H36: Democrat
A37: Emmaus | B37: Lehigh | C37: Regression | D37: 5598 | E37: 0.55161 | F37: 3088 | G37: 2510 | H37: Democrat
A38: Fountain Hill | B38: Lehigh | C38: Regression | D38: 1480 | E38: 0.66861305 | F38: 990 | G38: 490 | H38: Democrat
A39: Hanover | B39: Lehigh | C39: Regression | D39: 431 | E39: 0.56391389 | F39: 243 | G39: 188 | H39: Democrat
A40: Heidelberg | B40: Lehigh | C40: Regression | D40: 1774 | E40: 0.3298394 | F40: 585 | G40: 1189 | H40: Republican
A41: Lower Macungie | B41: Lehigh | C41: Regression | D41: 17421 | E41: 0.52624106 | F41: 9168 | G41: 8253 | H41: Democrat
A42: Lower Milford | B42: Lehigh | C42: Regression | D42: 2422 | E42: 0.3989437 | F42: 966 | G42: 1456 | H42: Republican
... A116: Weissport Borough | B116: Carbon | C116: Registration Calibration | D116: 128 | E116: 0.403347 | F116: 52 | G116: 76 | H116: Republican

Sheet F04 Trend v3
A1: F04 · Simple Trend (municipal, v3)
A2: Run Sept. 16, 2026 · Level: Municipality (89) · Source: PA07_Analysis (2).xlsx (tracker: "Backtest & Forecast Analysis Update," Sept. 16)
A3: ← Back to Results
A5: Methodology
A6: What it does: extends each town’s Democratic share along a straight line drawn through its 2018–2024 House results.
A7: Data: certified returns for all 89 towns in the current district (Carbon and Monroe now real data). The 2020 result was corrected: Republicans won it, so the district has alternated D-R-D-R.
A8: Backtest: the line drawn through 2018–2022 only, used to predict 2024. Nothing from 2024 was used.
A13: 2026 forecast | E13: In plain terms
A14: Brooks (D) share of the two-party vote | C14: 0.47727 | E14: Predicts Mackenzie (47.7% Brooks). In 2024 it came within about a quarter point of the district result, one of the best simple-method backtests. A reliable, easy-to-explain reference forecast.
A15: Mackenzie (R) share of the two-party vote | C15: =1-C14 -> 0.52273
A16: Margin: Brooks minus Mackenzie (points) | C16: =(C14-C15)*100 -> -4.546
A17: Predicted winner | C17: =IF(C14>0.5,"Brooks","Mackenzie") -> Mackenzie
A18: Brooks votes
A19: Mackenzie votes
A21: 2024 backtest | E21: Rating
A22: Average miss per town or precinct (points) | C22: 1.99 | E22: Good | F22: See “How to Read” for what the ratings mean.
A23: Towns or precincts where the winner was called correctly | C23: 86 of 89 towns
A24: District result miss, 2024 (points; negative = too Republican) | C24: 0.26874283
A25: District result miss, 2022 (points) | C25: not available
A26: How strict the backtest was | C26: Out of sample
A29: 2026 forecast detail | I29: 2024 backtest detail
A30: Municipality | B30: County | C30: Projected Total Votes | D30: Projected Dem Share | E30: Projected Dem Votes | F30: Projected Rep Votes | G30: Projected Winner | I30: Municipality | J30: Predicted Dem Share (Trend) | K30: Actual Dem Share | L30: Trend Error (pts) | M30: Trend Winner Correct?
A31: Banks Township | B31: Carbon | C31: 391 | D31: 0.3558994 | E31: 139 | F31: 252 | G31: Republican | I31: Banks Township | J31: 0.30658478 | K31: 0.38841202 | L31: -8.1827236 | M31: 1
A32: Beaver Meadows Borough | B32: Carbon | C32: 341 | D32: 0.25054939 | E32: 85 | F32: 256 | G32: Republican | I32: Beaver Meadows Borough | J32: 0.21872725 | K32: 0.28229665 | L32: -6.3569402 | M32: 1
A33: Bowmanstown Borough | B33: Carbon | C33: 411 | D33: 0.30379586 | E33: 125 | F33: 286 | G33: Republican | I33: Bowmanstown Borough | J33: 0.30806586 | K33: 0.31718062 | L33: -0.91147571 | M33: 1
A34: East Penn Township | B34: Carbon | C34: 1483 | D34: 0.23635959 | E34: 351 | F34: 1132 | G34: Republican | I34: East Penn Township | J34: 0.24380138 | K34: 0.25901833 | L34: -1.5216955 | M34: 1
A35: East Side Borough | B35: Carbon | C35: 111 | D35: 0.2823389 | E35: 31 | F35: 80 | G35: Republican | I35: East Side Borough | J35: 0.3031894 | K35: 0.32758621 | L35: -2.4396811 | M35: 1
A36: Franklin Township | B36: Carbon | C36: 2258 | D36: 0.25857475 | E36: 584 | F36: 1674 | G36: Republican | I36: Franklin Township | J36: 0.25135692 | K36: 0.27721222 | L36: -2.5855293 | M36: 1
A37: Jim Thorpe Borough | B37: Carbon | C37: 2411 | D37: 0.41121642 | E37: 991 | F37: 1420 | G37: Republican | I37: Jim Thorpe Borough | J37: 0.42151537 | K37: 0.4270793 | L37: -0.55639296 | M37: 1
A38: Kidder Township | B38: Carbon | C38: 912 | D38: 0.32519874 | E38: 297 | F38: 615 | G38: Republican | I38: Kidder Township | J38: 0.30908561 | K38: 0.33492366 | L38: -2.5838053 | M38: 1
A39: Lansford Borough | B39: Carbon | C39: 1078 | D39: 0.3584428 | E39: 386 | F39: 692 | G39: Republican | I39: Lansford Borough | J39: 0.37118771 | K39: 0.395189 | L39: -2.4001294 | M39: 1
A40: Lausanne Township | B40: Carbon | C40: 142 | D40: 0.25381798 | E40: 36 | F40: 106 | G40: Republican | I40: Lausanne Township | J40: 0.29698511 | K40: 0.26206897 | L40: 3.4916149 | M40: 1
A41: Lehigh Township | B41: Carbon | C41: 278 | D41: 0.21907245 | E41: 61 | F41: 217 | G41: Republican | I41: Lehigh Township | J41: 0.21574705 | K41: 0.21167883 | L41: 0.40682152 | M41: 1
A42: Lehighton Borough | B42: Carbon | C42: 1900 | D42: 0.37121931 | E42: 705 | F42: 1195 | G42: Republican | I42: Lehighton Borough | J42: 0.38906899 | K42: 0.38847737 | L42: 0.05916284 | M42: 1
... A119: Wind Gap | B119: Northampton | C119: 1391 | D119: 0.42454097 | E119: 591 | F119: 800 | G119: Republican | I119: Wind Gap | J119: 0.42983453 | K119: 0.42550336 | L119: 0.4331177 | M119: 1

Sheet F05 Beta v3
A1: F05 · Beta-Adjusted (municipal, v3)
A2: Run Sept. 16, 2026 · Level: Municipality (89) · Source: PA07_Analysis (2).xlsx (tracker: "Backtest & Forecast Analysis Update," Sept. 16)
A3: ← Back to Results
A5: Methodology
A6: What it does: each town’s 2024 result plus its beta (how strongly it swings with the district) times the district’s projected 2024→2026 shift.
A7: Data: certified returns for all 89 towns. Betas are measured over 2018–2024; the backtest betas use 2018–2022 only.
A8: Backtest: best town-by-town accuracy of the Sept. 16 methods (1.81 pts), but the town errors added up to a district miss of about 1.3 points.
A13: 2026 forecast | E13: In plain terms
A14: Brooks (D) share of the two-party vote | C14: 0.46765 | E14: Predicts a clear Mackenzie win (46.8% Brooks). It placed individual towns well, but the town-level errors leaned in the same direction, so the district total missed by 1.3 points. Its Brooks share is among the lowest of all forecasts.
A15: Mackenzie (R) share of the two-party vote | C15: =1-C14 -> 0.53235
A16: Margin: Brooks minus Mackenzie (points) | C16: =(C14-C15)*100 -> -6.47
A17: Predicted winner | C17: =IF(C14>0.5,"Brooks","Mackenzie") -> Mackenzie
A18: Brooks votes
A19: Mackenzie votes
A21: 2024 backtest | E21: Rating
A22: Average miss per town or precinct (points) | C22: 1.81 | E22: Fair | F22: See “How to Read” for what the ratings mean.
A23: Towns or precincts where the winner was called correctly | C23: 86 of 89 towns
A24: District result miss, 2024 (points; negative = too Republican) | C24: 1.2854274
A25: District result miss, 2022 (points) | C25: not available
A26: How strict the backtest was | C26: Out of sample
A29: 2026 forecast detail | I29: 2024 backtest detail
A30: Municipality | B30: County | C30: Projected Total Votes | D30: Projected Dem Share | E30: Projected Dem Votes | F30: Projected Rep Votes | G30: Projected Winner | I30: Municipality | J30: Beta-Adj Predicted Share | K30: Actual Dem Share | L30: Beta-Adj Error (pts) | M30: Beta-Adj Winner Correct?
A31: Banks Township | B31: Carbon | C31: 391 | D31: 0.36354873 | E31: 142 | F31: 249 | G31: Republican | I31: Banks Township | J31: 0.34217727 | K31: 0.38841202 | L31: -4.6234743 | M31: 1
A32: Beaver Meadows Borough | B32: Carbon | C32: 341 | D32: 0.25230594 | E32: 86 | F32: 255 | G32: Republican | I32: Beaver Meadows Borough | J32: 0.25367759 | K32: 0.28229665 | L32: -2.8619061 | M32: 1
A33: Bowmanstown Borough | B33: Carbon | C33: 411 | D33: 0.27130024 | E33: 112 | F33: 299 | G33: Republican | I33: Bowmanstown Borough | J33: 0.32656465 | K33: 0.31718062 | L33: 0.93840325 | M33: 1
A34: East Penn Township | B34: Carbon | C34: 1483 | D34: 0.2221331 | E34: 329 | F34: 1154 | G34: Republican | I34: East Penn Township | J34: 0.2697552 | K34: 0.25901833 | L34: 1.0736871 | M34: 1
A35: East Side Borough | B35: Carbon | C35: 111 | D35: 0.28804306 | E35: 32 | F35: 79 | G35: Republican | I35: East Side Borough | J35: 0.35033421 | K35: 0.32758621 | L35: 2.2747999 | M35: 1
A36: Franklin Township | B36: Carbon | C36: 2258 | D36: 0.25100756 | E36: 567 | F36: 1691 | G36: Republican | I36: Franklin Township | J36: 0.27261462 | K36: 0.27721222 | L36: -0.45975927 | M36: 1
A37: Jim Thorpe Borough | B37: Carbon | C37: 2411 | D37: 0.39365254 | E37: 949 | F37: 1462 | G37: Republican | I37: Jim Thorpe Borough | J37: 0.44051077 | K37: 0.4270793 | L37: 1.3431469 | M37: 1
A38: Kidder Township | B38: Carbon | C38: 912 | D38: 0.32089831 | E38: 293 | F38: 619 | G38: Republican | I38: Kidder Township | J38: 0.3206431 | K38: 0.33492366 | L38: -1.4280567 | M38: 1
A39: Lansford Borough | B39: Carbon | C39: 1078 | D39: 0.35484185 | E39: 383 | F39: 695 | G39: Republican | I39: Lansford Borough | J39: 0.41069815 | K39: 0.395189 | L39: 1.5509146 | M39: 1
A40: Lausanne Township | B40: Carbon | C40: 142 | D40: 0.23780742 | E40: 34 | F40: 108 | G40: Republican | I40: Lausanne Township | J40: 0.30648463 | K40: 0.26206897 | L40: 4.4415667 | M40: 1
A41: Lehigh Township | B41: Carbon | C41: 278 | D41: 0.21076248 | E41: 59 | F41: 219 | G41: Republican | I41: Lehigh Township | J41: 0.20900933 | K41: 0.21167883 | L41: -0.26695065 | M41: 1
A42: Lehighton Borough | B42: Carbon | C42: 1900 | D42: 0.34833996 | E42: 662 | F42: 1238 | G42: Republican | I42: Lehighton Borough | J42: 0.4100046 | K42: 0.38847737 | L42: 2.1527237 | M42: 1
... A119: Wind Gap | B119: Northampton | C119: 1391 | D119: 0.40437863 | E119: 562 | F119: 829 | G119: Republican | I119: Wind Gap | J119: 0.43333593 | K119: 0.42550336 | L119: 0.78325749 | M119: 1

Sheet F06 Regression v3
A1: F06 · Multi-Variable Regression (municipal, v3)
A2: Run Sept. 16, 2026 · Level: Municipality (89) · Source: PA07_Analysis (2).xlsx (tracker: "Backtest & Forecast Analysis Update," Sept. 16)
A3: ← Back to Results
A5: Methodology
A6: What it does: a regression on party registration, % bachelor’s degree, presidential year and the previous result.
A7: Equation: Dem share = 9.61 + 0.0975 × (registration D−R, pts) + 10.539 × (% bachelor’s) − 4.688 × (presidential year) + 0.767 × (previous Dem share).
A8: Backtest: trained on 2020–2022 only, used to predict 2024. It had the worst backtest of the three methods, likely because it relies on “last result plus a change,” which fails in a district that alternates parties.
A13: 2026 forecast | E13: In plain terms
A14: Brooks (D) share of the two-party vote | C14: 0.50644 | E14: Predicts a Brooks win (50.6%), but it had the worst backtest of the municipal methods: it missed the 2024 district result by about 2.3 points, predicting it too Republican. Treat with caution.
A15: Mackenzie (R) share of the two-party vote | C15: =1-C14 -> 0.49356
A16: Margin: Brooks minus Mackenzie (points) | C16: =(C14-C15)*100 -> 1.288
A17: Predicted winner | C17: =IF(C14>0.5,"Brooks","Mackenzie") -> Brooks
A18: Brooks votes
A19: Mackenzie votes
A21: 2024 backtest | E21: Rating
A22: Average miss per town or precinct (points) | C22: 3.09 | E22: Weak | F22: See “How to Read” for what the ratings mean.
A23: Towns or precincts where the winner was called correctly | C23: 82 of 89 towns
A24: District result miss, 2024 (points; negative = too Republican) | C24: -2.2876796
A25: District result miss, 2022 (points) | C25: not available
A26: How strict the backtest was | C26: Out of sample
A29: 2026 forecast detail | I29: 2024 backtest detail
A30: Municipality | B30: County | C30: Projected Total Votes | D30: Projected Dem Share | E30: Projected Dem Votes | F30: Projected Rep Votes | G30: Projected Winner | I30: Municipality | J30: Reg. Predicted Share | K30: Actual Dem Share | L30: Reg. Error (pts) | M30: Reg. Winner Correct?
A31: Banks Township | B31: Carbon | C31: 391 | D31: 0.40803849 | E31: 160 | F31: 231 | G31: Republican | I31: Banks Township | J31: 0.31908422 | K31: 0.38841202 | L31: -6.9327796 | M31: 1
A32: Beaver Meadows Borough | B32: Carbon | C32: 341 | D32: 0.30210975 | E32: 103 | F32: 238 | G32: Republican | I32: Beaver Meadows Borough | J32: 0.22278668 | K32: 0.28229665 | L32: -5.9509975 | M32: 1
A33: Bowmanstown Borough | B33: Carbon | C33: 411 | D33: 0.34649276 | E33: 142 | F33: 269 | G33: Republican | I33: Bowmanstown Borough | J33: 0.31367265 | K33: 0.31718062 | L33: -0.35079667 | M33: 1
A34: East Penn Township | B34: Carbon | C34: 1483 | D34: 0.28076953 | E34: 416 | F34: 1067 | G34: Republican | I34: East Penn Township | J34: 0.23340984 | K34: 0.25901833 | L34: -2.560849 | M34: 1
A35: East Side Borough | B35: Carbon | C35: 111 | D35: 0.34821671 | E35: 39 | F35: 72 | G35: Republican | I35: East Side Borough | J35: 0.30071708 | K35: 0.32758621 | L35: -2.686913 | M35: 1
A36: Franklin Township | B36: Carbon | C36: 2258 | D36: 0.3014448 | E36: 681 | F36: 1577 | G36: Republican | I36: Franklin Township | J36: 0.24035086 | K36: 0.27721222 | L36: -3.6861353 | M36: 1
A37: Jim Thorpe Borough | B37: Carbon | C37: 2411 | D37: 0.45039431 | E37: 1086 | F37: 1325 | G37: Republican | I37: Jim Thorpe Borough | J37: 0.41312678 | K37: 0.4270793 | L37: -1.3952527 | M37: 1
A38: Kidder Township | B38: Carbon | C38: 912 | D38: 0.36018189 | E38: 328 | F38: 584 | G38: Republican | I38: Kidder Township | J38: 0.29159561 | K38: 0.33492366 | L38: -4.3328058 | M38: 1
A39: Lansford Borough | B39: Carbon | C39: 1078 | D39: 0.41157552 | E39: 444 | F39: 634 | G39: Republican | I39: Lansford Borough | J39: 0.36738246 | K39: 0.395189 | L39: -2.7806541 | M39: 1
A40: Lausanne Township | B40: Carbon | C40: 142 | D40: 0.27654167 | E40: 39 | F40: 103 | G40: Republican | I40: Lausanne Township | J40: 0.24647011 | K40: 0.26206897 | L40: -1.5598859 | M40: 1
A41: Lehigh Township | B41: Carbon | C41: 278 | D41: 0.21887815 | E41: 61 | F41: 217 | G41: Republican | I41: Lehigh Township | J41: 0.148859 | K41: 0.21167883 | L41: -6.2819836 | M41: 1
A42: Lehighton Borough | B42: Carbon | C42: 1900 | D42: 0.39809846 | E42: 756 | F42: 1144 | G42: Republican | I42: Lehighton Borough | J42: 0.36640698 | K42: 0.38847737 | L42: -2.2070388 | M42: 1
... A119: Wind Gap | B119: Northampton | C119: 1391 | D119: 0.44142103 | E119: 614 | F119: 777 | G119: Republican | I119: Wind Gap | J119: 0.39863344 | K119: 0.42550336 | L119: -2.6869913 | M119: 1

Sheet F07 Precinct Trend
A1: F07 · Simple Trend (precinct)
A2: Run Sept. 17, 2026 · Level: Precinct (408) · Source: Precinct Backtest & Forecast Analysis.xlsx (tracker, Sept. 17)
A3: ← Back to Results
A5: Methodology
A6: What it does: the straight-line trend method from F04, applied to each precinct instead of each town.
A7: Data: certified precinct House results for 2018–2024 from the Department of State precinct summary, which keeps precinct codes stable across years.
A8: Backtest: line drawn through 2018–2022, used to predict 2024. District-level miss is measured over in-district precincts only.
A13: 2026 forecast | E13: In plain terms
A14: Brooks (D) share of the two-party vote | C14: 0.48313 | E14: Predicts Mackenzie (48.3% Brooks). Its 2024 backtest came within about 0.4 points of the district result. Confirms F04 at a finer level of detail.
A15: Mackenzie (R) share of the two-party vote | C15: =1-C14 -> 0.51687
A16: Margin: Brooks minus Mackenzie (points) | C16: =(C14-C15)*100 -> -3.374
A17: Predicted winner | C17: =IF(C14>0.5,"Brooks","Mackenzie") -> Mackenzie
A18: Brooks votes
A19: Mackenzie votes
A21: 2024 backtest | E21: Rating
A22: Average miss per town or precinct (points) | C22: 2.24 | E22: Good | F22: See “How to Read” for what the ratings mean.
A23: Towns or precincts where the winner was called correctly | C23: 387 of 408 precincts
A24: District result miss, 2024 (points; negative = too Republican) | C24: 0.38745946
A25: District result miss, 2022 (points) | C25: not available
A26: How strict the backtest was | C26: Out of sample
A29: 2026 forecast detail | J29: 2024 backtest detail
A30: County | B30: Municipality | C30: Precinct | D30: Projected Total Votes | E30: Projected Dem Share | F30: Projected Dem Votes | G30: Projected Rep Votes | H30: Projected Winner | J30: County | K30: Municipality | L30: Precinct | M30: Trend Predicted | N30: Actual Dem Share | O30: Trend Error | P30: Trend Correct?
A31: Carbon | B31: BANKS | C31: 10 | D31: 391 | E31: 0.3558994 | F31: 139 | G31: 252 | H31: Republican | J31: Carbon | K31: BANKS | L31: 10 | M31: 0.30658478 | N31: 0.38841202 | O31: -8.1827236 | P31: 1
A32: Carbon | B32: BEAVER MEADOWS | C32: 40 | D32: 341 | E32: 0.25054939 | F32: 85 | G32: 256 | H32: Republican | J32: Carbon | K32: BEAVER MEADOWS | L32: 40 | M32: 0.21872725 | N32: 0.28229665 | O32: -6.3569402 | P32: 1
A33: Carbon | B33: BOWMANSTOWN | C33: 50 | D33: 411 | E33: 0.30379586 | F33: 125 | G33: 286 | H33: Republican | J33: Carbon | K33: BOWMANSTOWN | L33: 50 | M33: 0.30806586 | N33: 0.31718062 | O33: -0.91147571 | P33: 1
A34: Carbon | B34: EAST PENN | C34: 60 | D34: 786 | E34: 0.21578077 | F34: 170 | G34: 616 | H34: Republican | J34: Carbon | K34: EAST PENN | L34: 60 | M34: 0.23626047 | N34: 0.24085006 | O34: -0.45895919 | P34: 1
A35: Carbon | B35: EAST PENN | C35: 65 | D35: 697 | E35: 0.25733276 | F35: 179 | G35: 518 | H35: Republican | J35: Carbon | K35: EAST PENN | L35: 65 | M35: 0.25260566 | N35: 0.27725118 | O35: -2.4645523 | P35: 1
A36: Carbon | B36: EAST SIDE | C36: 70 | D36: 111 | E36: 0.2823389 | F36: 31 | G36: 80 | H36: Republican | J36: Carbon | K36: EAST SIDE | L36: 70 | M36: 0.3031894 | N36: 0.32758621 | O36: -2.4396811 | P36: 1
A37: Carbon | B37: FRANKLIN | C37: 80 | D37: 522 | E37: 0.24215798 | F37: 126 | G37: 396 | H37: Republican | J37: Carbon | K37: FRANKLIN | L37: 80 | M37: 0.25228175 | N37: 0.26666667 | O37: -1.438492 | P37: 1
A38: Carbon | B38: FRANKLIN | C38: 90 | D38: 960 | E38: 0.26608357 | F38: 255 | G38: 705 | H38: Republican | J38: Carbon | K38: FRANKLIN | L38: 90 | M38: 0.25731054 | N38: 0.2877095 | O38: -3.0398958 | P38: 1
A39: Carbon | B39: FRANKLIN | C39: 100 | D39: 776 | E39: 0.2612572 | F39: 203 | G39: 573 | H39: Republican | J39: Carbon | K39: FRANKLIN | L39: 100 | M39: 0.24367968 | N39: 0.2716763 | O39: -2.7996617 | P39: 1
A40: Carbon | B40: JIM THORPE | C40: 110 | D40: 480 | E40: 0.39462235 | F40: 189 | G40: 291 | H40: Republican | J40: Carbon | K40: JIM THORPE | L40: 110 | M40: 0.38427139 | N40: 0.43984962 | O40: -5.5578234 | P40: 1
A41: Carbon | B41: JIM THORPE | C41: 120 | D41: 338 | E41: 0.43354982 | F41: 147 | G41: 191 | H41: Republican | J41: Carbon | K41: JIM THORPE | L41: 120 | M41: 0.44973264 | N41: 0.41943734 | O41: 3.0295296 | P41: 1
A42: Carbon | B42: JIM THORPE | C42: 130 | D42: 690 | E42: 0.34762431 | F42: 240 | G42: 450 | H42: Republican | J42: Carbon | K42: JIM THORPE | L42: 130 | M42: 0.33993793 | N42: 0.38278146 | O42: -4.2843525 | P42: 1
... A438: Northampton | B438: WIND GAP | C438: 1360 | D438: 1391 | E438: 0.42454097 | F438: 591 | G438: 800 | H438: Republican | J438: Northampton | K438: WIND GAP | L438: 1360 | M438: 0.42983453 | N438: 0.42550336 | O438: 0.4331177 | P438: 1

Sheet F08 Precinct Beta
A1: F08 · Beta-Adjusted (precinct)
A2: Run Sept. 17, 2026 · Level: Precinct (408) · Source: Precinct Backtest & Forecast Analysis.xlsx (tracker, Sept. 17)
A3: ← Back to Results
A5: Methodology
A6: What it does: the beta method from F05, applied to each precinct.
A7: Data: the same precinct file as F07.
A8: Backtest: betas measured on 2018–2022 only, used to predict 2024.
A13: 2026 forecast | E13: In plain terms
A14: Brooks (D) share of the two-party vote | C14: 0.47277 | E14: Predicts Mackenzie (47.3% Brooks). Best district-level backtest of any town- or precinct-level method: it missed 2024 by only 0.21 points. One of the most credible forecasts in this workbook.
A15: Mackenzie (R) share of the two-party vote | C15: =1-C14 -> 0.52723
A16: Margin: Brooks minus Mackenzie (points) | C16: =(C14-C15)*100 -> -5.446
A17: Predicted winner | C17: =IF(C14>0.5,"Brooks","Mackenzie") -> Mackenzie
A18: Brooks votes
A19: Mackenzie votes
A21: 2024 backtest | E21: Rating
A22: Average miss per town or precinct (points) | C22: 2.09 | E22: Good | F22: See “How to Read” for what the ratings mean.
A23: Towns or precincts where the winner was called correctly | C23: 390 of 408 precincts
A24: District result miss, 2024 (points; negative = too Republican) | C24: 0.20996571
A25: District result miss, 2022 (points) | C25: not available
A26: How strict the backtest was | C26: Out of sample
A29: 2026 forecast detail | J29: 2024 backtest detail
A30: County | B30: Municipality | C30: Precinct | D30: Projected Total Votes | E30: Projected Dem Share | F30: Projected Dem Votes | G30: Projected Rep Votes | H30: Projected Winner | J30: County | K30: Municipality | L30: Precinct | M30: Beta-Adj Predicted | N30: Actual Dem Share | O30: Beta-Adj Error | P30: Beta-Adj Correct?
A31: Carbon | B31: BANKS | C31: 10 | D31: 391 | E31: 0.36102331 | F31: 141 | G31: 250 | H31: Republican | J31: Carbon | K31: BANKS | L31: 10 | M31: 0.30751194 | N31: 0.38841202 | O31: -8.0900074 | P31: 1
A32: Carbon | B32: BEAVER MEADOWS | C32: 40 | D32: 341 | E32: 0.24892555 | F32: 85 | G32: 256 | H32: Republican | J32: Carbon | K32: BEAVER MEADOWS | L32: 40 | M32: 0.21906598 | N32: 0.28229665 | O32: -6.3230675 | P32: 1
A33: Carbon | B33: BOWMANSTOWN | C33: 50 | D33: 411 | E33: 0.26896879 | F33: 111 | G33: 300 | H33: Republican | J33: Carbon | K33: BOWMANSTOWN | L33: 50 | M33: 0.29731179 | N33: 0.31718062 | O33: -1.9868823 | P33: 1
A34: Carbon | B34: EAST PENN | C34: 60 | D34: 786 | E34: 0.19585538 | F34: 154 | G34: 632 | H34: Republican | J34: Carbon | K34: EAST PENN | L34: 60 | M34: 0.23489374 | N34: 0.24085006 | O34: -0.59563202 | P34: 1
A35: Carbon | B35: EAST PENN | C35: 65 | D35: 697 | E35: 0.24003787 | F35: 167 | G35: 530 | H35: Republican | J35: Carbon | K35: EAST PENN | L35: 65 | M35: 0.24844072 | N35: 0.27725118 | O35: -2.8810468 | P35: 1
A36: Carbon | B36: EAST SIDE | C36: 70 | D36: 111 | E36: 0.27943649 | F36: 31 | G36: 80 | H36: Republican | J36: Carbon | K36: EAST SIDE | L36: 70 | M36: 0.31139583 | N36: 0.32758621 | O36: -1.6190375 | P36: 1
A37: Carbon | B37: FRANKLIN | C37: 80 | D37: 522 | E37: 0.22717362 | F37: 119 | G37: 403 | H37: Republican | J37: Carbon | K37: FRANKLIN | L37: 80 | M37: 0.25147165 | N37: 0.26666667 | O37: -1.5195013 | P37: 1
A38: Carbon | B38: FRANKLIN | C38: 90 | D38: 960 | E38: 0.25396894 | F38: 244 | G38: 716 | H38: Republican | J38: Carbon | K38: FRANKLIN | L38: 90 | M38: 0.25489235 | N38: 0.2877095 | O38: -3.2817151 | P38: 1
A39: Carbon | B39: FRANKLIN | C39: 100 | D39: 776 | E39: 0.25691682 | F39: 199 | G39: 577 | H39: Republican | J39: Carbon | K39: FRANKLIN | L39: 100 | M39: 0.24148246 | N39: 0.2716763 | O39: -3.019384 | P39: 1
A40: Carbon | B40: JIM THORPE | C40: 110 | D40: 480 | E40: 0.38057657 | F40: 183 | G40: 297 | H40: Republican | J40: Carbon | K40: JIM THORPE | L40: 110 | M40: 0.38447955 | N40: 0.43984962 | O40: -5.5370076 | P40: 1
A41: Carbon | B41: JIM THORPE | C41: 120 | D41: 338 | E41: 0.40570315 | F41: 137 | G41: 201 | H41: Republican | J41: Carbon | K41: JIM THORPE | L41: 120 | M41: 0.43893209 | N41: 0.41943734 | O41: 1.9494748 | P41: 1
A42: Carbon | B42: JIM THORPE | C42: 130 | D42: 690 | E42: 0.34048708 | F42: 235 | G42: 455 | H42: Republican | J42: Carbon | K42: JIM THORPE | L42: 130 | M42: 0.34158488 | N42: 0.38278146 | O42: -4.1196576 | P42: 1
... A438: Northampton | B438: WIND GAP | C438: 1360 | D438: 1391 | E438: 0.40398174 | F438: 562 | G438: 829 | H438: Republican | J438: Northampton | K438: WIND GAP | L438: 1360 | M438: 0.42277467 | N438: 0.42550336 | O438: -0.27286822 | P438: 1

Sheet F09 Precinct Regression
A1: F09 · Multi-Variable Regression (precinct)
A2: Run Sept. 17, 2026 · Level: Precinct (408) · Source: Precinct Backtest & Forecast Analysis.xlsx (tracker, Sept. 17)
A3: ← Back to Results
A5: Methodology
A6: What it does: a regression on registration margin, presidential year and the previous result, applied to each precinct.
A7: Equation: Dem share = 5.39 + 0.0211 × (registration margin, pts) − 5.726 × (presidential year) + 0.927 × (previous Dem share). No education variable, because Census areas do not line up with precincts.
A8: Backtest: trained on 2020–2022 only, used to predict 2024.
A13: 2026 forecast | E13: In plain terms
A14: Brooks (D) share of the two-party vote | C14: 0.50897 | E14: Predicts a narrow Brooks win (50.9%), but like F06 it had the weakest backtest at its level, missing 2024 by about 1.8 points. Treat with caution.
A15: Mackenzie (R) share of the two-party vote | C15: =1-C14 -> 0.49103
A16: Margin: Brooks minus Mackenzie (points) | C16: =(C14-C15)*100 -> 1.794
A17: Predicted winner | C17: =IF(C14>0.5,"Brooks","Mackenzie") -> Brooks
A18: Brooks votes
A19: Mackenzie votes
A21: 2024 backtest | E21: Rating
A22: Average miss per town or precinct (points) | C22: 2.46 | E22: Weak | F22: See “How to Read” for what the ratings mean.
A23: Towns or precincts where the winner was called correctly | C23: 366 of 408 precincts
A24: District result miss, 2024 (points; negative = too Republican) | C24: -1.8266567
A25: District result miss, 2022 (points) | C25: not available
A26: How strict the backtest was | C26: Out of sample
A29: 2026 forecast detail | J29: 2024 backtest detail
A30: County | B30: Municipality | C30: Precinct | D30: Projected Total Votes | E30: Projected Dem Share | F30: Projected Dem Votes | G30: Projected Rep Votes | H30: Projected Winner | J30: County | K30: Municipality | L30: Precinct | M30: Reg. Predicted | N30: Actual Dem Share | O30: Reg. Error | P30: Reg. Correct?
A31: Carbon | B31: BANKS | C31: 10 | D31: 391 | E31: 0.41514832 | F31: 162 | G31: 229 | H31: Republican | J31: Carbon | K31: BANKS | L31: 10 | M31: 0.3268433 | N31: 0.38841202 | O31: -6.1568722 | P31: 1
A32: Carbon | B32: BEAVER MEADOWS | C32: 40 | D32: 341 | E32: 0.31079283 | F32: 106 | G32: 235 | H32: Republican | J32: Carbon | K32: BEAVER MEADOWS | L32: 40 | M32: 0.23983137 | N32: 0.28229665 | O32: -4.2465279 | P32: 1
A33: Carbon | B33: BOWMANSTOWN | C33: 50 | D33: 411 | E33: 0.34374916 | F33: 141 | G33: 270 | H33: Republican | J33: Carbon | K33: BOWMANSTOWN | L33: 50 | M33: 0.3254381 | N33: 0.31718062 | O33: 0.82574803 | P33: 1
A34: Carbon | B34: EAST PENN | C34: 60 | D34: 786 | E34: 0.26968264 | F34: 212 | G34: 574 | H34: Republican | J34: Carbon | K34: EAST PENN | L34: 60 | M34: 0.24813145 | N34: 0.24085006 | O34: 0.72813919 | P34: 1
A35: Carbon | B35: EAST PENN | C35: 65 | D35: 697 | E35: 0.30412349 | F35: 212 | G35: 485 | H35: Republican | J35: Carbon | K35: EAST PENN | L35: 65 | M35: 0.26377401 | N35: 0.27725118 | O35: -1.3477179 | P35: 1
A36: Carbon | B36: EAST SIDE | C36: 70 | D36: 111 | E36: 0.35523338 | F36: 39 | G36: 72 | H36: Republican | J36: Carbon | K36: EAST SIDE | L36: 70 | M36: 0.31973805 | N36: 0.32758621 | O36: -0.78481555 | P36: 1
A37: Carbon | B37: FRANKLIN | C37: 80 | D37: 522 | E37: 0.29460479 | F37: 154 | G37: 368 | H37: Republican | J37: Carbon | K37: FRANKLIN | L37: 80 | M37: 0.26171184 | N37: 0.26666667 | O37: -0.49548301 | P37: 1
A38: Carbon | B38: FRANKLIN | C38: 90 | D38: 960 | E38: 0.31384595 | F38: 301 | G38: 659 | H38: Republican | J38: Carbon | K38: FRANKLIN | L38: 90 | M38: 0.26610164 | N38: 0.2877095 | O38: -2.1607859 | P38: 1
A39: Carbon | B39: FRANKLIN | C39: 100 | D39: 776 | E39: 0.29854819 | F39: 232 | G39: 544 | H39: Republican | J39: Carbon | K39: FRANKLIN | L39: 100 | M39: 0.23618003 | N39: 0.2716763 | O39: -3.5496268 | P39: 1
A40: Carbon | B40: JIM THORPE | C40: 110 | D40: 480 | E40: 0.46286138 | F40: 222 | G40: 258 | H40: Republican | J40: Carbon | K40: JIM THORPE | L40: 110 | M40: 0.41922519 | N40: 0.43984962 | O40: -2.0624434 | P40: 1
A41: Carbon | B41: JIM THORPE | C41: 120 | D41: 338 | E41: 0.44313695 | F41: 150 | G41: 188 | H41: Republican | J41: Carbon | K41: JIM THORPE | L41: 120 | M41: 0.42154455 | N41: 0.41943734 | O41: 0.21072104 | P41: 1
A42: Carbon | B42: JIM THORPE | C42: 130 | D42: 690 | E42: 0.4061555 | F42: 280 | G42: 410 | H42: Republican | J42: Carbon | K42: JIM THORPE | L42: 130 | M42: 0.35595855 | N42: 0.38278146 | O42: -2.682291 | P42: 1
... A438: Northampton | B438: WIND GAP | C438: 1360 | D438: 1391 | E438: 0.4467196 | F438: 621 | G438: 770 | H438: Republican | J438: Northampton | K438: WIND GAP | L438: 1360 | M438: 0.41322716 | N438: 0.42550336 | O438: -1.2276193 | P438: 1

Sheet F10 Muni Template Trend
A1: F10 · Simple Trend (municipal template)
A2: Run Sept. 24, 2026 · Level: Municipality (89) · Source: Meringer Municipal Forecast.xlsx (tracker, Sept. 24)
A3: ← Back to Results
A5: Methodology
A6: Same method and same backtest as F04, entered in the class forecast template, where district totals are formulas that add up the rows. The Brooks share differs from F04 because the template uses a different projected turnout for each town or precinct, which changes how much each one counts.
A7: For the full method description, see F04.
A13: 2026 forecast | E13: In plain terms
A14: Brooks (D) share of the two-party vote | C14: 0.46939 | E14: Predicts Mackenzie (46.9% Brooks). The template version of F04; same strong backtest.
A15: Mackenzie (R) share of the two-party vote | C15: =1-C14 -> 0.53061
A16: Margin: Brooks minus Mackenzie (points) | C16: =(C14-C15)*100 -> -6.122
A17: Predicted winner | C17: =IF(C14>0.5,"Brooks","Mackenzie") -> Mackenzie
A18: Brooks votes | C18: 152819
A19: Mackenzie votes | C19: 172750
A21: 2024 backtest | E21: Rating
A22: Average miss per town or precinct (points) | C22: 1.99 | E22: Good | F22: See “How to Read” for what the ratings mean.
A23: Towns or precincts where the winner was called correctly | C23: 86 of 89 towns
A24: District result miss, 2024 (points; negative = too Republican) | C24: 0.26874283
A25: District result miss, 2022 (points) | C25: not available
A26: How strict the backtest was | C26: Out of sample (same backtest as F04)
A29: 2026 forecast detail | I29: 2024 backtest detail
A30: County | B30: Municipality | C30: Brooks votes | D30: Mackenzie votes | E30: Total votes | F30: Brooks share | G30: Mackenzie share | I30: Municipality | J30: Predicted Dem Share (Trend) | K30: Actual Dem Share | L30: Trend Error (pts) | M30: Trend Winner Correct?
A31: Carbon | B31: BANKS TOWNSHIP | C31: 139 | D31: 252 | E31: 391 | F31: 0.35549872 | G31: 0.64450128 | I31: Banks Township | J31: 0.30658478 | K31: 0.38841202 | L31: -8.1827236 | M31: 1
A32: Carbon | B32: BEAVER MEADOWS BOROUGH | C32: 85 | D32: 256 | E32: 341 | F32: 0.24926686 | G32: 0.75073314 | I32: Beaver Meadows Borough | J32: 0.21872725 | K32: 0.28229665 | L32: -6.3569402 | M32: 1
A33: Carbon | B33: BOWMANSTOWN BOROUGH | C33: 125 | D33: 286 | E33: 411 | F33: 0.30413625 | G33: 0.69586375 | I33: Bowmanstown Borough | J33: 0.30806586 | K33: 0.31718062 | L33: -0.91147571 | M33: 1
A34: Carbon | B34: EAST PENN TOWNSHIP | C34: 351 | D34: 1132 | E34: 1483 | F34: 0.2366824 | G34: 0.7633176 | I34: East Penn Township | J34: 0.24380138 | K34: 0.25901833 | L34: -1.5216955 | M34: 1
A35: Carbon | B35: EAST SIDE BOROUGH | C35: 31 | D35: 80 | E35: 111 | F35: 0.27927928 | G35: 0.72072072 | I35: East Side Borough | J35: 0.3031894 | K35: 0.32758621 | L35: -2.4396811 | M35: 1
A36: Carbon | B36: FRANKLIN TOWNSHIP | C36: 584 | D36: 1674 | E36: 2258 | F36: 0.25863596 | G36: 0.74136404 | I36: Franklin Township | J36: 0.25135692 | K36: 0.27721222 | L36: -2.5855293 | M36: 1
A37: Carbon | B37: JIM THORPE BOROUGH | C37: 991 | D37: 1420 | E37: 2411 | F37: 0.41103277 | G37: 0.58896723 | I37: Jim Thorpe Borough | J37: 0.42151537 | K37: 0.4270793 | L37: -0.55639296 | M37: 1
A38: Carbon | B38: KIDDER TOWNSHIP | C38: 297 | D38: 615 | E38: 912 | F38: 0.32565789 | G38: 0.67434211 | I38: Kidder Township | J38: 0.30908561 | K38: 0.33492366 | L38: -2.5838053 | M38: 1
A39: Carbon | B39: LANSFORD BOROUGH | C39: 386 | D39: 692 | E39: 1078 | F39: 0.3580705 | G39: 0.6419295 | I39: Lansford Borough | J39: 0.37118771 | K39: 0.395189 | L39: -2.4001294 | M39: 1
A40: Carbon | B40: LAUSANNE TOWNSHIP | C40: 36 | D40: 106 | E40: 142 | F40: 0.25352113 | G40: 0.74647887 | I40: Lausanne Township | J40: 0.29698511 | K40: 0.26206897 | L40: 3.4916149 | M40: 1
A41: Carbon | B41: LEHIGH TOWNSHIP | C41: 61 | D41: 217 | E41: 278 | F41: 0.21942446 | G41: 0.78057554 | I41: Lehigh Township | J41: 0.21574705 | K41: 0.21167883 | L41: 0.40682152 | M41: 1
A42: Carbon | B42: LEHIGHTON BOROUGH | C42: 705 | D42: 1195 | E42: 1900 | F42: 0.37105263 | G42: 0.62894737 | I42: Lehighton Borough | J42: 0.38906899 | K42: 0.38847737 | L42: 0.05916284 | M42: 1
... A119: Northampton | B119: WIND GAP BORO | C119: 591 | D119: 800 | E119: 1391 | F119: 0.42487419 | G119: 0.57512581 | I119: Wind Gap | J119: 0.42983453 | K119: 0.42550336 | L119: 0.4331177 | M119: 1

Sheet F11 Muni Template Beta
A1: F11 · Beta-Adjusted (municipal template)
A2: Run Sept. 24, 2026 · Level: Municipality (89) · Source: Meringer Municipal Forecast.xlsx (tracker, Sept. 24)
A3: ← Back to Results
A5: Methodology
A6: Same method and same backtest as F05, entered in the class forecast template, where district totals are formulas that add up the rows. The Brooks share differs from F05 because the template uses a different projected turnout for each town or precinct, which changes how much each one counts.
A7: For the full method description, see F05.
A13: 2026 forecast | E13: In plain terms
A14: Brooks (D) share of the two-party vote | C14: 0.4597 | E14: Predicts Mackenzie (46.0% Brooks), the lowest Brooks share of any forecast. The template version of F05.
A15: Mackenzie (R) share of the two-party vote | C15: =1-C14 -> 0.5403
A16: Margin: Brooks minus Mackenzie (points) | C16: =(C14-C15)*100 -> -8.06
A17: Predicted winner | C17: =IF(C14>0.5,"Brooks","Mackenzie") -> Mackenzie
A18: Brooks votes | C18: 149665
A19: Mackenzie votes | C19: 175904
A21: 2024 backtest | E21: Rating
A22: Average miss per town or precinct (points) | C22: 1.81 | E22: Fair | F22: See “How to Read” for what the ratings mean.
A23: Towns or precincts where the winner was called correctly | C23: 86 of 89 towns
A24: District result miss, 2024 (points; negative = too Republican) | C24: 1.2854274
A25: District result miss, 2022 (points) | C25: not available
A26: How strict the backtest was | C26: Out of sample (same backtest as F05)
A29: 2026 forecast detail | I29: 2024 backtest detail
A30: County | B30: Municipality | C30: Brooks votes | D30: Mackenzie votes | E30: Total votes | F30: Brooks share | G30: Mackenzie share | I30: Municipality | J30: Beta-Adj Predicted Share | K30: Actual Dem Share | L30: Beta-Adj Error (pts) | M30: Beta-Adj Winner Correct?
A31: Carbon | B31: BANKS TOWNSHIP | C31: 142 | D31: 249 | E31: 391 | F31: 0.36317136 | G31: 0.63682864 | I31: Banks Township | J31: 0.34217727 | K31: 0.38841202 | L31: -4.6234743 | M31: 1
A32: Carbon | B32: BEAVER MEADOWS BOROUGH | C32: 86 | D32: 255 | E32: 341 | F32: 0.25219941 | G32: 0.74780059 | I32: Beaver Meadows Borough | J32: 0.25367759 | K32: 0.28229665 | L32: -2.8619061 | M32: 1
A33: Carbon | B33: BOWMANSTOWN BOROUGH | C33: 112 | D33: 299 | E33: 411 | F33: 0.27250608 | G33: 0.72749392 | I33: Bowmanstown Borough | J33: 0.32656465 | K33: 0.31718062 | L33: 0.93840325 | M33: 1
A34: Carbon | B34: EAST PENN TOWNSHIP | C34: 329 | D34: 1154 | E34: 1483 | F34: 0.22184761 | G34: 0.77815239 | I34: East Penn Township | J34: 0.2697552 | K34: 0.25901833 | L34: 1.0736871 | M34: 1
A35: Carbon | B35: EAST SIDE BOROUGH | C35: 32 | D35: 79 | E35: 111 | F35: 0.28828829 | G35: 0.71171171 | I35: East Side Borough | J35: 0.35033421 | K35: 0.32758621 | L35: 2.2747999 | M35: 1
A36: Carbon | B36: FRANKLIN TOWNSHIP | C36: 567 | D36: 1691 | E36: 2258 | F36: 0.25110717 | G36: 0.74889283 | I36: Franklin Township | J36: 0.27261462 | K36: 0.27721222 | L36: -0.45975927 | M36: 1
A37: Carbon | B37: JIM THORPE BOROUGH | C37: 949 | D37: 1462 | E37: 2411 | F37: 0.39361261 | G37: 0.60638739 | I37: Jim Thorpe Borough | J37: 0.44051077 | K37: 0.4270793 | L37: 1.3431469 | M37: 1
A38: Carbon | B38: KIDDER TOWNSHIP | C38: 293 | D38: 619 | E38: 912 | F38: 0.32127193 | G38: 0.67872807 | I38: Kidder Township | J38: 0.3206431 | K38: 0.33492366 | L38: -1.4280567 | M38: 1
A39: Carbon | B39: LANSFORD BOROUGH | C39: 383 | D39: 695 | E39: 1078 | F39: 0.35528757 | G39: 0.64471243 | I39: Lansford Borough | J39: 0.41069815 | K39: 0.395189 | L39: 1.5509146 | M39: 1
A40: Carbon | B40: LAUSANNE TOWNSHIP | C40: 34 | D40: 108 | E40: 142 | F40: 0.23943662 | G40: 0.76056338 | I40: Lausanne Township | J40: 0.30648463 | K40: 0.26206897 | L40: 4.4415667 | M40: 1
A41: Carbon | B41: LEHIGH TOWNSHIP | C41: 59 | D41: 219 | E41: 278 | F41: 0.21223022 | G41: 0.78776978 | I41: Lehigh Township | J41: 0.20900933 | K41: 0.21167883 | L41: -0.26695065 | M41: 1
A42: Carbon | B42: LEHIGHTON BOROUGH | C42: 662 | D42: 1238 | E42: 1900 | F42: 0.34842105 | G42: 0.65157895 | I42: Lehighton Borough | J42: 0.4100046 | K42: 0.38847737 | L42: 2.1527237 | M42: 1
... A119: Northampton | B119: WIND GAP BORO | C119: 562 | D119: 829 | E119: 1391 | F119: 0.40402588 | G119: 0.59597412 | I119: Wind Gap | J119: 0.43333593 | K119: 0.42550336 | L119: 0.78325749 | M119: 1

Sheet F12 Muni Template Reg
A1: F12 · Regression (municipal template)
A2: Run Sept. 24, 2026 · Level: Municipality (89) · Source: Meringer Municipal Forecast.xlsx (tracker, Sept. 24)
A3: ← Back to Results
A5: Methodology
A6: Same method and same backtest as F06, entered in the class forecast template, where district totals are formulas that add up the rows. The Brooks share differs from F06 because the template uses a different projected turnout for each town or precinct, which changes how much each one counts.
A7: For the full method description, see F06.
A13: 2026 forecast | E13: In plain terms
A14: Brooks (D) share of the two-party vote | C14: 0.49935 | E14: Essentially a tie (49.9% Brooks), tipping to Mackenzie. The template version of F06, which had the worst municipal backtest.
A15: Mackenzie (R) share of the two-party vote | C15: =1-C14 -> 0.50065
A16: Margin: Brooks minus Mackenzie (points) | C16: =(C14-C15)*100 -> -0.13
A17: Predicted winner | C17: =IF(C14>0.5,"Brooks","Mackenzie") -> Mackenzie
A18: Brooks votes | C18: 162574
A19: Mackenzie votes | C19: 162995
A21: 2024 backtest | E21: Rating
A22: Average miss per town or precinct (points) | C22: 3.09 | E22: Weak | F22: See “How to Read” for what the ratings mean.
A23: Towns or precincts where the winner was called correctly | C23: 82 of 89 towns
A24: District result miss, 2024 (points; negative = too Republican) | C24: -2.2876796
A25: District result miss, 2022 (points) | C25: not available
A26: How strict the backtest was | C26: Out of sample (same backtest as F06)
A29: 2026 forecast detail | I29: 2024 backtest detail
A30: County | B30: Municipality | C30: Brooks votes | D30: Mackenzie votes | E30: Total votes | F30: Brooks share | G30: Mackenzie share | I30: Municipality | J30: Reg. Predicted Share | K30: Actual Dem Share | L30: Reg. Error (pts) | M30: Reg. Winner Correct?
A31: Carbon | B31: BANKS TOWNSHIP | C31: 160 | D31: 231 | E31: 391 | F31: 0.40920716 | G31: 0.59079284 | I31: Banks Township | J31: 0.31908422 | K31: 0.38841202 | L31: -6.9327796 | M31: 1
A32: Carbon | B32: BEAVER MEADOWS BOROUGH | C32: 103 | D32: 238 | E32: 341 | F32: 0.30205279 | G32: 0.69794721 | I32: Beaver Meadows Borough | J32: 0.22278668 | K32: 0.28229665 | L32: -5.9509975 | M32: 1
A33: Carbon | B33: BOWMANSTOWN BOROUGH | C33: 142 | D33: 269 | E33: 411 | F33: 0.34549878 | G33: 0.65450122 | I33: Bowmanstown Borough | J33: 0.31367265 | K33: 0.31718062 | L33: -0.35079667 | M33: 1
A34: Carbon | B34: EAST PENN TOWNSHIP | C34: 416 | D34: 1067 | E34: 1483 | F34: 0.28051247 | G34: 0.71948753 | I34: East Penn Township | J34: 0.23340984 | K34: 0.25901833 | L34: -2.560849 | M34: 1
A35: Carbon | B35: EAST SIDE BOROUGH | C35: 39 | D35: 72 | E35: 111 | F35: 0.35135135 | G35: 0.64864865 | I35: East Side Borough | J35: 0.30071708 | K35: 0.32758621 | L35: -2.686913 | M35: 1
A36: Carbon | B36: FRANKLIN TOWNSHIP | C36: 681 | D36: 1577 | E36: 2258 | F36: 0.30159433 | G36: 0.69840567 | I36: Franklin Township | J36: 0.24035086 | K36: 0.27721222 | L36: -3.6861353 | M36: 1
A37: Carbon | B37: JIM THORPE BOROUGH | C37: 1086 | D37: 1325 | E37: 2411 | F37: 0.4504355 | G37: 0.5495645 | I37: Jim Thorpe Borough | J37: 0.41312678 | K37: 0.4270793 | L37: -1.3952527 | M37: 1
A38: Carbon | B38: KIDDER TOWNSHIP | C38: 328 | D38: 584 | E38: 912 | F38: 0.35964912 | G38: 0.64035088 | I38: Kidder Township | J38: 0.29159561 | K38: 0.33492366 | L38: -4.3328058 | M38: 1
A39: Carbon | B39: LANSFORD BOROUGH | C39: 444 | D39: 634 | E39: 1078 | F39: 0.41187384 | G39: 0.58812616 | I39: Lansford Borough | J39: 0.36738246 | K39: 0.395189 | L39: -2.7806541 | M39: 1
A40: Carbon | B40: LAUSANNE TOWNSHIP | C40: 39 | D40: 103 | E40: 142 | F40: 0.27464789 | G40: 0.72535211 | I40: Lausanne Township | J40: 0.24647011 | K40: 0.26206897 | L40: -1.5598859 | M40: 1
A41: Carbon | B41: LEHIGH TOWNSHIP | C41: 61 | D41: 217 | E41: 278 | F41: 0.21942446 | G41: 0.78057554 | I41: Lehigh Township | J41: 0.148859 | K41: 0.21167883 | L41: -6.2819836 | M41: 1
A42: Carbon | B42: LEHIGHTON BOROUGH | C42: 756 | D42: 1144 | E42: 1900 | F42: 0.39789474 | G42: 0.60210526 | I42: Lehighton Borough | J42: 0.36640698 | K42: 0.38847737 | L42: -2.2070388 | M42: 1
... A119: Northampton | B119: WIND GAP BORO | C119: 614 | D119: 777 | E119: 1391 | F119: 0.44140906 | G119: 0.55859094 | I119: Wind Gap | J119: 0.39863344 | K119: 0.42550336 | L119: -2.6869913 | M119: 1

Sheet F13 Pct Template Trend
A1: F13 · Simple Trend (precinct template)
A2: Run Sept. 24, 2026 · Level: Precinct (370) · Source: Meringer Precinct Forecast.xlsx (tracker, Sept. 24)
A3: ← Back to Results
A5: Methodology
A6: Same method and same backtest as F07, entered in the class forecast template, where district totals are formulas that add up the rows. The Brooks share differs from F07 because the template uses a different projected turnout for each town or precinct, which changes how much each one counts.
A7: For the full method description, see F07.
A13: 2026 forecast | E13: In plain terms
A14: Brooks (D) share of the two-party vote | C14: 0.4763 | E14: Predicts Mackenzie (47.6% Brooks). The template version of F07.
A15: Mackenzie (R) share of the two-party vote | C15: =1-C14 -> 0.5237
A16: Margin: Brooks minus Mackenzie (points) | C16: =(C14-C15)*100 -> -4.74
A17: Predicted winner | C17: =IF(C14>0.5,"Brooks","Mackenzie") -> Mackenzie
A18: Brooks votes | C18: 166113
A19: Mackenzie votes | C19: 182644
A21: 2024 backtest | E21: Rating
A22: Average miss per town or precinct (points) | C22: 2.24 | E22: Good | F22: See “How to Read” for what the ratings mean.
A23: Towns or precincts where the winner was called correctly | C23: 387 of 408 precincts
A24: District result miss, 2024 (points; negative = too Republican) | C24: 0.38745946
A25: District result miss, 2022 (points) | C25: not available
A26: How strict the backtest was | C26: Out of sample (same backtest as F07)
A29: 2026 forecast detail | J29: 2024 backtest detail
A30: County | B30: Municipality | C30: Precinct | D30: Brooks votes | E30: Mackenzie votes | F30: Total votes | G30: Brooks share | H30: Mackenzie share | J30: County | K30: Municipality | L30: Precinct | M30: Trend Predicted | N30: Actual Dem Share | O30: Trend Error | P30: Trend Correct?
A31: Carbon | B31: BANKS TOWNSHIP | C31: BANKS TOWNSHIP | D31: 139 | E31: 252 | F31: 391 | G31: 0.35549872 | H31: 0.64450128 | J31: Carbon | K31: BANKS | L31: 10 | M31: 0.30658478 | N31: 0.38841202 | O31: -8.1827236 | P31: 1
A32: Carbon | B32: BEAVER MEADOWS BOROUGH | C32: BEAVER MEADOWS BOROUGH | D32: 85 | E32: 256 | F32: 341 | G32: 0.24926686 | H32: 0.75073314 | J32: Carbon | K32: BEAVER MEADOWS | L32: 40 | M32: 0.21872725 | N32: 0.28229665 | O32: -6.3569402 | P32: 1
A33: Carbon | B33: BOWMANSTOWN BOROUGH | C33: BOWMANSTOWN BOROUGH | D33: 125 | E33: 286 | F33: 411 | G33: 0.30413625 | H33: 0.69586375 | J33: Carbon | K33: BOWMANSTOWN | L33: 50 | M33: 0.30806586 | N33: 0.31718062 | O33: -0.91147571 | P33: 1
A34: Carbon | B34: EAST PENN TOWNSHIP | C34: EAST PENN TOWNSHIP-NORTH | D34: 170 | E34: 616 | F34: 786 | G34: 0.21628499 | H34: 0.78371501 | J34: Carbon | K34: EAST PENN | L34: 60 | M34: 0.23626047 | N34: 0.24085006 | O34: -0.45895919 | P34: 1
A35: Carbon | B35: EAST PENN TOWNSHIP | C35: EAST PENN TOWNSHIP-SOUTH | D35: 179 | E35: 518 | F35: 697 | G35: 0.25681492 | H35: 0.74318508 | J35: Carbon | K35: EAST PENN | L35: 65 | M35: 0.25260566 | N35: 0.27725118 | O35: -2.4645523 | P35: 1
A36: Carbon | B36: EAST SIDE BOROUGH | C36: EAST SIDE BOROUGH | D36: 31 | E36: 80 | F36: 111 | G36: 0.27927928 | H36: 0.72072072 | J36: Carbon | K36: EAST SIDE | L36: 70 | M36: 0.3031894 | N36: 0.32758621 | O36: -2.4396811 | P36: 1
A37: Carbon | B37: FRANKLIN TOWNSHIP | C37: FRANKLIN TOWNSHIP-HARRITY | D37: 255 | E37: 705 | F37: 960 | G37: 0.265625 | H37: 0.734375 | J37: Carbon | K37: FRANKLIN | L37: 80 | M37: 0.25228175 | N37: 0.26666667 | O37: -1.438492 | P37: 1
A38: Carbon | B38: FRANKLIN TOWNSHIP | C38: FRANKLIN TOWNSHIP-IND DIST | D38: 584 | E38: 1674 | F38: 2258 | G38: 0.25863596 | H38: 0.74136404 | J38: Carbon | K38: FRANKLIN | L38: 90 | M38: 0.25731054 | N38: 0.2877095 | O38: -3.0398958 | P38: 1
A39: Carbon | B39: FRANKLIN TOWNSHIP | C39: FRANKLIN TOWNSHIP-LONG RUN | D39: 203 | E39: 573 | F39: 776 | G39: 0.26159794 | H39: 0.73840206 | J39: Carbon | K39: FRANKLIN | L39: 100 | M39: 0.24367968 | N39: 0.2716763 | O39: -2.7996617 | P39: 1
A40: Carbon | B40: JIM THORPE BOROUGH | C40: JIM THORPE BOROUGH-1ST | D40: 189 | E40: 291 | F40: 480 | G40: 0.39375 | H40: 0.60625 | J40: Carbon | K40: JIM THORPE | L40: 110 | M40: 0.38427139 | N40: 0.43984962 | O40: -5.5578234 | P40: 1
A41: Carbon | B41: JIM THORPE BOROUGH | C41: JIM THORPE BOROUGH-2ND | D41: 147 | E41: 191 | F41: 338 | G41: 0.43491124 | H41: 0.56508876 | J41: Carbon | K41: JIM THORPE | L41: 120 | M41: 0.44973264 | N41: 0.41943734 | O41: 3.0295296 | P41: 1
A42: Carbon | B42: JIM THORPE BOROUGH | C42: JIM THORPE BOROUGH-3RD | D42: 240 | E42: 450 | F42: 690 | G42: 0.34782609 | H42: 0.65217391 | J42: Carbon | K42: JIM THORPE | L42: 130 | M42: 0.33993793 | N42: 0.38278146 | O42: -4.2843525 | P42: 1
... A400: Northampton | B400: WIND GAP BORO | C400: WIND GAP | D400: 591 | E400: 800 | F400: 1391 | G400: 0.42487419 | H400: 0.57512581 | J400: Northampton | K400: NORTHAMPTON | L400: 980 | M400: 0.48441247 | N400: 0.42245989 | O400: 6.1952577 | P400: 1
J401: Northampton | K401: PALMER | L401: 990 | M401: 0.5572957 | N401: 0.54609343 | O401: 1.1202273 | P401: 1
J402: Northampton | K402: PALMER | L402: 1000 | M402: 0.46890038 | N402: 0.46838407 | O402: 0.051630818 | P402: 1
J403: Northampton | K403: PALMER | L403: 1010 | M403: 0.53152517 | N403: 0.50895615 | O403: 2.2569019 | P403: 1
J404: Northampton | K404: PALMER | L404: 1020 | M404: 0.46270824 | N404: 0.47210131 | O404: -0.93930683 | P404: 1
J405: Northampton | K405: PALMER | L405: 1030 | M405: 0.52813255 | N405: 0.54927164 | O405: -2.1139083 | P405: 1
J406: Northampton | K406: PALMER | L406: 1040 | M406: 0.49257677 | N406: 0.48898964 | O406: 0.3587137 | P406: 1
J407: Northampton | K407: PALMER | L407: 1050 | M407: 0.43223449 | N407: 0.43711844 | O407: -0.48839485 | P407: 1
J408: Northampton | K408: PEN ARGYL | L408: 1060 | M408: 0.36147873 | N408: 0.36012862 | O408: 0.13501106 | P408: 1
J409: Northampton | K409: PEN ARGYL | L409: 1070 | M409: 0.3576101 | N409: 0.35047361 | O409: 0.7136485 | P409: 1
J410: Northampton | K410: PEN ARGYL | L410: 1080 | M410: 0.39597685 | N410: 0.4039604 | O410: -0.79835469 | P410: 1
J411: Northampton | K411: PEN ARGYL | L411: 1090 | M411: 0.43550452 | N411: 0.3902439 | O411: 4.526062 | P411: 1
J412: Northampton | K412: PLAINFIELD | L412: 1100 | M412: 0.30351181 | N412: 0.34944869 | O412: -4.5936879 | P412: 1
... J438: Northampton | K438: WIND GAP | L438: 1360 | M438: 0.42983453 | N438: 0.42550336 | O438: 0.4331177 | P438: 1

Sheet F14 Pct Template Beta
A1: F14 · Beta-Adjusted (precinct template)
A2: Run Sept. 24, 2026 · Level: Precinct (370) · Source: Meringer Precinct Forecast.xlsx (tracker, Sept. 24)
A3: ← Back to Results
A5: Methodology
A6: Same method and same backtest as F08, entered in the class forecast template, where district totals are formulas that add up the rows. The Brooks share differs from F08 because the template uses a different projected turnout for each town or precinct, which changes how much each one counts.
A7: For the full method description, see F08.
A13: 2026 forecast | E13: In plain terms
A14: Brooks (D) share of the two-party vote | C14: 0.46573 | E14: Predicts Mackenzie (46.6% Brooks). The template version of F08, which had the best unit-level backtest.
A15: Mackenzie (R) share of the two-party vote | C15: =1-C14 -> 0.53427
A16: Margin: Brooks minus Mackenzie (points) | C16: =(C14-C15)*100 -> -6.854
A17: Predicted winner | C17: =IF(C14>0.5,"Brooks","Mackenzie") -> Mackenzie
A18: Brooks votes | C18: 162421
A19: Mackenzie votes | C19: 186323
A21: 2024 backtest | E21: Rating
A22: Average miss per town or precinct (points) | C22: 2.09 | E22: Good | F22: See “How to Read” for what the ratings mean.
A23: Towns or precincts where the winner was called correctly | C23: 390 of 408 precincts
A24: District result miss, 2024 (points; negative = too Republican) | C24: 0.20996571
A25: District result miss, 2022 (points) | C25: not available
A26: How strict the backtest was | C26: Out of sample (same backtest as F08)
A29: 2026 forecast detail | J29: 2024 backtest detail
A30: County | B30: Municipality | C30: Precinct | D30: Brooks votes | E30: Mackenzie votes | F30: Total votes | G30: Brooks share | H30: Mackenzie share | J30: County | K30: Municipality | L30: Precinct | M30: Beta-Adj Predicted | N30: Actual Dem Share | O30: Beta-Adj Error | P30: Beta-Adj Correct?
A31: Carbon | B31: BANKS TOWNSHIP | C31: BANKS TOWNSHIP | D31: 141 | E31: 250 | F31: 391 | G31: 0.36061381 | H31: 0.63938619 | J31: Carbon | K31: BANKS | L31: 10 | M31: 0.30751194 | N31: 0.38841202 | O31: -8.0900074 | P31: 1
A32: Carbon | B32: BEAVER MEADOWS BOROUGH | C32: BEAVER MEADOWS BOROUGH | D32: 85 | E32: 256 | F32: 341 | G32: 0.24926686 | H32: 0.75073314 | J32: Carbon | K32: BEAVER MEADOWS | L32: 40 | M32: 0.21906598 | N32: 0.28229665 | O32: -6.3230675 | P32: 1
A33: Carbon | B33: BOWMANSTOWN BOROUGH | C33: BOWMANSTOWN BOROUGH | D33: 111 | E33: 300 | F33: 411 | G33: 0.27007299 | H33: 0.72992701 | J33: Carbon | K33: BOWMANSTOWN | L33: 50 | M33: 0.29731179 | N33: 0.31718062 | O33: -1.9868823 | P33: 1
A34: Carbon | B34: EAST PENN TOWNSHIP | C34: EAST PENN TOWNSHIP-NORTH | D34: 154 | E34: 632 | F34: 786 | G34: 0.19592875 | H34: 0.80407125 | J34: Carbon | K34: EAST PENN | L34: 60 | M34: 0.23489374 | N34: 0.24085006 | O34: -0.59563202 | P34: 1
A35: Carbon | B35: EAST PENN TOWNSHIP | C35: EAST PENN TOWNSHIP-SOUTH | D35: 167 | E35: 530 | F35: 697 | G35: 0.23959828 | H35: 0.76040172 | J35: Carbon | K35: EAST PENN | L35: 65 | M35: 0.24844072 | N35: 0.27725118 | O35: -2.8810468 | P35: 1
A36: Carbon | B36: EAST SIDE BOROUGH | C36: EAST SIDE BOROUGH | D36: 31 | E36: 80 | F36: 111 | G36: 0.27927928 | H36: 0.72072072 | J36: Carbon | K36: EAST SIDE | L36: 70 | M36: 0.31139583 | N36: 0.32758621 | O36: -1.6190375 | P36: 1
A37: Carbon | B37: FRANKLIN TOWNSHIP | C37: FRANKLIN TOWNSHIP-HARRITY | D37: 244 | E37: 716 | F37: 960 | G37: 0.25416667 | H37: 0.74583333 | J37: Carbon | K37: FRANKLIN | L37: 80 | M37: 0.25147165 | N37: 0.26666667 | O37: -1.5195013 | P37: 1
A38: Carbon | B38: FRANKLIN TOWNSHIP | C38: FRANKLIN TOWNSHIP-IND DIST | D38: 567 | E38: 1691 | F38: 2258 | G38: 0.25110717 | H38: 0.74889283 | J38: Carbon | K38: FRANKLIN | L38: 90 | M38: 0.25489235 | N38: 0.2877095 | O38: -3.2817151 | P38: 1
A39: Carbon | B39: FRANKLIN TOWNSHIP | C39: FRANKLIN TOWNSHIP-LONG RUN | D39: 199 | E39: 577 | F39: 776 | G39: 0.2564433 | H39: 0.7435567 | J39: Carbon | K39: FRANKLIN | L39: 100 | M39: 0.24148246 | N39: 0.2716763 | O39: -3.019384 | P39: 1
A40: Carbon | B40: JIM THORPE BOROUGH | C40: JIM THORPE BOROUGH-1ST | D40: 183 | E40: 297 | F40: 480 | G40: 0.38125 | H40: 0.61875 | J40: Carbon | K40: JIM THORPE | L40: 110 | M40: 0.38447955 | N40: 0.43984962 | O40: -5.5370076 | P40: 1
A41: Carbon | B41: JIM THORPE BOROUGH | C41: JIM THORPE BOROUGH-2ND | D41: 137 | E41: 201 | F41: 338 | G41: 0.40532544 | H41: 0.59467456 | J41: Carbon | K41: JIM THORPE | L41: 120 | M41: 0.43893209 | N41: 0.41943734 | O41: 1.9494748 | P41: 1
A42: Carbon | B42: JIM THORPE BOROUGH | C42: JIM THORPE BOROUGH-3RD | D42: 235 | E42: 455 | F42: 690 | G42: 0.34057971 | H42: 0.65942029 | J42: Carbon | K42: JIM THORPE | L42: 130 | M42: 0.34158488 | N42: 0.38278146 | O42: -4.1196576 | P42: 1
... A400: Northampton | B400: WIND GAP BORO | C400: WIND GAP | D400: 562 | E400: 829 | F400: 1391 | G400: 0.40402588 | H400: 0.59597412 | J400: Northampton | K400: NORTHAMPTON | L400: 980 | M400: 0.47885439 | N400: 0.42245989 | O400: 5.6394496 | P400: 1
J401: Northampton | K401: PALMER | L401: 990 | M401: 0.55546521 | N401: 0.54609343 | O401: 0.93717825 | P401: 1
J402: Northampton | K402: PALMER | L402: 1000 | M402: 0.46768444 | N402: 0.46838407 | O402: -0.069963218 | P402: 1
J403: Northampton | K403: PALMER | L403: 1010 | M403: 0.52663404 | N403: 0.50895615 | O403: 1.7677899 | P403: 1
J404: Northampton | K404: PALMER | L404: 1020 | M404: 0.46130371 | N404: 0.47210131 | O404: -1.0797598 | P404: 1
J405: Northampton | K405: PALMER | L405: 1030 | M405: 0.52611376 | N405: 0.54927164 | O405: -2.315788 | P405: 1
J406: Northampton | K406: PALMER | L406: 1040 | M406: 0.49054892 | N406: 0.48898964 | O406: 0.15592794 | P406: 1
J407: Northampton | K407: PALMER | L407: 1050 | M407: 0.43311393 | N407: 0.43711844 | O407: -0.40045072 | P407: 1
J408: Northampton | K408: PEN ARGYL | L408: 1060 | M408: 0.3556018 | N408: 0.36012862 | O408: -0.45268152 | P408: 1
J409: Northampton | K409: PEN ARGYL | L409: 1070 | M409: 0.35643375 | N409: 0.35047361 | O409: 0.59601363 | P409: 1
J410: Northampton | K410: PEN ARGYL | L410: 1080 | M410: 0.39876982 | N410: 0.4039604 | O410: -0.51905772 | P410: 1
J411: Northampton | K411: PEN ARGYL | L411: 1090 | M411: 0.43218162 | N411: 0.3902439 | O411: 4.193772 | P411: 1
J412: Northampton | K412: PLAINFIELD | L412: 1100 | M412: 0.30653331 | N412: 0.34944869 | O412: -4.2915373 | P412: 1
... J438: Northampton | K438: WIND GAP | L438: 1360 | M438: 0.42277467 | N438: 0.42550336 | O438: -0.27286822 | P438: 1

Sheet F15 Pct Template Reg
A1: F15 · Regression (precinct template)
A2: Run Sept. 24, 2026 · Level: Precinct (370) · Source: Meringer Precinct Forecast.xlsx (tracker, Sept. 24)
A3: ← Back to Results
A5: Methodology
A6: Same method and same backtest as F09, entered in the class forecast template, where district totals are formulas that add up the rows. The Brooks share differs from F09 because the template uses a different projected turnout for each town or precinct, which changes how much each one counts.
A7: For the full method description, see F09.
A13: 2026 forecast | E13: In plain terms
A14: Brooks (D) share of the two-party vote | C14: 0.50487 | E14: Predicts a narrow Brooks win (50.5%). The template version of F09, which had a weak backtest.
A15: Mackenzie (R) share of the two-party vote | C15: =1-C14 -> 0.49513
A16: Margin: Brooks minus Mackenzie (points) | C16: =(C14-C15)*100 -> 0.974
A17: Predicted winner | C17: =IF(C14>0.5,"Brooks","Mackenzie") -> Brooks
A18: Brooks votes | C18: 176075
A19: Mackenzie votes | C19: 172675
A21: 2024 backtest | E21: Rating
A22: Average miss per town or precinct (points) | C22: 2.46 | E22: Weak | F22: See “How to Read” for what the ratings mean.
A23: Towns or precincts where the winner was called correctly | C23: 366 of 408 precincts
A24: District result miss, 2024 (points; negative = too Republican) | C24: -1.8266567
A25: District result miss, 2022 (points) | C25: not available
A26: How strict the backtest was | C26: Out of sample (same backtest as F09)
A29: 2026 forecast detail | J29: 2024 backtest detail
A30: County | B30: Municipality | C30: Precinct | D30: Brooks votes | E30: Mackenzie votes | F30: Total votes | G30: Brooks share | H30: Mackenzie share | J30: County | K30: Municipality | L30: Precinct | M30: Reg. Predicted | N30: Actual Dem Share | O30: Reg. Error | P30: Reg. Correct?
A31: Carbon | B31: BANKS TOWNSHIP | C31: BANKS TOWNSHIP | D31: 162 | E31: 229 | F31: 391 | G31: 0.41432225 | H31: 0.58567775 | J31: Carbon | K31: BANKS | L31: 10 | M31: 0.3268433 | N31: 0.38841202 | O31: -6.1568722 | P31: 1
A32: Carbon | B32: BEAVER MEADOWS BOROUGH | C32: BEAVER MEADOWS BOROUGH | D32: 106 | E32: 235 | F32: 341 | G32: 0.31085044 | H32: 0.68914956 | J32: Carbon | K32: BEAVER MEADOWS | L32: 40 | M32: 0.23983137 | N32: 0.28229665 | O32: -4.2465279 | P32: 1
A33: Carbon | B33: BOWMANSTOWN BOROUGH | C33: BOWMANSTOWN BOROUGH | D33: 141 | E33: 270 | F33: 411 | G33: 0.34306569 | H33: 0.65693431 | J33: Carbon | K33: BOWMANSTOWN | L33: 50 | M33: 0.3254381 | N33: 0.31718062 | O33: 0.82574803 | P33: 1
A34: Carbon | B34: EAST PENN TOWNSHIP | C34: EAST PENN TOWNSHIP-NORTH | D34: 212 | E34: 574 | F34: 786 | G34: 0.2697201 | H34: 0.7302799 | J34: Carbon | K34: EAST PENN | L34: 60 | M34: 0.24813145 | N34: 0.24085006 | O34: 0.72813919 | P34: 1
A35: Carbon | B35: EAST PENN TOWNSHIP | C35: EAST PENN TOWNSHIP-SOUTH | D35: 212 | E35: 485 | F35: 697 | G35: 0.30416069 | H35: 0.69583931 | J35: Carbon | K35: EAST PENN | L35: 65 | M35: 0.26377401 | N35: 0.27725118 | O35: -1.3477179 | P35: 1
A36: Carbon | B36: EAST SIDE BOROUGH | C36: EAST SIDE BOROUGH | D36: 39 | E36: 72 | F36: 111 | G36: 0.35135135 | H36: 0.64864865 | J36: Carbon | K36: EAST SIDE | L36: 70 | M36: 0.31973805 | N36: 0.32758621 | O36: -0.78481555 | P36: 1
A37: Carbon | B37: FRANKLIN TOWNSHIP | C37: FRANKLIN TOWNSHIP-HARRITY | D37: 301 | E37: 659 | F37: 960 | G37: 0.31354167 | H37: 0.68645833 | J37: Carbon | K37: FRANKLIN | L37: 80 | M37: 0.26171184 | N37: 0.26666667 | O37: -0.49548301 | P37: 1
A38: Carbon | B38: FRANKLIN TOWNSHIP | C38: FRANKLIN TOWNSHIP-IND DIST | D38: 681 | E38: 1577 | F38: 2258 | G38: 0.30159433 | H38: 0.69840567 | J38: Carbon | K38: FRANKLIN | L38: 90 | M38: 0.26610164 | N38: 0.2877095 | O38: -2.1607859 | P38: 1
A39: Carbon | B39: FRANKLIN TOWNSHIP | C39: FRANKLIN TOWNSHIP-LONG RUN | D39: 232 | E39: 544 | F39: 776 | G39: 0.29896907 | H39: 0.70103093 | J39: Carbon | K39: FRANKLIN | L39: 100 | M39: 0.23618003 | N39: 0.2716763 | O39: -3.5496268 | P39: 1
A40: Carbon | B40: JIM THORPE BOROUGH | C40: JIM THORPE BOROUGH-1ST | D40: 222 | E40: 258 | F40: 480 | G40: 0.4625 | H40: 0.5375 | J40: Carbon | K40: JIM THORPE | L40: 110 | M40: 0.41922519 | N40: 0.43984962 | O40: -2.0624434 | P40: 1
A41: Carbon | B41: JIM THORPE BOROUGH | C41: JIM THORPE BOROUGH-2ND | D41: 150 | E41: 188 | F41: 338 | G41: 0.44378698 | H41: 0.55621302 | J41: Carbon | K41: JIM THORPE | L41: 120 | M41: 0.42154455 | N41: 0.41943734 | O41: 0.21072104 | P41: 1
A42: Carbon | B42: JIM THORPE BOROUGH | C42: JIM THORPE BOROUGH-3RD | D42: 280 | E42: 410 | F42: 690 | G42: 0.4057971 | H42: 0.5942029 | J42: Carbon | K42: JIM THORPE | L42: 130 | M42: 0.35595855 | N42: 0.38278146 | O42: -2.682291 | P42: 1
... A400: Northampton | B400: WIND GAP BORO | C400: WIND GAP | D400: 614 | E400: 777 | F400: 1391 | G400: 0.44140906 | H400: 0.55859094 | J400: Northampton | K400: NORTHAMPTON | L400: 980 | M400: 0.46016367 | N400: 0.42245989 | O400: 3.770378 | P400: 1
J401: Northampton | K401: PALMER | L401: 990 | M401: 0.53477781 | N401: 0.54609343 | O401: -1.1315617 | P401: 1
J402: Northampton | K402: PALMER | L402: 1000 | M402: 0.45673312 | N402: 0.46838407 | O402: -1.1650951 | P402: 1
J403: Northampton | K403: PALMER | L403: 1010 | M403: 0.49146732 | N403: 0.50895615 | O403: -1.7488824 | P403: 0
J404: Northampton | K404: PALMER | L404: 1020 | M404: 0.44454462 | N404: 0.47210131 | O404: -2.7556686 | P404: 1
J405: Northampton | K405: PALMER | L405: 1030 | M405: 0.51060607 | N405: 0.54927164 | O405: -3.8665562 | P405: 1
J406: Northampton | K406: PALMER | L406: 1040 | M406: 0.4521312 | N406: 0.48898964 | O406: -3.6858436 | P406: 1
J407: Northampton | K407: PALMER | L407: 1050 | M407: 0.42896668 | N407: 0.43711844 | O407: -0.81517597 | P407: 1
J408: Northampton | K408: PEN ARGYL | L408: 1060 | M408: 0.37184709 | N408: 0.36012862 | O408: 1.1718468 | P408: 1
J409: Northampton | K409: PEN ARGYL | L409: 1070 | M409: 0.31588596 | N409: 0.35047361 | O409: -3.4587651 | P409: 1
J410: Northampton | K410: PEN ARGYL | L410: 1080 | M410: 0.39081181 | N410: 0.4039604 | O410: -1.3148586 | P410: 1
J411: Northampton | K411: PEN ARGYL | L411: 1090 | M411: 0.42524109 | N411: 0.3902439 | O411: 3.4997185 | P411: 1
J412: Northampton | K412: PLAINFIELD | L412: 1100 | M412: 0.31322618 | N412: 0.34944869 | O412: -3.6222501 | P412: 1
... J438: Northampton | K438: WIND GAP | L438: 1360 | M438: 0.41322716 | N438: 0.42550336 | O438: -1.2276193 | P438: 1

Sheet F16 Bellwether (v0.1)
A1: F16 · Bellwether reading, 10-precinct set, on the v0.1 baseline
A2: Run Oct. 21–22, 2026 · Level: 10 precincts · Source: Bellwether analysis (tracker, Oct. 26); group baseline PA07_2026_Forecast_Precinct.xlsx (v0.1)
A3: ← Back to Results
A5: Methodology
A6: What it does: reads the district result from 10 “bellwether” precincts, places whose combined vote has closely matched the district.
A7: Selection rule (fixed in advance, no hand-picking): at least 300 two-party votes in 2022 and 2024; the precinct still exists on the 2026 lines; the 10 with the smallest gap from the district in both years.
A8: Forecast: the group’s v0.1 baseline prediction for these 10 precincts combined, minus the set’s usual lean (its average gap from the district).
A9: Backtest: the set chosen from 2022 results alone, scored against 2024.
A10: Caveat: v0.1’s 2024 backtest counted votes using actual 2024 turnout, so the backtest tests vote share only.
A13: 2026 forecast | E13: In plain terms
A14: Brooks (D) share of the two-party vote | C14: 0.49968331 | E14: Essentially a tie (49.97% Brooks), tipping to Mackenzie. Best 2024 backtest in the workbook (0.15 pts), though that test is less strict than F18’s. It shows that the v0.1 baseline’s own precinct forecasts imply a closer race than its district total of 48.7%.
A15: Mackenzie (R) share of the two-party vote | C15: =1-C14 -> 0.50031669
A16: Margin: Brooks minus Mackenzie (points) | C16: =(C14-C15)*100 -> -0.063337901
A17: Predicted winner | C17: =IF(C14>0.5,"Brooks","Mackenzie") -> Mackenzie
A18: Brooks votes
A19: Mackenzie votes
A21: 2024 backtest | E21: Rating
A22: Average miss per town or precinct (points) | C22: not available | E22: Good (with caveat) | F22: See “How to Read” for what the ratings mean.
A23: Towns or precincts where the winner was called correctly | C23: —
A24: District result miss, 2024 (points; negative = too Republican) | C24: -0.14586132
A25: District result miss, 2022 (points) | C25: not available
A26: How strict the backtest was | C26: Out of sample selection; baseline backtest used actual turnout
A29: 2026 forecast detail (bellwether precincts) | H29: 2024 backtest detail (set chosen from 2022 only)
A30: Precinct | B30: Gap 2022 (pts) | C30: Gap 2024 (pts) | D30: v0.1 2026 Brooks share | E30: Brooks votes | F30: Mackenzie votes | H30: Precinct | I30: Gap 2022 (pts) | J30: v0.1 predicted 2024 share | K30: Actual 2024 share
A31: LOWER MACUNGIE 1ST DISTRICT | B31: 1.09 | C31: 0.07 | D31: 0.50605187 | E31: 878 | F31: 857 | H31: COOPERSBURG | I31: -0.04 | J31: 0.48992853 | K31: 0.47758285
A32: LOWER MACUNGIE 2ND DISTRICT | B32: 0.58 | C32: 0.35 | D32: 0.50940905 | E32: 1543 | F32: 1486 | H32: LOWER MACUNGIE 3RD DISTRICT | I32: -0.18 | J32: 0.48727466 | K32: 0.48038176
A33: LOWER MACUNGIE 10TH DISTRICT | B33: -0.29 | C33: -1.06 | D33: 0.49194068 | E33: 763 | F33: 788 | H33: LOWER MACUNGIE 4TH DISTRICT | I33: -0.36 | J33: 0.49546485 | K33: 0.4829932
A34: SALISBURY 1ST WARD | B34: -0.83 | C34: -0.41 | D34: 0.48983543 | E34: 506 | F34: 527 | H34: LOWER MACUNGIE 10TH DISTRICT | I34: -0.29 | J34: 0.4848643 | K34: 0.48434238
A35: SALISBURY 2ND WARD | B35: 0.08 | C35: 0.04 | D35: 0.50123865 | E35: 607 | F35: 604 | H35: SALISBURY 2ND WARD | I35: 0.08 | J35: 0.50030845 | K35: 0.49537323
A36: SALISBURY 5TH WARD 2ND DIST | B36: 0.37 | C36: 0.41 | D36: 0.50157398 | E36: 478 | F36: 475 | H36: SALISBURY 5TH WARD 2ND DIST | I36: 0.37 | J36: 0.4906367 | K36: 0.49906367
A37: UPPER SAUCON 1ST DISTRICT | B37: -0.15 | C37: -0.86 | D37: 0.49359331 | E37: 886 | F37: 909 | H37: UPPER SAUCON 1ST DISTRICT | I37: -0.15 | J37: 0.49067432 | K37: 0.48637016
A38: NAZARETH BORO 1ST WARD | B38: -0.93 | C38: 0.34 | D38: 0.49336057 | E38: 483 | F38: 496 | H38: BETHLEHEM TWSP 4TH WARD 2ND DISTRICT | I38: -0.53 | J38: 0.49380362 | K38: 0.51000953
A39: NORTH CATASAUQUA 2ND WARD | B39: 0.98 | C39: 0.99 | D39: 0.50690755 | E39: 477 | F39: 464 | H39: BETHLEHEM TWSP 4TH WARD 3RD DISTRICT | I39: -0.47 | J39: 0.50155119 | K39: 0.51602896
A40: NORTHAMPTON BORO 2ND WARD | B40: -0.26 | C40: -1.14 | D40: 0.48891482 | E40: 419 | F40: 438 | H40: NORTHAMPTON BORO 2ND WARD | I40: -0.26 | J40: 0.48930921 | K40: 0.48355263
H43: Set prediction 2026 (v0.1) | K43: 0.49985799
H44: Set lean used (avg 2022/2024 gap, pts) | K44: 0.017468439
H45: Bellwether forecast 2026 | K45: 0.49968331
H46: Set prediction 2024 (v0.1 backtest) | K46: 0.49183039
H47: Set lean used for 2024 (2022 gap, pts) | K47: -0.17499972
H48: Bellwether estimate 2024 | K48: 0.49358039
H49: Actual 2024 district | K49: 0.495039

Sheet F17 Bellwether Crain 6
A1: F17 · Bellwether reading, Professor Crain’s 6 precincts, on the v0.1 baseline
A2: Run Oct. 22, 2026 · Level: 6 precincts · Source: Professor Crain’s bellwether list; group baseline v0.1
A3: ← Back to Results
A5: Methodology
A6: What it does: the same bellwether reading as F16, using Professor Crain’s six precincts, chosen for how closely they move with a 200-precinct benchmark.
A7: Because these precincts lean Democratic (about 2 points more than the district), their usual lean is subtracted before reading the district result.
A8: Backtest: v0.1’s 2024 predictions for the six, minus their 2022 lean, compared with the actual 2024 result.
A9: Caveat: the data used to choose the six are not available, so the backtest may not be fully out of sample; v0.1 also used actual 2024 turnout.
A13: 2026 forecast | E13: In plain terms
A14: Brooks (D) share of the two-party vote | C14: 0.49217551 | E14: Predicts Mackenzie (49.2% Brooks). Its backtest missed by about 0.6 points. It needs the lean adjustment: read directly, it would have called 2024 for the wrong candidate.
A15: Mackenzie (R) share of the two-party vote | C15: =1-C14 -> 0.50782449
A16: Margin: Brooks minus Mackenzie (points) | C16: =(C14-C15)*100 -> -1.5648982
A17: Predicted winner | C17: =IF(C14>0.5,"Brooks","Mackenzie") -> Mackenzie
A18: Brooks votes
A19: Mackenzie votes
A21: 2024 backtest | E21: Rating
A22: Average miss per town or precinct (points) | C22: not available | E22: Fair (with caveat) | F22: See “How to Read” for what the ratings mean.
A23: Towns or precincts where the winner was called correctly | C23: —
A24: District result miss, 2024 (points; negative = too Republican) | C24: -0.62822898
A25: District result miss, 2022 (points) | C25: not available
A26: How strict the backtest was | C26: Selection data unknown; baseline backtest used actual turnout
A29: 2026 forecast detail (bellwether precincts) | H29: 2024 backtest detail
A30: Precinct | B30: Gap 2022 (pts) | C30: Gap 2024 (pts) | D30: v0.1 2026 Brooks share | E30: Brooks votes | F30: Mackenzie votes | H30: Precinct | I30: Gap 2022 (pts) | J30: v0.1 predicted 2024 share | K30: Actual 2024 share
A31: LOWER MACUNGIE 3RD DISTRICT | B31: -0.18 | C31: -1.46 | D31: 0.493803 | E31: 757 | F31: 776 | H31: LOWER MACUNGIE 3RD DISTRICT | I31: -0.18 | J31: 0.48727466 | K31: 0.48038176
A32: SOUTH WHITEHALL 2ND DISTRICT | B32: 2.33 | C32: 0.56 | D32: 0.50224888 | E32: 335 | F32: 332 | H32: SOUTH WHITEHALL 2ND DISTRICT | I32: 2.33 | J32: 0.51170569 | K32: 0.50055741
A33: SOUTH WHITEHALL 8TH DISTRICT | B33: 1.26 | C33: 1 | D33: 0.50694112 | E33: 1059 | F33: 1030 | H33: SOUTH WHITEHALL 8TH DISTRICT | I33: 1.26 | J33: 0.5118865 | K33: 0.50498466
A34: UPPER MACUNGIE 4TH DISTRICT | B34: 5.35 | C34: 3.46 | D34: 0.53985122 | E34: 508 | F34: 433 | H34: UPPER MACUNGIE 4TH DISTRICT | I34: 5.35 | J34: 0.54827089 | K34: 0.5295389
A35: UPPER MILFORD EASTERN DISTRICT | B35: -2.39 | C35: -2.93 | D35: 0.46312915 | E35: 1187 | F35: 1376 | H35: UPPER MILFORD EASTERN DISTRICT | I35: -2.39 | J35: 0.45463168 | K35: 0.46569712
A36: BETHLEHEM 9TH WARD EAST | B36: 19.92 | C36: 18.09 | D36: 0.66789216 | E36: 545 | F36: 271 | H36: BETHLEHEM 9TH WARD EAST | I36: 19.92 | J36: 0.67015209 | K36: 0.67585551
H39: Set prediction 2026 (v0.1) | K39: 0.51004762
H40: Set lean used (avg 2022/2024 gap, pts) | K40: 1.7872116
H41: Bellwether forecast 2026 | K41: 0.49217551
H42: Set prediction 2024 (v0.1 backtest) | K42: 0.51091504
H43: Set lean used for 2024 (2022 gap, pts) | K43: 2.2158334
H44: Bellwether estimate 2024 | K44: 0.48875671
H45: Actual 2024 district | K45: 0.495039

Sheet F18 Bellwether (v11)
A1: F18 · Bellwether reading on the v11 baseline (honest rule)
A2: Run Oct. 26, 2026 · Level: 10 precincts · Source: Bellwether + Baseline PA07 Forecast Meringer.xlsx (tracker, Oct. 26); v11 baseline
A3: ← Back to Results
A5: Methodology
A6: What it does: the bellwether reading, rebuilt on the group’s v11 baseline, which has fully honest backtests for both 2022 and 2024.
A7: For each election, the 10 bellwethers are chosen from the two elections before it only: 2018–2020 for the 2022 test, 2020–2022 for 2024, 2022–2024 for 2026.
A8: Forecast: v11’s prediction for the 10 precincts, minus their average lean over the two selection elections.
A9: Backtests: v11 was trained only on earlier elections and projected its own turnout, so nothing from the target year leaks in.
A13: 2026 forecast | E13: In plain terms
A14: Brooks (D) share of the two-party vote | C14: 0.50011074 | E14: A dead heat (50.01% Brooks). The most rigorous bellwether test, but it missed both backtests by more than the v11 baseline alone (0.27 pts in 2022, 0.51 in 2024), because bellwethers chosen from earlier elections drifted away from the district.
A15: Mackenzie (R) share of the two-party vote | C15: =1-C14 -> 0.49988926
A16: Margin: Brooks minus Mackenzie (points) | C16: =(C14-C15)*100 -> 0.022148892
A17: Predicted winner | C17: =IF(C14>0.5,"Brooks","Mackenzie") -> Brooks
A18: Brooks votes
A19: Mackenzie votes
A21: 2024 backtest | E21: Rating
A22: Average miss per town or precinct (points) | C22: not available | E22: Strongest | F22: See “How to Read” for what the ratings mean.
A23: Towns or precincts where the winner was called correctly | C23: —
A24: District result miss, 2024 (points; negative = too Republican) | C24: -0.51046282
A25: District result miss, 2022 (points) | C25: 0.2670494
A26: How strict the backtest was | C26: Fully out of sample (2022 and 2024)
A29: Forecast and backtests
A30: Election | B30: Bellwethers chosen from | C30: Set lean (pts) | D30: Baseline prediction for set | E30: Bellwether reading | F30: Baseline (all precincts) | G30: Baseline + bellwether | H30: Actual
A31: 2022 backtest | B31: 2018 + 2020 | C31: -0.045432627 | D31: 0.50996917 | E31: 0.51042349 | F31: 0.50796007 | G31: 0.50919178 | H31: 0.507753
A32: 2024 backtest | B32: 2020 + 2022 | C32: 0.065659526 | D32: 0.48817687 | E32: 0.48752028 | F32: 0.49084073 | G32: 0.48918051 | H32: 0.49262491
A33: 2026 forecast | B33: 2022 + 2024 | C33: 0.017468439 | D33: 0.50028543 | E33: 0.50011074 | F33: 0.49494302 | G33: 0.49752688
A36: 2022 set | D36: 2024 set | G36: 2026 set
A37: 2022 bellwethers | D37: 2024 bellwethers | G37: 2026 bellwethers
A38: EMMAUS 5TH DISTRICT | D38: SALISBURY 2ND WARD | G38: SALISBURY 2ND WARD
A39: SOUTH WHITEHALL 8TH DISTRICT | D39: LOWER MACUNGIE 2ND DISTRICT | G39: SALISBURY 5TH WARD 2ND DIST
A40: SALISBURY 1ST WARD | D40: SALISBURY 1ST WARD | G40: LOWER MACUNGIE 2ND DISTRICT
A41: SALISBURY 2ND WARD | D41: BETHLEHEM TWSP 3RD WARD 5TH DISTRICT | G41: SALISBURY 1ST WARD
A42: BETHLEHEM TWSP 2ND WARD 3RD DISTRICT | D42: BETHLEHEM TWSP 3RD WARD 2ND DISTRICT | G42: UPPER SAUCON 1ST DISTRICT
A43: SOUTH WHITEHALL 1ST DISTRICT | D43: UPPER MACUNGIE 2ND DISTRICT | G43: NAZARETH BORO 1ST WARD
A44: SALISBURY 3RD WARD 2ND DIST | D44: LOWER MACUNGIE 1ST DISTRICT | G44: NORTH CATASAUQUA 2ND WARD
A45: HANOVER #4 | D45: NORTH CATASAUQUA 2ND WARD | G45: LOWER MACUNGIE 10TH DISTRICT
A46: UPPER MACUNGIE 1ST DISTRICT | D46: LOWER MACUNGIE 5TH DISTRICT | G46: LOWER MACUNGIE 1ST DISTRICT
A47: SALISBURY 3RD WARD 1ST DIST | D47: NAZARETH BORO 1ST WARD | G47: NORTHAMPTON BORO 2ND WARD

Sheet F19 Baseline+Bellwether
A1: F19 · Baseline + bellwether blend (50/50, v11)
A2: Run Oct. 26, 2026 · Level: District · Source: Bellwether + Baseline PA07 Forecast Meringer.xlsx (tracker, Oct. 26)
A3: ← Back to Results
A5: Methodology
A6: What it does: averages the v11 baseline (all precincts) and the bellwether reading (F18), 50/50.
A7: Equal weights were used because only two backtests exist; tuning the weight to fit them would overstate accuracy.
A8: Backtests: the same strict 2022 and 2024 tests as F18.
A13: 2026 forecast | E13: In plain terms
A14: Brooks (D) share of the two-party vote | C14: 0.49752688 | E14: Predicts a narrow Mackenzie win (49.75% Brooks). In both backtests the blend was further from the result than the v11 baseline alone (0.14 vs 0.02 pts in 2022; 0.34 vs 0.18 in 2024). Conclusion: adding bellwethers does not improve the forecast, so they are best used as an election-night check.
A15: Mackenzie (R) share of the two-party vote | C15: =1-C14 -> 0.50247312
A16: Margin: Brooks minus Mackenzie (points) | C16: =(C14-C15)*100 -> -0.49462402
A17: Predicted winner | C17: =IF(C14>0.5,"Brooks","Mackenzie") -> Mackenzie
A18: Brooks votes
A19: Mackenzie votes
A21: 2024 backtest | E21: Rating
A22: Average miss per town or precinct (points) | C22: not available | E22: Strongest | F22: See “How to Read” for what the ratings mean.
A23: Towns or precincts where the winner was called correctly | C23: —
A24: District result miss, 2024 (points; negative = too Republican) | C24: -0.34444009
A25: District result miss, 2022 (points) | C25: 0.14387802
A26: How strict the backtest was | C26: Fully out of sample (2022 and 2024)
A29: Forecast and backtests
A30: Election | B30: Bellwethers chosen from | C30: Set lean (pts) | D30: Baseline prediction for set | E30: Bellwether reading | F30: Baseline (all precincts) | G30: Baseline + bellwether | H30: Actual
A31: 2022 backtest | B31: 2018 + 2020 | C31: -0.045432627 | D31: 0.50996917 | E31: 0.51042349 | F31: 0.50796007 | G31: 0.50919178 | H31: 0.507753
A32: 2024 backtest | B32: 2020 + 2022 | C32: 0.065659526 | D32: 0.48817687 | E32: 0.48752028 | F32: 0.49084073 | G32: 0.48918051 | H32: 0.49262491
A33: 2026 forecast | B33: 2022 + 2024 | C33: 0.017468439 | D33: 0.50028543 | E33: 0.50011074 | F33: 0.49494302 | G33: 0.49752688
A36: 2022 set | D36: 2024 set | G36: 2026 set
A37: 2022 bellwethers | D37: 2024 bellwethers | G37: 2026 bellwethers
A38: EMMAUS 5TH DISTRICT | D38: SALISBURY 2ND WARD | G38: SALISBURY 2ND WARD
A39: SOUTH WHITEHALL 8TH DISTRICT | D39: LOWER MACUNGIE 2ND DISTRICT | G39: SALISBURY 5TH WARD 2ND DIST
A40: SALISBURY 1ST WARD | D40: SALISBURY 1ST WARD | G40: LOWER MACUNGIE 2ND DISTRICT
A41: SALISBURY 2ND WARD | D41: BETHLEHEM TWSP 3RD WARD 5TH DISTRICT | G41: SALISBURY 1ST WARD
A42: BETHLEHEM TWSP 2ND WARD 3RD DISTRICT | D42: BETHLEHEM TWSP 3RD WARD 2ND DISTRICT | G42: UPPER SAUCON 1ST DISTRICT
A43: SOUTH WHITEHALL 1ST DISTRICT | D43: UPPER MACUNGIE 2ND DISTRICT | G43: NAZARETH BORO 1ST WARD
A44: SALISBURY 3RD WARD 2ND DIST | D44: LOWER MACUNGIE 1ST DISTRICT | G44: NORTH CATASAUQUA 2ND WARD
A45: HANOVER #4 | D45: NORTH CATASAUQUA 2ND WARD | G45: LOWER MACUNGIE 10TH DISTRICT
A46: UPPER MACUNGIE 1ST DISTRICT | D46: LOWER MACUNGIE 5TH DISTRICT | G46: LOWER MACUNGIE 1ST DISTRICT
A47: SALISBURY 3RD WARD 1ST DIST | D47: NAZARETH BORO 1ST WARD | G47: NORTHAMPTON BORO 2ND WARD

Sheet Bellwether Tests
A1: Bellwether precinct tests: full results
A2: ← Back to Results
A4: What a bellwether is, and how they were chosen
A5: A bellwether precinct is one whose vote has closely matched the district’s. The rule below was fixed before looking at which precincts it would pick, and it was applied by formula, so no precinct was chosen by hand.
A6: 1. Universe: every precinct in today’s PA-07.
A7: 2. Size: at least 300 two-party House votes in both 2022 and 2024 (in smaller precincts a few voters move the share by a point or more).
A8: 3. Must still exist on the 2026 precinct lines (precincts in seven redrawn Northampton towns are excluded). 296 precincts qualify.
A9: 4. Score: the larger of the precinct’s 2022 and 2024 gaps from the district. A bellwether must be close in both years, not just on average.
A10: 5. The 10 precincts with the lowest scores form the set.
A12: The 10-precinct set
A13: Precinct | B13: County | C13: Gap from district, 2022 (pts) | D13: Gap from district, 2024 (pts) | E13: Net registration D−R, 2026 | F13: v0.1 baseline forecast 2026 (Brooks)
A14: Salisbury Ward 2 | B14: Lehigh | C14: 0.08 | D14: 0.04 | E14: 0.091 | F14: 0.501
A15: Salisbury Ward 5, District 2 | B15: Lehigh | C15: 0.37 | D15: 0.41 | E15: -0.026 | F15: 0.502
A16: Lower Macungie District 2 | B16: Lehigh | C16: 0.58 | D16: 0.35 | E16: -0.038 | F16: 0.509
A17: Salisbury Ward 1 | B17: Lehigh | C17: -0.83 | D17: -0.41 | E17: 0.088 | F17: 0.49
A18: Upper Saucon District 1 | B18: Lehigh | C18: -0.15 | D18: -0.86 | E18: -0.08 | F18: 0.494
A19: Nazareth Borough Ward 1 | B19: Northampton | C19: -0.93 | D19: 0.34 | E19: -0.069 | F19: 0.493
A20: North Catasauqua Ward 2 | B20: Northampton | C20: 0.98 | D20: 0.99 | E20: 0.037 | F20: 0.507
A21: Lower Macungie District 10 | B21: Lehigh | C21: -0.29 | D21: -1.06 | E21: -0.069 | F21: 0.492
A22: Lower Macungie District 1 | B22: Lehigh | C22: 1.09 | D22: 0.07 | E22: -0.01 | F22: 0.506
A23: Northampton Borough Ward 2 | B23: Northampton | C23: -0.26 | D23: -1.14 | E23: 0.042 | F23: 0.489
A24: Combined | C24: 0.16 | D24: -0.13 | E24: -0.01 | F24: 0.5
A25: The district was 50.98% Democratic in 2022 and 49.50% in 2024. Together the 10 precincts cast about 17,500 two-party votes in 2024, about 4% of the district.
A27: Stability tests
A28: Test | B28: What was checked | C28: Result
A29: Out of sample | B29: The rule applied to 2022 alone; its picks scored on 2024. | C29: 9 of 10 stayed within 2 pts; the combined vote missed 2024 by 0.57 pts.
A30: Carryover | B30: How many of the 2022-only picks remain once 2024 is added. | C30: 5 of 10. Individual precincts drift; the set as a whole is the signal.
A31: Drop any one precinct | B31: Recompute the 2024 gap with each precinct removed. | C31: Gap stays between −0.25 and −0.01 pts. No single precinct drives the result.
A32: Drop the worst fit | B32: Remove Northampton Borough Ward 2 (largest score). | C32: 2024 gap moves from −0.13 to −0.05 pts.
A33: Old district lines | B33: Compare with the old PA-07 in 2018 and 2020. | C33: The set ran 3–4 pts more Republican. It is a bellwether for today’s lines only.
A34: Geography | B34: Where the precincts are. | C34: All suburban Lehigh and Northampton; none in Carbon, Allentown, Bethlehem or Easton.
A36: Registration trend (net registered Democrats minus Republicans, as a share of all registered)
A37: Group | B37: 2022 | C37: 2024 | D37: May 2026 primary | E37: Change since 2024
A38: 10-precinct set | B38: 0.009 | C38: -0.013 | D38: -0.01 | E38: +0.4 pts toward D
A39: Professor Crain’s 6 | B39: 0.017 | C39: -0.002 | D39: -0.001 | E39: +0.1 pts toward D
A40: District | B40: 0.078 | C40: 0.045 | D40: 0.033 | E40: −1.2 pts toward R
A41: Both bellwether sets vote like the district while being registered several points less Democratic, and since 2024 they have edged toward Democrats while the district moved toward Republicans. To be updated with the Oct. 5 registration snapshot.
A43: Demographics (county voter files, Aug. 31, 2026)
A44: Measure | B44: District | C44: 10-precinct set | D44: Crain’s 6
A45: Registered voters, 2026 | B45: 531739 | C45: 21367 | D45: 13457
A46: Registered Democrats | B46: 0.415 | C46: 0.4 | D46: 0.403
A47: Registered Republicans | B47: 0.382 | C47: 0.412 | D47: 0.404
A48: Unaffiliated / other | B48: 0.204 | C48: 0.188 | D48: 0.192
A49: Gen Z | B49: 0.157 | C49: 0.133 | D49: 0.145
A50: Millennials | B50: 0.255 | C50: 0.237 | D50: 0.236
A51: Gen X | B51: 0.248 | C51: 0.247 | D51: 0.256
A52: Baby Boomers | B52: 0.28 | C52: 0.303 | D52: 0.302
A53: Silent / Greatest | B53: 0.06 | C53: 0.08 | D53: 0.061
A54: Turnout, 2024 general | B54: 0.757 | C54: 0.816 | D54: 0.81
A55: Turnout, 2022 midterm | B55: 0.581 | C55: 0.653 | D55: 0.642
A56: Midterm turnout as % of presidential | B56: 0.768 | C56: 0.8 | D56: 0.792
... A58: 2024 voters who voted by mail | B58: 0.296 | C58: 0.318 | D58: 0.323
A59: Both sets are older, more Republican by registration and higher-turnout than the district, yet vote like it, so unaffiliated voters and some Republicans there vote Democratic for House more often than elsewhere. Their turnout falls less in midterms, so the 2026 electorate may look more like these sets than 2024’s did.
A61: Comparison with Professor Crain’s 6 bellwether precincts
A62: The two sets share no precincts. The 10-precinct set is chosen to vote at the same level as the district; Crain’s 6 are chosen to move with a 200-precinct benchmark, even if they sit above or below it.
A63: Test | B63: 10-precinct set | C63: Crain’s 6
A64: Combined gap from district, 2022 | B64: +0.16 pts | C64: +2.22 pts
A65: Combined gap from district, 2024 | B65: −0.13 pts | C65: +1.36 pts
A66: Swing 2022→2024 (district −1.49) | B66: −1.78 pts | C66: −2.34 pts
A67: Average swing miss per precinct | B67: 0.54 pts | C67: 1.26 pts
A68: Swing 2018→2020, old lines (district −3.30) | B68: −2.14 pts | C68: −3.58 pts
A69: Change in lean, 2022→2024 | B69: −0.29 pts | C69: −0.86 pts
A70: v0.1 baseline 2024 estimate, read directly (actual 49.50%) | B70: 49.73% | C70: 51.09% (wrong winner)
A71: v0.1 baseline 2024 estimate, lean-adjusted | B71: 49.57% | C71: 48.88%
A72: 2026 forecast, lean-adjusted (Brooks) | B72: 50.0% | C72: 49.2%
A73: The 10-precinct set fits today’s district better; Crain’s 6 hold up better under the old district lines, as a correlation-based set should. Both point to a closer race than the v0.1 baseline (48.7%).
A75: Does adding bellwethers improve the baseline? (v11 baseline, strict backtests)
B76: v11 baseline | C76: Bellwether reading (F18) | D76: 50/50 blend (F19)
A77: 2022 backtest miss | B77: +0.02 | C77: +0.27 | D77: +0.14
A78: 2024 backtest miss | B78: −0.18 | C78: −0.51 | D78: −0.34
A79: Average size of miss | B79: 0.10 | C79: 0.39 | D79: 0.24
A80: 2026 forecast (Brooks) | B80: 49.5% | C80: 50.0% | D80: 49.7%
A81: No. In both strict backtests the baseline alone was closest, and every bit of weight shifted to the bellwethers made the miss larger. Bellwethers chosen from earlier elections drifted 0.9–1.7 points from the district in the year being predicted. Best use: an election-night check, comparing the 10 precincts’ returns with their forecast.

Sheet Backtest-Only Tests
A1: Methods tested on 2024 only (no 2026 forecast was made with them)
A2: These methods were run as experiments: each was trained on earlier elections and checked against the 2024 results, town by town (89 towns). None was used to produce a 2026 forecast, so they are not counted in the winner tally. “In-sample” tests were fitted and scored on the same 2024 data, which makes them look better than they would on new data; they are not fair comparisons.
A3: ← Back to Results
A5: Rank (by average miss) | B5: Method | C5: What it does | D5: Average miss per town (pts) | E5: Towns called correctly | F5: Test type
A6: 1 | B6: Stacking (learned-weight ensemble) | C6: Combines Trend, Beta-Adjusted and Regression with weights learned by 5-fold cross-validation. | D6: 1.2771 | E6: 86 / 89 | F6: Out-of-sample (5-fold CV)
A7: 2 | B7: Uniform Swing | C7: Applies the same district-wide swing to every town, with no town-specific adjustment. | D7: 1.4095 | E7: 87 / 89 | F7: Out-of-sample holdout
A8: 3 | B8: County Fixed Effect | C8: Replaces each town’s residual with its county’s average residual (fit and tested on 2024). | D8: 1.469 | E8: — | F8: IN-SAMPLE (not a fair test)
A9: 4 | B9: Empirical Bayes Hierarchical | C9: Blends each town’s beta with the overall average beta, using a shrinkage factor estimated from the data. | D9: 1.6727 | E9: 87 / 89 | F9: Out-of-sample holdout
A10: 5 | B10: Female Dem Reg Correction | C10: Adjusts for Democratic registration share among women (only a current snapshot exists, so fit on 2024). | D10: 1.6889 | E10: — | F10: IN-SAMPLE (not a fair test)
A11: 6 | B11: Cycle-Type Beta | C11: Beta computed only from the 2018→2020 transition, the same midterm-to-presidential type as 2022→2024. | D11: 1.7507 | E11: 86 / 89 | F11: Out-of-sample holdout
A12: 7 | B12: Random Forest | C12: 500 trees, depth 4, trained on 2020 and 2022 (registration margin, % bachelor’s, presidential year, lagged share). | D12: 1.799 | E12: 87 / 89 | F12: Out-of-sample holdout
A13: 8 | B13: Beta-Adjusted (pooled) -- original best | C13: The original Beta-Adjusted method (F05), for reference. | D13: 1.8066 | E13: 86 / 89 | F13: Out-of-sample holdout
A14: 9 | B14: Mail D-Share Correction | C14: Adds a correction from the 2022 mail-ballot Democratic share (coefficient fit on 2024). | D14: 1.8572 | E14: — | F14: IN-SAMPLE (not a fair test)
A15: 10 | B15: Trend | C15: The original Simple Trend method (F04), for reference. | D15: 1.9894 | E15: 86 / 89 | F15: Out-of-sample holdout
A16: 11 | B16: Naive (=2022) | C16: Assumes every town repeats its 2022 result. | D16: 2.256 | E16: 83 / 89 | F16: Out-of-sample holdout
A17: 12 | B17: Multi-Variable Regression | C17: The original Regression method (F06), for reference. | D17: 3.0936 | E17: 82 / 89 | F17: Out-of-sample holdout -- worst
A18: Beta-Adjusted, Trend, Naive and Multi-Variable Regression appear for reference; their 2026 forecasts are F04–F06.
A19: Probabilistic calibration (Sept. 27) converted Beta-Adjusted predictions into win probabilities; Brier score 0.037, well calibrated and slightly underconfident.
A21: Takeaway
A22: Among the fair (out-of-sample) tests, Stacking (1.28 pts) and Uniform Swing (1.41 pts) placed individual towns best, ahead of every method used for a 2026 forecast. The more complex Random Forest (1.80 pts) did no better than the simple Beta-Adjusted method (1.81 pts). Running 2026 forecasts with Stacking and Uniform Swing is a natural next step.

Sheet Final Assessment
A1: Final assessment: which forecasts did best, and who is expected to win
A3: 1. Ranking by 2024 district-level backtest miss
A4: Forecasts are ranked by how close they came to the actual 2024 district result in their backtest. This is the one test that almost every forecast has, and it is the one that matters for calling the race. F02 and F03 have no district-level backtest and are not ranked (the two blank rows at the bottom).
A6: Rank | B6: ID | C6: Forecast | D6: |2024 district miss| (pts) | E6: 2024 district miss (pts) | F6: Brooks share 2026 | G6: Predicted winner | H6: Uses superseded data? | I6: Backtest type | K6: (helper) abs miss + row tiebreak | L6: (helper) weight
A7: 1 | B7: {=IFERROR(INDEX(Results!$A$5:$A$23,MATCH(SMALL($K$7:$K$25,A7),$K$7:$K$25,0)),"")} -> F16 | C7: {=IFERROR(INDEX(Results!$B$5:$B$23,MATCH(SMALL($K$7:$K$25,A7),$K$7:$K$25,0)),"")} -> Bellwether reading, 10-precinct set, on the v0.1 baseline | D7: {=IFERROR(ABS(INDEX(Results!$K$5:$K$23,MATCH(SMALL($K$7:$K$25,A7),$K$7:$K$25,0))),"")} -> 0.14586132 | E7: {=IFERROR(INDEX(Results!$K$5:$K$23,MATCH(SMALL($K$7:$K$25,A7),$K$7:$K$25,0)),"")} -> -0.14586132 | F7: {=IFERROR(INDEX(Results!$E$5:$E$23,MATCH(SMALL($K$7:$K$25,A7),$K$7:$K$25,0)),"")} -> 0.49968331 | G7: {=IFERROR(INDEX(Results!$H$5:$H$23,MATCH(SMALL($K$7:$K$25,A7),$K$7:$K$25,0)),"")} -> Mackenzie | H7: {=IFERROR(INDEX(Results!$N$5:$N$23,MATCH(SMALL($K$7:$K$25,A7),$K$7:$K$25,0)),"")} -> No | I7: {=IFERROR(INDEX(Results!$M$5:$M$23,MATCH(SMALL($K$7:$K$25,A7),$K$7:$K$25,0)),"")} -> Out of sample selection; baseline backtest used actual turnout | K7: =IF(ISNUMBER(Results!K5),ABS(Results!K5)+ROW(Results!K5)/1000000,"") -> 1.7410024 | L7: =IF(ISNUMBER(Results!K5),1/(0.25+ABS(Results!K5)),0) -> 0.50226082
A8: 2 | B8: {=IFERROR(INDEX(Results!$A$5:$A$23,MATCH(SMALL($K$7:$K$25,A8),$K$7:$K$25,0)),"")} -> F08 | C8: {=IFERROR(INDEX(Results!$B$5:$B$23,MATCH(SMALL($K$7:$K$25,A8),$K$7:$K$25,0)),"")} -> Beta-Adjusted (precinct) | D8: {=IFERROR(ABS(INDEX(Results!$K$5:$K$23,MATCH(SMALL($K$7:$K$25,A8),$K$7:$K$25,0))),"")} -> 0.20996571 | E8: {=IFERROR(INDEX(Results!$K$5:$K$23,MATCH(SMALL($K$7:$K$25,A8),$K$7:$K$25,0)),"")} -> 0.20996571 | F8: {=IFERROR(INDEX(Results!$E$5:$E$23,MATCH(SMALL($K$7:$K$25,A8),$K$7:$K$25,0)),"")} -> 0.47277 | G8: {=IFERROR(INDEX(Results!$H$5:$H$23,MATCH(SMALL($K$7:$K$25,A8),$K$7:$K$25,0)),"")} -> Mackenzie | H8: {=IFERROR(INDEX(Results!$N$5:$N$23,MATCH(SMALL($K$7:$K$25,A8),$K$7:$K$25,0)),"")} -> No | I8: {=IFERROR(INDEX(Results!$M$5:$M$23,MATCH(SMALL($K$7:$K$25,A8),$K$7:$K$25,0)),"")} -> Out of sample | K8: =IF(ISNUMBER(Results!K6),ABS(Results!K6)+ROW(Results!K6)/1000000,"") | L8: =IF(ISNUMBER(Results!K6),1/(0.25+ABS(Results!K6)),0) -> 0
A9: 3 | B9: {=IFERROR(INDEX(Results!$A$5:$A$23,MATCH(SMALL($K$7:$K$25,A9),$K$7:$K$25,0)),"")} -> F14 | C9: {=IFERROR(INDEX(Results!$B$5:$B$23,MATCH(SMALL($K$7:$K$25,A9),$K$7:$K$25,0)),"")} -> Beta-Adjusted (precinct template) | D9: {=IFERROR(ABS(INDEX(Results!$K$5:$K$23,MATCH(SMALL($K$7:$K$25,A9),$K$7:$K$25,0))),"")} -> 0.20996571 | E9: {=IFERROR(INDEX(Results!$K$5:$K$23,MATCH(SMALL($K$7:$K$25,A9),$K$7:$K$25,0)),"")} -> 0.20996571 | F9: {=IFERROR(INDEX(Results!$E$5:$E$23,MATCH(SMALL($K$7:$K$25,A9),$K$7:$K$25,0)),"")} -> 0.46573 | G9: {=IFERROR(INDEX(Results!$H$5:$H$23,MATCH(SMALL($K$7:$K$25,A9),$K$7:$K$25,0)),"")} -> Mackenzie | H9: {=IFERROR(INDEX(Results!$N$5:$N$23,MATCH(SMALL($K$7:$K$25,A9),$K$7:$K$25,0)),"")} -> No | I9: {=IFERROR(INDEX(Results!$M$5:$M$23,MATCH(SMALL($K$7:$K$25,A9),$K$7:$K$25,0)),"")} -> Out of sample (same backtest as F08) | K9: =IF(ISNUMBER(Results!K7),ABS(Results!K7)+ROW(Results!K7)/1000000,"") | L9: =IF(ISNUMBER(Results!K7),1/(0.25+ABS(Results!K7)),0) -> 0
A10: 4 | B10: {=IFERROR(INDEX(Results!$A$5:$A$23,MATCH(SMALL($K$7:$K$25,A10),$K$7:$K$25,0)),"")} -> F04 | C10: {=IFERROR(INDEX(Results!$B$5:$B$23,MATCH(SMALL($K$7:$K$25,A10),$K$7:$K$25,0)),"")} -> Simple Trend (municipal, v3) | D10: {=IFERROR(ABS(INDEX(Results!$K$5:$K$23,MATCH(SMALL($K$7:$K$25,A10),$K$7:$K$25,0))),"")} -> 0.26874283 | E10: {=IFERROR(INDEX(Results!$K$5:$K$23,MATCH(SMALL($K$7:$K$25,A10),$K$7:$K$25,0)),"")} -> 0.26874283 | F10: {=IFERROR(INDEX(Results!$E$5:$E$23,MATCH(SMALL($K$7:$K$25,A10),$K$7:$K$25,0)),"")} -> 0.47727 | G10: {=IFERROR(INDEX(Results!$H$5:$H$23,MATCH(SMALL($K$7:$K$25,A10),$K$7:$K$25,0)),"")} -> Mackenzie | H10: {=IFERROR(INDEX(Results!$N$5:$N$23,MATCH(SMALL($K$7:$K$25,A10),$K$7:$K$25,0)),"")} -> No | I10: {=IFERROR(INDEX(Results!$M$5:$M$23,MATCH(SMALL($K$7:$K$25,A10),$K$7:$K$25,0)),"")} -> Out of sample | K10: =IF(ISNUMBER(Results!K8),ABS(Results!K8)+ROW(Results!K8)/1000000,"") -> 0.26875083 | L10: =IF(ISNUMBER(Results!K8),1/(0.25+ABS(Results!K8)),0) -> 1.9277375
A11: 5 | B11: {=IFERROR(INDEX(Results!$A$5:$A$23,MATCH(SMALL($K$7:$K$25,A11),$K$7:$K$25,0)),"")} -> F10 | C11: {=IFERROR(INDEX(Results!$B$5:$B$23,MATCH(SMALL($K$7:$K$25,A11),$K$7:$K$25,0)),"")} -> Simple Trend (municipal template) | D11: {=IFERROR(ABS(INDEX(Results!$K$5:$K$23,MATCH(SMALL($K$7:$K$25,A11),$K$7:$K$25,0))),"")} -> 0.26874283 | E11: {=IFERROR(INDEX(Results!$K$5:$K$23,MATCH(SMALL($K$7:$K$25,A11),$K$7:$K$25,0)),"")} -> 0.26874283 | F11: {=IFERROR(INDEX(Results!$E$5:$E$23,MATCH(SMALL($K$7:$K$25,A11),$K$7:$K$25,0)),"")} -> 0.46939 | G11: {=IFERROR(INDEX(Results!$H$5:$H$23,MATCH(SMALL($K$7:$K$25,A11),$K$7:$K$25,0)),"")} -> Mackenzie | H11: {=IFERROR(INDEX(Results!$N$5:$N$23,MATCH(SMALL($K$7:$K$25,A11),$K$7:$K$25,0)),"")} -> No | I11: {=IFERROR(INDEX(Results!$M$5:$M$23,MATCH(SMALL($K$7:$K$25,A11),$K$7:$K$25,0)),"")} -> Out of sample (same backtest as F04) | K11: =IF(ISNUMBER(Results!K9),ABS(Results!K9)+ROW(Results!K9)/1000000,"") -> 1.2854364 | L11: =IF(ISNUMBER(Results!K9),1/(0.25+ABS(Results!K9)),0) -> 0.65128444
A12: 6 | B12: {=IFERROR(INDEX(Results!$A$5:$A$23,MATCH(SMALL($K$7:$K$25,A12),$K$7:$K$25,0)),"")} -> F19 | C12: {=IFERROR(INDEX(Results!$B$5:$B$23,MATCH(SMALL($K$7:$K$25,A12),$K$7:$K$25,0)),"")} -> Baseline + bellwether blend (50/50, v11) | D12: {=IFERROR(ABS(INDEX(Results!$K$5:$K$23,MATCH(SMALL($K$7:$K$25,A12),$K$7:$K$25,0))),"")} -> 0.34444009 | E12: {=IFERROR(INDEX(Results!$K$5:$K$23,MATCH(SMALL($K$7:$K$25,A12),$K$7:$K$25,0)),"")} -> -0.34444009 | F12: {=IFERROR(INDEX(Results!$E$5:$E$23,MATCH(SMALL($K$7:$K$25,A12),$K$7:$K$25,0)),"")} -> 0.49752688 | G12: {=IFERROR(INDEX(Results!$H$5:$H$23,MATCH(SMALL($K$7:$K$25,A12),$K$7:$K$25,0)),"")} -> Mackenzie | H12: {=IFERROR(INDEX(Results!$N$5:$N$23,MATCH(SMALL($K$7:$K$25,A12),$K$7:$K$25,0)),"")} -> No | I12: {=IFERROR(INDEX(Results!$M$5:$M$23,MATCH(SMALL($K$7:$K$25,A12),$K$7:$K$25,0)),"")} -> Fully out of sample (2022 and 2024) | K12: =IF(ISNUMBER(Results!K10),ABS(Results!K10)+ROW(Results!K10)/1000000,"") -> 2.2876896 | L12: =IF(ISNUMBER(Results!K10),1/(0.25+ABS(Results!K10)),0) -> 0.39406077
A13: 7 | B13: {=IFERROR(INDEX(Results!$A$5:$A$23,MATCH(SMALL($K$7:$K$25,A13),$K$7:$K$25,0)),"")} -> F07 | C13: {=IFERROR(INDEX(Results!$B$5:$B$23,MATCH(SMALL($K$7:$K$25,A13),$K$7:$K$25,0)),"")} -> Simple Trend (precinct) | D13: {=IFERROR(ABS(INDEX(Results!$K$5:$K$23,MATCH(SMALL($K$7:$K$25,A13),$K$7:$K$25,0))),"")} -> 0.38745946 | E13: {=IFERROR(INDEX(Results!$K$5:$K$23,MATCH(SMALL($K$7:$K$25,A13),$K$7:$K$25,0)),"")} -> 0.38745946 | F13: {=IFERROR(INDEX(Results!$E$5:$E$23,MATCH(SMALL($K$7:$K$25,A13),$K$7:$K$25,0)),"")} -> 0.48313 | G13: {=IFERROR(INDEX(Results!$H$5:$H$23,MATCH(SMALL($K$7:$K$25,A13),$K$7:$K$25,0)),"")} -> Mackenzie | H13: {=IFERROR(INDEX(Results!$N$5:$N$23,MATCH(SMALL($K$7:$K$25,A13),$K$7:$K$25,0)),"")} -> No | I13: {=IFERROR(INDEX(Results!$M$5:$M$23,MATCH(SMALL($K$7:$K$25,A13),$K$7:$K$25,0)),"")} -> Out of sample | K13: =IF(ISNUMBER(Results!K11),ABS(Results!K11)+ROW(Results!K11)/1000000,"") -> 0.38747046 | L13: =IF(ISNUMBER(Results!K11),1/(0.25+ABS(Results!K11)),0) -> 1.5687272
A14: 8 | B14: {=IFERROR(INDEX(Results!$A$5:$A$23,MATCH(SMALL($K$7:$K$25,A14),$K$7:$K$25,0)),"")} -> F13 | C14: {=IFERROR(INDEX(Results!$B$5:$B$23,MATCH(SMALL($K$7:$K$25,A14),$K$7:$K$25,0)),"")} -> Simple Trend (precinct template) | D14: {=IFERROR(ABS(INDEX(Results!$K$5:$K$23,MATCH(SMALL($K$7:$K$25,A14),$K$7:$K$25,0))),"")} -> 0.38745946 | E14: {=IFERROR(INDEX(Results!$K$5:$K$23,MATCH(SMALL($K$7:$K$25,A14),$K$7:$K$25,0)),"")} -> 0.38745946 | F14: {=IFERROR(INDEX(Results!$E$5:$E$23,MATCH(SMALL($K$7:$K$25,A14),$K$7:$K$25,0)),"")} -> 0.4763 | G14: {=IFERROR(INDEX(Results!$H$5:$H$23,MATCH(SMALL($K$7:$K$25,A14),$K$7:$K$25,0)),"")} -> Mackenzie | H14: {=IFERROR(INDEX(Results!$N$5:$N$23,MATCH(SMALL($K$7:$K$25,A14),$K$7:$K$25,0)),"")} -> No | I14: {=IFERROR(INDEX(Results!$M$5:$M$23,MATCH(SMALL($K$7:$K$25,A14),$K$7:$K$25,0)),"")} -> Out of sample (same backtest as F07) | K14: =IF(ISNUMBER(Results!K12),ABS(Results!K12)+ROW(Results!K12)/1000000,"") -> 0.20997772 | L14: =IF(ISNUMBER(Results!K12),1/(0.25+ABS(Results!K12)),0) -> 2.1740751
A15: 9 | B15: {=IFERROR(INDEX(Results!$A$5:$A$23,MATCH(SMALL($K$7:$K$25,A15),$K$7:$K$25,0)),"")} -> F18 | C15: {=IFERROR(INDEX(Results!$B$5:$B$23,MATCH(SMALL($K$7:$K$25,A15),$K$7:$K$25,0)),"")} -> Bellwether reading on the v11 baseline (honest rule) | D15: {=IFERROR(ABS(INDEX(Results!$K$5:$K$23,MATCH(SMALL($K$7:$K$25,A15),$K$7:$K$25,0))),"")} -> 0.51046282 | E15: {=IFERROR(INDEX(Results!$K$5:$K$23,MATCH(SMALL($K$7:$K$25,A15),$K$7:$K$25,0)),"")} -> -0.51046282 | F15: {=IFERROR(INDEX(Results!$E$5:$E$23,MATCH(SMALL($K$7:$K$25,A15),$K$7:$K$25,0)),"")} -> 0.50011074 | G15: {=IFERROR(INDEX(Results!$H$5:$H$23,MATCH(SMALL($K$7:$K$25,A15),$K$7:$K$25,0)),"")} -> Brooks | H15: {=IFERROR(INDEX(Results!$N$5:$N$23,MATCH(SMALL($K$7:$K$25,A15),$K$7:$K$25,0)),"")} -> No | I15: {=IFERROR(INDEX(Results!$M$5:$M$23,MATCH(SMALL($K$7:$K$25,A15),$K$7:$K$25,0)),"")} -> Fully out of sample (2022 and 2024) | K15: =IF(ISNUMBER(Results!K13),ABS(Results!K13)+ROW(Results!K13)/1000000,"") -> 1.8266697 | L15: =IF(ISNUMBER(Results!K13),1/(0.25+ABS(Results!K13)),0) -> 0.48154325
A16: 10 | B16: {=IFERROR(INDEX(Results!$A$5:$A$23,MATCH(SMALL($K$7:$K$25,A16),$K$7:$K$25,0)),"")} -> F17 | C16: {=IFERROR(INDEX(Results!$B$5:$B$23,MATCH(SMALL($K$7:$K$25,A16),$K$7:$K$25,0)),"")} -> Bellwether reading, Professor Crain’s 6 precincts, on the v0.1 baseline | D16: {=IFERROR(ABS(INDEX(Results!$K$5:$K$23,MATCH(SMALL($K$7:$K$25,A16),$K$7:$K$25,0))),"")} -> 0.62822898 | E16: {=IFERROR(INDEX(Results!$K$5:$K$23,MATCH(SMALL($K$7:$K$25,A16),$K$7:$K$25,0)),"")} -> -0.62822898 | F16: {=IFERROR(INDEX(Results!$E$5:$E$23,MATCH(SMALL($K$7:$K$25,A16),$K$7:$K$25,0)),"")} -> 0.49217551 | G16: {=IFERROR(INDEX(Results!$H$5:$H$23,MATCH(SMALL($K$7:$K$25,A16),$K$7:$K$25,0)),"")} -> Mackenzie | H16: {=IFERROR(INDEX(Results!$N$5:$N$23,MATCH(SMALL($K$7:$K$25,A16),$K$7:$K$25,0)),"")} -> No | I16: {=IFERROR(INDEX(Results!$M$5:$M$23,MATCH(SMALL($K$7:$K$25,A16),$K$7:$K$25,0)),"")} -> Selection data unknown; baseline backtest used actual turnout | K16: =IF(ISNUMBER(Results!K14),ABS(Results!K14)+ROW(Results!K14)/1000000,"") -> 0.26875683 | L16: =IF(ISNUMBER(Results!K14),1/(0.25+ABS(Results!K14)),0) -> 1.9277375
A17: 11 | B17: {=IFERROR(INDEX(Results!$A$5:$A$23,MATCH(SMALL($K$7:$K$25,A17),$K$7:$K$25,0)),"")} -> F05 | C17: {=IFERROR(INDEX(Results!$B$5:$B$23,MATCH(SMALL($K$7:$K$25,A17),$K$7:$K$25,0)),"")} -> Beta-Adjusted (municipal, v3) | D17: {=IFERROR(ABS(INDEX(Results!$K$5:$K$23,MATCH(SMALL($K$7:$K$25,A17),$K$7:$K$25,0))),"")} -> 1.2854274 | E17: {=IFERROR(INDEX(Results!$K$5:$K$23,MATCH(SMALL($K$7:$K$25,A17),$K$7:$K$25,0)),"")} -> 1.2854274 | F17: {=IFERROR(INDEX(Results!$E$5:$E$23,MATCH(SMALL($K$7:$K$25,A17),$K$7:$K$25,0)),"")} -> 0.46765 | G17: {=IFERROR(INDEX(Results!$H$5:$H$23,MATCH(SMALL($K$7:$K$25,A17),$K$7:$K$25,0)),"")} -> Mackenzie | H17: {=IFERROR(INDEX(Results!$N$5:$N$23,MATCH(SMALL($K$7:$K$25,A17),$K$7:$K$25,0)),"")} -> No | I17: {=IFERROR(INDEX(Results!$M$5:$M$23,MATCH(SMALL($K$7:$K$25,A17),$K$7:$K$25,0)),"")} -> Out of sample | K17: =IF(ISNUMBER(Results!K15),ABS(Results!K15)+ROW(Results!K15)/1000000,"") -> 1.2854424 | L17: =IF(ISNUMBER(Results!K15),1/(0.25+ABS(Results!K15)),0) -> 0.65128444
A18: 12 | B18: {=IFERROR(INDEX(Results!$A$5:$A$23,MATCH(SMALL($K$7:$K$25,A18),$K$7:$K$25,0)),"")} -> F11 | C18: {=IFERROR(INDEX(Results!$B$5:$B$23,MATCH(SMALL($K$7:$K$25,A18),$K$7:$K$25,0)),"")} -> Beta-Adjusted (municipal template) | D18: {=IFERROR(ABS(INDEX(Results!$K$5:$K$23,MATCH(SMALL($K$7:$K$25,A18),$K$7:$K$25,0))),"")} -> 1.2854274 | E18: {=IFERROR(INDEX(Results!$K$5:$K$23,MATCH(SMALL($K$7:$K$25,A18),$K$7:$K$25,0)),"")} -> 1.2854274 | F18: {=IFERROR(INDEX(Results!$E$5:$E$23,MATCH(SMALL($K$7:$K$25,A18),$K$7:$K$25,0)),"")} -> 0.4597 | G18: {=IFERROR(INDEX(Results!$H$5:$H$23,MATCH(SMALL($K$7:$K$25,A18),$K$7:$K$25,0)),"")} -> Mackenzie | H18: {=IFERROR(INDEX(Results!$N$5:$N$23,MATCH(SMALL($K$7:$K$25,A18),$K$7:$K$25,0)),"")} -> No | I18: {=IFERROR(INDEX(Results!$M$5:$M$23,MATCH(SMALL($K$7:$K$25,A18),$K$7:$K$25,0)),"")} -> Out of sample (same backtest as F05) | K18: =IF(ISNUMBER(Results!K16),ABS(Results!K16)+ROW(Results!K16)/1000000,"") -> 2.2876956 | L18: =IF(ISNUMBER(Results!K16),1/(0.25+ABS(Results!K16)),0) -> 0.39406077
... A25: 19 | B25: {=IFERROR(INDEX(Results!$A$5:$A$23,MATCH(SMALL($K$7:$K$25,A25),$K$7:$K$25,0)),"")} | C25: {=IFERROR(INDEX(Results!$B$5:$B$23,MATCH(SMALL($K$7:$K$25,A25),$K$7:$K$25,0)),"")} | D25: {=IFERROR(ABS(INDEX(Results!$K$5:$K$23,MATCH(SMALL($K$7:$K$25,A25),$K$7:$K$25,0))),"")} | E25: {=IFERROR(INDEX(Results!$K$5:$K$23,MATCH(SMALL($K$7:$K$25,A25),$K$7:$K$25,0)),"")} | F25: {=IFERROR(INDEX(Results!$E$5:$E$23,MATCH(SMALL($K$7:$K$25,A25),$K$7:$K$25,0)),"")} | G25: {=IFERROR(INDEX(Results!$H$5:$H$23,MATCH(SMALL($K$7:$K$25,A25),$K$7:$K$25,0)),"")} | H25: {=IFERROR(INDEX(Results!$N$5:$N$23,MATCH(SMALL($K$7:$K$25,A25),$K$7:$K$25,0)),"")} | I25: {=IFERROR(INDEX(Results!$M$5:$M$23,MATCH(SMALL($K$7:$K$25,A25),$K$7:$K$25,0)),"")} | K25: =IF(ISNUMBER(Results!K23),ABS(Results!K23)+ROW(Results!K23)/1000000,"") -> 0.34446309 | L25: =IF(ISNUMBER(Results!K23),1/(0.25+ABS(Results!K23)),0) -> 1.6822553
A27: F02 and F03 are not ranked because their town-by-town backtest predictions were not saved.
A29: 2. Who is predicted to win, and how often
A30: Group of forecasts | B30: Number of forecasts | C30: Predict Brooks | D30: Predict Mackenzie | E30: Share predicting Mackenzie | F30: Average Brooks share | G30: Median Brooks share
A31: All of Kiley’s forecasts (F01–F19) | B31: =COUNTA(Results!$A$5:$A$23) -> 19 | C31: =COUNTIF(Results!$H$5:$H$23,"Brooks") -> 5 | D31: =COUNTIF(Results!$H$5:$H$23,"Mackenzie") -> 14 | E31: =D31/B31 -> 0.73684211 | F31: =AVERAGE(Results!$E$5:$E$23) -> 0.48812613 | G31: =MEDIAN(Results!$E$5:$E$23) -> 0.49217551
A32: Current data only (excludes F01–F03) | B32: =COUNTIF(Results!$N$5:$N$23,"No") -> 16 | C32: =COUNTIFS(Results!$H$5:$H$23,"Brooks",Results!$N$5:$N$23,"No") -> 4 | D32: =COUNTIFS(Results!$H$5:$H$23,"Mackenzie",Results!$N$5:$N$23,"No") -> 12 | E32: =D32/B32 -> 0.75 | F32: =AVERAGEIF(Results!$N$5:$N$23,"No",Results!$E$5:$E$23) -> 0.48631665
A33: Best backtests: 2024 district miss within ±0.5 pts | B33: =COUNTIFS(Results!$K$5:$K$23,">=-0.5",Results!$K$5:$K$23,"<=0.5") -> 8 | C33: =COUNTIFS(Results!$K$5:$K$23,">=-0.5",Results!$K$5:$K$23,"<=0.5",Results!$H$5:$H$23,"Brooks") -> 0 | D33: =COUNTIFS(Results!$K$5:$K$23,">=-0.5",Results!$K$5:$K$23,"<=0.5",Results!$H$5:$H$23,"Mackenzie") -> 8 | E33: =D33/B33 -> 1 | F33: =AVERAGEIFS(Results!$E$5:$E$23,Results!$K$5:$K$23,">=-0.5",Results!$K$5:$K$23,"<=0.5") -> 0.48022502
A35: 3. Accuracy-weighted forecast
A36: Each forecast with a 2024 district miss gets a weight of 1 ÷ (0.25 + the size of its miss), so the forecasts that came closest to the 2024 result count most. The 0.25-point floor stops any one forecast from dominating. Note: template repeats (F10–F15) count alongside their originals, which gives those methods extra weight.
A37: Accuracy-weighted Brooks share | F37: =SUMPRODUCT($L$7:$L$25,Results!$E$5:$E$23)/SUM($L$7:$L$25) -> 0.48351408
A38: Implied margin, Brooks minus Mackenzie (pts) | F38: =(2*F37-1)*100 -> -3.2971835
A39: Implied winner | F39: =IF(F37>0.5,"Brooks","Mackenzie") -> Mackenzie
A41: 4. Conclusion
A42: 1. Most forecasts predict Mackenzie: 14 of 19 overall, and all 8 forecasts that came within half a point of the 2024 district result.
A43: 2. Four of the five forecasts predicting Brooks are regression versions (F03, F06, F09, F15), which had the worst district-level backtests. The fifth (F18) is a dead heat at 50.0%.
A44: 3. The best-backtested forecasts are the v0.1 bellwether reading (F16, off by 0.15 pts) and precinct Beta-Adjusted (F08, off by 0.21 pts). The most rigorously tested forecasts (the v11 baseline, F18 and F19) all put Brooks between 49.5% and 50.0%.
A45: 4. Overall expectation: Mackenzie is the more likely winner, but narrowly. The accuracy-weighted forecast puts Brooks at about 48.4% (Mackenzie by about 3 points); the strictest tests suggest a margin under 1 point. The race is best called Lean Republican, not safe.
A46: 5. Caveats: backtests differ in strictness, most methods were tested on 2024 only, and F01–F03 used incomplete data. No forecast here produces a win probability.

Sheet Data & Caveats
A1: Data used, and known limitations
A3: How the data improved over the project
A4: Date | B4: Forecasts | C4: Data change
A5: Sept. 14 | B5: F01–F03 | C5: First municipal file. Carbon votes were missing (estimated from registration, R² 0.93–0.94); Monroe was missing; the 2020 race was misreported as a Democratic win.
A6: Sept. 16 | B6: F04–F06 | C6: Certified returns for all 89 towns, including Carbon and Monroe. 2020 corrected: Republicans won by about 2,600 votes, so the district alternates D-R-D-R.
A7: Sept. 17 | B7: F07–F09 | C7: Precinct-level certified results, 2018–2024, keyed by stable Department of State precinct codes.
A8: Sept. 24 | B8: F10–F15 | C8: The same methods entered in the class template, with district totals built from the rows.
A9: Oct. 21–26 | B9: F16–F19 | C9: Bellwether analysis on the group baselines, plus 2026 voter-file registration and demographics (Aug. 31, 2026 snapshot).
A11: Known limitations
A12: • Only one or two test elections. Most methods were tested on 2024 alone, and only 2022 and 2024 were held under today’s district lines.
A13: • 2026 is a midterm with a Republican president. National swing is not modeled by any forecast here; polls and prediction markets that price it point toward Brooks (Polymarket about 85% Brooks in early October).
A14: • Turnout. Several forecasts convert shares into votes using 2022 midterm turnout. The bellwether work found this assumption moves the v0.1 forecast about 0.8 points toward Mackenzie.
A15: • The v0.1 baseline’s 2024 backtest used actual 2024 turnout, so F16 and F17 test vote share only.
A16: • District lines changed. Carbon was not in PA-07 before 2022 and most of Monroe left after 2022; earlier years use each place’s own history as a guide to today’s district.
A17: • Redrawn precincts. Seven Northampton towns redrew precinct lines for 2026, so their precincts cannot be compared one-to-one with past results.
A18: • No win probabilities. Every forecast gives a vote share; none gives a probability of winning.
A19: • Ethnicity, income and education are not in the voter file, so demographic comparisons cover party, age, sex, turnout and mail voting only.
A21: Sources
A22: See the Sources tab for file-level citations. Election results and registration come from Pennsylvania Department of State certified returns and registration statistics.

Sheet Sources
A1: Sources
A3: F01–F03 | B3: PA07_Analysis.xlsx (tracker: "Analysis Workbook," Sept. 14)
A4: F04–F06 | B4: PA07_Analysis (2).xlsx (tracker: "Backtest & Forecast Analysis Update," Sept. 16)
A5: F07–F09 | B5: Precinct Backtest & Forecast Analysis.xlsx (tracker, Sept. 17)
A6: F10–F12 | B6: Meringer Municipal Forecast.xlsx (tracker, Sept. 24)
A7: F13–F15 | B7: Meringer Precinct Forecast.xlsx (tracker, Sept. 24)
A8: Backtest-only tests | B8: Meringer Municiaplity NEW TESTS.xlsx (Sept. 24) and New Combined Methods Meringer.xlsx (Sept. 27), PA-07 Project Tracker
A9: F16–F17 | B9: Bellwether analysis (Oct. 21–26); group baseline PA07_2026_Forecast_Precinct.xlsx (random forest v0.1); Professor Crain’s bellwether list
A10: F18–F19 | B10: Bellwether + Baseline PA07 Forecast Meringer.xlsx (tracker, Oct. 26); group baseline PA07_Precinct_Results_Forecasts_ABC_v11_MostAccurate.xlsx (Oct. 6)
A11: Election and registration data | B11: Pennsylvania Department of State certified returns and registration statistics, as compiled in PA_07_Precinct_Data.xlsx (Max Muller, Sept. 17) and the municipal data files
A12: District-level 2024 misses for F01–F15 | B12: Computed for this workbook: each method’s town or precinct predictions weighted by actual 2024 two-party votes, compared with the certified district result (49.50%). F01 covers Lehigh and Northampton only.
A13: Tracker | B13: https://github.com/weinsteincharles27-del/PA-07-Project-Tracker
